Workbook

Sheet Synthèse
A1: Cahier de recette · branche integration/recette-2026-10-29
A2: Contenu : claude/new-session-xm8ptu + tests-performance + anomalies-support + audits-code (sans l'inventaire des JSP). Cas tirés des changements depuis la dernière version de dev (05/10). Tests sur la copie de travail, jamais la base de production.
A4: Module (feuille) | B4: Menu | C4: Cas | D4: OK | E4: KO | F4: Bloqué | G4: Non testé | H4: Tests auto OK / KO | I4: Avancement
A5: Connexion et sécurité | B5: Page de connexion · GESTION DES UTILISATEURS | C5: =COUNTA('Connexion et sécurité'!$A$6:$A$19) -> 14 | D5: =COUNTIF('Connexion et sécurité'!$H$6:$H$19,"OK") -> 0 | E5: =COUNTIF('Connexion et sécurité'!$H$6:$H$19,"KO") -> 0 | F5: =COUNTIF('Connexion et sécurité'!$H$6:$H$19,"Bloqué") -> 0 | G5: =C5-COUNTA('Connexion et sécurité'!$H$6:$H$19) -> 14 | H5: =COUNTIF('Connexion et sécurité'!$G$6:$G$19,"OK")&" / "&COUNTIF('Connexion et sécurité'!$G$6:$G$19,"KO") -> 2 / 0 | I5: =IF(C5=0,0,(D5+E5+F5)/C5) -> 0
A6: Ventes | B6: SERVICE CLIENT | C6: =COUNTA(Ventes!$A$6:$A$20) -> 15 | D6: =COUNTIF(Ventes!$H$6:$H$20,"OK") -> 0 | E6: =COUNTIF(Ventes!$H$6:$H$20,"KO") -> 0 | F6: =COUNTIF(Ventes!$H$6:$H$20,"Bloqué") -> 0 | G6: =C6-COUNTA(Ventes!$H$6:$H$20) -> 15 | H6: =COUNTIF(Ventes!$G$6:$G$20,"OK")&" / "&COUNTIF(Ventes!$G$6:$G$20,"KO") -> 10 / 2 | I6: =IF(C6=0,0,(D6+E6+F6)/C6) -> 0
A7: Caisse et gestion courante | B7: GESTION COURANTE | C7: =COUNTA('Caisse et gestion courante'!$A$6:$A$13) -> 8 | D7: =COUNTIF('Caisse et gestion courante'!$H$6:$H$13,"OK") -> 0 | E7: =COUNTIF('Caisse et gestion courante'!$H$6:$H$13,"KO") -> 0 | F7: =COUNTIF('Caisse et gestion courante'!$H$6:$H$13,"Bloqué") -> 0 | G7: =C7-COUNTA('Caisse et gestion courante'!$H$6:$H$13) -> 8 | H7: =COUNTIF('Caisse et gestion courante'!$G$6:$G$13,"OK")&" / "&COUNTIF('Caisse et gestion courante'!$G$6:$G$13,"KO") -> 2 / 0 | I7: =IF(C7=0,0,(D7+E7+F7)/C7) -> 0
A8: Facturation et différés | B8: FACTURATION | C8: =COUNTA('Facturation et différés'!$A$6:$A$14) -> 9 | D8: =COUNTIF('Facturation et différés'!$H$6:$H$14,"OK") -> 0 | E8: =COUNTIF('Facturation et différés'!$H$6:$H$14,"KO") -> 0 | F8: =COUNTIF('Facturation et différés'!$H$6:$H$14,"Bloqué") -> 0 | G8: =C8-COUNTA('Facturation et différés'!$H$6:$H$14) -> 9 | H8: =COUNTIF('Facturation et différés'!$G$6:$G$14,"OK")&" / "&COUNTIF('Facturation et différés'!$G$6:$G$14,"KO") -> 8 / 0 | I8: =IF(C8=0,0,(D8+E8+F8)/C8) -> 0
A9: Tiers-payants et clients | B9: GESTION DES TIERS-PAYANTS · GESTION CLIENT | C9: =COUNTA('Tiers-payants et clients'!$A$6:$A$15) -> 10 | D9: =COUNTIF('Tiers-payants et clients'!$H$6:$H$15,"OK") -> 0 | E9: =COUNTIF('Tiers-payants et clients'!$H$6:$H$15,"KO") -> 0 | F9: =COUNTIF('Tiers-payants et clients'!$H$6:$H$15,"Bloqué") -> 0 | G9: =C9-COUNTA('Tiers-payants et clients'!$H$6:$H$15) -> 10 | H9: =COUNTIF('Tiers-payants et clients'!$G$6:$G$15,"OK")&" / "&COUNTIF('Tiers-payants et clients'!$G$6:$G$15,"KO") -> 8 / 0 | I9: =IF(C9=0,0,(D9+E9+F9)/C9) -> 0
A10: Commandes et PharmaML | B10: GESTION DES COMMANDES | C10: =COUNTA('Commandes et PharmaML'!$A$6:$A$16) -> 11 | D10: =COUNTIF('Commandes et PharmaML'!$H$6:$H$16,"OK") -> 0 | E10: =COUNTIF('Commandes et PharmaML'!$H$6:$H$16,"KO") -> 0 | F10: =COUNTIF('Commandes et PharmaML'!$H$6:$H$16,"Bloqué") -> 0 | G10: =C10-COUNTA('Commandes et PharmaML'!$H$6:$H$16) -> 11 | H10: =COUNTIF('Commandes et PharmaML'!$G$6:$G$16,"OK")&" / "&COUNTIF('Commandes et PharmaML'!$G$6:$G$16,"KO") -> 8 / 1 | I10: =IF(C10=0,0,(D10+E10+F10)/C10) -> 0
A11: Stock | B11: GESTION DU STOCK | C11: =COUNTA(Stock!$A$6:$A$15) -> 10 | D11: =COUNTIF(Stock!$H$6:$H$15,"OK") -> 0 | E11: =COUNTIF(Stock!$H$6:$H$15,"KO") -> 0 | F11: =COUNTIF(Stock!$H$6:$H$15,"Bloqué") -> 0 | G11: =C11-COUNTA(Stock!$H$6:$H$15) -> 10 | H11: =COUNTIF(Stock!$G$6:$G$15,"OK")&" / "&COUNTIF(Stock!$G$6:$G$15,"KO") -> 7 / 0 | I11: =IF(C11=0,0,(D11+E11+F11)/C11) -> 0
A12: Étiquettes | B12: GESTION DU STOCK > Étiquettage Pro | C12: =COUNTA(Étiquettes!$A$6:$A$12) -> 7 | D12: =COUNTIF(Étiquettes!$H$6:$H$12,"OK") -> 0 | E12: =COUNTIF(Étiquettes!$H$6:$H$12,"KO") -> 0 | F12: =COUNTIF(Étiquettes!$H$6:$H$12,"Bloqué") -> 0 | G12: =C12-COUNTA(Étiquettes!$H$6:$H$12) -> 7 | H12: =COUNTIF(Étiquettes!$G$6:$G$12,"OK")&" / "&COUNTIF(Étiquettes!$G$6:$G$12,"KO") -> 4 / 0 | I12: =IF(C12=0,0,(D12+E12+F12)/C12) -> 0
A13: Analyse et pilotage | B13: ANALYSE DE GESTION | C13: =COUNTA('Analyse et pilotage'!$A$6:$A$15) -> 10 | D13: =COUNTIF('Analyse et pilotage'!$H$6:$H$15,"OK") -> 0 | E13: =COUNTIF('Analyse et pilotage'!$H$6:$H$15,"KO") -> 0 | F13: =COUNTIF('Analyse et pilotage'!$H$6:$H$15,"Bloqué") -> 0 | G13: =C13-COUNTA('Analyse et pilotage'!$H$6:$H$15) -> 10 | H13: =COUNTIF('Analyse et pilotage'!$G$6:$G$15,"OK")&" / "&COUNTIF('Analyse et pilotage'!$G$6:$G$15,"KO") -> 6 / 0 | I13: =IF(C13=0,0,(D13+E13+F13)/C13) -> 0
A14: Campagnes et avis clients | B14: CAMPAGNES SMS / WHATSAPP · AVIS CLIENTS | C14: =COUNTA('Campagnes et avis clients'!$A$6:$A$11) -> 6 | D14: =COUNTIF('Campagnes et avis clients'!$H$6:$H$11,"OK") -> 0 | E14: =COUNTIF('Campagnes et avis clients'!$H$6:$H$11,"KO") -> 0 | F14: =COUNTIF('Campagnes et avis clients'!$H$6:$H$11,"Bloqué") -> 0 | G14: =C14-COUNTA('Campagnes et avis clients'!$H$6:$H$11) -> 6 | H14: =COUNTIF('Campagnes et avis clients'!$G$6:$G$11,"OK")&" / "&COUNTIF('Campagnes et avis clients'!$G$6:$G$11,"KO") -> 0 / 0 | I14: =IF(C14=0,0,(D14+E14+F14)/C14) -> 0
A15: Ressources humaines | B15: RESSOURCES HUMAINES | C15: =COUNTA('Ressources humaines'!$A$6:$A$12) -> 7 | D15: =COUNTIF('Ressources humaines'!$H$6:$H$12,"OK") -> 0 | E15: =COUNTIF('Ressources humaines'!$H$6:$H$12,"KO") -> 0 | F15: =COUNTIF('Ressources humaines'!$H$6:$H$12,"Bloqué") -> 0 | G15: =C15-COUNTA('Ressources humaines'!$H$6:$H$12) -> 7 | H15: =COUNTIF('Ressources humaines'!$G$6:$G$12,"OK")&" / "&COUNTIF('Ressources humaines'!$G$6:$G$12,"KO") -> 0 / 0 | I15: =IF(C15=0,0,(D15+E15+F15)/C15) -> 0
A16: Support et serveur | B16: CENTRE DE SUPPORT | C16: =COUNTA('Support et serveur'!$A$6:$A$11) -> 6 | D16: =COUNTIF('Support et serveur'!$H$6:$H$11,"OK") -> 0 | E16: =COUNTIF('Support et serveur'!$H$6:$H$11,"KO") -> 0 | F16: =COUNTIF('Support et serveur'!$H$6:$H$11,"Bloqué") -> 0 | G16: =C16-COUNTA('Support et serveur'!$H$6:$H$11) -> 6 | H16: =COUNTIF('Support et serveur'!$G$6:$G$11,"OK")&" / "&COUNTIF('Support et serveur'!$G$6:$G$11,"KO") -> 2 / 2 | I16: =IF(C16=0,0,(D16+E16+F16)/C16) -> 0
A17: Performances et charge | B17: Tous menus | C17: =COUNTA('Performances et charge'!$A$6:$A$11) -> 6 | D17: =COUNTIF('Performances et charge'!$H$6:$H$11,"OK") -> 0 | E17: =COUNTIF('Performances et charge'!$H$6:$H$11,"KO") -> 0 | F17: =COUNTIF('Performances et charge'!$H$6:$H$11,"Bloqué") -> 0 | G17: =C17-COUNTA('Performances et charge'!$H$6:$H$11) -> 6 | H17: =COUNTIF('Performances et charge'!$G$6:$G$11,"OK")&" / "&COUNTIF('Performances et charge'!$G$6:$G$11,"KO") -> 1 / 3 | I17: =IF(C17=0,0,(D17+E17+F17)/C17) -> 0
A18: Éditions et modèles | B18: Toutes éditions | C18: =COUNTA('Éditions et modèles'!$A$6:$A$10) -> 5 | D18: =COUNTIF('Éditions et modèles'!$H$6:$H$10,"OK") -> 0 | E18: =COUNTIF('Éditions et modèles'!$H$6:$H$10,"KO") -> 0 | F18: =COUNTIF('Éditions et modèles'!$H$6:$H$10,"Bloqué") -> 0 | G18: =C18-COUNTA('Éditions et modèles'!$H$6:$H$10) -> 5 | H18: =COUNTIF('Éditions et modèles'!$G$6:$G$10,"OK")&" / "&COUNTIF('Éditions et modèles'!$G$6:$G$10,"KO") -> 4 / 0 | I18: =IF(C18=0,0,(D18+E18+F18)/C18) -> 0
A19: TOTAL | C19: =SUM(C5:C18) -> 124 | D19: =SUM(D5:D18) -> 0 | E19: =SUM(E5:E18) -> 0 | F19: =SUM(F5:F18) -> 0 | G19: =SUM(G5:G18) -> 124 | I19: =IF(C19=0,0,(D19+E19+F19)/C19) -> 0

Sheet Connexion et sécurité
A1: Cahier de recette · Connexion et sécurité | F1: Menu : Page de connexion · GESTION DES UTILISATEURS
A2: Branche : integration/recette-2026-10-29 · base de test : copie de travail, jamais la production
A3: Cas | B3: =COUNTA($A$6:$A$19) -> 14 | C3: OK | D3: =COUNTIF($H$6:$H$19,"OK") -> 0 | E3: KO | F3: =COUNTIF($H$6:$H$19,"KO") -> 0 | G3: Non testé | H3: =COUNTA($A$6:$A$19)-COUNTA($H$6:$H$19) -> 14 | I3: Auto OK / KO | J3: =COUNTIF($G$6:$G$19,"OK")&" / "&COUNTIF($G$6:$G$19,"KO") -> 2 / 0
A4: Remplir les cellules jaunes · Statut : OK, KO (décrire, ouvrir un ticket), Bloqué, N/A · Test auto : résultat des tests d'écran sur la branche
A5: N° | B5: Écran | C5: Cas à vérifier | D5: Étapes | E5: Résultat attendu | F5: Prio. | G5: Test auto | H5: Statut | I5: Testeur · date | J5: Observation / ticket
A6: 1 | B6: Connexion | C6: Connexion normale | D6: 1. Identifiant, mot de passe, Entrée | E6: Accueil ouvert avec les menus du profil | F6: Haute | G6: Manuel
A7: 2 | B7: Connexion | C7: Mots de passe faux répétés | D7: 1. 10 essais faux 2. Attendre, réessayer | E7: Refus au-delà de 10 essais, nouvelle série après l'attente ; message sans dire si le compte existe | F7: Haute | G7: Manuel
A8: 3 | B8: Connexion | C8: Connexion par badge QR | D8: 1. « Se connecter avec mon badge » 2. Scanner le badge | E8: Session au nom de l'employé ; badge régénéré ou désactivé refusé | F8: Haute | G8: Manuel
A9: 4 | B9: Connexion | C9: Douchette QWERTY / Verr. Maj. | D9: 1. Scanner le badge avec la douchette mal réglée | E9: Connexion acceptée ou message « lecture déformée » explicite | F9: Basse | G9: Manuel
A10: 5 | B10: Connexion | C10: Bouton « Pointage » | D10: 1. Cliquer « Pointage » sur la page de connexion | E10: Le QR de pointage mobile s'affiche | F10: Basse | G10: Manuel
A11: 6 | B11: Session | C11: Expiration après inactivité | D11: 1. Laisser la session inactive 2. Agir | E11: Retour à la connexion ; aucune page protégée sans session | F11: Haute | G11: Manuel
A12: 7 | B12: Droits | C12: Super administrateur invisible | D12: 1. Se connecter en administrateur 2. Ouvrir la liste des utilisateurs et le Centre de support | E12: Super administrateur absent de la liste ; Centre de support (sauf « Me contacter ») et audit réservés | F12: Haute | G12: Manuel
A13: 8 | B13: Droits | C13: Droits vérifiés par le serveur | D13: 1. Profil sans le droit (ajustement, réserve, inventaire…) 2. Tenter l'action | E13: Refus du serveur même si le bouton est appelé directement | F13: Haute | G13: Manuel
A14: 9 | B14: Droits | C14: Vente close par un profil prévente | D14: 1. Profil prévente 2. Tenter de terminer une vente | E14: Refus : seul un caissier clôture | F14: Haute | G14: OK
A15: 10 | B15: Gestion de profils | C15: Créer, modifier, attribuer les privilèges | D15: 1. Créer un profil 2. Le modifier, attribuer des privilèges | E15: Fenêtres modales, enregistrement correct | F15: Moyenne | G15: Manuel
A16: 11 | B16: Utilisateurs | C16: Empreinte du mot de passe | D16: 1. Ouvrir la liste des utilisateurs (outils du navigateur) | E16: Aucune empreinte de mot de passe envoyée au navigateur | F16: Haute | G16: Manuel
A17: 12 | B17: Menus | C17: Libellés et ordre des menus | D17: 1. Parcourir les menus | E17: Libellés en MAJUSCULES, 25 caractères au plus, ordre fixe des modules | F17: Basse | G17: OK
... A19: 14 | B19: Postes | C19: Rappel « date ou heure fausse » | D19: 1. Poste à l'heure décalée | E19: Rappel avec « Mettre à jour » et « Masquer » | F19: Basse | G19: Manuel

Sheet Ventes
A1: Cahier de recette · Ventes | F1: Menu : SERVICE CLIENT
A2: Branche : integration/recette-2026-10-29 · base de test : copie de travail, jamais la production
A3: Cas | B3: =COUNTA($A$6:$A$20) -> 15 | C3: OK | D3: =COUNTIF($H$6:$H$20,"OK") -> 0 | E3: KO | F3: =COUNTIF($H$6:$H$20,"KO") -> 0 | G3: Non testé | H3: =COUNTA($A$6:$A$20)-COUNTA($H$6:$H$20) -> 15 | I3: Auto OK / KO | J3: =COUNTIF($G$6:$G$20,"OK")&" / "&COUNTIF($G$6:$G$20,"KO") -> 10 / 2
A4: Remplir les cellules jaunes · Statut : OK, KO (décrire, ouvrir un ticket), Bloqué, N/A · Test auto : résultat des tests d'écran sur la branche
A5: N° | B5: Écran | C5: Cas à vérifier | D5: Étapes | E5: Résultat attendu | F5: Prio. | G5: Test auto | H5: Statut | I5: Testeur · date | J5: Observation / ticket
A6: 1 | B6: Ventes | C6: Vente au comptant | D6: 1. Nouvelle vente, scanner, quantité 2. Terminer, régler en espèces | E6: Ticket, stock et caisse à jour | F6: Haute | G6: KO | J6: KO : ui-caisse-deconditionnement
A7: 2 | B7: Ventes | C7: Vente assurance avec remise | D7: 1. Vente assurance, articles, remise 2. Terminer | E7: Remise sur la part client de chaque produit, plafond réparti au prorata | F7: Haute | G7: KO | J7: KO : repro-vente-assurance
A8: 3 | B8: Ventes | C8: Quantité décimale | D8: 1. Taper 1.5 en quantité | E8: Refus avec message clair, quantité précédente gardée | F8: Moyenne | G8: OK
A9: 4 | B9: Ventes | C9: Vendeur tapé sans être choisi | D9: 1. Taper un vendeur, Tab 2. Ajouter un article | E9: Vendeur reconnu ou signalé ; le 1er article s'ajoute | F9: Moyenne | G9: OK
A10: 5 | B10: Ventes | C10: QR publicitaire scanné | D10: 1. Scanner un QR de site internet | E10: « QR code publicitaire » sans fenêtre, aucune recherche | F10: Basse | G10: OK
A11: 6 | B11: Ventes | C11: Étiquette GS1 / DataMatrix | D11: 1. Scanner une boîte GS1 | E11: Produit trouvé, lot contrôlé, péremption effacée après l'ajout | F11: Moyenne | G11: OK
A12: 7 | B12: Ventes | C12: Alerte d'interactions | D12: 1. Activer l'alerte 2. Vendre deux produits qui interagissent | E12: Alerte affichée ; coupée par défaut | F12: Basse | G12: OK
A13: 8 | B13: Ventes | C13: Points fidélité | D13: 1. Client fidélité, case « Utiliser » 2. Régler en points | E13: Points déduits, restitués à l'annulation | F13: Moyenne | G13: Manuel
A14: 9 | B14: Ventes | C14: Nouveau client depuis la vente | D14: 1. « Nouveau client » dans la vente 2. Enregistrer | E14: Client créé sans erreur JavaScript | F14: Moyenne | G14: Manuel
A15: 10 | B15: Ventes terminées | C15: Modifier une vente | D15: 1. Ventes terminées > Modifier 2. Changer, terminer | E15: Copie modifiée ; vente facturée ou différé réglé : refus avec la raison | F15: Haute | G15: OK
A16: 11 | B16: Ventes terminées | C16: Annuler une vente | D16: 1. Annuler 2. Annuler de nouveau | E16: Stock rendu, une seule annulation ; refus si en cours de modification ou différé réglé | F16: Haute | G16: OK
A17: 12 | B17: Ventes terminées | C17: Colonnes et retour | D17: 1. Ouvrir la liste, Modifier puis Retour | E17: Date et heure, « Différé », poste ; retour avec les mêmes critères | F17: Basse | G17: OK
A18: 13 | B18: Prévente | C18: Ticket de prévente scanné | D18: 1. Scanner le ticket en caisse | E18: Prévente retrouvée (même lu « 261025)00145 ») ; QR dans le rouleau | F18: Moyenne | G18: Manuel
A19: 14 | B19: Vente dépôt | C19: Vente à un dépôt | D19: 1. Nouvelle vente dépôt, articles, terminer | E19: Stocks officine et dépôt à jour ; historique cohérent | F19: Moyenne | G19: OK
A20: 15 | B20: Proforma | C20: Proforma | D20: 1. Nouveau proforma, client, articles, imprimer | E20: Aucun mouvement de stock | F20: Basse | G20: OK

Sheet Caisse et gestion courante
A1: Cahier de recette · Caisse et gestion courante | F1: Menu : GESTION COURANTE
A2: Branche : integration/recette-2026-10-29 · base de test : copie de travail, jamais la production
A3: Cas | B3: =COUNTA($A$6:$A$13) -> 8 | C3: OK | D3: =COUNTIF($H$6:$H$13,"OK") -> 0 | E3: KO | F3: =COUNTIF($H$6:$H$13,"KO") -> 0 | G3: Non testé | H3: =COUNTA($A$6:$A$13)-COUNTA($H$6:$H$13) -> 8 | I3: Auto OK / KO | J3: =COUNTIF($G$6:$G$13,"OK")&" / "&COUNTIF($G$6:$G$13,"KO") -> 2 / 0
A4: Remplir les cellules jaunes · Statut : OK, KO (décrire, ouvrir un ticket), Bloqué, N/A · Test auto : résultat des tests d'écran sur la branche
A5: N° | B5: Écran | C5: Cas à vérifier | D5: Étapes | E5: Résultat attendu | F5: Prio. | G5: Test auto | H5: Statut | I5: Testeur · date | J5: Observation / ticket
A6: 1 | B6: Ouverture / clôture | C6: Ouvrir puis clôturer la caisse | D6: 1. Ouvrir avec le fonds 2. Ventes 3. Clôturer | E6: Billetage et total conformes ; « négatif = manquant » | F6: Haute | G6: Manuel
A7: 2 | B7: Gestion de caisse | C7: Données du jour à l'ouverture | D7: 1. Ouvrir Gestion de caisse | E7: Données du jour affichées sans recherche | F7: Basse | G7: Manuel
A8: 3 | B8: Gestion de caisse | C8: Onglet Analyse des écarts | D8: 1. Ouvrir l'onglet | E8: Écarts par caissier et par jour | F8: Basse | G8: Manuel
A9: 4 | B9: Ticket Z | C9: Ticket Z | D9: 1. Éditer le Ticket Z du jour, imprimer | E9: Totaux = caisse ; écran sans iframe ; moins de 2 s | F9: Haute | G9: Manuel
A10: 5 | B10: Balance | C10: Balance vente / caisse PDF | D10: 1. Choisir la période, imprimer | E10: Officine centrée, « Imprimé le … par » en bas à droite, résumé sur deux colonnes | F10: Moyenne | G10: OK
A11: 6 | B11: Liste des caisses | C11: Impression de la liste | D11: 1. Imprimer un mois | E11: PDF en quelques secondes | F11: Basse | G11: Manuel
A12: 7 | B12: Mouvements de caisse | C12: Entrée / sortie et édition | D12: 1. Saisir un mouvement 2. Éditer | E12: Mouvement pris dans la clôture ; édition correcte | F12: Moyenne | G12: Manuel
A13: 8 | B13: Journal | C13: Journal complet | D13: 1. Filtrer par poste 2. Afficher les alertes | E13: Poste, IP, application ; annulations en série signalées | F13: Basse | G13: OK

Sheet Facturation et différés
A1: Cahier de recette · Facturation et différés | F1: Menu : FACTURATION
A2: Branche : integration/recette-2026-10-29 · base de test : copie de travail, jamais la production
A3: Cas | B3: =COUNTA($A$6:$A$14) -> 9 | C3: OK | D3: =COUNTIF($H$6:$H$14,"OK") -> 0 | E3: KO | F3: =COUNTIF($H$6:$H$14,"KO") -> 0 | G3: Non testé | H3: =COUNTA($A$6:$A$14)-COUNTA($H$6:$H$14) -> 9 | I3: Auto OK / KO | J3: =COUNTIF($G$6:$G$14,"OK")&" / "&COUNTIF($G$6:$G$14,"KO") -> 8 / 0
A4: Remplir les cellules jaunes · Statut : OK, KO (décrire, ouvrir un ticket), Bloqué, N/A · Test auto : résultat des tests d'écran sur la branche
A5: N° | B5: Écran | C5: Cas à vérifier | D5: Étapes | E5: Résultat attendu | F5: Prio. | G5: Test auto | H5: Statut | I5: Testeur · date | J5: Observation / ticket
A6: 1 | B6: Différés | C6: Régler un différé | D6: 1. Choisir le client 2. Règlement partiel puis total | E6: Solde exact ; contrôles du serveur (appartenance, montant, total) | F6: Haute | G6: OK
A7: 2 | B7: Différés | C7: Modifier une vente différée | D7: 1. Modifier une vente différée non réglée | E7: Solde recalculé, aucune dette en double | F7: Haute | G7: OK
A8: 3 | B8: Différés | C8: Solde et relevé PDF / Excel | D8: 1. Onglet Solde, période 2. Imprimer, exporter | E8: Montants « 4 000 » avec séparateur ; mêmes chiffres qu'à l'écran | F8: Moyenne | G8: OK
A9: 4 | B9: Factures | C9: Générer les factures | D9: 1. Générer pour un organisme | E9: Numérotation sans doublon, même en concurrence | F9: Haute | G9: OK
A10: 5 | B10: Factures | C10: Cachet / signature | D10: 1. Imprimer une facture | E10: Cachet / signature à la place de « LE PHARMACIEN » | F10: Basse | G10: Manuel
A11: 6 | B11: Factures | C11: Icônes de la liste | D11: 1. Ouvrir la liste des factures et des factures de groupe | E11: Icônes au trait (supprimer, régler, verrou, certifier) | F11: Basse | G11: OK
A12: 7 | B12: Factures subrogatoires | C12: Liste et impression | D12: 1. Période, recherche, imprimer | E12: Mêmes ventes que l'ancienne liste ; PDF en onglet | F12: Moyenne | G12: OK
A13: 8 | B13: Règlements | C13: Liste des règlements | D13: 1. Filtrer, imprimer | E13: Règlements de la période, totaux justes | F13: Moyenne | G13: OK
A14: 9 | B14: Récap organisme | C14: Récapitulatif par organisme | D14: 1. Choisir l'organisme et la période | E14: Totaux = factures ; édition PDF | F14: Basse | G14: OK

Sheet Tiers-payants et clients
A1: Cahier de recette · Tiers-payants et clients | F1: Menu : GESTION DES TIERS-PAYANTS · GESTION CLIENT
A2: Branche : integration/recette-2026-10-29 · base de test : copie de travail, jamais la production
A3: Cas | B3: =COUNTA($A$6:$A$15) -> 10 | C3: OK | D3: =COUNTIF($H$6:$H$15,"OK") -> 0 | E3: KO | F3: =COUNTIF($H$6:$H$15,"KO") -> 0 | G3: Non testé | H3: =COUNTA($A$6:$A$15)-COUNTA($H$6:$H$15) -> 10 | I3: Auto OK / KO | J3: =COUNTIF($G$6:$G$15,"OK")&" / "&COUNTIF($G$6:$G$15,"KO") -> 8 / 0
A4: Remplir les cellules jaunes · Statut : OK, KO (décrire, ouvrir un ticket), Bloqué, N/A · Test auto : résultat des tests d'écran sur la branche
A5: N° | B5: Écran | C5: Cas à vérifier | D5: Étapes | E5: Résultat attendu | F5: Prio. | G5: Test auto | H5: Statut | I5: Testeur · date | J5: Observation / ticket
A6: 1 | B6: Fiche client | C6: Assurances complémentaires | D6: 1. Fiche client > assurances 2. Modifier taux, matricule, priorité | E6: Enregistrés ; priorité unique contrôlée | F6: Haute | G6: OK
A7: 2 | B7: Fiche client | C7: Nouveau tiers payant principal | D7: 1. Associer un nouveau RO | E7: Ancien RO gardé actif, priorités cohérentes | F7: Haute | G7: OK
A8: 3 | B8: Vente | C8: Modifier le tiers payant d'une vente | D8: 1. Vente en cours > Modifier le tiers-payant | E8: Pas d'erreur ; part de la vente gardée au même taux | F8: Haute | G8: OK
A9: 4 | B9: Vente en dépôt | C9: Grille des complémentaires | D9: 1. Vente en dépôt, client 2. Modifier la grille | E9: Mêmes contrôles que la fiche client ; fenêtres qui se ferment | F9: Moyenne | G9: OK
A10: 5 | B10: Clients | C10: Recherche « commence par / contient » | D10: 1. Rechercher un client par un morceau du nom | E10: Trouvé en « Contient » seulement ; téléphone avec ou sans séparateurs | F10: Moyenne | G10: OK
A11: 6 | B11: Clients | C11: Import et filtre Type client | D11: 1. « Importer » 2. Filtrer par type | E11: Un seul bouton Importer, filtre séparé de la recherche | F11: Basse | G11: Manuel
A12: 7 | B12: Carnet dépôt | C12: Gérer carnet dépôt | D12: 1. Choisir un carnet | E12: Seuls les carnets en dépôt sont proposés ; recherche lancée | F12: Moyenne | G12: OK
A13: 8 | B13: Carnet dépôt | C13: Retour carnet scanné | D13: 1. Nouveau retour, scanner le produit | E13: Code lu encodé (« / » et « # » acceptés) | F13: Basse | G13: OK
A14: 9 | B14: Tiers payants désactivés | C14: Liste | D14: 1. Ouvrir, rechercher | E14: Liste remplie, recherche OK | F14: Basse | G14: Manuel
A15: 10 | B15: Suivi dossier client | C15: Fiche et suivi de consommation | D15: 1. Ouvrir un client 2. Par vente / par produit | E15: Date de naissance et sexe complétables, suivi correct | F15: Basse | G15: OK

Sheet Commandes et PharmaML
A1: Cahier de recette · Commandes et PharmaML | F1: Menu : GESTION DES COMMANDES
A2: Branche : integration/recette-2026-10-29 · base de test : copie de travail, jamais la production
A3: Cas | B3: =COUNTA($A$6:$A$16) -> 11 | C3: OK | D3: =COUNTIF($H$6:$H$16,"OK") -> 0 | E3: KO | F3: =COUNTIF($H$6:$H$16,"KO") -> 0 | G3: Non testé | H3: =COUNTA($A$6:$A$16)-COUNTA($H$6:$H$16) -> 11 | I3: Auto OK / KO | J3: =COUNTIF($G$6:$G$16,"OK")&" / "&COUNTIF($G$6:$G$16,"KO") -> 8 / 1
A4: Remplir les cellules jaunes · Statut : OK, KO (décrire, ouvrir un ticket), Bloqué, N/A · Test auto : résultat des tests d'écran sur la branche
A5: N° | B5: Écran | C5: Cas à vérifier | D5: Étapes | E5: Résultat attendu | F5: Prio. | G5: Test auto | H5: Statut | I5: Testeur · date | J5: Observation / ticket
A6: 1 | B6: Suggestion | C6: Créer une suggestion (grand volume) | D6: 1. Analyse tiers payant ou articles vendus 2. « Créer une suggestion » | E6: Suggestion créée en moins d'une minute (4 186 produits : 21 s) | F6: Haute | G6: OK
A7: 2 | B7: Suggestion | C7: Produit géré en réserve | D7: 1. Vendre un produit en réserve | E7: Comparé au seuil avec rayon + réserve ; réassort plafonné au rayon | F7: Moyenne | G7: OK
A8: 3 | B8: Suggestion | C8: Équivalents DCI | D8: 1. Ouvrir une suggestion 2. « Équivalents DCI » | E8: Couverture, retrait, reliquat commandé, journal | F8: Moyenne | G8: OK
A9: 4 | B9: PharmaML | C9: Commander par PharmaML | D9: 1. « Commander » au bas de la suggestion | E9: Envoi en arrière-plan, statut et réponse sur la ligne | F9: Haute | G9: OK
A10: 5 | B10: Commandes en cours | C10: Onglets Ruptures, Substitutions, Alertes | D10: 1. Ouvrir les onglets | E10: Ruptures (heure, motif), substitutions suivies, alertes | F10: Moyenne | G10: OK
A11: 6 | B11: Commandes en cours | C11: Supprimer une commande | D11: 1. Icône de suppression, 2e clic | E11: Confirmation dans l'icône, pas de fenêtre ; pas d'erreur au 2e envoi | F11: Moyenne | G11: Manuel
A12: 7 | B12: Commandes en cours | C12: Import de commande annulé | D12: 1. Importer, puis Annuler | E12: Rien de créé, écran propre | F12: Basse | G12: OK
A13: 8 | B13: Entrée en stock | C13: Entrée d'un BL | D13: 1. Entrer le BL 2. Prix, lots, réserve | E13: Stocks, prix et lots justes ; suggestion de réserve ouverte au seuil | F13: Haute | G13: KO | J13: KO : test-prix-bl
A14: 9 | B14: Pointage BL | C14: Pointer les BL / avoirs | D14: 1. Importer le relevé du grossiste | E14: Rapprochement BL / avoirs, colonnes mémorisées par grossiste | F14: Moyenne | G14: Manuel
A15: 10 | B15: Péremptions courtes | C15: Écran et exports | D15: 1. Filtrer, changer un statut dans la grille 2. Excel, PDF | E15: Statut enregistré sans fenêtre ; exports corrects | F15: Basse | G15: OK
A16: 11 | B16: Retours fournisseurs | C16: Retour par utilisateur | D16: 1. Filtrer par utilisateur 2. Tableau de bord, impression | E16: Stock jamais négatif ; retours par utilisateur | F16: Moyenne | G16: OK

Sheet Stock
A1: Cahier de recette · Stock | F1: Menu : GESTION DU STOCK
A2: Branche : integration/recette-2026-10-29 · base de test : copie de travail, jamais la production
A3: Cas | B3: =COUNTA($A$6:$A$15) -> 10 | C3: OK | D3: =COUNTIF($H$6:$H$15,"OK") -> 0 | E3: KO | F3: =COUNTIF($H$6:$H$15,"KO") -> 0 | G3: Non testé | H3: =COUNTA($A$6:$A$15)-COUNTA($H$6:$H$15) -> 10 | I3: Auto OK / KO | J3: =COUNTIF($G$6:$G$15,"OK")&" / "&COUNTIF($G$6:$G$15,"KO") -> 7 / 0
A4: Remplir les cellules jaunes · Statut : OK, KO (décrire, ouvrir un ticket), Bloqué, N/A · Test auto : résultat des tests d'écran sur la branche
A5: N° | B5: Écran | C5: Cas à vérifier | D5: Étapes | E5: Résultat attendu | F5: Prio. | G5: Test auto | H5: Statut | I5: Testeur · date | J5: Observation / ticket
A6: 1 | B6: Fiche article | C6: Détail, courbes, comparaison | D6: 1. Ouvrir un article vendu sur 2 ans 2. Courbes, « Comparer » | E6: Comparaison des années, sections conservées | F6: Moyenne | G6: OK
A7: 2 | B7: Fiche article | C7: Lots et péremptions | D7: 1. Voir les lots 2. Supprimer un lot (2 clics) | E7: Lot supprimé, liste rechargée ; « Qté restante lot » | F7: Moyenne | G7: OK
A8: 3 | B8: Fiche article | C8: Dernière entrée et EAN fabricant | D8: 1. Ouvrir Modifier et Détail | E8: Dern. entrée = mise en stock ; EAN en lecture seule au détail | F8: Basse | G8: OK
A9: 4 | B9: Inventaire | C9: Inventaire partiel, saisie, clôture | D9: 1. Créer par lettres du nom 2. Saisir, clôturer | E9: Aucune saisie après clôture ; auteur enregistré | F9: Haute | G9: Manuel
A10: 5 | B10: Ajustement | C10: Ajustement du stock | D10: 1. Créer, clôturer | E10: Une seule clôture, pas d'annulation après | F10: Moyenne | G10: Manuel
A11: 6 | B11: Réserve | C11: Suggestions de réassort | D11: 1. Ouvrir la réserve 2. Suggestions | E11: Réassort proposé, icônes dessinées | F11: Moyenne | G11: OK
A12: 7 | B12: Emplacements | C12: Basculement d'emplacement | D12: 1. Basculer depuis une ligne | E12: Origine en tête, produits actifs seulement | F12: Basse | G12: OK
A13: 8 | B13: Périmés | C13: Saisie et onglet Analyse | D13: 1. Saisir des périmés 2. Analyse : objectif, intervalles | E13: Taux vs objectif, intervalles = total de la période | F13: Moyenne | G13: OK
A14: 9 | B14: Déconditionnement | C14: Historique des mouvements | D14: 1. Vendre au détail une boîte ouverte | E14: Chaîne cohérente : ouverture puis vente | F14: Moyenne | G14: OK
A15: 10 | B15: Comparaison stock | C15: Exports et impression | D15: 1. Exporter Excel / CSV, imprimer | E15: Quelques secondes (327 s avant) | F15: Basse | G15: Manuel

Sheet Étiquettes
A1: Cahier de recette · Étiquettes | F1: Menu : GESTION DU STOCK > Étiquettage Pro
A2: Branche : integration/recette-2026-10-29 · base de test : copie de travail, jamais la production
A3: Cas | B3: =COUNTA($A$6:$A$12) -> 7 | C3: OK | D3: =COUNTIF($H$6:$H$12,"OK") -> 0 | E3: KO | F3: =COUNTIF($H$6:$H$12,"KO") -> 0 | G3: Non testé | H3: =COUNTA($A$6:$A$12)-COUNTA($H$6:$H$12) -> 7 | I3: Auto OK / KO | J3: =COUNTIF($G$6:$G$12,"OK")&" / "&COUNTIF($G$6:$G$12,"KO") -> 4 / 0
A4: Remplir les cellules jaunes · Statut : OK, KO (décrire, ouvrir un ticket), Bloqué, N/A · Test auto : résultat des tests d'écran sur la branche
A5: N° | B5: Écran | C5: Cas à vérifier | D5: Étapes | E5: Résultat attendu | F5: Prio. | G5: Test auto | H5: Statut | I5: Testeur · date | J5: Observation / ticket
A6: 1 | B6: Étiquettage Pro | C6: Imprimer depuis une entrée en stock | D6: 1. Entrée en stock > étiquettes | E6: Écran épuré, « Retour à commande en cours » | F6: Moyenne | G6: OK
A7: 2 | B7: Étiquettage Pro | C7: Lire une étiquette | D7: 1. « Lire une étiquette », scanner deux fois de suite | E7: Aucun chiffre perdu, produit reconnu | F7: Haute | G7: Manuel
A8: 3 | B8: Étiquettage Pro | C8: Codes GS1 QR / DataMatrix | D8: 1. Imprimer une planche GS1 | E8: Codes lisibles, informations à gauche | F8: Moyenne | G8: OK
A9: 4 | B9: Étiquettage Pro | C9: Personnalisation de la disposition | D9: 1. Modifier la disposition, valider 2. Imprimer | E9: Disposition appliquée ; droit réservé à l'administrateur | F9: Moyenne | G9: OK
A10: 5 | B10: Étiquettage Pro | C10: Saisie à la main | D10: 1. Rechercher, choisir le lot, quantité au clavier | E10: Enchaînement au clavier sans souris | F10: Basse | G10: Manuel
A11: 6 | B11: Étiquettage Pro | C11: Types d'étiquette | D11: 1. Filtrer, cocher des produits | E11: Filtres sur une ligne, mise à jour sélective | F11: Basse | G11: Manuel
A12: 7 | B12: Ancien menu Gestion étiquette | C12: Passerelle | D12: 1. Ouvrir l'ancien menu | E12: 7 derniers jours par défaut ; impression par Étiquettage Pro | F12: Basse | G12: OK

Sheet Analyse et pilotage
A1: Cahier de recette · Analyse et pilotage | F1: Menu : ANALYSE DE GESTION
A2: Branche : integration/recette-2026-10-29 · base de test : copie de travail, jamais la production
A3: Cas | B3: =COUNTA($A$6:$A$15) -> 10 | C3: OK | D3: =COUNTIF($H$6:$H$15,"OK") -> 0 | E3: KO | F3: =COUNTIF($H$6:$H$15,"KO") -> 0 | G3: Non testé | H3: =COUNTA($A$6:$A$15)-COUNTA($H$6:$H$15) -> 10 | I3: Auto OK / KO | J3: =COUNTIF($G$6:$G$15,"OK")&" / "&COUNTIF($G$6:$G$15,"KO") -> 6 / 0
A4: Remplir les cellules jaunes · Statut : OK, KO (décrire, ouvrir un ticket), Bloqué, N/A · Test auto : résultat des tests d'écran sur la branche
A5: N° | B5: Écran | C5: Cas à vérifier | D5: Étapes | E5: Résultat attendu | F5: Prio. | G5: Test auto | H5: Statut | I5: Testeur · date | J5: Observation / ticket
A6: 1 | B6: Tableau de bord | C6: Tuiles et courbes | D6: 1. Ouvrir le tableau de bord | E6: Mêmes chiffres que l'ancien ; valorisation rayon et total | F6: Haute | G6: OK
A7: 2 | B7: Tableau de bord | C7: Carte d'affluence | D7: 1. Choisir une semaine | E7: Carte jour × heure correcte | F7: Basse | G7: Manuel
A8: 3 | B8: Pilotage | C8: Onglets À suivre, Stock, Qualité | D8: 1. Ouvrir chaque onglet | E8: Chiffres = base (annulations, péremptions < 6 mois) | F8: Moyenne | G8: OK
A9: 4 | B9: Pilotage | C9: Rentabilité | D9: 1. Saisir les charges du mois | E9: Résultat net calculé | F9: Basse | G9: Manuel
A10: 5 | B10: Audit & rapprochements | C10: Analyse, rapports, régularisations | D10: 1. Proposer, commenter, valider | E10: Sans commentaire : refus ; appliquées une seule fois, journalisées | F10: Haute | G10: OK
A11: 6 | B11: Statistiques | C11: Familles, rayons, grossistes | D11: 1. Période sans vente puis normale | E11: Aucune erreur ; résultats en quelques secondes | F11: Moyenne | G11: Manuel
A12: 7 | B12: CA par zone / dépôt | C12: CA et PDF par laboratoire | D12: 1. Filtres multiples, imprimer | E12: Noms des filtres sur l'édition, montants « 1 234 » | F12: Basse | G12: OK
A13: 8 | B13: Activité des équipes | C13: Données et analyses | D13: 1. Filtrer, « Vider les champs » | E13: Pastilles stables, infobulles entières | F13: Basse | G13: Manuel
A14: 9 | B14: Anomalies par employé | C14: Onglet Anomalies | D14: 1. Ouvrir, filtrer un employé | E14: Chaque occurrence et son fil d'actions | F14: Basse | G14: OK
A15: 10 | B15: Rappels traitement | C15: Onglet Analyse et exports | D15: 1. Ouvrir, exporter PDF / CSV | E15: Analyse et exports corrects | F15: Basse | G15: OK

Sheet Campagnes et avis clients
A1: Cahier de recette · Campagnes et avis clients | F1: Menu : CAMPAGNES SMS / WHATSAPP · AVIS CLIENTS
A2: Branche : integration/recette-2026-10-29 · base de test : copie de travail, jamais la production
A3: Cas | B3: =COUNTA($A$6:$A$11) -> 6 | C3: OK | D3: =COUNTIF($H$6:$H$11,"OK") -> 0 | E3: KO | F3: =COUNTIF($H$6:$H$11,"KO") -> 0 | G3: Non testé | H3: =COUNTA($A$6:$A$11)-COUNTA($H$6:$H$11) -> 6 | I3: Auto OK / KO | J3: =COUNTIF($G$6:$G$11,"OK")&" / "&COUNTIF($G$6:$G$11,"KO") -> 0 / 0
A4: Remplir les cellules jaunes · Statut : OK, KO (décrire, ouvrir un ticket), Bloqué, N/A · Test auto : résultat des tests d'écran sur la branche
A5: N° | B5: Écran | C5: Cas à vérifier | D5: Étapes | E5: Résultat attendu | F5: Prio. | G5: Test auto | H5: Statut | I5: Testeur · date | J5: Observation / ticket
A6: 1 | B6: Campagnes | C6: Campagne WhatsApp avec pièce jointe | D6: 1. Nouvelle campagne, image ou PDF 2. Envoyer | E6: WhatsApp par défaut, suivi des envois | F6: Moyenne | G6: Manuel
A7: 2 | B7: Campagnes | C7: Listes de diffusion et automatiques | D7: 1. Créer une liste 2. Régler un envoi automatique | E7: 10 onglets ; délai de réponse paramétrable | F7: Basse | G7: Manuel
A8: 3 | B8: Discussions | C8: Réponses clients et STOP | D8: 1. Un client répond STOP | E8: Fil de discussion, motif STOP visible, plus d'envoi | F8: Haute | G8: Manuel
A9: 4 | B9: Bannière WhatsApp | C9: Session à reconnecter | D9: 1. Couper le service WhatsApp | E9: Toast pour l'administrateur seulement, « Reconnecter » relance | F9: Moyenne | G9: Manuel
A10: 5 | B10: Avis clients | C10: Saisie publique et analyse | D10: 1. Saisir un avis par la page publique 2. Analyse, réglages, affiche | E10: Avis enregistré, analyse et affiche PDF | F10: Basse | G10: Manuel
A11: 6 | B11: Sécurité | C11: Jetons hors du navigateur | D11: 1. Ouvrir les écrans (outils du navigateur) | E11: Aucun jeton WhatsApp ni identifiant SMS côté navigateur | F11: Haute | G11: Manuel

Sheet Ressources humaines
A1: Cahier de recette · Ressources humaines | F1: Menu : RESSOURCES HUMAINES
A2: Branche : integration/recette-2026-10-29 · base de test : copie de travail, jamais la production
A3: Cas | B3: =COUNTA($A$6:$A$12) -> 7 | C3: OK | D3: =COUNTIF($H$6:$H$12,"OK") -> 0 | E3: KO | F3: =COUNTIF($H$6:$H$12,"KO") -> 0 | G3: Non testé | H3: =COUNTA($A$6:$A$12)-COUNTA($H$6:$H$12) -> 7 | I3: Auto OK / KO | J3: =COUNTIF($G$6:$G$12,"OK")&" / "&COUNTIF($G$6:$G$12,"KO") -> 0 / 0
A4: Remplir les cellules jaunes · Statut : OK, KO (décrire, ouvrir un ticket), Bloqué, N/A · Test auto : résultat des tests d'écran sur la branche
A5: N° | B5: Écran | C5: Cas à vérifier | D5: Étapes | E5: Résultat attendu | F5: Prio. | G5: Test auto | H5: Statut | I5: Testeur · date | J5: Observation / ticket
A6: 1 | B6: Employés | C6: Créer un employé depuis un utilisateur | D6: 1. Nouvel employé, choisir l'utilisateur | E6: Fiche en fenêtre modale | F6: Moyenne | G6: Manuel
A7: 2 | B7: Badges | C7: Créer et imprimer un badge | D7: 1. Créer, imprimer (une carte par page) | E7: N° PRE-AA-NNNNN-C, QR centré, nom sur une ligne | F7: Moyenne | G7: Manuel
A8: 3 | B8: Badges | C8: Régénérer un badge | D8: 1. Régénérer le QR 2. Scanner l'ancien | E8: Ancien refusé ; réimpression identique sinon | F8: Haute | G8: Manuel
A9: 4 | B9: Pointage | C9: Pointer avec l'application | D9: 1. Pointer par QR + GPS | E9: Pointage enregistré avec photo de contrôle | F9: Moyenne | G9: Manuel
A10: 5 | B10: Bornes de pointage | C10: Enrôler une borne | D10: 1. Onglet Bornes, enrôler | E10: Appels signés acceptés sans session | F10: Basse | G10: Manuel
A11: 6 | B11: Demandes | C11: Valider une demande | D11: 1. Profil sans droit puis avec | E11: Chacun ne voit que ses demandes ; validation selon le droit | F11: Moyenne | G11: Manuel
A12: 7 | B12: Éditions | C12: PDF de chaque onglet | D12: 1. Imprimer chaque onglet | E12: PDF lisibles | F12: Basse | G12: Manuel

Sheet Support et serveur
A1: Cahier de recette · Support et serveur | F1: Menu : CENTRE DE SUPPORT
A2: Branche : integration/recette-2026-10-29 · base de test : copie de travail, jamais la production
A3: Cas | B3: =COUNTA($A$6:$A$11) -> 6 | C3: OK | D3: =COUNTIF($H$6:$H$11,"OK") -> 0 | E3: KO | F3: =COUNTIF($H$6:$H$11,"KO") -> 0 | G3: Non testé | H3: =COUNTA($A$6:$A$11)-COUNTA($H$6:$H$11) -> 6 | I3: Auto OK / KO | J3: =COUNTIF($G$6:$G$11,"OK")&" / "&COUNTIF($G$6:$G$11,"KO") -> 2 / 2
A4: Remplir les cellules jaunes · Statut : OK, KO (décrire, ouvrir un ticket), Bloqué, N/A · Test auto : résultat des tests d'écran sur la branche
A5: N° | B5: Écran | C5: Cas à vérifier | D5: Étapes | E5: Résultat attendu | F5: Prio. | G5: Test auto | H5: Statut | I5: Testeur · date | J5: Observation / ticket
A6: 1 | B6: Stabilité du serveur | C6: État, arrêts, réglages | D6: 1. Ouvrir l'écran | E6: Tuiles mémoire, base, pool ; courbes ; lexique | F6: Moyenne | G6: OK
A7: 2 | B7: Diagnostic & bugs | C7: Aucune nouvelle erreur | D7: 1. Après la recette, ouvrir le diagnostic | E7: Pas de nouvelle erreur due aux tests | F7: Haute | G7: KO | J7: KO : test-saisie-ecrans
A8: 3 | B8: Détails de vente | C8: Lignes d'une vente | D8: 1. Ouvrir le détail, actualiser | E8: Réponse immédiate, lignes gardées | F8: Moyenne | G8: OK
A9: 4 | B9: Anomalies lot 1 et 4 | C9: Corrections du centre de support | D9: 1. Rejouer les cas (proforma sans client, findone…) | E9: Plus d'erreur ; réponses lisibles | F9: Moyenne | G9: KO | J9: KO : test-lot1-ecrans
A10: 5 | B10: Auto-diagnostic | C10: Migrations et contrôle de nuit | D10: 1. Ouvrir l'auto-diagnostic | E10: Migration en échec signalée ; pas de fausse alerte quotidienne | F10: Basse | G10: Manuel
A11: 6 | B11: Journaux | C11: Aucun secret | D11: 1. Lire server.log après la recette | E11: Ni mot de passe, ni jeton, ni texte de message patient | F11: Haute | G11: Manuel

Sheet Performances et charge
A1: Cahier de recette · Performances et charge | F1: Menu : Tous menus
A2: Branche : integration/recette-2026-10-29 · base de test : copie de travail, jamais la production
A3: Cas | B3: =COUNTA($A$6:$A$11) -> 6 | C3: OK | D3: =COUNTIF($H$6:$H$11,"OK") -> 0 | E3: KO | F3: =COUNTIF($H$6:$H$11,"KO") -> 0 | G3: Non testé | H3: =COUNTA($A$6:$A$11)-COUNTA($H$6:$H$11) -> 6 | I3: Auto OK / KO | J3: =COUNTIF($G$6:$G$11,"OK")&" / "&COUNTIF($G$6:$G$11,"KO") -> 1 / 3
A4: Remplir les cellules jaunes · Statut : OK, KO (décrire, ouvrir un ticket), Bloqué, N/A · Test auto : résultat des tests d'écran sur la branche
A5: N° | B5: Écran | C5: Cas à vérifier | D5: Étapes | E5: Résultat attendu | F5: Prio. | G5: Test auto | H5: Statut | I5: Testeur · date | J5: Observation / ticket
A6: 1 | B6: Connexion | C6: 15 postes en même temps | D6: 1. Connecter 15 postes ensemble | E6: Tous connectés en quelques secondes (scripts en un seul appel) | F6: Haute | G6: OK
A7: 2 | B7: Ventes | C7: Ventes simultanées du même article | D7: 1. Deux caisses vendent le même article | E7: Stock exact, aucune vente perdue | F7: Haute | G7: Manuel
A8: 3 | B8: Écrans | C8: Ouverture des écrans principaux | D8: 1. Ouvrir Ventes, Pilotage, Fiche article | E8: Utilisables en moins de 3 s | F8: Moyenne | G8: KO | J8: KO : test-defilement-ecrans
A9: 4 | B9: Lectures | C9: Aucune lecture de plus de 30 s | D9: 1. Parcourir les écrans de liste | E9: Toutes les listes en moins de 30 s (lots sans filtre à surveiller) | F9: Moyenne | G9: KO | J9: KO : test-saisie-api
A10: 5 | B10: Exports | C10: Exports lourds | D10: 1. Export ERP d'une semaine 2. Comparaison stock | E10: Quelques secondes au lieu de plusieurs minutes | F10: Basse | G10: Manuel
A11: 6 | B11: Mobile | C11: Application mobile | D11: 1. Infos produit, BL de 500 lignes | E11: Réponses en 1 à 3 s | F11: Moyenne | G11: KO | J11: KO : test-mobile-54-55

Sheet Éditions et modèles
A1: Cahier de recette · Éditions et modèles | F1: Menu : Toutes éditions
A2: Branche : integration/recette-2026-10-29 · base de test : copie de travail, jamais la production
A3: Cas | B3: =COUNTA($A$6:$A$10) -> 5 | C3: OK | D3: =COUNTIF($H$6:$H$10,"OK") -> 0 | E3: KO | F3: =COUNTIF($H$6:$H$10,"KO") -> 0 | G3: Non testé | H3: =COUNTA($A$6:$A$10)-COUNTA($H$6:$H$10) -> 5 | I3: Auto OK / KO | J3: =COUNTIF($G$6:$G$10,"OK")&" / "&COUNTIF($G$6:$G$10,"KO") -> 4 / 0
A4: Remplir les cellules jaunes · Statut : OK, KO (décrire, ouvrir un ticket), Bloqué, N/A · Test auto : résultat des tests d'écran sur la branche
A5: N° | B5: Écran | C5: Cas à vérifier | D5: Étapes | E5: Résultat attendu | F5: Prio. | G5: Test auto | H5: Statut | I5: Testeur · date | J5: Observation / ticket
A6: 1 | B6: Modèles d'état | C6: Modèles du dossier des rapports | D6: 1. Comparer le dossier REPORTS du serveur au dépôt | E6: balance, analyse d'inventaire, garde : version du dépôt | F6: Haute | G6: OK
A7: 2 | B7: Montants | C7: Séparateur des milliers | D7: 1. Imprimer relevé de différés, carnet, récap caisse | E7: « 4 000 » et non « 4000 » | F7: Moyenne | G7: OK
A8: 3 | B8: Dossier PDF | C8: Dossier des éditions | D8: 1. Démarrer sur un serveur neuf 2. Imprimer | E8: data/reports/pdf créé automatiquement | F8: Moyenne | G8: Manuel
A9: 4 | B9: Ouverture | C9: PDF en onglet | D9: 1. Imprimer depuis différents écrans | E9: PDF ouvert dans un onglet, en flux | F9: Basse | G9: OK
A10: 5 | B10: Filtres | C10: Noms des filtres sur les éditions | D10: 1. Filtrer rayons / familles, imprimer | E10: Filtres repris en en-tête | F10: Basse | G10: OK
