Workbook

Sheet Mode d'emploi
A1: Cahier de recette complet : tests d'écran de la branche d'intégration
A3: Version testée | B3: Branche integration/recette-2026-10-29, déployée sur le poste local (domain1, http://localhost:8080/prestige), copie de travail laborex_v1_db.
A4: Résultat de Claude | B4: 422 tests joués par l'écran, 369 OK, 53 en échec. Chaque test a été joué seul, par le vrai chemin de l'écran, et retire ses données à la fin.
A5: Base | B5: Une copie de travail uniquement, jamais une base de production.
A6: Une ligne | B6: Un test d'écran. « Scénario » dit ce qui est fait et ce qui est attendu ; « Contrôles faits par Claude » liste chaque vérification (✓ conforme, ✗ écart) avec la valeur mesurée entre crochets.
A7: À remplir | B7: Rejouer le scénario à l'écran, noter ce que vous voyez dans « Résultat testeur », choisir le « Statut testeur » (OK, Échec, Bloqué, Non joué), votre nom et la date.
A8: Comparaison | B8: « Concorde ? » se remplit seul : « Oui » si votre statut est celui de Claude, « Non » sinon (ligne en jaune) ; ce sont ces lignes à examiner ensemble.
A9: Catégorie et suite | B9: Pour les échecs déjà triés : la cause retenue et ce qui est prévu.
A10: Onglets | B10: Synthèse, puis un onglet par module (dossier des tests).

Sheet Synthèse
A1: SYNTHÈSE — 422 tests, 369 OK, 53 en échec selon Claude
A3: Module | B3: N° | C3: Tests | D3: OK Claude | E3: Échec Claude | F3: Joués testeur | G3: Concordants | H3: Discordants
A4: Achats et contrôles | B4: 1 à 2 | C4: 2 | D4: 2 | E4: 0 | F4: =COUNTA('Achats et contrôles'!$I$5:$I$6) | G4: =COUNTIF('Achats et contrôles'!$L$5:$L$6,"Oui") | H4: =COUNTIF('Achats et contrôles'!$L$5:$L$6,"Non")
A5: Analyses | B5: 3 à 6 | C5: 4 | D5: 4 | E5: 0 | F5: =COUNTA('Analyses'!$I$5:$I$8) | G5: =COUNTIF('Analyses'!$L$5:$L$8,"Oui") | H5: =COUNTIF('Analyses'!$L$5:$L$8,"Non")
A6: Audit | B6: 7 à 9 | C6: 3 | D6: 3 | E6: 0 | F6: =COUNTA('Audit'!$I$5:$I$7) | G6: =COUNTIF('Audit'!$L$5:$L$7,"Oui") | H6: =COUNTIF('Audit'!$L$5:$L$7,"Non")
A7: Corrections d'audit | B7: 10 à 23 | C7: 14 | D7: 14 | E7: 0 | F7: =COUNTA('Corrections d'audit'!$I$5:$I$18) | G7: =COUNTIF('Corrections d'audit'!$L$5:$L$18,"Oui") | H7: =COUNTIF('Corrections d'audit'!$L$5:$L$18,"Non")
A8: Caisse | B8: 24 à 25 | C8: 2 | D8: 2 | E8: 0 | F8: =COUNTA('Caisse'!$I$5:$I$6) | G8: =COUNTIF('Caisse'!$L$5:$L$6,"Oui") | H8: =COUNTIF('Caisse'!$L$5:$L$6,"Non")
A9: Campagnes et WhatsApp | B9: 26 à 33 | C9: 8 | D9: 7 | E9: 1 | F9: =COUNTA('Campagnes et WhatsApp'!$I$5:$I$12) | G9: =COUNTIF('Campagnes et WhatsApp'!$L$5:$L$12,"Oui") | H9: =COUNTIF('Campagnes et WhatsApp'!$L$5:$L$12,"Non")
A10: Carnet dépôt | B10: 34 à 34 | C10: 1 | D10: 1 | E10: 0 | F10: =COUNTA('Carnet dépôt'!$I$5:$I$5) | G10: =COUNTIF('Carnet dépôt'!$L$5:$L$5,"Oui") | H10: =COUNTIF('Carnet dépôt'!$L$5:$L$5,"Non")
A11: Clients | B11: 35 à 38 | C11: 4 | D11: 4 | E11: 0 | F11: =COUNTA('Clients'!$I$5:$I$8) | G11: =COUNTIF('Clients'!$L$5:$L$8,"Oui") | H11: =COUNTIF('Clients'!$L$5:$L$8,"Non")
A12: Ergonomie | B12: 39 à 41 | C12: 3 | D12: 3 | E12: 0 | F12: =COUNTA('Ergonomie'!$I$5:$I$7) | G12: =COUNTIF('Ergonomie'!$L$5:$L$7,"Oui") | H12: =COUNTIF('Ergonomie'!$L$5:$L$7,"Non")
A13: Espace produit | B13: 42 à 42 | C13: 1 | D13: 0 | E13: 1 | F13: =COUNTA('Espace produit'!$I$5:$I$5) | G13: =COUNTIF('Espace produit'!$L$5:$L$5,"Oui") | H13: =COUNTIF('Espace produit'!$L$5:$L$5,"Non")
A14: Menus et articles | B14: 43 à 43 | C14: 1 | D14: 1 | E14: 0 | F14: =COUNTA('Menus et articles'!$I$5:$I$5) | G14: =COUNTIF('Menus et articles'!$L$5:$L$5,"Oui") | H14: =COUNTIF('Menus et articles'!$L$5:$L$5,"Non")
A15: Étape 2 | B15: 44 à 44 | C15: 1 | D15: 1 | E15: 0 | F15: =COUNTA('Étape 2'!$I$5:$I$5) | G15: =COUNTIF('Étape 2'!$L$5:$L$5,"Oui") | H15: =COUNTIF('Étape 2'!$L$5:$L$5,"Non")
A16: Étape 3 | B16: 45 à 46 | C16: 2 | D16: 2 | E16: 0 | F16: =COUNTA('Étape 3'!$I$5:$I$6) | G16: =COUNTIF('Étape 3'!$L$5:$L$6,"Oui") | H16: =COUNTIF('Étape 3'!$L$5:$L$6,"Non")
A17: Étape 5 | B17: 47 à 47 | C17: 1 | D17: 1 | E17: 0 | F17: =COUNTA('Étape 5'!$I$5:$I$5) | G17: =COUNTIF('Étape 5'!$L$5:$L$5,"Oui") | H17: =COUNTIF('Étape 5'!$L$5:$L$5,"Non")
A18: Facturation | B18: 48 à 48 | C18: 1 | D18: 1 | E18: 0 | F18: =COUNTA('Facturation'!$I$5:$I$5) | G18: =COUNTIF('Facturation'!$L$5:$L$5,"Oui") | H18: =COUNTIF('Facturation'!$L$5:$L$5,"Non")
A19: Filtres des écrans | B19: 49 à 52 | C19: 4 | D19: 3 | E19: 1 | F19: =COUNTA('Filtres des écrans'!$I$5:$I$8) | G19: =COUNTIF('Filtres des écrans'!$L$5:$L$8,"Oui") | H19: =COUNTIF('Filtres des écrans'!$L$5:$L$8,"Non")
A20: Inventaire | B20: 53 à 53 | C20: 1 | D20: 1 | E20: 0 | F20: =COUNTA('Inventaire'!$I$5:$I$5) | G20: =COUNTIF('Inventaire'!$L$5:$L$5,"Oui") | H20: =COUNTIF('Inventaire'!$L$5:$L$5,"Non")
A21: Journal | B21: 54 à 65 | C21: 12 | D21: 10 | E21: 2 | F21: =COUNTA('Journal'!$I$5:$I$16) | G21: =COUNTIF('Journal'!$L$5:$L$16,"Oui") | H21: =COUNTIF('Journal'!$L$5:$L$16,"Non")
A22: Lot 3 | B22: 66 à 68 | C22: 3 | D22: 2 | E22: 1 | F22: =COUNTA('Lot 3'!$I$5:$I$7) | G22: =COUNTIF('Lot 3'!$L$5:$L$7,"Oui") | H22: =COUNTIF('Lot 3'!$L$5:$L$7,"Non")
A23: Lot 4 | B23: 69 à 70 | C23: 2 | D23: 2 | E23: 0 | F23: =COUNTA('Lot 4'!$I$5:$I$6) | G23: =COUNTIF('Lot 4'!$L$5:$L$6,"Oui") | H23: =COUNTIF('Lot 4'!$L$5:$L$6,"Non")
A24: Application mobile | B24: 71 à 71 | C24: 1 | D24: 0 | E24: 1 | F24: =COUNTA('Application mobile'!$I$5:$I$5) | G24: =COUNTIF('Application mobile'!$L$5:$L$5,"Oui") | H24: =COUNTIF('Application mobile'!$L$5:$L$5,"Non")
A25: Performances | B25: 72 à 82 | C25: 11 | D25: 8 | E25: 3 | F25: =COUNTA('Performances'!$I$5:$I$15) | G25: =COUNTIF('Performances'!$L$5:$L$15,"Oui") | H25: =COUNTIF('Performances'!$L$5:$L$15,"Non")
A26: Pilotage | B26: 83 à 83 | C26: 1 | D26: 1 | E26: 0 | F26: =COUNTA('Pilotage'!$I$5:$I$5) | G26: =COUNTIF('Pilotage'!$L$5:$L$5,"Oui") | H26: =COUNTIF('Pilotage'!$L$5:$L$5,"Non")
A27: Points du 28-10 | B27: 84 à 91 | C27: 8 | D27: 8 | E27: 0 | F27: =COUNTA('Points du 28-10'!$I$5:$I$12) | G27: =COUNTIF('Points du 28-10'!$L$5:$L$12,"Oui") | H27: =COUNTIF('Points du 28-10'!$L$5:$L$12,"Non")
A28: Productivité | B28: 92 à 97 | C28: 6 | D28: 6 | E28: 0 | F28: =COUNTA('Productivité'!$I$5:$I$10) | G28: =COUNTIF('Productivité'!$L$5:$L$10,"Oui") | H28: =COUNTIF('Productivité'!$L$5:$L$10,"Non")
A29: Divers | B29: 98 à 104 | C29: 7 | D29: 5 | E29: 2 | F29: =COUNTA('Divers'!$I$5:$I$11) | G29: =COUNTIF('Divers'!$L$5:$L$11,"Oui") | H29: =COUNTIF('Divers'!$L$5:$L$11,"Non")
A30: Récapitulatifs | B30: 105 à 105 | C30: 1 | D30: 1 | E30: 0 | F30: =COUNTA('Récapitulatifs'!$I$5:$I$5) | G30: =COUNTIF('Récapitulatifs'!$L$5:$L$5,"Oui") | H30: =COUNTIF('Récapitulatifs'!$L$5:$L$5,"Non")
A31: Règlements | B31: 106 à 106 | C31: 1 | D31: 1 | E31: 0 | F31: =COUNTA('Règlements'!$I$5:$I$5) | G31: =COUNTIF('Règlements'!$L$5:$L$5,"Oui") | H31: =COUNTIF('Règlements'!$L$5:$L$5,"Non")
A32: Retours des officines | B32: 107 à 388 | C32: 282 | D32: 245 | E32: 37 | F32: =COUNTA('Retours des officines'!$I$5:$I$286) | G32: =COUNTIF('Retours des officines'!$L$5:$L$286,"Oui") | H32: =COUNTIF('Retours des officines'!$L$5:$L$286,"Non")
A33: Sécurité | B33: 389 à 401 | C33: 13 | D33: 12 | E33: 1 | F33: =COUNTA('Sécurité'!$I$5:$I$17) | G33: =COUNTIF('Sécurité'!$L$5:$L$17,"Oui") | H33: =COUNTIF('Sécurité'!$L$5:$L$17,"Non")
A34: Stock | B34: 402 à 402 | C34: 1 | D34: 1 | E34: 0 | F34: =COUNTA('Stock'!$I$5:$I$5) | G34: =COUNTIF('Stock'!$L$5:$L$5,"Oui") | H34: =COUNTIF('Stock'!$L$5:$L$5,"Non")
A35: Centre de support | B35: 403 à 417 | C35: 15 | D35: 12 | E35: 3 | F35: =COUNTA('Centre de support'!$I$5:$I$19) | G35: =COUNTIF('Centre de support'!$L$5:$L$19,"Oui") | H35: =COUNTIF('Centre de support'!$L$5:$L$19,"Non")
A36: Ventes | B36: 418 à 422 | C36: 5 | D36: 5 | E36: 0 | F36: =COUNTA('Ventes'!$I$5:$I$9) | G36: =COUNTIF('Ventes'!$L$5:$L$9,"Oui") | H36: =COUNTIF('Ventes'!$L$5:$L$9,"Non")
A37: Total | C37: =SUM(C4:C36) | D37: =SUM(D4:D36) | E37: =SUM(E4:E36) | F37: =SUM(F4:F36) | G37: =SUM(G4:G36) | H37: =SUM(H4:H36)

Sheet Achats et contrôles
A1: CAHIER DE RECETTE — Achats et contrôles
A2: 2 tests : 2 OK, 0 en échec selon Claude
A4: N° | B4: Test | C4: Scénario : ce qui est fait et ce qui est attendu | D4: Contrôles faits par Claude (valeur mesurée) | E4: Résultat Claude | F4: Écart constaté par Claude | G4: Catégorie et suite | H4: Résultat testeur | I4: Statut testeur | J4: Testeur | K4: Date | L4: Concorde ? | M4: Commentaire
A5: 1 | B5: achats/test-controle-achats-inventaire.js | C5: ETAT DE CONTROLE DES ACHATS : INVENTAIRE D'UN BON (retours du 13/10, point 5). - un bon de livraison entre en stock RAYON : l'inventaire cree depuis la ligne est un inventaire de l'emplacement (type « emplacement »), pas un inventaire reserve, et chaque produit y part de son stock rayon ; - la question puis le resultat s'affichent EN ENTIER dans la page (bandeau), sans fenetre surgissante ; - « Annuler » ne cree rien. Par l'ecran, admin. Inventaires crees retires a la fin. | D5: 11 / 11 conformes ✓ Précondition : un bon avec des produits en stock [ABJ/641734 : 3] ✓ Question affichée dans la page, en entier, sans fenêtre [{"visible":true,"texte":"Créer un inventaire des produits du bon ABJ/641734 ? Il portera sur le stock rayon, celui où le bon est entré. Créer l'inventaire Annuler","tronque":false,"boite":false}] ✓ La question dit que l'inventaire porte sur le stock rayon [Créer un inventaire des produits du bon ABJ/641734 ? Il portera sur le stock rayon, celui où le bon est entré. Créer l'inventaire Annuler] ✓ Annuler : rien n'est créé, le bandeau disparaît ✓ Un inventaire créé [1] ✓ Inventaire de l'emplacement (stock rayon), pas un inventaire réserve [emplacement / 1] ✓ Tous les produits du bon y sont ✓ Chaque produit part de son stock rayon ✓ Résultat affiché en entier dans la page, sans fenêtre [Inventaire créé : 3 article(s), sur le stock rayon. Il s'appelle « Inventaire rayon BL ABJ/641734 30102026-095216 » dans la liste des inventaires. Fermer] ✓ Aucune fenêtre du navigateur [] ✓ Inventaires d'essai retirés | E5: OK | L5: =IF(I5="","",IF(I5=E5,"Oui","Non"))
A6: 2 | B6: achats/test-controle-achats.js | C6: Point 17 : etat de controle des achats. - filtre sur le statut du controle (Controle / Non controle / Tous) ; - filtre sur les ecarts (Avec ecarts / Sans ecart / Tous) ; - bouton Details par ligne ; - impression respectant les filtres et rappelant les criteres. | D6: 16 / 16 conformes ✓ ecran Etat de controle des achats ouvert ✓ le filtre de statut propose Controle / Non controle / Tous [["TOUS","CONTROLE","NON_CONTROLE"]] ✓ le filtre d ecarts propose Avec / Sans / Tous [["TOUS","AVEC_ECART","SANS_ECART"]] ✓ la colonne Details est presente sur chaque ligne ✓ la liste sans filtre repond [total=17255] ✓ les deux statuts se partagent exactement la liste [controles=3972 non=13283 total=17255] ✓ les deux valeurs d ecart se partagent exactement la liste [avec=3162 sans=14093 total=17255] ✓ le bon prepare en ecart est bien retenu par le filtre [avec ecart=3162] ✓ les deux filtres se combinent [combine=3099] ✓ l impression aboutit [{"msg":"/data/reports/pdf/controle_achats_2026_10_30_09_58_54.pdf","success":true}] ✓ le PDF a bien ete ecrit [D:\payara5\payara5\glassfish\domains\domain1\applications\prestige\data\reports\pdf\controle_achats_2026_10_30_09_58_54.pdf] ✓ le fichier est un PDF non vide [octets=641250] ✓ les criteres retenus sont rappeles sur l etat [longueur texte=5254902] ✓ l etat est regroupe par grossiste avec sous-totaux ✓ le total general est edite ✓ aucune erreur JavaScript | E6: OK | L6: =IF(I6="","",IF(I6=E6,"Oui","Non"))

Sheet Analyses
A1: CAHIER DE RECETTE — Analyses
A2: 4 tests : 4 OK, 0 en échec selon Claude
A4: N° | B4: Test | C4: Scénario : ce qui est fait et ce qui est attendu | D4: Contrôles faits par Claude (valeur mesurée) | E4: Résultat Claude | F4: Écart constaté par Claude | G4: Catégorie et suite | H4: Résultat testeur | I4: Statut testeur | J4: Testeur | K4: Date | L4: Concorde ? | M4: Commentaire
A5: 3 | B5: analyse/test-analyse-tierspayant.js | C5: Point 5 : analyse tiers payant. - export Excel du resultat complet, aux deux niveaux ; - le choix d'un groupe tiers payant declenche la recherche ; - creation d'une suggestion a partir des produits du RESULTAT COURANT, avec le nombre integre. | D5: 13 / 13 conformes ✓ ecran Analyse tiers payant ouvert ✓ les deux grilles sont alimentees [{"tp":519,"produits":4364}] ✓ boutons Excel et Créer une suggestion presents [{"excel":true,"excelTp":true,"excelProd":true,"suggestion":true}] ✓ export Excel TIERSPAYANT : classeur valide [{"status":200,"taille":32757,"signature":"PK"}] ✓ export Excel PRODUIT : classeur valide [{"status":200,"taille":246770,"signature":"PK"}] ✓ choisir un groupe tiers payant lance la recherche [groupe=WILLIS TOWERS WATSON appels avant=2 apres=3] ✓ la suggestion est creee [{"success":true,"count":4186,"produitsDuResultat":4364,"produitsCommandables":4364}] ✓ la suggestion de tout le resultat est creee en moins de 60 s [25 s pour 4186 produits] ✓ le nombre de produits integres est annonce [{"success":true,"count":4186,"produitsDuResultat":4364,"produitsCommandables":4364}] ✓ le perimetre du resultat courant est rappele [{"success":true,"count":4186,"produitsDuResultat":4364,"produitsCommandables":4364}] ✓ la suggestion ne retient que les produits du resultat filtre [cip=3532111 -> {"success":true,"count":1,"produitsDuResultat":1,"produitsCommandables":1}] ✓ une recherche sans resultat ne cree pas de suggestion [{"msg":"Aucun produit dans le résultat courant : la suggestion n'a pas été créée.","success":false}] ✓ aucune erreur JavaScript | E5: OK | L5: =IF(I5="","",IF(I5=E5,"Oui","Non"))
A6: 4 | B6: analyse/test-selecteur-periodes.js | C6: Le selecteur de periodes de comparaison. Deux choses sont verifiees ici, et ce sont les deux ou une erreur passerait inapercue. 1. LA REGLE DES BORNES. « 3 derniers mois » designe les trois mois REVOLUS, et le mois en cours est rappele EN PLUS, marque comme tel. Compter le mois entame comme un mois complet ferait lire un effondrement du chiffre d'affaires le 2 du mois -- un chiffre faux, mais plausible. 2. LA BASCULE A DEUX. Une seule periode donne les chiffres bruts ; a partir de deux, les ecarts apparaissent. Afficher une colonne d'ecart vide sans rien dire laisserait croire a une stagnation. | D6: 35 / 35 conformes ✓ Le fichier de configuration est charge ✓ Il liste les deux menus demandes [cazonegeomanager, balancesalecahs] ✓ Il porte les quatre choix [TROIS_SEMAINES, TROIS_MOIS, SIX_MOIS, TROIS_ANS, LIBRE] ✓ Il expose le point d'accroche ✓ La balance porte son propre selecteur (onglet Analyse) ✓ L'injecteur le laisse tel quel ✓ Il propose 3 dernieres semaines par defaut (retours des tests 4) [TROIS_SEMAINES] ✓ Une seconde application n'en pose pas un deuxieme [1] ✓ L'onglet Balance n'a pas de liste deroulante de periode ✓ La balance a bien ses onglets (Balance, Analyse comparative, Evolution par mode, Balance (ancienne) cachee) [Balance | Analyse comparative | &Eacute;volution par mode de paiement | Balance (ancienne)] ✓ Le second est l'analyse comparative [Balance | Analyse comparative | &Eacute;volution par mode de paiement | Balance (ancienne)] ✓ L'ecran qui avait deja son selecteur n'en recoit pas un second [1] ✓ Et il lit la MEME liste de choix [TROIS_SEMAINES, TROIS_MOIS, SIX_MOIS, TROIS_ANS, LIBRE] ✓ Un ecran hors liste ne recoit rien ✓ 3 derniers mois rend 4 tranches [2026-07 | 2026-08 | 2026-09 | 2026-10] ✓ Ce sont les 3 mois revolus, plus le mois en cours [2026-07 | 2026-08 | 2026-09 | 2026-10 attendu 2026-07 | 2026-08 | 2026-09 | 2026-10] ✓ Seule la derniere tranche est marquee en cours [2026-07=false | 2026-08=false | 2026-09=false | 2026-10=true] ✓ Les tranches revolues sont completes [2026-07-01..2026-07-31 | 2026-08-01..2026-08-31 | 2026-09-01..2026-09-30 | 2026-10-01..2026-10-30] ✓ La tranche en cours s'arrete aujourd'hui [2026-10-30] ✓ 6 derniers mois rend 7 tranches [7] ✓ Ce sont les 6 mois revolus, plus le mois en cours [2026-04 | 2026-05 | 2026-06 | 2026-07 | 2026-08 | 2026-09 | 2026-10] ✓ 3 dernieres semaines rend 4 tranches [2026-W41 | 2026-W42 | 2026-W43 | 2026-W44] ✓ Les semaines vont du lundi au dimanche [2026-10-05..2026-10-11 | 2026-10-12..2026-10-18 | 2026-10-19..2026-10-25 | 2026-10-26..2026-10-30] ✓ 3 dernieres annees rend 4 tranches [2023 | 2024 | 2025 | 2026] ✓ Ce sont les 3 annees revolues, plus celle en cours [2023 | 2024 | 2025 | 2026] ✓ Plusieurs periodes : le mode comparatif est annonce ✓ La premiere tranche n'a pas d'ecart [{"libelle":"2023","montantMobilePayment":0,"fin":"2023-12-31","montantTTC":0,"montantAchat":28454723,"montantEsp":0,"montantRemise":0,"enCours":false,"nbreVente":0,"montantMobile":0,"debut":"2023-01-01","montantNet":0,"marge":0,"montantCB":0,"panierMoyen":0,"montantTp":0,"parModes":{},"montantDiff":] ✓ Les suivantes en ont un [ | 581767223 | 666240336 | 201062768] ✓ Une seule periode : le mode comparatif est refuse [{"total":1,"graphique":{"series":[{"valeurs":{"montantNet":[0],"panierMoyen":[0],"montantTp":[0],"montantMobilePayment":[0],"montantAchat":[0],"montantEsp":[0],"nbreVente":[0]},"libelle":"Valeur"}],"i] ✓ Et son ecart reste vide [{"libelle":"29/10","montantMobilePayment":0,"fin":"2026-10-29","montantTTC":0,"montantAchat":0,"montantEsp":0,"montantRemise":0,"enCours":false,"nbreVente":0,"montantMobile":0,"debut":"2026-10-29","montantNet":0,"marge":0,"montantCB":0,"panierMoyen":0,"montantTp":0,"parModes":{},"montantDiff":0,"eca] ✓ L'analyse d'une tranche donne les MEMES chiffres que la balance de la meme periode [analyse 0/0 vs balance 0/0] ✓ L'export Excel de l'analyse repond [{"statut":200,"taille":6144,"type":"application/vnd.ms-excel"}] ✓ La classe « periode-en-cours » existe en CSS ✓ Les classes « classe-abc-* » existent en CSS ✓ Aucune erreur JavaScript | E6: OK | L6: =IF(I6="","",IF(I6=E6,"Oui","Non"))
A7: 5 | B7: analyse/test-stats-famille-rayon-vide.js | C7: STATISTIQUES PAR FAMILLE / RAYON / GROSSISTE SUR UNE PERIODE SANS VENTE (journaux du 13/10). Avant : NullPointerException (total HT vide) puis NumberFormatException « Infinite or NaN » (division par zero), avalees : totaux et pourcentages absents, et sur une periode ou le HT total est nul la liste etait tronquee au premier rayon. - periode vide : reponse complete, totaux a 0, aucune erreur dans le journal du serveur ; - periode avec ventes : memes resultats qu'avant (pourcentages identiques, somme des lignes = total). Lecture seule. | D7: 16 / 16 conformes ✓ familles, période sans vente : réponse complète, totaux à 0 [{"totalRemiseVeto":0,"montantCumulHT":0,"MARGE POURCENTAGE":0,"totalCaVeto":0,"montantRemise":0,"totalRemiseVetoVNO":0,"totalRemiseVO":0,"pourcentageCumulTH":0,"totalRemiseVNO":0,"MONTANT NET TTC":0,"] ✓ familles, période sans vente : aucune erreur dans le journal du serveur [] ✓ familles, période avec ventes : lignes complètes, somme des lignes = total [11 lignes, 154253420 / 154253420] ✓ familles, période avec ventes : pourcentages calculés [28] ✓ rayons, période sans vente : réponse complète, totaux à 0 [{"totalRemiseVeto":0,"montantCumulHT":0,"MARGE POURCENTAGE":0,"totalCaVeto":0,"montantRemise":0,"totalRemiseVetoVNO":0,"totalRemiseVO":0,"pourcentageCumulTH":0,"totalRemiseVNO":0,"MONTANT NET TTC":0,"] ✓ rayons, période sans vente : aucune erreur dans le journal du serveur [] ✓ rayons, période avec ventes : lignes complètes, somme des lignes = total [35 lignes, 154253420 / 154253420] ✓ rayons, période avec ventes : pourcentages calculés [28] ✓ grossistes, période sans vente : réponse complète, totaux à 0 [{"totalRemiseVeto":0,"montantCumulHT":0,"MARGE POURCENTAGE":0,"totalCaVeto":0,"montantRemise":0,"totalRemiseVetoVNO":0,"totalRemiseVO":0,"pourcentageCumulTH":0,"totalRemiseVNO":0,"MONTANT NET TTC":0,"] ✓ grossistes, période sans vente : aucune erreur dans le journal du serveur [] ✓ grossistes, période avec ventes : lignes complètes, somme des lignes = total [41 lignes, 154253420 / 154253420] ✓ grossistes, période avec ventes : pourcentages calculés [28] ✓ veto, période sans vente : réponse complète, totaux à 0 [{"totalRemiseVeto":0,"montantCumulHT":0,"MARGE POURCENTAGE":0,"totalCaVeto":0,"montantRemise":0,"totalRemiseVetoVNO":0,"totalRemiseVO":0,"pourcentageCumulTH":0,"totalRemiseVNO":0,"MONTANT NET TTC":0,"] ✓ veto, période sans vente : aucune erreur dans le journal du serveur [] ✓ veto, période avec ventes : lignes complètes, somme des lignes = total [11 lignes, 154253420 / 154253420] ✓ veto, période avec ventes : pourcentages calculés [28] | E7: OK | L7: =IF(I7="","",IF(I7=E7,"Oui","Non"))
A8: 6 | B8: analyse/test-unites-vendues-vno-vo.js | C8: UNITES VENDUES : COLONNES « Nbre.VNO » ET « Nbre.VO » (demande du 16/10). La requete calculait le total de l'article puis le rangeait en VNO ou en VO selon le type d'UNE vente prise au hasard parmi les siennes : les deux colonnes changeaient d'un appel a l'autre. Ce que le test etablit (lecture seule) : - deux appels de suite donnent les memes colonnes ; - pour chaque article : Nbre.VNO = quantite des ventes au comptant (type 1), Nbre.VO = quantite des ventes VO, calculees en SQL avec les memes filtres (periode, emplacement, cloturees, non annulees, montant > 0, hors depot) ; - Nbre.VNO + Nbre.VO = quantite vendue. | D8: 3 / 3 conformes ✓ Deux appels de suite : mêmes colonnes VNO / VO [4756 articles] ✓ Chaque article : Nbre.VNO et Nbre.VO = quantités vendues au comptant et en VO (SQL) [0 écarts sur 4756 ; ] ✓ Nbre.VNO + Nbre.VO = quantité vendue [0 écarts] | E8: OK | L8: =IF(I8="","",IF(I8=E8,"Oui","Non"))

Sheet Audit
A1: CAHIER DE RECETTE — Audit
A2: 3 tests : 3 OK, 0 en échec selon Claude
A4: N° | B4: Test | C4: Scénario : ce qui est fait et ce qui est attendu | D4: Contrôles faits par Claude (valeur mesurée) | E4: Résultat Claude | F4: Écart constaté par Claude | G4: Catégorie et suite | H4: Résultat testeur | I4: Statut testeur | J4: Testeur | K4: Date | L4: Concorde ? | M4: Commentaire
A5: 7 | B5: audit/test-audit-analyse.js | C5: AUDIT & RAPPROCHEMENTS, onglet Analyse (besoins du 11/10, point 6). Par l'ecran (menu Centre de support) : - un ecart connu est pose dans chaque controle, puis l'analyse est lancee depuis l'ecran ; - un reassort reserve -> rayon posterieur au dernier mouvement n'est pas un ecart de stock ; un ecart apres reassort se compte depuis le stock rayon apres reassort ; - chaque tuile passe au rouge et son detail montre la ligne posee, avec l'ecart attendu : stock reel / historique (+7), stock negatif (-3), caisse ouverte depuis 3 jours, billetage (-10 000 000, pour rester parmi les plus gros ecarts rendus sur une base reelle), differe (reste du 4 000 / releve 5 000), carnet depot (+1 000) ; controles de coherence listes ; - l'analyse n'ecrit rien (sommes de controle des tables lues identiques avant et apres) ; - aucune fenetre ; sans le droit P_SM_AUDIT, l'API refuse. Tout ce qui est pose est retire a la fin, rapports conserves par « Lancer l'analyse » compris. | D5: 17 / 17 conformes ✓ Analyse à l'ouverture en moins de 10 s avec 300 clients en différé et 7200 règlements [{"ms":4087}] ✓ Menu « Audit & rapprochements » (≤ 25 caractères) dans le Centre de support [Audit & rapprochements] ✓ L'analyse n'écrit rien (sommes de contrôle de 10 tables identiques) ✓ Stock / historique : tuile rouge, produit modifié présent avec un écart de +7 [{"cip":"3000147","libelle":"A 313 POM TB/50G","emplacement":"OFFICINE","stockReel":7,"stockHistorique":0,"ecart":7,"dernierMouvement":"19/07/2026 16:21","produitId":"14824102650702805490"}] ✓ Stock / historique : un réassort réserve → rayon après le dernier mouvement n'est pas un écart ✓ Stock / historique : écart compté depuis le réassort (stock historique = rayon après réassort, +2) [{"cip":"8637783","libelle":"A CERUMEN UNIDOSE 2ML B/ 10 AFR","emplacement":"OFFICINE","stockReel":27,"stockHistorique":25,"ecart":2,"dernierMouvement":"30/10/2026 14:24","produitId":"14113164653813600217"}] ✓ Stocks négatifs : produit à −3 présent [{"cip":"8486901D","libelle":"CLOTRIMAZOLE UBI 200MG VAG/10 BT/3 DET","emplacement":"OFFICINE","stockReel":-3,"produitId":"57339880756001606"}] ✓ Caisses ouvertes : caisse ouverte il y a 3 jours présente (3 jours) [{"caissier":"Essai E2E SA","ouverture":"27/10/2026 08:30","jours":3,"caisse":"E2E-AUD-OUV"}] ✓ Billetage : manquant de 10 000 000 sur la caisse de la veille [{"caissier":"Essai E2E SA","ouverture":"29/10/2026 08:00","fermeture":"29/10/2026 18:00","attendu":100000000,"billetage":90000000,"ecart":-10000000,"caisse":"E2E-AUD-FER"}] ✓ Différés : reste dû 4 000 / relevé 5 000 (écart −1 000) [{"client":"ZZAUDIT Differe","ventes":10000,"reglements":5000,"soldeReleve":5000,"resteDu":4000,"ecart":-1000,"clientId":"E2E-AUD-C"}] ✓ Carnets dépôt : ZZ E2E AUDIT DEPOT avec un écart de +1 000 [{"depot":"ZZ E2E AUDIT DEPOT","solde":1000,"ventes":0,"reglements":0,"retours":0,"soldeCalcule":0,"ecart":1000,"tiersPayantId":"E2E-AUD-TP"}] ✓ Contrôles de cohérence : les contrôles actifs sont listés [18] ✓ Le détail choisi s'explique en clair au-dessus de la liste [Contrôles de cohérence : Contrôles automatiques du centre de support, rejoués ic] ✓ Aucune fenêtre affichée [] ✓ Écart retiré : il disparaît à l'analyse suivante ✓ Sans le droit P_SM_AUDIT : analyse refusée par le serveur [{"msg":"Vous n'avez pas le droit de consulter l'audit.","success":false}] ✓ Données d'essai retirées | E5: OK | L5: =IF(I5="","",IF(I5=E5,"Oui","Non"))
A6: 8 | B6: audit/test-audit-rapports.js | C6: AUDIT & RAPPROCHEMENTS, onglet Rapports (besoins du 11/10, point 6). Par l'ecran : - ouvrir l'ecran ne conserve aucun rapport ; « Lancer l'analyse » en conserve un (auteur, periode, resultat) ; - rapport 1 avec un ecart de stock pose sur un produit, rapport 2 apres l'avoir retire et pose un stock negatif ; - onglet Rapports : les deux rapports, le plus recent en tete, nombre d'ecarts par controle ; - comparaison des deux : l'ecart de stock est « resolu », le stock negatif est « nouveau » ; - « Voir le rapport » l'affiche dans l'onglet Analyse avec un bandeau (ce n'est pas la situation actuelle) ; - PDF (contenu lu) et Excel ; le PDF s'ouvre dans un onglet du navigateur, aucune fenetre de message. Tout ce qui est pose (stocks, rapports du test) est retire a la fin. | D6: 18 / 18 conformes ✓ Ouvrir l'écran ne conserve aucun rapport ✓ « Lancer l'analyse » conserve le rapport 1 ✓ Rapport 1 : auteur et période du billetage enregistrés [Essai E2E SA 2026-10-01 2026-10-30] ✓ « Lancer l'analyse » conserve le rapport 2 ✓ Liste : les deux rapports, le plus récent en tête [30/10/2026 10:01 / 30/10/2026 10:01] ✓ Liste : nombre d'écarts par contrôle (stocks négatifs : 1 de plus dans le rapport 2) [[{"CONTROLES":4,"DIFFERES":0,"CAISSES_OUVERTES":9,"STOCK":23,"STOCK_NEGATIF":11,"BILLETAGE":103,"CARNETS":0},{"CONTROLES":4,"DIFFERES":0,"CAISSES_OUVERTES":9,"STOCK":22,"STOCK_NEGATIF":12,"BILLETAGE":103,"CARNETS":0}]] ✓ Aucun rapport coché : boutons inactifs ✓ Deux rapports cochés : « Comparer » actif, « Voir » et éditions inactifs ✓ Comparaison : l'écart de stock du produit modifié est résolu [8452598 3 HP KIT GEL/2 + CPR/4 KIT/14 (OFFICINE) : écart 7] ✓ Comparaison : le stock négatif est un nouvel écart [8486901D CLOTRIMAZOLE UBI 200MG VAG/10 BT/3 DET (OFFICINE) : stock -3] ✓ Un rapport coché : « Voir », PDF et Excel actifs ✓ « Voir » : rapport 1 dans l'onglet Analyse, bandeau affiché, écart du produit modifié présent [ongletAnalyse] ✓ « Revenir à l'analyse du jour » retire le bandeau sans conserver de rapport ✓ PDF : ouvert dans un onglet du navigateur [http://localhost:8080/prestige/api/v1/audit/rapports/38607071-6f76-40b7-992a-929dace1bb4e/pdf] ✓ PDF : titre, synthèse des contrôles et ligne du produit modifié [GRANDE PHARMACIE DE LA CAPITALE ✓ Excel : fichier .xls (classeur) téléchargé [{"type":"application/vnd.ms-excel","debut":[208,207,17,224],"taille":19456,"nom":"attachment; filename=\"audit_301020261001.xls\""}] ✓ Aucune fenêtre de message [] ✓ Données retirées (stocks, rapports du test) | E6: OK | L6: =IF(I6="","",IF(I6=E6,"Oui","Non"))
A7: 9 | B7: audit/test-audit-regularisations.js | C7: AUDIT & RAPPROCHEMENTS, onglet Regularisations (besoins du 11/10, point 6). Par l'ecran, sur des donnees du test : - historique pose sur deux produits sans aucun mouvement, en aout 2038 (aucune donnee reelle) : une entree au depot ecrite a l'envers (4 -> 1 pour +3), un deconditionnement gonfle (104 -> 204) et la vente de la meme seconde partant du stock d'avant ouverture (4 -> 99 pour 5) ; - une caisse oubliee (ouverte il y a 3 jours) d'un caissier d'essai ; - les quatre regularisations sont proposees ; sans commentaire, la validation est refusee a l'ecran ; - validees : entree 4 -> 7, deconditionnement 4 -> 104 puis vente 104 -> 99 (chaine coherente), caisse fermee au nom de son caissier avec le montant compte (billetage enregistre) ; - journal : une ligne par regularisation, auteur, commentaire, valeurs d'avant ; une regularisation appliquee n'est plus proposee, et la rejouer par l'API ne change rien ; - les ecarts a corriger ailleurs ouvrent leur ecran habituel ; sans le droit P_AUDIT_REGULARISER, l'API refuse ; - aucune fenetre. Tout ce qui est pose ou produit est retire a la fin. | D7: 17 / 17 conformes ✓ Proposées : entrée au dépôt à l'envers, déconditionnement gonflé, vente après ouverture, caisse oubliée [HISTO_DECON_204, HISTO_VENTE_DECON, HISTO_ENTREE_DEPOT, CAISSE_OUVERTE] ✓ Chaque proposition dit ce qui sera fait ✓ Sans commentaire : rien n'est appliqué, message dans la page [<span style="color:#c0392b">Le commentaire est obligatoire.</span>] ✓ Entrée au dépôt : 4 → 7 (hausse) [4>7] ✓ Déconditionnement : 104 → 204 ramené à 4 → 104 [4>104] ✓ Appliquées : elles ne sont plus proposées ✓ Vente : part de 104 (stock après ouverture) → 99 : chaîne 4 → 104 → 99 [104>99] ✓ Caisse : se valide seule, le montant compté se saisit alors [{"valider":true,"montant":true} bloquée avec d'autres : true] ✓ Caisse sans montant : refusée à l'écran [<span style="color:#c0392b">Indiquez le montant compté dans la caisse.</span>] ✓ Caisse fermée au nom de son caissier, billetage de 12 500 enregistré [is_Process|12500.00] ✓ Journal : 4 régularisations, auteur et valeurs d'avant enregistrés [4 4 4] ✓ Journal affiché : commentaire, objet et montant de la caisse [[{"date":"30/10/2026 10:02","auteur":"Essai E2E SA","type":"Caisse oubliée à fermer","objet":"ZZESSAI Caissier, caisse ouverte le 27/10/2026 08:30","lignes":1,"montant":12500,"commentaire":"Caisse oubliée, comptée le matin"},{"date":"30/10/2026 10:02","auteur":"Essai E2E SA","type":"Historique : ven] ✓ Rejouée par l'API : refusée (« plus d'objet »), historique inchangé [{"msg":"Cette régularisation n'a plus d'objet (déjà appliquée ?).","success":false}] ✓ Écarts à corriger ailleurs : liens vers leur écran (ajustement, caisse, différés, carnets, diagnostic) [ajustementmanager, ajustementmanager, gestcaissemanager, supportdiagnostic] ✓ Aucune fenêtre [] ✓ Sans le droit : consultation possible, validation refusée par le serveur [{"msg":"Vous n'avez pas le droit de valider les régularisations.","success":false}] ✓ Données du test retirées | E7: OK | L7: =IF(I7="","",IF(I7=E7,"Oui","Non"))

Sheet Corrections d'audit
A1: CAHIER DE RECETTE — Corrections d'audit
A2: 14 tests : 14 OK, 0 en échec selon Claude
A4: N° | B4: Test | C4: Scénario : ce qui est fait et ce qui est attendu | D4: Contrôles faits par Claude (valeur mesurée) | E4: Résultat Claude | F4: Écart constaté par Claude | G4: Catégorie et suite | H4: Résultat testeur | I4: Statut testeur | J4: Testeur | K4: Date | L4: Concorde ? | M4: Commentaire
A5: 10 | B5: audits/repro-assurances-liens.js | C5: REPRODUCTION — MODULE ASSURANCES : LIENS CLIENT / TIERS PAYANT (constats M1, M2, M3, M4). Regle metier de reference : un seul RO actif par client, un carnet n'est jamais RO. Clients d'essai crees par l'ecran client, tiers payants d'essai copies d'organismes existants. FAIL = defaut reproduit (mesure entre crochets). Lancement seul : node src/test/e2e/audits/repro-assurances-liens.js | D5: 15 / 15 conformes ✓ N8 attendu : un client assuré créé avec succès par l'écran existe en base (client / compte / ayant droit = 1 / 1 / 1) [réponse succès, identifiant fca6ca98-57b3-49dc-b44d-021b619bc340 ; en base client / compte / ayant droit : 1 / 1 / 1] ✓ M1 attendu : associer un carnet à un client assuré garde son assurance active et RO, le carnet n'est pas RO [réponse {"data":{"strLASTNAME":"ZZAUDIT M1","lgTIERSPAYANTID":"ZZAUDIT-TP-M1A","fullName ; liens avant M1A/enable/RO=1/prio=1 ; après M1A/enable/RO=1/prio=1 ; M1K/enable/RO=0/prio=2] ✓ M2 attendu : après « Modifier client / tiers payant » vers un organisme non rattaché, le client n'a qu'un seul RO actif [réponse {"msg":"Opération effectuée avec succèss","success":true,"refId":"1ab947df-fb98- ; RO actifs 1 ; liens M2A/enable/RO=0/prio=2 ; M2B/enable/RO=1/prio=1] ✓ M3 attendu : la complémentaire C remplaçant un lien supprimé est créée active avec une priorité ≥ 1, sans hériter du lien supprimé [réponse {"msg":"Opération effectuée avec succèss","success":true,"refId":"dff9800b-7f78- ; liens M3A/enable/RO=1/prio=1 ; M3B/delete/RO=0/prio=-1 ; M3C/enable/RO=0/prio=2] ✓ M2 attendu (case « principal » non cochée) : un seul RO actif après le changement d'organisme [réponse {"msg":"Opération effectuée avec succèss","success":true,"refId":"aef71b08-06f2- ; RO actifs 1 ; liens M2bA/enable/RO=1/prio=1 ; M2bB/enable/RO=0/prio=2] ✓ M3 attendu (case « principal » non cochée) : la complémentaire C est créée active avec une priorité ≥ 1 [réponse {"msg":"Opération effectuée avec succèss","success":true,"refId":"161758e1-f279- ; liens M3bA/enable/RO=1/prio=1 ; M3bC/enable/RO=0/prio=2 ; M3bB/delete/RO=0/prio=-1] ✓ M4 attendu : enregistrer la modification sans rien changer laisse l'assurance RO et le carnet non RO [réponse {"msg":"Opération effectuée avec succèss","success":true,"refId":"6b183754-82bc- ; liens avant M4A/enable/RO=1/prio=2 ; M4K/enable/RO=0/prio=1 ; M4D/delete/RO=0/prio=-1 ; après M4A/enable/RO=1/prio=2 ; M4K/enable/RO=0/prio=1 ; M4D/delete/RO=0/prio=-1] ✓ M4 attendu : le lien supprimé garde sa priorité -1 (il n'est pas reclassé avec les liens actifs) [M4A/enable/RO=1/prio=2 ; M4K/enable/RO=0/prio=1 ; M4D/delete/RO=0/prio=-1] ✓ P21-a attendu : RO changé de A en B par « Modifier infos client » : B RO en priorité 1, A reste actif (non RO) en priorité libre, aucune priorité en double [réponse {"data":{"strLASTNAME":"ZZAUDIT P21A","lgTIERSPAYANTID":"ZZAUDIT-TP-P21aB","full ; liens avant P21aA/enable/RO=1/prio=1 ; P21aC/enable/RO=0/prio=2 ; après P21aA/enable/RO=0/prio=3 ; P21aB/enable/RO=1/prio=1 ; P21aC/enable/RO=0/prio=2 ; doublons priorité / organisme - / -] ✓ P21-b attendu : un complémentaire ajouté avec une priorité déjà occupée prend la priorité libre suivante [réponse {"data":{"strLASTNAME":"ZZAUDIT P21B","lgTIERSPAYANTID":"ZZAUDIT-TP-P21bA","full ; liens avant P21bA/enable/RO=1/prio=1 ; P21bC/enable/RO=0/prio=2 ; après P21bA/enable/RO=1/prio=1 ; P21bD/enable/RO=0/prio=3 ; P21bC/enable/RO=0/prio=2 ; doublons priorité / organisme - / -] ✓ P21-c attendu : RO changé vers un organisme déjà rattaché : son lien est repris (pas de second lien), RO en priorité 1 ; A reste actif en priorité libre [réponse {"data":{"strLASTNAME":"ZZAUDIT P21C","lgTIERSPAYANTID":"ZZAUDIT-TP-P21cC","full ; liens avant P21cA/enable/RO=1/prio=1 ; P21cC/enable/RO=0/prio=2 ; après P21cA/enable/RO=0/prio=3 ; P21cC/enable/RO=1/prio=1 ; doublons priorité / organisme - / -] ✓ P21-d attendu (non-régression) : enregistrer la fiche sans changement garde A RO en priorité 1 et C en priorité 2 [réponse {"data":{"strLASTNAME":"ZZAUDIT P21D","lgTIERSPAYANTID":"ZZAUDIT-TP-P21dA","full ; liens avant P21dA/enable/RO=1/prio=1 ; P21dC/enable/RO=0/prio=2 ; après P21dA/enable/RO=1/prio=1 ; P21dC/enable/RO=0/prio=2] ✓ P21-e attendu : le lien créé par la modification de vente ne reprend pas une priorité déjà occupée [réponse {"msg":"Opération effectuée avec succèss","success":true,"refId":"b6756a67-fcba- ; liens avant P21eA/enable/RO=1/prio=1 ; P21eC/enable/RO=0/prio=2 ; après P21eA/enable/RO=1/prio=1 ; P21eD/enable/RO=0/prio=3 ; P21eC/enable/RO=0/prio=2 ; doublons priorité / organisme - / -] ✓ Aucune erreur JavaScript [] ✓ Jeu d'essai retiré (ventes, clients, tiers payants, factures), stocks et paramètres remis [ventes restantes 0] | E5: OK | L5: =IF(I5="","",IF(I5=E5,"Oui","Non"))
A6: 11 | B6: audits/repro-carnet.js | C6: REPRODUCTION — MODULE CARNET DEPOT ET RETOURS CARNET (constats CA-06, CA-07, CA-08/CA-15, CA-12). Carnet depot d'essai (copie d'un carnet existant, solde 5 000 F), retours par les routes de l'ecran « Retour carnet ». FAIL = defaut reproduit (mesure entre crochets). Lancement seul : node src/test/e2e/audits/repro-carnet.js | D6: 10 / 10 conformes ✓ CA-06 précondition : solde du carnet dépôt d'essai = 5 000 [5000] ✓ CA-06 attendu : un règlement de carnet dépôt de −1 000 F est refusé, solde inchangé [réponse {"msg":"Le montant du règlement doit être supérieur à zéro (montant négatif ou nul refusé).","success":false,"http":200} ; solde 5000 → 5000] ✓ CA-07 précondition : retour carnet de 2 boîtes créé (stock 100) [{"data":{"id":7526},"success":true,"http":200}] ✓ CA-12 attendu : le détail du retour (une entrée en stock) note stock final = stock initial + 2 [stock initial 100 ; stock final noté 102 ; quantité 2] ✓ CA-07 attendu : clôturer deux fois le même retour ne recompte ni le stock ni le solde [clôtures true/true ; stock 100 → 102 → 102 ; solde 5000 → 3290 → 3290] ✓ CA-12 attendu : l'historique de stock du retour enchaîne (début + quantité = fin) et n'est écrit qu'une fois [mouvements : 100+2=102] ✓ CA-08 attendu : un retour de −3 boîtes est refusé [réponse {"msg":"La quantité retournée doit être supérieure à zéro.","success":false,"http":200} ; stock 102 → 102] ✓ CA-15 attendu : un retour sans motif est refusé avec un message (pas une erreur 500) [HTTP 200 ; {"msg":"Choisissez le motif du retour.","success":false,"http":200}] ✓ Aucune erreur JavaScript [] ✓ Jeu d'essai retiré (ventes, clients, tiers payants, factures), stocks et paramètres remis [ventes restantes 0] | E6: OK | L6: =IF(I6="","",IF(I6=E6,"Oui","Non"))
A7: 12 | B7: audits/repro-differes.js | C7: REPRODUCTION — MODULE DIFFERES (constats DIF-01, DIF-02, DIF-03, D2/DIF-05, D3/DIF-06, D4/DIF-04, D5, DIF-07, DIF-08, DIF-09). Ventes comptant reglees en differe (mode 4) pour des clients d'essai, reglements par la route de l'ecran « Faire un reglement ». Invariant de reference : caisse nette de la vente + dette restante = prix de la vente. FAIL = defaut reproduit (mesure entre crochets). Lancement seul : node src/test/e2e/audits/repro-differes.js | D7: 13 / 13 conformes ✓ DIF-01 attendu : un règlement fait pendant la modification est refusé, ou déduit de la dette de la copie (caisse + dette = prix) [règlement pendant modification {"s":false,"m":"Une des ventes choisies a été annulée ou modifiée : rechargez la liste."} ; clôture copie false ; dette restante 5510 + réglé 0 = 5510 (prix 5510)] ✓ DIF-02 précondition : vente différée de 5510 avec 2755 d'acompte ; caisse + dette = prix [caisse 2755 ; dette 2755] ✓ DIF-02 attendu : après modification sans changement (copie en différé, 0 reçu), caisse + dette = prix [clôture copie true ; caisse nette 0 + dette 5510 = 5510 (prix 5510)] ✓ DIF-03 attendu : vente déjà réglée de 2755 puis passée à un autre client : refus, ou règlement reporté (dettes + réglé = prix) [clôture copie false ; dette client 1 2755 ; dette client 2 0 ; réglé par le client 1 2755 ; total 5510 (prix 5510)] ✓ D2 attendu : annuler une vente différée déjà réglée en partie est refusé (ou un avoir est créé) [annulation {"s":false,"m":"Ce différé a déjà reçu un règlement (partiel ou total) : il ne peut plus être annulé ; dette 2755 ; réglé resté en caisse 2755] ✓ D3 attendu : la liste des règlements de différés du jour montre les règlements de tous les clients (dont celui dont la vente a été annulée) [lignes renvoyées 3 (règlements du jour faits par le test : 2 clients)] ✓ D4 attendu : le solde du relevé = reste dû (prix 5510 − acompte 2755 = 2755) [solde du relevé 2755 ; reste dû 2755] ✓ D5 attendu : une vente portant deux lignes de dette (doublon, données réelles) est annulée sans laisser de dette [annulation true ; lignes de dette encore actives 0 ; dette du client 0] ✓ DIF-07 attendu : un règlement partiel qui déclare 1 F reçu pour 2755 F payés est refusé [règlement {"s":false,"m":"Le montant reçu (1 F) est inférieur au montant réglé (2755 F)."} ; dette 5510] ✓ DIF-08 attendu : la date de la ligne de dette reste celle de la vente (il y a 30 jours) après un règlement [date de la vente | date de la ligne de dette après règlement : 2026-09-30 | 2026-09-30 (la liste « Différés » affiche, trie et filtre sur cette date : ReglementServiceImpl.java:213-215, :242)] ✓ DIF-09 attendu : un règlement partiel solde d'abord la vente la plus ancienne [reste de l'ancienne 0 ; reste de la récente 2755] ✓ Aucune erreur JavaScript [] ✓ Jeu d'essai retiré (ventes, clients, tiers payants, factures), stocks et paramètres remis [ventes restantes 0] | E7: OK | L7: =IF(I7="","",IF(I7=E7,"Oui","Non"))
A8: 13 | B8: audits/repro-facturation.js | C8: REPRODUCTION — MODULE FACTURATION DES TIERS PAYANTS (constats F1, F2, F3, F4, F5, F6). Factures definitives par le chemin des ecrans (« Edition des factures » : groupe-tierspayant/facturation-bons et facturation-groupe, ancien controleur GroupeTierspayantController), provisoires par facturation/summary/generer, reglement par reglement-facture/do-reglement. Tiers payants, clients, groupe et factures d'essai retires a la fin ; compteur des numeros de facture remis a sa valeur. FAIL = defaut reproduit (mesure entre crochets). Lancement seul : node src/test/e2e/audits/repro-facturation.js | D8: 10 / 10 conformes ✓ F2 précondition : facture définitive générée, bon marqué « charged » [{"status":1,"http":200} ; statut charged ; factures 6221] ✓ F2 attendu (définitive, écran resté ouvert) : un bon déjà facturé n'est pas facturé une seconde fois [seconde génération {"status":0,"http":200} ; factures définitives portant le bon : 6221] ✓ F2 attendu (provisoire) : un bon déjà facturé n'entre pas dans une facture provisoire [génération provisoire {"success":true,"http":200} ; provisoires portant le bon : ] ✓ F1 attendu : supprimer une facture définitive par DELETE facturation/{id} est refusé (ou ses bons redeviennent facturables) [HTTP 200 ; facture encore en base ? 1 ; statut du bon charged ; factures définitives restantes portant le bon : 6221] ✓ F3 attendu : 5 paires de générations simultanées produisent toujours deux numéros différents [0 paire(s) sur 5 avec le même numéro : 6222,6223 ; 6224,6225 ; 6226,6227 ; 6228,6229 ; 6230,6231] ✓ F4 (chemin de l'écran) attendu : montants du groupe = somme des factures membres (4584), brut des membres = net (sans remise) [rattachement 2 ; génération {"status":1,"http":200} ; membres code/brut/net/père : 6233/2292.000/2292.000/16103010341224623616,6234/2292.000/2292.000/16103010341234472478 ; t_groupe_factures code/montant : 6232/2292,6232/2292 ; facture de groupe agrégée dans t_facture : 6233/2292.000/2292.000,6234/2292.000/2292.000] ✓ F5 attendu : facturer un seul des deux bons laisse l'encours de l'autre (2292) [encours organisme 4584 → 2292 ; encours client 4584 → 2292] ✓ F6 attendu : un règlement de facture de −5 000 F est refusé, facture inchangée [réponse {"success":"Echec de reglement ","str_ref":"16103010342919634968","lg_DOSSIER_REGLEMENT_ID":"","errors":"0","http":200} ; facture payé|restant|statut 0.000|2292.000|enable → 0.000|2292.000|enable] ✓ Aucune erreur JavaScript [] ✓ Jeu d'essai retiré (ventes, clients, tiers payants, factures), stocks et paramètres remis [ventes restantes 0] | E8: OK | L8: =IF(I8="","",IF(I8=E8,"Oui","Non"))
A9: 14 | B9: audits/repro-remise-caisse.js | C9: REPRODUCTION — REMISES DE LA VENTE COMPTANT ET MOUVEMENTS DE CAISSE (constats VC-05, VC-06, VC-07, VC-16). Remise d'essai de 10 % (t_remise, t_grille_remise, t_workflow_remise_article marques ZZAUDIT) appliquee a un produit TVA 18 % compte dans le chiffre d'affaires ; code remise du produit remis a la fin. FAIL = defaut reproduit (mesure entre crochets). Lancement seul : node src/test/e2e/audits/repro-remise-caisse.js | D9: 8 / 8 conformes ✓ VC-05/07 précondition : remise de 10 % posée et appliquée (prix 3270 F, TVA 18 %) [pose {"msg":"Opération effectuée avec success","success":true,"http":200} ; net {"montantAccount":0,"margeUg":0,"montant":3270,"remise":325,"restructuring":false,"cmuAmount":0,"montantTva":499,"montantNet":2945,"marge":198,"montantTtcUg":0,"montantTp":0,"montantTvaUg":0,"tiersPay] ✓ VC-05 attendu : TVA de la vente = somme des TVA des lignes [clôture true ; TVA en-tête 499 ; somme des lignes 499 ; TVA du mouvement de caisse 499] ✓ VC-07 attendu : la remise enregistrée est celle affichée et encaissée (prix − remise = net payé) [remise affichée 325 ; net affiché 2945 ; remise enregistrée (vente) 325 ; prix − remise enregistrée 2945 ; transaction remise|net|payé 325|2945|2945] ✓ VC-06 attendu : une vente encaissée au net sans remise n'enregistre pas de remise (remise de la vente = 0) [net demandé sans remiseId 3270 (plein tarif 3270) ; clôture true ; remise enregistrée sur la vente 0 ; transaction montant|remise|payé 3270|0|3270] ✓ VC-16 attendu : un mouvement de caisse saisi à la date d'hier porte la même date dans le mouvement, le règlement et la transaction [{"msg":"Opération effectuée .","mvtId":"782d5c43-677f-4c31-afd4-3a45e7f995cc","success":true,"http": ; mouvement 2026-10-29 | règlement 2026-10-29 | transaction 2026-10-29] ✓ VC-16 attendu : un mouvement de caisse daté de demain est refusé [{"msg":"La date du mouvement ne peut pas être dans le futur.","success":false,"http":200}] ✓ Aucune erreur JavaScript [] ✓ Jeu d'essai retiré (ventes, clients, tiers payants, factures), stocks et paramètres remis [ventes restantes 0] | E9: OK | L9: =IF(I9="","",IF(I9=E9,"Oui","Non"))
A10: 15 | B10: audits/repro-vente-assurance.js | C10: REPRODUCTION — MODULE VENTE ASSURANCE (constats CR-01, CR-02, CR-03, CR-04, CR-05/N3, CR-06, CR-07, CR-09, CR-10, CA-03, CA-09/N5). Tiers payants d'essai (copies d'un organisme existant, compteurs a zero) et clients d'essai crees par l'ecran client ; chaque cas a ses propres tiers payants, pour que les compteurs ne se melangent pas. FAIL = defaut reproduit (mesure entre crochets). Lancement seul : node src/test/e2e/audits/repro-vente-assurance.js | D10: 17 / 17 conformes ✓ CR-01 précondition : vente assurance encaissée, encours organisme et client = part tiers payant (564) [encours organisme|client 564|564 ; net 140] ✓ CR-01 attendu : après annulation, l'encours revient à 0 [annulation true ; encours organisme 564 → 0 ; encours client 564 → 0] ✓ CR-02 précondition : modification ouverte [0e2bd896-7a29-4c28-8f1f-ffd4a3b4f314] ✓ CR-02 attendu : modification sans changement → encours = une seule part (564) [clôture copie {"s":true,"m":"Opération effectuée avec success"} ; encours organisme 564 ; encours client 564] ✓ CR-03 attendu : clôture refusée (bon déjà utilisé) → aucun encours modifié, aucune ligne tiers payant close [clôture {"s":false,"m":"Le numéro de ZZAUDIT-DOUBLON est déjà utilisé par l'assureur :: ZZAUDIT-TP-CR03B"} ; encours A 353 → 353 ; encours B 212 → 212 ; vente is_Process ; lignes ZZAUDIT-TP-CR03A/50/353/is_Process/unpaid ; ZZAUDIT-TP-CR03B/30/212/is_Process/unpaid] ✓ CR-03 attendu : un second essai identique ne recompte rien [second essai false ; encours A 353 → 353] ✓ CR-04 attendu : 3 paires de clôtures simultanées sur le même organisme → encours = somme des parts [clôtures réussies 6/6 ; somme des parts 3384 ; encours organisme 3384 ; encours client 3384] ✓ CR-07 attendu : une part de 1 F et un taux de 1 % renvoyés par le poste (calcul serveur : 80 %) sont refusés, ou ignorés au profit du calcul serveur [clôture true ; part calculée [] ; ligne enregistrée ZZAUDIT-TP-CR07/80/564/is_Closed/unpaid ; encours organisme 564] ✓ CR-09 attendu : ajouter un tiers payant à 250 % est refusé [réponse {"msg":"Le taux du tiers payant doit être compris entre 0 et 100 %.","success":false,"http":200} ; lignes ZZAUDIT-TP-CR09A/70/0/is_Process/unpaid] ✓ CR-10 attendu : retirer le tiers payant d'une vente assurance encaissée est refusé, la ligne reste facturable [réponse {"msg":"Cette vente (N° 261030_00169) a été clôturée le 30/10/2026 10:04 : elle ne peut plus être mo ; lignes avant ZZAUDIT-TP-CR10/80/564/is_Closed/unpaid ; après ZZAUDIT-TP-CR10/80/564/is_Closed/unpaid] ✓ CA-03 précondition : la vente du tiers payant exclu a sa ligne vente_exclu ✓ CA-03 attendu : aucune des 8 ventes ordinaires suivantes n'a de ligne « vente exclue » [0 vente(s) ordinaire(s) enregistrée(s) comme exclues, au nom de -] ✓ CA-03 remise en état : une vente ordinaire après une vente « dépôt » n'est plus enregistrée comme exclue ✓ CA-09 attendu : la part passe de l'organisme A à l'organisme B (encours A 564 → 0, B 0 → 564) [réponse {"msg":"Opération effectuée avec succèss","success":true,"refId":"b41274a0-a8c2-4303-8bfa-52303a5984 ; encours A 0 ; encours B 564 ; lignes ZZAUDIT-TP-CA09B/80/564/is_Closed/unpaid] ✓ N5 attendu : changer le tiers payant d'une vente déjà facturée (ligne « charged ») est refusé, la ligne facturée reste [réponse {"msg":"Cette vente a déjà été facturée à l'organisme : son client ou ses tiers payants ne se modifi ; ligne facturée encore présente ? 1 ; lignes de la vente ZZAUDIT-TP-CA09A/80/564/is_Closed/charged] ✓ Aucune erreur JavaScript [] ✓ Jeu d'essai retiré (ventes, clients, tiers payants, factures), stocks et paramètres remis [ventes restantes 0] | E10: OK | L10: =IF(I10="","",IF(I10=E10,"Oui","Non"))
A11: 16 | B11: audits/repro-vente-comptant.js | C11: REPRODUCTION — MODULE VENTE COMPTANT (constats VC-01, VC-02, VC-04, VC-08, VC-09, VC-11, VC-12, VC-14, N1, N2). Chaque cas joue le parcours de l'ecran de vente par son API (session du compte de test) et affirme le comportement ATTENDU : FAIL = defaut reproduit, avec la mesure entre crochets. Jeu d'essai retire a la fin. | D11: 17 / 17 conformes ✓ VC-01 précondition : vente comptant de 2 boîtes encaissée [8d09a52f-8793-423d-8a3a-776661739806] ✓ VC-01 attendu : modifier la quantité d'une ligne d'une vente encaissée est refusé, ligne inchangée (2 boîtes) [réponse {"msg":"Cette vente (N° 261030_00185) a été clôturée le 30/10/2026 10:05 : elle ne peut plus être modifiée ici. Pour retirer un produit, passez par « Ventes ter ; ligne après = qté|montant 2|6950 ; vente {"statut":"is_Closed","annulee":false,"prix":6950,"remise":0,"partClient":0,"tva":0,"client":"NULL"} ; stock 98] ✓ VC-02 attendu : « Terminer la prévente » sur une vente encaissée est refusé, statut is_Closed conservé [réponse {"msg":"Cette vente (N° 261030_00186) a été clôturée le 30/10/2026 10:05 : elle ne peut plus être modifiée ici. Pour ret ; statut après is_Closed ; transactions de caisse 1] ✓ VC-04 précondition : modification ouverte (copie en cours) [{"msg":"Opération effectuée avec success","data":{"lgPREENREGISTREMENTID":"bd0c40ad-22a6-4fb3-a526-ae8c8f93d17a","intPRICE":3475,"intPRICEREMISE":0,"strREF":"26] ✓ VC-04 attendu : annuler la vente pendant sa modification est refusé, ou la clôture de la copie ne la réannule pas (une seule annulation ; stock = stock de départ − 1 car la copie est vendue) [annulation {"msg":"Cette vente est en cours de modification : terminez ou abandonnez la mod ; clôture copie {"s":true,"m":"Opération effectuée avec success"} ; annulations de l'origine 1 ; stock départ 97 → fin 96 ; somme caisse origine+copie+annulations 3475 (attendu 3475)] ✓ VC-08 précondition : vente encaissée rattachée au client d'essai [{"statut":"is_Closed","annulee":false,"prix":3475,"remise":0,"partClient":0,"tva":0,"client":"ZZAUDIT-CL-VC08"}] ✓ VC-08 attendu : changer le client d'une vente encaissée (identifiant inconnu) est refusé, client conservé [réponse {"msg":"Cette vente (N° 261030_00189) a été clôturée le 30/10/2026 10:05 : elle ne peut plus être modifiée ici. Pour ret ; client après ZZAUDIT-CL-VC08] ✓ VC-09 précondition : deux ventes en cours de 1 boîte chacune, stock 1, FORCER_STOCK_VENTE = 0 [128320bc-eb22-4d99-93aa-ef7bc838cdc5 / fb72b796-9118-4a70-bf0c-ce8f5b7e357e] ✓ VC-09 attendu : la seconde validation est refusée, le stock ne passe pas sous zéro [clôture 1 true ; clôture 2 {"s":false,"m":"Impossible de valider la vente : stock insuffisant pour A CIN 500MG CPR PELL B/3 (une autre vente l'a peut-être pris entre-temps). Veuillez modifier la vente."} ; stock final 0] ✓ VC-11 précondition : lot A (péremption proche) épuisé, lot B à 5 ; la vente de 2 boîtes sort du lot B [ZZAUDIT-LOT-A=0,ZZAUDIT-LOT-B=3] ✓ VC-11 attendu : l'annulation rend les 2 boîtes au lot B d'où elles sont sorties (A=0, B=5) [annulation true ; lots après annulation ZZAUDIT-LOT-A=0,ZZAUDIT-LOT-B=5] ✓ VC-12 attendu : toutes les écritures de la modification d'une vente d'hier portent la même date [clôture copie true ; transaction de la copie 2026-10-29 ; contre-passation 2026-10-29,2026-10-29 ; recette de la copie 2026-10-29 ; mouvement de stock de la copie 2026-10-29 ; mouvement de stock de l'annulation 2026-10-29,2026-10-29 ; aujourd'hui 2026-10-30] ✓ VC-14 attendu : une clôture qui déclare 1 F payé pour une vente de 6950 F est refusée [clôture {"s":false,"m":"Le montant réglé (1 F) est inférieur au net de la vente (6950 F) : vérifiez les montants saisis, ou choisissez le règlement en différé."} ; transaction montant|net|payé|réglé ; recette aucune] ✓ N1 attendu : une annulation qui échoue (produit sans ligne de stock dans l'emplacement) ne laisse aucune écriture [réponse {"msg":"Annulation impossible : le produit A CIN 500MG CPR PELL B/3 n'a pas de ligne de stock dans l'emplacement de la v ; vente annulée ? false ; copies d'annulation 0 ; contre-passations 0] ✓ N2 attendu : ouvrir la modification d'une vente annulée est refusé [réponse {"msg":"Seule une vente terminée et non annulée peut être modifiée : actualisez la liste des ventes.","success":false,"http":200} ; vente renvoyée comme « copie » : statut|copy|prix|annule -] ✓ Aucune erreur JavaScript [] ✓ Jeu d'essai retiré (ventes, clients, tiers payants, factures), stocks et paramètres remis [ventes restantes 0] | E11: OK | L11: =IF(I11="","",IF(I11=E11,"Oui","Non"))
A12: 17 | B12: audits/repro-vo-remise.js | C12: REPRODUCTION — REMISE SUR LA VENTE ASSURANCE (constats CR-05, N3, CR-06). Remise d'essai de 10 % (grille VO), tiers payant d'essai a 80 % puis a 95 %, client pose en base. FAIL = defaut reproduit (mesure entre crochets). Lancement seul : node src/test/e2e/audits/repro-vo-remise.js | D12: 9 / 9 conformes ✓ CR-05 précondition : remise appliquée sur la vente assurance [{"statut":"is_Closed","annulee":false,"prix":2010,"remise":40,"partClient":362,"tva":0,"client":"ZZAUDIT-CL-VR80"} ; net affiché 360] ✓ CR-05 attendu : en espèces, le montant réglé de la transaction = montant payé par le client (net arrondi de la part client 362) [prix 2010 ; remise 40 ; parts TP 1608 ; part client 362 ; transaction payé|réglé|remise 360|360|40] ✓ N3 attendu : en différé sans acompte, la dette du client = part client (362) [part client 362 ; remise 40 ; dette prix|reste 362|362] ✓ CR-06 attendu : avec une remise (10 %) supérieure à la part client (5 %), parts TP + part client = prix − remise [prix 2010 ; remise 10 ; parts TP 1909 ; part client 91 ; total 2000 (attendu 2000)] ✓ Règle 1 attendu : produit remisable seul à 80 % : remise = part client (402) × 10 % = 40, part client = 362 [prix 2010 ; parts TP 1608 ; remise 40 (ligne 40) ; part client 362] ✓ Règle 2 attendu : remisable + non remisable : remise sur la seule part client du remisable (402 → 40), 0 sur l'autre, part client = total des parts client − remise [clôture true ; prix 2010 + 2755 ; parts TP 3812 ; remises lignes 40 / 0 ; remise vente 40 ; part client 913 (attendu 913)] ✓ Règle 3 attendu : plafond par vente de 1 000 : part de l'organisme = 1 000, répartie au prorata ; remise sur la part client augmentée du remisable (1588 → 158) [clôture true ; prix 2010 + 2755 ; parts TP 1000 ; remises lignes 158 / 0 ; remise vente 158 ; part client 3607 (attendu 3607)] ✓ Aucune erreur JavaScript [] ✓ Jeu d'essai retiré (ventes, clients, tiers payants, factures), stocks et paramètres remis [ventes restantes 0] | E12: OK | L12: =IF(I12="","",IF(I12=E12,"Oui","Non"))
A13: 18 | B13: audits/test-ecran-assurances-client-depot.js | C13: VENTE EN DEPOT > FICHE DU CLIENT ASSURE : grille des complementaires modifiable, avec les memes controles que celle de l'ecran de vente de l'officine (decision du 29/10 au cahier de recette). La fiche du depot est une copie de celle de l'officine : la grille y etait restee en lecture seule, et « Associer une assurance » acceptait 0 % et une priorite deja prise. Preparation (hors parcours teste) : client d'essai, assurance principale A (80 %, priorite 1) et complementaires C (10 %, priorite 2) et F (10 %, priorite 3). Parcours de l'utilisateur, a la souris et au clavier : - GESTION DES TIERS-PAYANTS > « Gestion depots extensions », onglet « Saisir vente dépôt », type « Assurance », client cherche au clavier ; bouton de modification du client ; - grille : taux et matricule de C modifies d'un clic dans la cellule, « Enregistrer » : enregistres ; - grille : priorite de l'autre assurance et taux de 150 refuses, avec un message ; - « Associer une assurance » : taux 0 puis priorite prise refuses, la fenetre reste ouverte. Jeu d'essai retire a la fin. Lancement seul : node src/test/e2e/audits/test-ecran-assurances-client-depot.js | D13: 8 / 8 conformes ✓ Grille du dépôt : taux et matricule de C modifiés à l'écran puis enregistrés [15/ZZAUDIT-MATD {"data":{"strLASTNAME":"ZZAUDIT DEPOTG","lgTIERSPAYANTID":"ZZAUDIT-TP-GA","fullName":"ESSAI ZZAUDIT DEPOTG","preenregistrementstp":[],"lgCLIENTID":"ZZ] ✓ Grille du dépôt : priorité déjà portée refusée, avec un message [saisi 3, C garde 2, message « Priorité 3 déjà portée par ZZAUDIT-TP-GF »] ✓ Grille du dépôt : taux de 150 % refusé, avec un message [C garde 15 %, message « Taux de 1 à 100 % seulement »] ✓ « Associer une assurance » du dépôt : taux de 0 % refusé, la fenêtre reste ouverte, le champ marqué [fenêtre ouverte] ✓ « Associer une assurance » du dépôt : priorité déjà prise refusée, la fenêtre reste ouverte [] ✓ Après « Enregistrer » : aucune priorité en double, E non rattachée [ZZAUDIT-TP-GA/1/1 ; ZZAUDIT-TP-GC/2/0 ; ZZAUDIT-TP-GF/3/0] ✓ Aucune erreur JavaScript, aucun message d'erreur [] ✓ Jeu d'essai retiré (ventes, clients, tiers payants, factures), stocks et paramètres remis [ventes restantes 0] | E13: OK | L13: =IF(I13="","",IF(I13=E13,"Oui","Non"))
A14: 19 | B14: audits/test-ecran-assurances-client-priorites.js | C14: ECRAN DE VENTE > FICHE DU CLIENT ASSURE : une priorite n'est portee que par une assurance (retours de recette du 28/10, M3 et point 21). Rejoue le parcours signale, a la souris et au clavier, sans appel direct au serveur : - client d'essai : assurance principale A (90 %, priorite 1) et complementaire C (10 %, priorite 2) ; - SERVICE CLIENT > Ventes > nouvelle vente, type « Assurance » ; client cherche au clavier, ligne cliquee ; - bouton de modification du client : assurance principale remplacee par B (tapee, choisie dans la liste), « Enregistrer » : A reste rattachee et active, a une priorite libre ; - de nouveau la fiche : « Associer une assurance », D a 10 % avec la priorite proposee, « Enregistrer » deux fois : la priorite proposee est libre, et aucune priorite n'est portee par deux assurances actives. Jeu d'essai (tiers payants, client, vente ouverte) retire a la fin. | D14: 18 / 18 conformes ✓ Jeu d'essai : A priorité 1 (RO), C priorité 2 [ZZAUDIT-TP-SA/1/1 ; ZZAUDIT-TP-SC/2/0] ✓ Principale remplacée par B : enregistrement accepté [{"data":{"strLASTNAME":"ZZAUDIT SCENP","lgTIERSPAYANTID":"ZZAUDIT-TP-SB","fullName":"ESSAI ZZAUDIT SCENP","preenregistrementstp":[],"lgCLIENTID":"ZZAUDIT-CL-SCENP","dblPLAFOND":0,"lgCATEGORIEAYANTDROI] ✓ B devient la principale (priorité 1, RO) [ZZAUDIT-TP-SB/1/1 ; ZZAUDIT-TP-SC/2/0 ; ZZAUDIT-TP-SA/3/0] ✓ L'ancienne principale A reste rattachée et active, à une priorité libre (point 21) [ZZAUDIT-TP-SB/1/1 ; ZZAUDIT-TP-SC/2/0 ; ZZAUDIT-TP-SA/3/0] ✓ Aucune priorité portée par deux assurances (après le changement de principale) [ZZAUDIT-TP-SB/1/1 ; ZZAUDIT-TP-SC/2/0 ; ZZAUDIT-TP-SA/3/0] ✓ « Associer une assurance » propose une priorité libre [proposée 4, déjà prises 2,3] ✓ D associée : enregistrement accepté, D active [{"data":{"strLASTNAME":"ZZAUDIT SCENP","lgTIERSPAYANTID":"ZZAUDIT-TP-SB","fullName":"ESSAI ZZAUDIT SCENP","preenregistrementstp":[],"lgCLIENTID":"ZZAUDIT-CL-SCENP","dblPLAFOND":0,"lgCATEGORIEAYANTDROI / ZZAUDIT-TP-SB/1/1 ; ZZAUDIT-TP-SC/2/0 ; ZZAUDIT-TP-SA/3/0 ; ZZAUDIT-TP-SD/4/0] ✓ Aucune priorité portée par deux assurances (après l'association) [ZZAUDIT-TP-SB/1/1 ; ZZAUDIT-TP-SC/2/0 ; ZZAUDIT-TP-SA/3/0 ; ZZAUDIT-TP-SD/4/0] ✓ Une seule principale (RO) [ZZAUDIT-TP-SB/1/1 ; ZZAUDIT-TP-SC/2/0 ; ZZAUDIT-TP-SA/3/0 ; ZZAUDIT-TP-SD/4/0] ✓ Grille : taux et matricule de C modifiés à l'écran puis enregistrés [15/ZZAUDIT-MAT2] ✓ Aucune priorité portée par deux assurances (après la modification dans la grille) [ZZAUDIT-TP-SB/1/1 ; ZZAUDIT-TP-SC/2/0 ; ZZAUDIT-TP-SA/3/0 ; ZZAUDIT-TP-SD/4/0] ✓ Grille : priorité déjà portée par une autre assurance refusée, avec un message [saisi 3, C garde 2, message « Priorité 3 déjà portée par ZZAUDIT-TP-SA »] ✓ Grille : taux de 150 % refusé, avec un message [C garde 15 %, message « Taux de 1 à 100 % seulement »] ✓ « Associer une assurance » : taux de 0 % refusé, la fenêtre reste ouverte, le champ marqué [fenêtre ouverte] ✓ « Associer une assurance » : priorité déjà prise refusée, la fenêtre reste ouverte [] ✓ Après « Enregistrer » : aucune priorité en double, E non rattachée [ZZAUDIT-TP-SB/1/1 ; ZZAUDIT-TP-SC/2/0 ; ZZAUDIT-TP-SA/3/0 ; ZZAUDIT-TP-SD/4/0] ✓ Aucune erreur JavaScript, aucun message d'erreur [] ✓ Jeu d'essai retiré (ventes, clients, tiers payants, factures), stocks et paramètres remis [ventes restantes 0] | E14: OK | L14: =IF(I14="","",IF(I14=E14,"Oui","Non"))
A15: 20 | B15: audits/test-ecran-modifier-tp-vente-encours.js | C15: VENTES TERMINEES > « Modifier info client » : changement d'organisme et encours affiche (retours de recette du 28/10, CA-09). Constat : apres A -> B sur une vente, l'encours de B lu dans GESTION DES TIERS-PAYANTS > « Tiers-payants » ne bougeait pas (« 0 -> 0 »). Cet ecran additionne le reste du des bons ; le bon recree pour B avait un reste vide. Preparation (hors parcours teste) : tiers payants d'essai A, B, C ; client assure A 90 % (principale) et C 10 % ; une vente assurance encaissee sur A, au nom du compte de test. Parcours de l'utilisateur, a la souris et au clavier : - « Tiers-payants » : recherche « ZZAUDIT-TP-E », Entree, lecture de la colonne Encours de A et de B ; - SERVICE CLIENT > « Vente terminées » : dates et reference tapees, « rechercher », icone « Modifier info client » ; « Modifier le tiers-payant », B tape et choisi dans la liste, « Valider », « Enregistrer », « Non » a l'impression ; - « Tiers-payants » de nouveau : la part est sortie de A et entree dans B ; aucune priorite en double chez le client. Droit P_BTN_UPDATE_VENTE_CLIENT_TP accorde le temps du test. Jeu d'essai retire a la fin. | D15: 11 / 11 conformes ✓ Préparation : vente assurance encaissée sur A [261030_00203, part A 2551] ✓ « Tiers-payants » avant : A porte la part, B à 0 [{"A":2551,"B":0}] ✓ « Enregistrer » : modification acceptée [{"msg":"Opération effectuée avec succèss","success":true,"refId":"ac9e7cda-5413-45f2-bc93-fdbdea8746bc"}] ✓ Bon de la vente : porté par B, reste dû égal à sa part [ZZAUDIT-TP-EB|2551|2551] ✓ Bon de B : même part que celle de A à la vente [A 2551 → B 2551] ✓ « Tiers-payants » après : la part sort de A [{"A":2551,"B":0} → {"A":0,"B":2551}] ✓ « Tiers-payants » après : la part entre dans B (constat « B : 0 → 0 ») [{"A":2551,"B":0} → {"A":0,"B":2551}] ✓ Vente : part du client + part de B = prix de la vente [client 284 + B 2551 / prix 2835] ✓ Client : aucune priorité portée par deux tiers payants [ZZAUDIT-TP-EB/1/1 ; ZZAUDIT-TP-EA/2/0 ; ZZAUDIT-TP-EC/3/0] ✓ Aucune erreur JavaScript [] ✓ Jeu d'essai retiré (ventes, clients, tiers payants, factures), stocks et paramètres remis [ventes restantes 0] | E15: OK | L15: =IF(I15="","",IF(I15=E15,"Oui","Non"))
A16: 21 | B16: audits/test-ecran-modifier-vente-deja-modifiee.js | C16: VENTES TERMINEES > « Modifier » sur une vente deja modifiee (signale le 29/10 sur domain3, vente 261029_00003) : l'ecran de vente s'ouvrait vide. Le serveur refusait la modification : la copie cloturee d'une modification porte lg_PREENGISTREMENT_ANNULE_ID (sa vente d'origine), et le garde-fou N2 la prenait pour une annulation. L'ecran ignorait le refus et restait vide, sans message. Preparation (hors parcours teste) : vente comptant d'une boite encaissee, puis modifiee et la copie cloturee. Parcours de l'utilisateur, a la souris et au clavier : - SERVICE CLIENT > « Vente terminées » : date du jour, reference de la vente modifiee, « rechercher » ; - icone « Modifier » de la ligne : l'ecran de vente s'ouvre avec la vente chargee (ligne du produit visible). Jeu d'essai retire a la fin. Lancement seul : node src/test/e2e/audits/test-ecran-modifier-vente-deja-modifiee.js | D16: 6 / 6 conformes ✓ Préparation : vente modifiée, copie clôturée [261030_00021 {"s":true,"m":"Opération effectuée avec success"}] ✓ « Modifier » : le serveur ouvre la modification de la vente déjà modifiée [{"msg":"Opération effectuée avec success","data":{"lgPREENREGISTREMENTID":"6f6cfc3e-2d05-4914-a91b-23853b18288d","intPRICE":855,"intPRICEREMISE":0,"strREF":"261030_00044"},"success":true}] ✓ Écran de vente : la vente est chargée (ligne du produit visible) [ABZ 400MG CPR B/1] ✓ Une copie de modification en cours est rattachée à la vente modifiée [1] ✓ Aucune erreur JavaScript [] ✓ Jeu d'essai retiré (ventes, clients, tiers payants, factures), stocks et paramètres remis [ventes restantes 0] | E16: OK | L16: =IF(I16="","",IF(I16=E16,"Oui","Non"))
... A18: 23 | B18: audits/test-fiche-article-qte-restante-lot.js | C18: FICHE ARTICLE > « Voir les lots / péremptions » : stock restant du lot (retours de recette du 28/10, VC-11). Un lot d'essai de 10 boites dont 4 restent. Parcours de l'utilisateur, a la souris et au clavier : - menu GESTION DU STOCK > « Fiche Article » ; CIP tape dans la recherche, touche Entree ; - sur la ligne du produit, icone « Voir les lots / péremptions », ou menu « Autres actions » puis cette entree ; - la fenetre des lots montre « Quantité saisie » 10 et « Quantité restante lot » 4 sur la ligne du lot. Le stock restant vient du champ quantiteRestante de api/v1/fichearticle/perimes (version de « Recherche perimes » retenue le 28/10, branche claude/new-session-xm8ptu) : sans lui la colonne reste vide. Lot et stock d'essai retires a la fin. | D18: 4 / 4 conformes ✓ Fenêtre des lots : colonnes « Quantité saisie » puis « Quantité restante lot » [Date péremption | Quantité saisie | Quantité restante lot | N° Lot | Statut | Modifier | Supprimer] ✓ Ligne du lot d'essai : Quantité saisie 10, Quantité restante lot 4 [09/12/2026 | 10 | 4 | ZZAUDIT-LOT-FA | Périme dans 1 mois 9 jour(s) | | ] ✓ Aucune erreur JavaScript [] ✓ Jeu d'essai retiré (ventes, clients, tiers payants, factures), stocks et paramètres remis [ventes restantes 0] | E18: OK | L18: =IF(I18="","",IF(I18=E18,"Oui","Non"))

Sheet Caisse
A1: CAHIER DE RECETTE — Caisse
A2: 2 tests : 2 OK, 0 en échec selon Claude
A4: N° | B4: Test | C4: Scénario : ce qui est fait et ce qui est attendu | D4: Contrôles faits par Claude (valeur mesurée) | E4: Résultat Claude | F4: Écart constaté par Claude | G4: Catégorie et suite | H4: Résultat testeur | I4: Statut testeur | J4: Testeur | K4: Date | L4: Concorde ? | M4: Commentaire
A5: 24 | B5: caisse/test-mvt-caisse.js | C5: Point 6 : ecran Mouvements de caisse. - le filtre « Tous les types » porte bien sur les trois types du journal ; - le formulaire de creation ne propose que ces trois types ; - la date du mouvement est initialisee au jour ; - le mode de reglement est masque mais garde sa valeur ; - le montant est aligne en face du champ portant « Especes ». | D5: 11 / 11 conformes ✓ ecran mvtcaissemanager ouvert ✓ le filtre Type ne propose que les trois types du journal [["Entrees de caisse","Reglements 1/3 pay.","Sorties de caisse"]] ✓ Tous les types envoie bien les trois types [typeMvtId=5,3,4 (2 requetes observees)] ✓ le formulaire ne propose que les trois types du journal [["Entrees de caisse","Reglements 1/3 pay.","Sorties de caisse"]] ✓ la date du mouvement est initialisee au jour [true] ✓ le mode de reglement est masque [true] ✓ le mode de reglement conserve sa valeur en arriere-plan ["1"] ✓ le montant est sur la meme ligne que le champ Especes [{"memeLigne":true,"typeRegl":"Especes"}] ✓ Tous les types ramene bien les trois natures de mouvement [["Entrees de caisse","Reglements 1/3 pay.","Sorties de caisse"]] ✓ un type choisi ne ramene que ce type [["Entrees de caisse"]] ✓ aucune erreur JavaScript | E5: OK | L5: =IF(I5="","",IF(I5=E5,"Oui","Non"))
A6: 25 | B6: caisse/test-ticketz.js | C6: TICKET Z et TABLEAU DE BORD (retours du 25/10, points 3 et 4). - rapidite : le recapitulatif des 24 derniers jours (tous les mouvements, puis ventes seules, tous les caissiers) repond en moins de 5 s ; chaque vente chargee tirait une a une ses associations (30 s sur une base reelle) ; - ecran Ticket Z, ouvert par le menu (GESTION COURANTE > Ticket Z) : aucun iframe ; a l'ouverture, une carte par caissier et le total general, avec les montants de l'API ; « Ventes uniquement » relance la recherche ; - « Envoyer SMS » et « Imprimer » : l'etat s'affiche dans le bouton, sans fenetre (appels interceptes : aucun SMS envoye, rien d'imprime) ; « Aperçu » ouvre la page imprimable avec la periode et le recapitulatif ; - tableau de bord a l'accueil : le composant ExtJS, aucun iframe, meme avec KEY_TABLEAU_BORD_VERSION = ANCIEN. - retour au tableau de bord depuis le Ticket Z (ecran colle) : toute la largeur, pas un tiers. Le test ne pose aucune donnee ; le parametre du tableau de bord est remis a sa valeur. | D6: 17 / 17 conformes ✓ Connexion du compte d'essai [{"lg_EMPLACEMENT_ID":"1","privileges":[{"name":"canUpdatePrice","value":true},{"] ✓ Ticket Z sur 24 jours (ALL) : recapitulatif rendu [15 caissiers] ✓ Ticket Z sur 24 jours (ALL) en moins de 5 s [607 ms] ✓ Ticket Z sur 24 jours (VENTE) : recapitulatif rendu [13 caissiers] ✓ Ticket Z sur 24 jours (VENTE) en moins de 5 s [386 ms] ✓ Tableau de bord : composant ExtJS, aucun iframe (paramètre sur ANCIEN) [{"tableau":1,"iframes":0}] ✓ Ticket Z : ouvert par le menu, sans iframe ✓ Ticket Z : chargé à l'ouverture sur la journée (00:00 - 23:59, tous) [{"description":"ALL","userId":"ALL","dtStart":"2026-10-30","hrStart":"00:00","dtEnd":"2026-10-30","hrEnd":"23:59"}] ✓ Ticket Z de la veille : une carte par caissier + le total général, montants de l'API [2 cartes / 2] ✓ Couleurs : en-têtes des récapitulatifs colorés, deux caissiers voisins de couleurs différentes, total général coloré [{"entetes":["rgb(31, 111, 178)"],"total":"rgb(31, 58, 95)","ligneTotal":"rgb(232, 245, 238)","totalTexte":"rgb(31, 58, 95)"}] ✓ « Ventes uniquement » relance la recherche avec ce filtre [{"description":"VENTE","userId":"ALL","dtStart":"2026-10-28","hrStart":"00:00","dtEnd":"2026-10-28","hrEnd":"23:59"}] ✓ « Envoyer SMS » et « Imprimer » : appel envoyé, état dans le bouton [SMS envoyé / Envoyé à l'imprimante] ✓ Les boutons reprennent leur libellé ✓ Aperçu : période, filtre et récapitulatif [Imprimer Fermer ✓ Retour au tableau de bord après le Ticket Z : toute la largeur [{"corps":1567,"tableau":1551}] ✓ Aucune boîte de dialogue [] ✓ Paramètre du tableau de bord remis | E6: OK | L6: =IF(I6="","",IF(I6=E6,"Oui","Non"))

Sheet Campagnes et WhatsApp
A1: CAHIER DE RECETTE — Campagnes et WhatsApp
A2: 8 tests : 7 OK, 1 en échec selon Claude
A4: N° | B4: Test | C4: Scénario : ce qui est fait et ce qui est attendu | D4: Contrôles faits par Claude (valeur mesurée) | E4: Résultat Claude | F4: Écart constaté par Claude | G4: Catégorie et suite | H4: Résultat testeur | I4: Statut testeur | J4: Testeur | K4: Date | L4: Concorde ? | M4: Commentaire
A5: 26 | B5: campagnes/test-campagne-piece-jointe.js | C5: CAMPAGNES WHATSAPP : PIECE JOINTE (retour du 24/10, repris du CRM UBIPHARM), par l'ecran. Service WhatsApp Web d'essai (WHATSAPP_FAUX=1, trace des envois sans numero ni texte) lance par le test ; compte WEB pointe dessus, mode WhatsApp par defaut sur Web, mode test coupe pour que le message aille vraiment au service. Un seul client fictif (ZZPIECE) avec accord WhatsApp explicite. Tout est remis en place a la fin. - onglet « Infos clients » : le bouton « Joindre une image ou un PDF » n'apparait que pour un canal WhatsApp ; - un fichier texte est refuse avec le motif ; une image PNG est acceptee (nom et taille affiches, « Retirer ») ; - repasser en SMS retire la piece ; - envoi (confirmation dans le bouton) : la piece est gardee sur la campagne et le service la recoit intacte (meme empreinte), le message en legende ; - l'API refuse une piece pour le canal SMS, un fichier qui n'est ni image ni PDF, et le mode API de Meta ; - aucune fenetre, aucune erreur JavaScript ; le texte du message n'apparait pas dans les journaux. | D5: 21 / 21 conformes ✓ Canal SMS : pas de bouton « Joindre une image ou un PDF » ✓ Canal WhatsApp : bouton « Joindre une image ou un PDF » affiché ✓ Fichier texte refusé avec le motif, rien de joint [La pièce jointe doit être une image JPEG, PNG ou un document PDF.] ✓ Image PNG jointe : nom et taille affichés, « Retirer » proposé, motif effacé [ visuel-promo.png (1 Ko)] ✓ Retour au canal SMS : pièce retirée ✓ Un destinataire joignable (accord WhatsApp explicite) [1] ✓ La pièce reste jointe après la recherche et la saisie du message ✓ Confirmation dans le bouton (sans fenêtre) [Confirmer l'envoi à 1 client(s)] ✓ Envoi accepté ; la pièce est retirée de l'écran après l'envoi [1 message(s) WhatsApp en cours d'envoi.] ✓ Campagne : pièce gardée intacte (type, nom, empreinte) [WHATSAPP|image|image/png|visuel-promo.png|497790947d4666760ce38f3c00e852c71fdb66cae849bae8e9ede352719e1581] ✓ Service WhatsApp Web : image reçue intacte, message en légende, un seul envoi [[{"nature":"media","type":"image","mimeType":"image/png","nomFichier":"visuel-promo.png","octets":70,"sha256":"497790947d4666760ce38f3c00e852c71fdb66cae849bae8e9ede352719e1581","legende":true}]] ✓ Message WhatsApp du client : envoyé (pas simulé) [ENVOYE:0] ✓ La pièce n'est pas gardée sur le poste du service après l'envoi ✓ API : pièce jointe refusée pour le canal SMS [{"success":false,"message":"Une pièce jointe ne part que par WhatsApp : choisissez le canal WhatsApp."}] ✓ API : fichier ni image ni PDF refusé (reconnu à son contenu, pas à son nom) [{"success":false,"message":"La pièce jointe doit être une image JPEG, PNG ou un document PDF."}] ✓ API : mode WhatsApp « API de Meta » -> pièce refusée, avec la marche à suivre [{"success":false,"message":"Les pièces jointes partent par WhatsApp Web seulement : réglez le mode WhatsApp sur Web (Paramétrage WhatsApp)."}] ✓ Les refus ne créent aucune campagne ✓ Le texte du message n'apparaît ni dans le journal du serveur ni dans celui du service ✓ Aucune fenêtre [] ✓ Aucune erreur JavaScript [] ✓ Tout est remis en état | E5: OK | L5: =IF(I5="","",IF(I5=E5,"Oui","Non"))
A6: 27 | B6: campagnes/test-campagnes-canal-defaut.js | C6: CAMPAGNES : WHATSAPP SEUL PAR DEFAUT (retours du 25/10, point 14). Par les vues (admin), Campagnes SMS / WhatsApp > Campagnes : - chaque onglet d'envoi (Anniversaires, Fêtes, Infos clients, Infos pharmacie, Personnalisé) et l'onglet Propositions s'ouvrent sur le canal « WhatsApp » ; - les modeles proposes sont ceux du canal WhatsApp ; - SMS et « WhatsApp, repli SMS » restent au choix ; - aucune erreur JavaScript, aucune fenetre du navigateur. Rien n'est envoye ni ecrit. | D6: 4 / 4 conformes ✓ Onglets d'envoi et Propositions : canal WhatsApp par défaut [ongletPropositions=WHATSAPP, onglet-ANNIVERSAIRE=WHATSAPP, onglet-FETE=WHATSAPP, onglet-INFO_CLIENTS=WHATSAPP, onglet-INFO_PHARMACIE=WHATSAPP, onglet-PERSONNALISE=WHATSAPP] ✓ SMS et « WhatsApp, repli SMS » restent au choix [SMS,WHATSAPP,SMS_WHATSAPP] ✓ Modèles proposés : ceux du canal WhatsApp [WHATSAPP] ✓ Aucune erreur JavaScript, aucune fenêtre du navigateur [] | E6: OK | L6: =IF(I6="","",IF(I6=E6,"Oui","Non"))
A7: 28 | B7: campagnes/test-campagnes-destinataires-demande.js | C7: CAMPAGNES : DESTINATAIRES CHARGES A LA DEMANDE (retours du 25/10, point 14, lenteur des onglets). Par les vues (admin), Campagnes SMS / WhatsApp > Campagnes : - ouvrir les onglets Infos clients, Infos pharmacie et Personnalisé n'envoie aucune recherche de destinataires (avant : jusqu'a 5 000 clients charges a l'ouverture) ; la grille invite a cliquer sur « Voir les destinataires » ; - l'onglet Anniversaires charge toujours ses destinataires a son ouverture (clients du jour) ; - « Voir les destinataires » sur Infos pharmacie charge la liste ; - aucune erreur JavaScript, aucune fenetre du navigateur. Rien n'est envoye ni ecrit. | D7: 5 / 5 conformes ✓ Anniversaires : destinataires chargés à l'ouverture [ANNIVERSAIRE] ✓ Infos clients, Infos pharmacie, Personnalisé : aucune recherche à l'ouverture [] ✓ La grille invite à cliquer sur « Voir les destinataires » [0:true | 0:true] ✓ « Voir les destinataires » charge la liste [INFO_PHARMACIE] ✓ Aucune erreur JavaScript, aucune fenêtre du navigateur [] | E7: OK | L7: =IF(I7="","",IF(I7=E7,"Oui","Non"))
A8: 29 | B8: campagnes/test-campagnes-listes.js | C8: CAMPAGNES : LISTES DE DIFFUSION (retours du 25/10, point 14). Jeu d'essai : 3 clients d'essai « ZZLISTE » (WhatsApp accepte), retires a la fin avec la liste. Par les vues (admin), Campagnes SMS / WhatsApp > Campagnes > Listes de diffusion : - creer une liste nommee (nom vide refuse, nom en double refuse, message dans l'ecran) ; - chercher « ZZLISTE » (3 caracteres), cocher 2 clients, « Ajouter les clients cochés » : la liste en compte 2 ; - retirer un client : confirmation dans le bouton (1er clic), retrait au 2e clic ; - Infos clients, filtre « Liste » : « Voir les destinataires » ne donne que le client de la liste ; - supprimer la liste : confirmation dans le bouton ; - aucune erreur JavaScript, aucune fenetre (navigateur ou ExtJS). Rien n'est envoye. | D8: 13 / 13 conformes ✓ Nom vide : refusé, message dans l'écran [Donnez un nom à la liste.] ✓ Liste créée et choisie (Entrée) [Liste « E2E liste 1793355026480 » créée : ajoutez des clients à droite.] ✓ Nom en double : refusé [Une liste porte déjà ce nom.] ✓ Recherche « ZZLISTE », 2 clients cochés ajoutés [2 client(s) ajouté(s).] ✓ Nombre de clients affiché dans les listes ✓ Retrait : confirmation dans le bouton, rien retiré au 1er clic ✓ Retrait au 2e clic ✓ Infos clients, filtre « Liste » : seul le client de la liste [E2E-LISTE-0] ✓ Sans liste : les 3 clients « ZZLISTE » ✓ Suppression : confirmation dans le bouton ✓ Liste supprimée au 2e clic (inscriptions retirées, clients gardés) [Liste supprimée.] ✓ Aucune erreur JavaScript, aucune fenêtre [] ✓ Jeu d'essai retiré | E8: OK | L8: =IF(I8="","",IF(I8=E8,"Oui","Non"))
A9: 30 | B9: campagnes/test-campagnes-parametres-0825.js | C9: CAMPAGNES : PARAMETRES DU 25/10 (point 14). Par les vues (admin), Campagnes SMS / WhatsApp > Campagnes > Paramètres : - canal propose des campagnes automatiques : WhatsApp ; - « Réponse comptée dans les » : 7 jours par defaut ; 0 ou 91 refuses (message, rien d'enregistre) ; - delai mis a 3 jours : dans le Journal, une reponse ecrite 5 jours apres l'envoi n'est plus comptee, celle ecrite 2 jours apres l'est toujours ; - aucune erreur JavaScript, aucune fenetre. Parametres remis a leur valeur et jeu d'essai retire a la fin. | D9: 9 / 9 conformes ✓ Journal, délai par défaut (7 jours) : 2 réponses comptées ✓ Campagnes automatiques : canal WhatsApp [{"canal":"WHATSAPP","delai":7,"libelle":"Réponse comptée dans les (jours après l'envoi)"}] ✓ « Réponse comptée dans les » : 7 jours par défaut [{"canal":"WHATSAPP","delai":7,"libelle":"Réponse comptée dans les (jours après l'envoi)"}] ✓ Délai 0 refusé, rien enregistré [Le délai de réponse doit être compris entre 1 et 90 jours.] ✓ Délai 91 refusé, rien enregistré [Le délai de réponse doit être compris entre 1 et 90 jours.] ✓ Délai 3 jours enregistré ✓ Journal, délai 3 jours : seule la réponse à 2 jours est comptée ✓ Aucune erreur JavaScript, aucune fenêtre [] ✓ Paramètres remis, jeu d'essai retiré | E9: OK | L9: =IF(I9="","",IF(I9=E9,"Oui","Non"))
A10: 31 | B10: campagnes/test-campagnes-suivi.js | C10: CAMPAGNES : SUIVI MESSAGE PAR MESSAGE (retours du 25/10, point 14). Jeu d'essai : une campagne envoyee le jour meme a 5 clients d'essai (WhatsApp) : 1 lu et repondu (le client a ecrit dans les 7 jours), 1 distribue, 1 envoye, 1 en echec, 1 ecarte (motif). Retire a la fin. Par les vues (admin), Campagnes SMS / WhatsApp > Campagnes > Journal : - la ligne de la campagne donne Distribués 2, Lus 1, Répondus 1, Échecs 1 ; - un clic sur la ligne affiche, sous le journal (pas de fenetre), le suivi : un client par ligne avec son etat (Lu, Distribué, Envoyé, Échec, Exclu + motif) et « Répondu » ; les totaux au-dessus ; - un message passe a « lu » : le suivi se met a jour seul (toutes les 20 s) ; - la reponse du serveur ne contient aucun texte de message ; - aucune erreur JavaScript, aucune fenetre du navigateur. | D10: 8 / 8 conformes ✓ Journal : Distribués 2, Lus 1, Répondus 1, Échecs 1 (colonnes affichées) [{"d":2,"l":1,"rep":1,"e":1,"cols":["Date","Campagne","Origine","Statut","Canal","Modèle","Clients","Préparés","Partis","Distribués","Lus","Répondus","Échecs","Écartés","Par"]}] ✓ Suivi sous le journal, sans fenêtre [{"lignes":{"DELIVRE":"Distribué","ECHEC":"Échec","ENVOYE":"Envoyé","EXCLU":"Exclu:Sans numéro","LU":"Lu+R"},"totaux":"Envoyés : 3 · Distribués : 2 · Lus : 1 · Répondus : 1 · Échecs : 1 · En attente : 0 · Écartés : 1","dessous":true,"fenetres":0}] ✓ Un état par client (Lu + répondu, Distribué, Envoyé, Échec, Exclu + motif) [{"DELIVRE":"Distribué","ECHEC":"Échec","ENVOYE":"Envoyé","EXCLU":"Exclu:Sans numéro","LU":"Lu+R"}] ✓ Totaux : 3 envoyés, 2 distribués, 1 lu, 1 répondu, 1 échec [Envoyés : 3 · Distribués : 2 · Lus : 1 · Répondus : 1 · Échecs : 1 · En attente : 0 · Écartés : 1] ✓ Évolution des envois : le suivi se met à jour seul ✓ Aucun texte de message dans la réponse du serveur [752] ✓ Aucune erreur JavaScript, aucune fenêtre du navigateur [] ✓ Jeu d'essai retiré | E10: OK | L10: =IF(I10="","",IF(I10=E10,"Oui","Non"))
A11: 32 | B11: campagnes/test-campagnes.js | C11: CAMPAGNES SMS / WHATSAPP (besoins du 11/10, lot 4), par l'ecran. Jeu d'essai isole (clients fictifs ZZCAMPAGNE, numeros fictifs) et compte WhatsApp en MODE TEST : aucun message reel ne part (les envois du test passent par WhatsApp simule, jamais par SMS). - menu : 10 onglets dont « Rappels traitement » (l'ecran existant) et « Listes de diffusion » ; volet automatique desactive par defaut ; - propositions : « Préparer les propositions du jour » -> anniversaires du jour (refus SMS et numero invalide ecartes avec leur motif) ; la cloche compte les messages proposes ; on decoche un client, on envoie en WhatsApp (confirmation dans le bouton, sans fenetre) ; le decoche ne recoit rien ; pas de seconde proposition le meme jour ; - fetes : date d'une fete « a saisir » renseignee dans le calendrier ; proposition de la fete ; abandon (rien n'est envoye) ; - infos clients : filtres (recherche, sexe), motifs d'exclusion, « accord explicite seulement », message modifie (texte libre), apercu personnalise (nom de famille / prenom), envoi WhatsApp simule ; - journal ; le texte libre n'est conserve ni dans les tables des campagnes ni dans les journaux du serveur ; - sans le droit P_SM_CAMPAGNES, l'API refuse ; aucune fenetre, aucune erreur JavaScript ; tout est remis. | D11: 21 / 27 conformes ✗ Précondition : aucun vrai client actif né un 10-30 ✓ Menu « Campagnes SMS / WhatsApp » (menu principal) : sous-menus Campagnes, Comptes WhatsApp et Discussions WhatsApp [CAMPAGNES SMS / WHATSAPP > Campagnes, Comptes WhatsApp, Discussions WhatsApp] ✓ 10 onglets, dont Rappels traitement et Listes de diffusion [Propositions|Anniversaires|Fêtes|Infos clients|Infos pharmacie|Personnalisé|Rappels traitement|Listes de diffusion|Journal|Paramètres] ✓ Volet automatique désactivé par défaut (bandeau) [ La préparation automatique est désactivée (onglet Paramètres). Vous pouvez préparer les propositions du jour à la demande.] ✗ Proposition « Anniversaires du jour » : seuls les clients nés ce jour [{"titre":"Anniversaires du 30/10/2026","l":{"ZZCAMPAGNE AWA":"OK","ZZCAMPAGNE EMMA":"OK","ZZWHATSAPP AWA":"OK","ZZCAMPAGNE BINTOU":"A refusé les SMS","ZZCAMPAGNE CHANTAL":"Numéro absent ou invalide"},"coches":3,"onglet":"Propositions (3)"}] ✗ Refus SMS et numéro invalide écartés avec leur motif ; joignables cochés [{"titre":"Anniversaires du 30/10/2026","l":{"ZZCAMPAGNE AWA":"OK","ZZCAMPAGNE EMMA":"OK","ZZWHATSAPP AWA":"OK","ZZCAMPAGNE BINTOU":"A refusé les SMS","ZZCAMPAGNE CHANTAL":"Numéro absent ou invalide"},"coches":3,"onglet":"Propositions (3)"}] ✗ Cloche : 2 messages proposés, catégorie affichée d'office [{"n":3,"actif":true}] ✗ Bouton « Envoyer à 1 client(s) », confirmation dans le bouton (sans fenêtre) [Envoyer à 2 client(s) → Confirmer l'envoi à 2 client(s)] ✗ Envoyé à AWA seulement ; EMMA décochée ; écartés conservés [E2E-CMP-A:PREPARE,E2E-CMP-B:EXCLU,E2E-CMP-C:EXCLU,E2E-CMP-E:DECOCHE,E2E-WA-A:PREPARE] ✓ WhatsApp simulé (mode test) pour AWA, rien pour EMMA [E2E-CMP-A:SIMULE:1] ✓ Proposition envoyée, cloche à 0 ✓ Pas de seconde proposition le même jour ✓ Calendrier : date de Tabaski saisie pour 2026 ✓ Proposition de la fête du jour [Fêtes — Tabaski (Aïd el-Kébir) du 30/10/2026] ✓ Abandon à confirmer dans le bouton ✓ Abandon : rien n'est envoyé ✓ Filtres recherche + sexe F : 4 clientes, joignables d'abord [{"l":["ZZCAMPAGNE AWA=OK","ZZCAMPAGNE EMMA=OK","ZZCAMPAGNE BINTOU=A refusé les SMS","ZZCAMPAGNE CHANTAL=Numéro absent ou invalide"],"titre":"Destinataires : 2 joignable(s) sur 4","c":2}] ✓ WhatsApp + accord explicite seulement : DRISSA seul joignable, les autres « Pas d'accord explicite » [{"l":{"ZZCAMPAGNE DRISSA":"OK","ZZCAMPAGNE AWA":"Pas d'accord explicite","ZZCAMPAGNE BINTOU":"Pas d'accord explicite","ZZCAMPAGNE CHANTAL":"Pas d'accord explicite","ZZCAMPAGNE EMMA":"Pas d'accord explicite"},"c":1}] ✓ Un client non joignable ne se coche pas [1] ✓ Aperçu personnalisé : prénom (DRISSA), nom de famille non pris pour le prénom [Bonjour DRISSA, essai e2e 1793355085216 de la pharmacie.Pour ZZCAMPAGNE DRISSA · 56 caractères] ✓ Bouton « Envoyer à 1 client(s) » ✓ Campagne manuelle « Infos clients » : DRISSA, WhatsApp simulé, message saisi (pas de modèle) ✓ Journal : proposition envoyée, fête abandonnée, campagne manuelle [Infos clients du 30/10/2026|ENVOYEE|Manuelle ; Fêtes — Tabaski (Aïd el-Kébir) du 30/10/2026|ABANDONNEE|Proposition ; Anniversaires du 30/10/2026|ENVOYEE|Proposition] ✓ Texte libre absent des tables des campagnes et des journaux du serveur ✓ Sans le droit : l'API refuse [[{"success":false,"message":"Votre profil ne donne pas accès aux campagnes."},{"success":false,"message":"Votre profil ne donne pas accès aux campagnes."}]] ✓ Aucune fenêtre, aucune erreur JavaScript [] ✓ Jeu d'essai, campagnes, compte, paramètres et calendrier remis | E11: Échec | F11: Précondition : aucun vrai client actif né un 10-30 Proposition « Anniversaires du jour » : seuls les clients nés ce jour [{"titre":"Anniversaires du 30/10/2026","l":{"ZZCAMPAGNE AWA":"OK","ZZCAMPAGNE EMMA":"OK","ZZWHATSAPP AWA":"OK","ZZCAMPAGNE BINTOU":"A refusé les SMS","ZZCAMPAGNE CHANTAL":"Numéro absent ou invalide"},"coches":3,"onglet":"Propositions (3)"}] Refus SMS et numéro invalide écartés avec leur motif ; joignables cochés [{"titre":"Anniversaires du 30/10/2026","l":{"ZZCAMPAGNE AWA":"OK","ZZCAMPAGNE EMMA":"OK","ZZWHATSAPP AWA":"OK","ZZCAMPAGNE BINTOU":"A refusé les SMS","ZZCAMPAGNE CHANTAL":"Numéro absent ou invalide"},"coches":3,"onglet":"Propositions (3)"}] | G11: Données de la copie : Un vrai client actif est né un 30/10 : le test suppose qu'aucun ne l'est. | L11: =IF(I11="","",IF(I11=E11,"Oui","Non"))
A12: 33 | B12: campagnes/test-whatsapp-discussions.js | C12: FILS DE DISCUSSION WHATSAPP (demande du 25/10, repris du CRM UBIPHARM). Chemin reel des reponses : POST /api/v1/whatsapp/webhook-web avec le jeton partage (comme le service WhatsApp Web), corps {entrants:[{numero, texte, type, nom, id}]}. Puis par les vues (admin) : CAMPAGNES SMS / WHATSAPP > Discussions WhatsApp. Jeu d'essai isole (clients ZZDISC), compte WEB en mode test (aucun envoi reel), remis a la fin. - deux reponses du client A (dont une depuis l'ancien identifiant a 8 chiffres) et une du client B (qui a dit STOP) ; le meme message recu deux fois n'est garde qu'une fois ; - liste : A avec son nom de client et 2 non lus, B marque STOP ; recherche par mot du message ; « Non lues » ; - clic sur A : le fil, dans l'ordre, et les non lus passent a lus ; - reponse depuis un texte avec {prenom} : bouton « Envoyer » -> « Confirmer l'envoi » -> envoi simule ; la bulle affiche le prenom remplace, l'auteur et « simulé » ; reponse avec un PDF joint ; - B (STOP) : zone de reponse fermee avec le motif ; l'API refuse aussi ; - sans session : 401 ; le journal du serveur ne contient ni le texte des messages ni les numeros ; - aucune erreur JavaScript, aucune fenetre du navigateur. Donnees de l'essai retirees. | D12: 15 / 15 conformes ✓ Table des discussions créée par la migration [whatsapp_discussion] ✓ Webhook : 2 messages gardés pour A (doublon ignoré, ancien numéro à 8 chiffres rattaché), non lus [200 2|2|0] ✓ Liste : A au nom du client avec 2 non lus ; B marqué STOP [{"a":{"nom":"Awa ZZDISC","nl":"2","stop":false,"dernier":"Merci beaucoup"},"b":{"nom":"Bintou ZZDISC","nl":"1","stop":true,"dernier":"Bonjour"}}] ✓ Recherche « Doliprane » : seulement la discussion de A [0708771122] ✓ Clic sur A : le fil dans l'ordre ; messages passés à lus, pastille retirée [{"fil":["E:Bonjour, avez-vous du Doliprane 1000 ?","E:Merci beaucoup"],"lus":"2","pastille":false}] ✓ « Envoyer » : la confirmation se fait dans le bouton (« Confirmer l'envoi »), rien n'est parti [Confirmer l'envoi] ✓ Second clic : réponse simulée (mode test), {prenom} remplacé, auteur et « simulé » dans la bulle, zone vidée [{"bulle":{"texte":"Oui Awa, nous l'avons en stock.","meta":"Essai E2E · 10:13 · simulé","etat":"Réponse simulée (mode test) : aucun envoi réel.","saisie":""},"sortant":"SIMULE|1|Oui Awa, nous l'avons en stock."}] ✓ La réponse figure aussi au journal des envois WhatsApp (sans le texte) ✓ Réponse avec un PDF joint seul : partie (simulée), le fil affiche la pièce [ essai-discussion.pdf] ✓ Client B (STOP) : zone de réponse fermée, le motif lisible dans l'en-tête ; l'API refuse aussi, rien n'est gardé [{"stop":{"ferme":true,"etat":"Bintou ZZDISC STOP05 08 77 33 44Ce client a demandé l'arrêt des messages WhatsApp (STOP) : on ne peut plus lui écrire."},"api":{"msg":"Ce client a demandé l'arrêt des messages WhatsApp (STOP) : la réponse n'est pas envoyée.","success":false,"message":"Ce client a demand] ✓ « Non lues » : A (lu) n'y est plus [0707070701] ✓ Sans session : refusé (401) [401] ✓ Journal du serveur : ni le texte des messages, ni les numéros, ni le jeton ✓ Aucune erreur JavaScript, aucune fenêtre du navigateur [] ✓ Données de l'essai retirées, compte et mode remis | E12: OK | L12: =IF(I12="","",IF(I12=E12,"Oui","Non"))

Sheet Carnet dépôt
A1: CAHIER DE RECETTE — Carnet dépôt
A2: 1 tests : 1 OK, 0 en échec selon Claude
A4: N° | B4: Test | C4: Scénario : ce qui est fait et ce qui est attendu | D4: Contrôles faits par Claude (valeur mesurée) | E4: Résultat Claude | F4: Écart constaté par Claude | G4: Catégorie et suite | H4: Résultat testeur | I4: Statut testeur | J4: Testeur | K4: Date | L4: Concorde ? | M4: Commentaire
A5: 34 | B5: carnet-depot/test-facturation-carnet-depot.js | C5: Facturation des carnets depot. Scenarios A a G du cahier : isolation de la liste normale, onglet dedie, bons a facturer, creation, impressions, pagination. | D5: 33 / 33 conformes ✓ scenario A : la liste normale repond [factures=1] ✓ scenario A : aucune facture carnet depot dans la liste normale [E2ECD-F-ORD-0] ✓ scenario A : la facture provisoire du tiers payant ORDINAIRE y figure bien [E2ECD-F-ORD-0] ✓ scenario B : l onglet dedie repond [total=3] ✓ scenario B : les trois factures du carnet depot y figurent [E2ECD-F-DEP-0,E2ECD-F-DEP-1,E2ECD-F-DEP-2] ✓ scenario B : aucune facture de tiers payant ordinaire dans l onglet dedie [E2ECD-F-DEP-0,E2ECD-F-DEP-1,E2ECD-F-DEP-2] ✓ scenario B : provisoires ET definitives sont visibles cote depot [la 0 est provisoire, la 1 est definitive] ✓ scenario B : la ligne porte periode, nom, nombre de bons, montant et date [{"template":false,"nbDossier":4,"dblMONTANTRESTANT":0,"strCODEFACTURE":"E2ECDD1","strCUSTOMER":"E2ECD-TP-DEPOT","lgFACTUREID":"E2ECD-F-DEP-1","periode":"DU 01/09/2024 AU 30/09/2024","strFULLNAME":"E2ECD CARNET DEPOT","dtFINFACTURE":"30/09/2024","strADRESSE":"YAMOUSSOUKRO","strCOD] ✓ scenario B : le filtre tpid restreint bien a un carnet [total=3] ✓ scenario B : demander un tiers payant ORDINAIRE dans l onglet dedie ne rend rien [total=0] ✓ scenario C : l ecran normal ne propose pas les bons du carnet depot [E2ECD TP ORDINAIRE] ✓ scenario C : l ecran normal propose bien les bons du tiers payant ordinaire [E2ECD TP ORDINAIRE] ✓ scenario C : l ecran dedie propose les bons du carnet depot [E2ECD CARNET DEPOT] ✓ scenario C : l ecran dedie ne propose aucun bon de tiers payant ordinaire [E2ECD CARNET DEPOT] ✓ scenario C : le mode BONS applique lui aussi la separation [E2ECD-B-DEP] ✓ scenario C : en mode BONS, le circuit normal ignore le bon du depot [E2ECD-B-ORD] ✓ scenario G : le total annonce ne compte aucun tiers payant ordinaire [annonce=3 reel=3] ✓ scenario G : la premiere page rend le nombre demande [page 1 = 2 lignes] ✓ scenario G : les pages ne se recouvrent pas [{"page1":["E2ECD-F-DEP-0","E2ECD-F-DEP-1"],"page2":["E2ECD-F-DEP-2"]}] ✓ scenario F : un modele DETAIL_ARTICLE actif est configure [modeles = 1] ✓ scenario F : l impression detaillee aboutit et rend un PDF [%PDF-1.5 %âãÏÓ 4 0 obj <</Filter/FlateDecode/Length 916>>stream x­W]rÚH~×)úWJCÏÿ7!Gc[µµl¥([qÝ=Lkø(~ßlfEbJ.@#F3úz¾þ¦§ûÏ [ÒCÅuÁ»@À/¾ÒÇ_] ✓ scenario F : le document annonce le detail des medicaments [texte=3937] ✓ scenario F : les medicaments sont regroupes par vente [texte=3937] ✓ scenario F : le document contient les medicaments de la vente [cip cherches=8452598,8452598D texte=3937] ✓ scenario F : le document porte un total general [texte=3937] ✓ l onglet FACTURES est present dans Gerer carnet depot [["VENTES","REGLEMENTS","DEPENSES","PRODUITS","FACTURES"]] ✓ l onglet porte les colonnes demandees [["Période facturée","Dépôt / tiers-payant","N° facture","Nbre bons","Montant net","Date facture","Voir","Imprimer","Supprimer"]] ✓ l onglet est rempli avec les factures carnet depot [lignes=3] ✓ le bouton « Créer une facture » est present ✓ voir, imprimer et supprimer sur la ligne, suppression multiple en haut [icones=3 bouton haut imprimer=false] ✓ scenario D : l ecran de creation s ouvre en mode carnet depot ["Facturation des carnets dépôt"] ✓ scenario D : ses magasins transmettent carnetDepot au serveur [[{"carnetDepot":true},{"carnetDepot":true},{"carnetDepot":true}]] ✓ aucune erreur JavaScript | E5: OK | L5: =IF(I5="","",IF(I5=E5,"Oui","Non"))

Sheet Clients
A1: CAHIER DE RECETTE — Clients
A2: 4 tests : 4 OK, 0 en échec selon Claude
A4: N° | B4: Test | C4: Scénario : ce qui est fait et ce qui est attendu | D4: Contrôles faits par Claude (valeur mesurée) | E4: Résultat Claude | F4: Écart constaté par Claude | G4: Catégorie et suite | H4: Résultat testeur | I4: Statut testeur | J4: Testeur | K4: Date | L4: Concorde ? | M4: Commentaire
A5: 35 | B5: client/test-client-standard-naissance.js | C5: CLIENT STANDARD : DATE DE NAISSANCE ET SEXE (retours du 13/10, point 14). Par l'ecran « Clients », admin. - la fenetre « Créer client standard » propose la date de naissance et le sexe, tous deux FACULTATIFS ; - le premier champ (Nom) n'est plus colle au haut du cadre ; - Entree enchaine nom, prenoms, telephone, date de naissance, puis le bouton Enregistrer ; - creation avec date et sexe : enregistres sur la fiche ; creation sans : comme avant ; - date dans le futur : refusee a l'ecran et par le serveur. Clients d'essai retires a la fin. | D5: 10 / 10 conformes ✓ Date de naissance et sexe proposés, facultatifs [{"naissance":true,"sexe":true,"libelles":["Né(e) le","Sexe"],"ecartHaut":24}] ✓ Le premier champ (Nom) n'est plus collé au haut du cadre [24 px] ✓ Entrée : du téléphone à la date de naissance [datefield-1172-inputEl] ✓ Entrée : de la date au bouton Enregistrer ✓ Créé avec sa date de naissance et son sexe [1980-03-15|F|6|0708473791] ✓ Créé sans date ni sexe, comme avant [VIDE|VIDE|0708473792] ✓ Date future : refusée à l'écran, rien n'est créé ✓ Date future ou sexe inconnu : refusés par le serveur [{"success":false,"champ":"dt_NAISSANCE","errors":"La date de naissance ne peut pas être dans le futur."}] ✓ Aucune erreur JavaScript [] ✓ Clients d'essai retirés | E5: OK | L5: =IF(I5="","",IF(I5=E5,"Oui","Non"))
A6: 36 | B6: client/test-doublon-client.js | C6: Point 24 : normalisation du nom / des prenoms a la creation d'un client depuis une vente assurance ou carnet, et avertissement de doublon. Les appels sont faits depuis la page apres connexion, pour beneficier de la session. | D6: 8 / 8 conformes ✓ creation client carnet acceptee [{"data":{"strLASTNAME":"KONANTEST216554","lgTIERSPAYANTID":"15429183543436911984","fullName":"ALIDATEST216554 KONANTEST216554","preenregistrementstp":[],"lgCLIENTID":"54fd6d2d-b290-4a8c-8967-3995809cafb5","dblPLAFOND":0,] ✓ nom enregistre sans espace de fin ["KONANTEST216554"] ✓ prenoms enregistres sans espace de fin ["ALIDATEST216554"] ✓ doublon detecte malgre les espaces de fin [{"doublonClient":true,"msg":"Un client nomme [<span style=\"color: blue; \">ALIDATEST216554 KONANTEST216554<\/span>] existe deja.","success":false,"doublons":[{"assurance":"ABY KOKORA","strNUMEROSECURITESOCIAL":"","strLA] ✓ le client existant est propose [[{"assurance":"ABY KOKORA","strNUMEROSECURITESOCIAL":"","strLASTNAME":"KONANTEST216554","strCODEINTERNE":"134054","lgCLIENTID":"54fd6d2d-b290-4a8c-8967-3995809cafb5","strFIRSTNAME":"ALIDATEST216554"}]] ✓ creation forcee acceptee apres confirmation [{"data":{"strLASTNAME":"KONANTEST216554","lgTIERSPAYANTID":"15429183543436911984","fullName":"ALIDATEST216554 KONANTEST216554","preenregistrementstp":[],"lgCLIENTID":"f3fa1299-40e9-40ec-8ea9-768f0f1f4804","dblPLAFOND":0,] ✓ identite differente creee sans avertissement [{"data":{"strLASTNAME":"KONANTEST216554X","lgTIERSPAYANTID":"15429183543436911984","fullName":"ALIDATEST216554 KONANTEST216554X","preenregistrementstp":[],"lgCLIENTID":"77cd0982-cd5a-43ca-af8a-370285df5277","dblPLAFOND":] ✓ doublon detecte aussi sur le circuit assurance [{"doublonClient":true,"msg":"2 clients nommes [<span style=\"color: blue; \">ALIDATEST216554 KONANTEST216554<\/span>] existent deja.","success":false,"doublons":[{"assurance":"ABY KOKORA","strNUMEROSECURITESOCIAL":"","st] | E6: OK | L6: =IF(I6="","",IF(I6=E6,"Oui","Non"))
A7: 37 | B7: client/test-fiche-client-identite-conso.js | C7: FICHE CLIENT (retours du 13/10, points 13 et 14). Par la fenetre « Fiche client » de la gestion des clients, admin. - point 14 : un client sans date de naissance ni sexe : la fiche propose de les completer ; l'enregistrement met a jour la fiche client (t_client), sans fenetre ; ce qui est deja renseigne n'est jamais ecrase ; date future refusee ; le bloc disparait une fois la fiche complete ; - point 13 : suivi de consommation avec un choix « Par vente / Par produit », « Par vente » par defaut : chaque vente des 12 derniers mois (date, ticket, montant, produits) ; « Par produit » garde la vue d'avant. Client d'essai cree puis retire ; le client aux ventes est lu sans etre modifie. | D7: 11 / 11 conformes ✓ Client sans date ni sexe : la fiche propose de les compléter [{"visible":true,"date":true,"sexe":true}] ✓ Date future : refusée, rien n'est écrit ✓ Enregistré sur la fiche client [1975-05-12 00:00:00|M] ✓ Fiche complète : le bloc disparaît, l'identité affiche date, âge et sexe [{"visible":false,"identite":"ZZFICHE Identite Standard Né(e) le 12/05/1975 · 51 ans Sexe Masculin Ordonnances 0"}] ✓ Ce qui est déjà renseigné n'est jamais écrasé [{"success":false,"message":"Déjà renseigné : la fiche n'a pas été modifiée."}] ✓ Précondition : un client avec des ventes sur 12 mois [65d05ed2-7eb1-4d8d-a6e4-d2b616c05cff : 22767] ✓ Choix « Par vente / Par produit », « Par vente » par défaut [["Par vente*","Par produit"]] ✓ Par vente : une ligne par vente (date, ticket, montant, produits) [{"choix":["Par vente*","Par produit"],"entetes":["DATE","TICKET","MONTANT","PRODUITS"],"lignes":50}] ✓ Par produit : la vue d'avant (produit, achats, fréquence, habitude) [{"choix":["Par vente","Par produit*"],"entetes":["PRODUIT","ACHATS","FRÉQUENCE","DERNIER ACHAT","HABITUDE","STOCK"],"lignes":12}] ✓ Aucune fenêtre surgissante, aucune erreur JavaScript [] ✓ Client d'essai retiré | E7: OK | L7: =IF(I7="","",IF(I7=E7,"Oui","Non"))
A8: 38 | B8: client/test-gestion-clients-barre.js | C8: GESTION DES CLIENTS : BARRE D'OUTILS (retours du 13/10, point 15). Par l'ecran « Clients », admin. - le filtre « Type client » ne se confond plus avec le champ de recherche : largeur propre, ecart visible, le champ de recherche dit ce qu'il cherche ; - un seul bouton « Importer », avec un selecteur des deux imports (colonnes au choix / fichier modele) ; - chaque entree ouvre son import ; la recherche et le filtre fonctionnent toujours. Lecture seule. | D8: 8 / 8 conformes ✓ Filtre « Type client » et recherche bien séparés (écart visible) [{"ecart":36,"largeurType":295,"largeurRech":310,"aide":"Rechercher un client : nom, prénom, numéro…","boutonsImport":["Importer"],"menu":["Colonnes au choix, lignes contrôlées (recommandé)","Fichier modèle (import historique)"]}] ✓ Le champ de recherche dit ce qu'il cherche [Rechercher un client : nom, prénom, numéro…] ✓ Un seul bouton « Importer » [["Importer"]] ✓ Son sélecteur propose les deux imports [["Colonnes au choix, lignes contrôlées (recommandé)","Fichier modèle (import historique)"]] ✓ « Colonnes au choix » ouvre l'assistant d'import ✓ « Fichier modèle » ouvre l'import historique [["Importation des clients (fichier modèle)"]] ✓ La recherche fonctionne toujours [20] ✓ Aucune erreur JavaScript [] | E8: OK | L8: =IF(I8="","",IF(I8=E8,"Oui","Non"))

Sheet Ergonomie
A1: CAHIER DE RECETTE — Ergonomie
A2: 3 tests : 3 OK, 0 en échec selon Claude
A4: N° | B4: Test | C4: Scénario : ce qui est fait et ce qui est attendu | D4: Contrôles faits par Claude (valeur mesurée) | E4: Résultat Claude | F4: Écart constaté par Claude | G4: Catégorie et suite | H4: Résultat testeur | I4: Statut testeur | J4: Testeur | K4: Date | L4: Concorde ? | M4: Commentaire
A5: 39 | B5: ergonomie/test-confirmation-icones-ligne.js | C5: CONFIRMATION DANS L'ICONE DE LIGNE (regle : aucune fenetre surgissante pour une modification ; demande du 18/10 : « mets-le sur les autres icones de ligne »). 163 confirmations d'icones de ligne passent par PrestigeConfirmation.ligne : appel issu d'un clic sur l'icone -> l'icone devient « Confirmer ? » ; sinon, la fenetre d'avant. Echantillon par les vues, sur trois ecrans de PARAMETRAGES (ligne d'essai creee puis retiree) : - premier clic sur l'icone de suppression : « Confirmer ? » dans la ligne, aucune fenetre ; - sans second clic : l'icone revient apres 5 s, rien n'est supprime ; - double-clic : ne vaut pas confirmation, rien n'est supprime ; - second clic sur « Confirmer ? » : la ligne est supprimee (statut « delete »). | D5: 14 / 14 conformes ✓ Gerer Ville : premier clic → « Confirmer ? » posé sur l'icône de la ligne, aucune fenêtre [{"icone":{"x":1556,"y":342.5,"width":24,"height":24},"bouton":{"x":1504.1875,"y":343,"width":75.8125,"height":24}} ] ✓ Gerer Ville : sans second clic, l'icône revient après 5 s, rien n'est supprimé [enable] ✓ Gerer Ville : double-clic → rien n'est supprimé [enable] ✓ Gerer Ville : second clic sur « Confirmer ? » → ligne supprimée [delete] ✓ Groupe famille : premier clic → « Confirmer ? » posé sur l'icône de la ligne, aucune fenêtre [{"icone":{"x":1556,"y":571,"width":24,"height":24},"bouton":{"x":1504.1875,"y":571,"width":75.8125,"height":24}} ] ✓ Groupe famille : sans second clic, l'icône revient après 5 s, rien n'est supprimé [enable] ✓ Groupe famille : double-clic → rien n'est supprimé [enable] ✓ Groupe famille : second clic sur « Confirmer ? » → ligne supprimée [delete] ✓ Gerer Motif Retour : premier clic → « Confirmer ? » posé sur l'icône de la ligne, aucune fenêtre [{"icone":{"x":1556,"y":713.5,"width":24,"height":24},"bouton":{"x":1504.1875,"y":714,"width":75.8125,"height":24}} ] ✓ Gerer Motif Retour : sans second clic, l'icône revient après 5 s, rien n'est supprimé [enable] ✓ Gerer Motif Retour : double-clic → rien n'est supprimé [enable] ✓ Gerer Motif Retour : second clic sur « Confirmer ? » → ligne supprimée [delete] ✓ Aucune erreur JavaScript [] ✓ Lignes d'essai retirées | E5: OK | L5: =IF(I5="","",IF(I5=E5,"Oui","Non"))
A6: 40 | B6: ergonomie/test-indicateur-chargement.js | C6: INDICATEUR DE CHARGEMENT (retours du 13/10, points 8 et 9). Par l'ecran, admin. - Articles invendus, « Exporter » : le bouton montre aussitot une roue et le temps ecoule, une fine barre court en haut de l'ecran ; le fichier arrive (telechargement), le bouton dit « Fichier prêt » puis reprend son libelle ; - Previsions, « Recalculer maintenant » : meme indicateur pendant le calcul, puis « Prévisions recalculées » ; - aucune fenetre surgissante, aucune erreur JavaScript. Le recalcul des previsions ecrit le calcul du jour (comme la tache de nuit) : rien a retirer. | D6: 10 / 10 conformes ✓ Export : le bouton montre aussitôt une roue et le travail en cours, et ne se relance pas [{"texte":"Préparation de l'export…","roue":true,"inactif":true,"barre":true,"boite":false}] ✓ Export : une barre de progression court en haut de l'écran [{"texte":"Préparation de l'export…","roue":true,"inactif":true,"barre":true,"boite":false}] ✓ Export : le fichier arrive [articles-invendus_30_10_2026_10_15_44.xls] ✓ Export : le bouton dit que le fichier est prêt, la barre disparaît [{"texte":"✓ Fichier prêt","roue":false,"inactif":false,"barre":false,"boite":false}] ✓ Export : le bouton reprend son libellé [Export Excel / Export Excel] ✓ Prévisions : roue, travail en cours et barre pendant le calcul [{"texte":"Calcul des prévisions…","roue":true,"inactif":true,"barre":true,"boite":false}] ✓ Prévisions : le temps écoulé s'affiche pendant un calcul long [Calcul des prévisions… 2 s] ✓ Prévisions : le bouton dit comment le calcul s'est terminé [{"texte":"✓ Prévisions recalculées","roue":false,"inactif":false,"barre":false,"boite":false}] ✓ Aucune fenêtre surgissante [] ✓ Aucune erreur JavaScript [] | E6: OK | L6: =IF(I6="","",IF(I6=E6,"Oui","Non"))
A7: 41 | B7: ergonomie/test-onglets-gauche.js | C7: ONGLETS A GAUCHE (demande du 13/10). Lecture seule. Les 7 ecrans a onglets « boutons » (barre cec-onglets) : onglets alignes A GAUCHE de leur barre et centres VERTICALEMENT dans la barre (1,5 px pres) ; l'onglet actif reste le premier ; aucune erreur JavaScript. | D7: 22 / 22 conformes ✓ Rappels traitement : onglets à gauche [{"n":2,"gauche":9,"droite":1159,"ecartVertical":0,"actifPremier":true}] ✓ Rappels traitement : onglets centrés verticalement dans la barre [{"n":2,"gauche":9,"droite":1159,"ecartVertical":0,"actifPremier":true}] ✓ Rappels traitement : le premier onglet est actif à l'ouverture [{"n":2,"gauche":9,"droite":1159,"ecartVertical":0,"actifPremier":true}] ✓ Saisie produits périmés : onglets à gauche [{"n":2,"gauche":9,"droite":1159,"ecartVertical":0,"actifPremier":true}] ✓ Saisie produits périmés : onglets centrés verticalement dans la barre [{"n":2,"gauche":9,"droite":1159,"ecartVertical":0,"actifPremier":true}] ✓ Saisie produits périmés : le premier onglet est actif à l'ouverture [{"n":2,"gauche":9,"droite":1159,"ecartVertical":0,"actifPremier":true}] ✓ Produits : onglets à gauche [{"n":2,"gauche":9,"droite":1159,"ecartVertical":0,"actifPremier":true}] ✓ Produits : onglets centrés verticalement dans la barre [{"n":2,"gauche":9,"droite":1159,"ecartVertical":0,"actifPremier":true}] ✓ Produits : le premier onglet est actif à l'ouverture [{"n":2,"gauche":9,"droite":1159,"ecartVertical":0,"actifPremier":true}] ✓ Gestion de caisse : onglets à gauche [{"n":2,"gauche":9,"droite":1159,"ecartVertical":0,"actifPremier":true}] ✓ Gestion de caisse : onglets centrés verticalement dans la barre [{"n":2,"gauche":9,"droite":1159,"ecartVertical":0,"actifPremier":true}] ✓ Gestion de caisse : le premier onglet est actif à l'ouverture [{"n":2,"gauche":9,"droite":1159,"ecartVertical":0,"actifPremier":true}] ✓ Contrôle des achats : onglets à gauche [{"n":2,"gauche":9,"droite":1072,"ecartVertical":0,"actifPremier":true}] ✓ Contrôle des achats : onglets centrés verticalement dans la barre [{"n":2,"gauche":9,"droite":1072,"ecartVertical":0,"actifPremier":true}] ✓ Contrôle des achats : le premier onglet est actif à l'ouverture [{"n":2,"gauche":9,"droite":1072,"ecartVertical":0,"actifPremier":true}] ✓ Retours fournisseur : onglets à gauche [{"n":2,"gauche":9,"droite":1045,"ecartVertical":0,"actifPremier":true}] ✓ Retours fournisseur : onglets centrés verticalement dans la barre [{"n":2,"gauche":9,"droite":1045,"ecartVertical":0,"actifPremier":true}] ✓ Retours fournisseur : le premier onglet est actif à l'ouverture [{"n":2,"gauche":9,"droite":1045,"ecartVertical":0,"actifPremier":true}] ✓ Commandes en cours : onglets à gauche [{"n":7,"gauche":9,"droite":371,"ecartVertical":0,"actifPremier":true}] ✓ Commandes en cours : onglets centrés verticalement dans la barre [{"n":7,"gauche":9,"droite":371,"ecartVertical":0,"actifPremier":true}] ✓ Commandes en cours : le premier onglet est actif à l'ouverture [{"n":7,"gauche":9,"droite":371,"ecartVertical":0,"actifPremier":true}] ✓ Aucune erreur JavaScript | E7: OK | L7: =IF(I7="","",IF(I7=E7,"Oui","Non"))

Sheet Espace produit
A1: CAHIER DE RECETTE — Espace produit
A2: 1 tests : 0 OK, 1 en échec selon Claude
A4: N° | B4: Test | C4: Scénario : ce qui est fait et ce qui est attendu | D4: Contrôles faits par Claude (valeur mesurée) | E4: Résultat Claude | F4: Écart constaté par Claude | G4: Catégorie et suite | H4: Résultat testeur | I4: Statut testeur | J4: Testeur | K4: Date | L4: Concorde ? | M4: Commentaire
A5: 42 | B5: espace-produit/test-selecteur-dci.js | C5: ESPACE PRODUIT : LE SELECTEUR DE DCI (demande de l'officine du 21/09). L'Espace produit est la page LIBRE de l'ecran de connexion : on y cherche un produit par CIP ou par nom, sans compte. « Ajouter un selecteur de DCI en bas de la zone de recherche pour afficher les produits concernes par la DCI selectionnee. » CE QUE CE TEST ETABLIT, sur la page reelle, sans connexion : - le selecteur ne propose que les DCI qui ont des produits, avec leur nombre ; - choisir une DCI liste EXACTEMENT ses produits, sans rien taper ; - un texte ET une DCI se restreignent l'un l'autre ; - « Effacer » rend la recherche par texte, qui marche comme avant (aucune regression) ; - l'API refuse toujours une recherche sans DCI ni deux caracteres. DONNEES (13/10) : le test ne depend plus du banc. Il rattache lui-meme deux DCI a quelques produits par la route de la fiche article (v1/referentiel-article/dci-famille/associer, connecte), et retire ces rattachements a la fin. | D5: 2 / 5 conformes ✗ Préparation : 5 rattachements DCI–produit créés par la route de la fiche article [{"success":"0","errors":"Echec d'enregistrement. DCI inexistant ou incorrecte"}] ✗ Précondition : le banc porte des DCI rattachées à des produits [0 DCI] ✓ Le champ de DCI est un champ de SAISIE, placé sous la zone de recherche ✗ Le parcours va au bout [undefined is not iterable (cannot read property Symbol(Symbol.iterator)) at D:\projet\p3\prestige-integration\src\test\e2e\espace-produit\test-selecteur-dci.js:64:29] ✓ Rattachements d'essai retirés | E5: Échec | F5: Préparation : 5 rattachements DCI–produit créés par la route de la fiche article [{"success":"0","errors":"Echec d'enregistrement. DCI inexistant ou incorrecte"}] Précondition : le banc porte des DCI rattachées à des produits [0 DCI] Le parcours va au bout [undefined is not iterable (cannot read property Symbol(Symbol.iterator)) at D:\projet\p3\prestige-integration\src\test\e2e\espace-produit\test-selecteur-dci.js:64:29] | G5: Données de la copie : La copie n'a aucune DCI rattachée à un produit ; le test ne sait pas en créer. | L5: =IF(I5="","",IF(I5=E5,"Oui","Non"))

Sheet Menus et articles
A1: CAHIER DE RECETTE — Menus et articles
A2: 1 tests : 1 OK, 0 en échec selon Claude
A4: N° | B4: Test | C4: Scénario : ce qui est fait et ce qui est attendu | D4: Contrôles faits par Claude (valeur mesurée) | E4: Résultat Claude | F4: Écart constaté par Claude | G4: Catégorie et suite | H4: Résultat testeur | I4: Statut testeur | J4: Testeur | K4: Date | L4: Concorde ? | M4: Commentaire
A5: 43 | B5: etape1/test-menus-et-maj-article.js | C5: Etape 1 : quatre ecrans ajoutes a la presentation « collee », et deux donnees de plus dans la mise a jour selective de la fiche article (soumis a ordonnance, remise autorisee). | D5: 23 / 23 conformes ✓ la liste des ecrans colles est chargee [ecrans=145] ✓ ecran « tpventes » ajoute a la liste ✓ ecran « balancesalecahs » ajoute a la liste ✓ ecran « recap » ajoute a la liste ✓ ecran « ordonnancier » ajoute a la liste ✓ aucun doublon dans la liste [145 entrees, 145 distinctes] ✓ l xtype « tpventes » correspond a une vue reelle ✓ l xtype « balancesalecahs » correspond a une vue reelle ✓ l xtype « recap » correspond a une vue reelle ✓ l xtype « ordonnancier » correspond a une vue reelle ✓ la liste des donnees a mettre a jour est accessible [["GROSSISTE","FAMILLE","TVA","CODE_REMISE","CODE_TABLEAU","LABORATOIRE","GAMME","ORDONNANCIER","REMISE"]] ✓ « Soumis a ordonnance » est propose [["GROSSISTE","FAMILLE","TVA","CODE_REMISE","CODE_TABLEAU","LABORATOIRE","GAMME","ORDONNANCIER","REMISE"]] ✓ « Remise autorisee » est proposee [["GROSSISTE","FAMILLE","TVA","CODE_REMISE","CODE_TABLEAU","LABORATOIRE","GAMME","ORDONNANCIER","REMISE"]] ✓ mise a jour « soumis a ordonnance = Oui » [{"success":true,"count":3}] ✓ les trois produits sont bien marques [marques = 3] ✓ mise a jour « soumis a ordonnance = Non » [{"success":true,"count":3}] ✓ le retour a Non est bien enregistre [non marques = 3] ✓ mise a jour « remise autorisee = Oui » [{"success":true,"count":3}] ✓ la remise est bien autorisee sur les trois ✓ mise a jour « remise autorisee = Non » [{"success":true,"count":3}] ✓ une donnee inconnue est refusee [{"success":false,"count":0,"message":"Donnée à mettre à jour inconnue : INEXISTANT"}] ✓ non-regression : la mise a jour du code TVA fonctionne toujours [{"success":true,"count":1}] ✓ aucune erreur JavaScript | E5: OK | L5: =IF(I5="","",IF(I5=E5,"Oui","Non"))

Sheet Étape 2
A1: CAHIER DE RECETTE — Étape 2
A2: 1 tests : 1 OK, 0 en échec selon Claude
A4: N° | B4: Test | C4: Scénario : ce qui est fait et ce qui est attendu | D4: Contrôles faits par Claude (valeur mesurée) | E4: Résultat Claude | F4: Écart constaté par Claude | G4: Catégorie et suite | H4: Résultat testeur | I4: Statut testeur | J4: Testeur | K4: Date | L4: Concorde ? | M4: Commentaire
A5: 44 | B5: etape2/test-tp-maj-selective.js | C5: Etape 2 : la mise a jour selective des tiers payants passe d'un formulaire de trois reglages figes a un selecteur de donnees a cocher, avec dix donnees de plus. Ce qui compte ici : une donnee NON cochee ne doit jamais bouger. Un ecran qui ecrit en masse et deborde sur des colonnes qu'on ne lui a pas demandees ferait perdre le parametrage de dizaines d'organismes d'un coup. Chaque assertion le verifie explicitement. | D5: 31 / 31 conformes ✓ L'ecran offre un selecteur de donnees ✓ Treize donnees sont proposees (3 historiques + 10 nouvelles) [13] ✓ Les dix nouvelles donnees sont bien la [codeEditBordereau,nbBonsParPage,taillePolice,NBRE_EXEMPLAIRE_BORD,NBREBONS,MONTANTFAC,MODE_TRI_FACTURE,PLAFOND_CREDIT,PLAFOND_VENTE,IS_ABSOLUTE,COMPTE_CONTRIBUABLE,REGISTRE_COMMERCE,CODE_OFFICINE] ✓ Un editeur par donnee [13] ✓ Aucun editeur visible tant que rien n'est coche ✓ Les nouvelles colonnes sont masquees au depart ✓ Les trois colonnes historiques restent visibles ✓ Cocher une donnee revele son editeur ✓ Cocher une donnee revele sa colonne actuelle ✓ Les editeurs des donnees non cochees restent masques ✓ donneesChoisies() ne rend que la donnee cochee [1] ✓ Decocher vide l'editeur ✓ Decocher remasque la colonne ✓ La recherche renvoie les dix valeurs actuelles [int_MONTANTFAC,str_MODE_TRI_FACTURE,dbl_PLAFOND_VENTE,str_CODE_OFFICINE,str_FULLNAME,int_TAILLE_POLICE,int_NBRE_EXEMPLAIRE_BORD,dbl_PLAFOND_CREDIT,str_CODE_ORGANISME,lg_TIERS_PAYANT_ID,str_COMPTE_CONTRIBUABLE,int_NBREBONS,b_IsAbsolute,str_CODE_EDIT_BORDEREAU,int_NB_BONS_PAR_PAGE,str_REGISTRE_COMMERC] ✓ Deux donnees appliquees en un seul passage [{"success":"1","errors":"3 tiers payant(s) mis à jour."}] ✓ Les deux donnees sont ecrites [{"int_NBRE_EXEMPLAIRE_BORD":"1","int_NBREBONS":"25","int_MONTANTFAC":"0","str_MODE_TRI_FACTURE":"ALPHABETIQUE","dbl_PLAFOND_CREDIT":"150000.00","dbl_PLAFOND_VENTE":"0.00","b_IsAbsolute":"0","str_COMPTE_CONTRIBUABLE":"","str_REGISTRE_COMMERCE":"","str_CODE_OFFICINE":"","int_NB_BONS_PAR_PAGE":"0","int] ✓ Les onze autres donnees n'ont pas bouge [ | | ] ✓ Les huit donnees restantes s'appliquent [{"success":"1","errors":"3 tiers payant(s) mis à jour."}] ✓ Chaque donnee atterrit sur sa colonne [{"int_NBRE_EXEMPLAIRE_BORD":"3","int_NBREBONS":"25","int_MONTANTFAC":"500000","str_MODE_TRI_FACTURE":"DATE_BON","dbl_PLAFOND_CREDIT":"150000.00","dbl_PLAFOND_VENTE":"20000.00","b_IsAbsolute":"1","str_COMPTE_CONTRIBUABLE":"CC-E2E","str_REGISTRE_COMMERCE":"RC-E2E","str_CODE_OFFICINE":"OFF-E2E","int_NB] ✓ Un nombre illisible est refuse [{"success":"0","errors":"Nombre maximum de bons par facture : « vingt » n'est pas un nombre entier."}] ✓ Un refus ne modifie rien ✓ Un mode de tri inconnu est refuse [{"success":"0","errors":"Mode de tri de la facture : « PAR_MONTANT » n'est pas un mode de tri connu."}] ✓ Un plafond negatif est refuse [{"success":"0","errors":"Plafond de crédit : un montant négatif n'a pas de sens."}] ✓ Un texte trop long est refuse au lieu d'etre tronque [{"success":"0","errors":"Registre de commerce : 100 caractères au maximum (101 saisis)."}] ✓ Aucun refus n'a laisse de trace [RC-E2E] ✓ Aucune donnee demandee : l'appel est refuse [{"success":"0","errors":"Renseignez au moins une donnée à appliquer. Une donnée non cochée n'est pas modifiée."}] ✓ Aucun tiers payant coche : l'appel est refuse [{"success":"0","errors":"Cochez au moins un tiers payant."}] ✓ Les trois reglages historiques fonctionnent toujours [{"success":"1","errors":"3 tiers payant(s) mis à jour."}] ✓ Bons par page et police sont ecrits [{"int_NBRE_EXEMPLAIRE_BORD":"3","int_NBREBONS":"25","int_MONTANTFAC":"500000","str_MODE_TRI_FACTURE":"DATE_BON","dbl_PLAFOND_CREDIT":"150000.00","dbl_PLAFOND_VENTE":"20000.00","b_IsAbsolute":"1","str_COMPTE_CONTRIBUABLE":"CC-E2E","str_REGISTRE_COMMERCE":"RC-E2E","str_CODE_OFFICINE":"OFF-E2E","int_NB] ✓ Aucune erreur JavaScript ✓ Etat initial des tiers payants retabli [{"int_NBRE_EXEMPLAIRE_BORD":"1","int_NBREBONS":"0","int_MONTANTFAC":"0","str_MODE_TRI_FACTURE":"ALPHABETIQUE","dbl_PLAFOND_CREDIT":"0.00","dbl_PLAFOND_VENTE":"0.00","b_IsAbsolute":"0","str_COMPTE_CONTRIBUABLE":"","str_REGISTRE_COMMERCE":"","str_CODE_OFFICINE":"","int_NB_BONS_PAR_PAGE":"0","int_TAILL] | E5: OK | L5: =IF(I5="","",IF(I5=E5,"Oui","Non"))

Sheet Étape 3
A1: CAHIER DE RECETTE — Étape 3
A2: 2 tests : 2 OK, 0 en échec selon Claude
A4: N° | B4: Test | C4: Scénario : ce qui est fait et ce qui est attendu | D4: Contrôles faits par Claude (valeur mesurée) | E4: Résultat Claude | F4: Écart constaté par Claude | G4: Catégorie et suite | H4: Résultat testeur | I4: Statut testeur | J4: Testeur | K4: Date | L4: Concorde ? | M4: Commentaire
A5: 45 | B5: etape3/test-ordonnancier.js | C5: Etape 3 : les correctifs de l'ordonnancier. L'ecran presentait quatre defauts. La colonne « Medecin » restait vide alors que la requete ne rapporte QUE des ventes rattachees a un medecin ; le (+) ouvrait une zone vide ; le nom du patient n'apparaissait nulle part ; et on ne pouvait ni chercher un client, ni imprimer, ni exporter, ni faire un inventaire des produits delivres. La base de test ne contient aucune vente rattachee a un medecin, ni aucun produit soumis a ordonnance : la suite construit donc son propre jeu d'essai et le retire integralement a la fin. | D5: 62 / 62 conformes ✓ Les trois delivrances du jour remontent [3] ✓ La colonne Medecin est renseignee [DOCTEUR ESSAI ORDONNANCIER | DOCTEUR ESSAI ORDONNANCIER | DOCTEUR ESSAI ORDONNANCIER] ✓ Le numero d'ordre du medecin suit [E2E-9001 | E2E-9001 | E2E-9001] ✓ La liste ne transporte aucun produit [[0,0,0]] ✓ Le modele ExtJS ne retient pas de produits ✓ Le detail d'une vente se charge a la demande [{"total":2,"data":[{"uniteGratuite":0,"montantNetHt":1000,"lgFAMILLEID":"14124271737540974008","seuil":0,"lgPREENREGISTREMENTID":"E2EORD-1","montantHt":1000,"strSTATUT":"enable","prixHt":500,"avoir":f] ✓ Chaque produit porte son code tableau [A CIN 500MG CPR PELL B/3=A | ABZ 200MG/5ML SUSP BUV F/10ML=C] ✓ Chaque produit porte CIP, quantite et montant [[["8074624",2,1000],["8050457",3,2000]]] ✓ Le detail rend le bon nombre de produits par vente [1] ✓ Une vente inconnue rend une liste vide, pas une erreur [{"total":0,"data":[],"success":true}] ✓ La fenetre de detail nomme la vente ouverte [Produits de la vente [E2EORD-REF-1]] ✓ Elle interroge le point d'entree de l'ordonnancier [../api/v1/ventestats/ventesordonnanciers/detail/E2EORD-1] ✓ Elle montre le code tableau [CIP | Produit | Tableau | Qt&eacute; | P.U. | Montant] ✓ La meme fenetre sert les suppressions, sans colonne Tableau [CIP | Produit | Qt&eacute; | P.U. | Montant] ✓ La colonne Client est renseignee [ALLALY AHOUSSOU IGOR YANNICK | ADOU EKORA NADIA | ALLALY AHOUSSOU IGOR YANNICK] ✓ La recherche par nom de client filtre bien [EKORA -> E2EORD-REF-2] ✓ La recherche accepte aussi la reference [E2EORD-REF-3] ✓ Une recherche sans resultat ne rend rien ✓ Une recherche vide ne filtre rien [3] ✓ Le filtre par medecin fonctionne toujours [3] ✓ Un medecin inconnu ne rend rien ✓ L'edition PDF aboutit [{"msg":"/data/reports/pdf/ordonnancier_2026_10_30_10_16_22.pdf","success":true,"url":"/data/reports/pdf/ordonnancier_2026_10_30_10_16_22.pdf"}] ✓ Le fichier PDF est ecrit sur le disque [D:\payara5\payara5\glassfish\domains\domain1\applications\prestige\data\reports\pdf\ordonnancier_2026_10_30_10_16_22.pdf] ✓ L'edition porte le titre ORDONNANCIER ✓ L'edition nomme le medecin [0 1 -1 0 595 0 cm ✓ L'edition est une ligne par produit delivre, pas par vente [REF-1 apparait 2 fois] ✓ L'export Excel repond [{"statut":200,"taille":6144,"type":"application/vnd.ms-excel"}] ✓ L'export Excel n'est pas vide [6144] ✓ L'export Excel a le bon type [application/vnd.ms-excel] ✓ Le controle compte les produits distincts [{"success":true,"count":3,"ventes":3}] ✓ Le controle compte les delivrances [{"success":true,"count":3,"ventes":3}] ✓ Le controle ne cree aucun inventaire ✓ L'inventaire est cree [{"success":true,"count":3}] ✓ L'inventaire porte un nom parlant ✓ L'analyse repond [{"topProduits":[{"delivrances":2,"libelle":"ABZ 200MG/5ML SUSP BUV F/10ML","montant":3000,"complement":"8050457 - tableau C","quantite":5},{"delivrances":1,"libelle":"A CIN 500MG CPR PELL B/3","montan] ✓ Elle compte 3 delivrances, pas 4 lignes [{"medecinsDistincts":1,"delivrances":3,"lignes":4,"produitsDistincts":3,"quantiteTotale":9,"clientsDistincts":2,"montantTotal":5000}] ✓ Elle compte 4 lignes de produit [{"medecinsDistincts":1,"delivrances":3,"lignes":4,"produitsDistincts":3,"quantiteTotale":9,"clientsDistincts":2,"montantTotal":5000}] ✓ Elle compte 3 produits distincts [{"medecinsDistincts":1,"delivrances":3,"lignes":4,"produitsDistincts":3,"quantiteTotale":9,"clientsDistincts":2,"montantTotal":5000}] ✓ Elle compte 2 clients distincts [{"medecinsDistincts":1,"delivrances":3,"lignes":4,"produitsDistincts":3,"quantiteTotale":9,"clientsDistincts":2,"montantTotal":5000}] ✓ Elle compte 1 medecin prescripteur [{"medecinsDistincts":1,"delivrances":3,"lignes":4,"produitsDistincts":3,"quantiteTotale":9,"clientsDistincts":2,"montantTotal":5000}] ✓ Elle totalise 9 unites [{"medecinsDistincts":1,"delivrances":3,"lignes":4,"produitsDistincts":3,"quantiteTotale":9,"clientsDistincts":2,"montantTotal":5000}] ✓ Elle totalise 5000 de montant [{"medecinsDistincts":1,"delivrances":3,"lignes":4,"produitsDistincts":3,"quantiteTotale":9,"clientsDistincts":2,"montantTotal":5000}] ✓ Le palmares des produits est rempli [[{"delivrances":2,"libelle":"ABZ 200MG/5ML SUSP BUV F/10ML","montant":3000,"complement":"8050457 - tableau C","quantite":5},{"delivrances":1,"libelle":"A CIN 500MG CPR PELL B/3","montant":1000,"complement":"8074624 - tableau A","quantite":2},{"delivrances":1,"libelle":"ABZ 400MG CPR B/1","montant":1] ✓ Il est trie par quantite decroissante [ABZ 200MG/5ML SUSP BUV F/10ML=5 | A CIN 500MG CPR PELL B/3=2 | ABZ 400MG CPR B/1=2] ✓ Chaque produit porte son CIP et son code tableau [8050457 - tableau C | 8074624 - tableau A | 8059783 - tableau C] ✓ Le client servi deux fois compte 2 delivrances [ALLALY AHOUSSOU IGOR YANNICK=2 | ADOU EKORA NADIA=1] ✓ Le medecin totalise les 3 delivrances [[{"delivrances":3,"libelle":"DOCTEUR ESSAI ORDONNANCIER","montant":5000,"complement":"E2E-9001","quantite":9}]] ✓ Le numero d'ordre suit le medecin [[{"delivrances":3,"libelle":"DOCTEUR ESSAI ORDONNANCIER","montant":5000,"complement":"E2E-9001","quantite":9}]] ✓ La recherche filtre aussi l'analyse [{"medecinsDistincts":1,"delivrances":1,"lignes":1,"produitsDistincts":1,"quantiteTotale":2,"clientsDistincts":1,"montantTotal":1000}] ✓ La limite coupe le palmares sans fausser les indicateurs [{"medecinsDistincts":1,"delivrances":3,"lignes":4,"produitsDistincts":3,"quantiteTotale":9,"clientsDistincts":2,"montantTotal":5000}] ✓ L'edition de l'analyse aboutit [{"msg":"/data/reports/pdf/analyse_ordonnancier_2026_10_30_10_16_22.pdf","success":true,"url":"/data/reports/pdf/analyse_ordonnancier_2026_10_30_10_16_22.pdf"}] ✓ Le PDF de l'analyse est ecrit sur le disque [/data/reports/pdf/analyse_ordonnancier_2026_10_30_10_16_22.pdf] ✓ L'export Excel de l'analyse repond [{"statut":200,"taille":5632}] ✓ L'ecran a deux onglets [Registre | Analyse] ✓ Registre et Analyse [Registre|Analyse] ✓ Les filtres sont partages par les deux onglets ✓ La grille du registre porte son propre itemId ✓ Les trois palmares sont presents ✓ L'onglet Analyse a ses filtres et ses actions ✓ Rien n'est calcule tant que l'onglet n'est pas ouvert ✓ Aucune erreur JavaScript ✓ Jeu d'essai entierement retire | E5: OK | L5: =IF(I5="","",IF(I5=E5,"Oui","Non"))
A6: 46 | B6: etape3/test-removed-detail.js | C6: Suppressions de vente : le (+) mort remplace par un bouton « Voir detail ». L'ecran ouvrait un (+) sur chaque ligne, alimente par un champ « details » que le serveur ne remplit jamais : la zone s'ouvrait vide. Le detail se demande desormais vente par vente. Le piege de cet ecran : sa colonne d'action emet UN SEUL evenement « click » pour toutes ses icones. Sans marqueur, ouvrir le detail declencherait une reimpression de ticket. C'est ce que verifient les assertions sur « action ». | D6: 9 / 9 conformes ✓ Le (+) a disparu de l'ecran des suppressions ✓ La colonne d'action porte deux icones [imprimer,detail] ✓ Chaque icone est marquee, pour ne pas confondre les deux actions [imprimer,detail] ✓ L'icone de detail est explicite [Réimprimer le ticket | Voir le détail des produits] ✓ Cliquer « detail » ouvre le detail [detail,imprimer] ✓ Cliquer « imprimer » imprime toujours le ticket [detail,imprimer] ✓ Le detail generique rend tous les produits de la vente [3 attendu 3] ✓ Une vente inconnue rend une liste vide, pas une erreur [{"total":0,"data":[],"success":true}] ✓ Aucune erreur JavaScript | E6: OK | L6: =IF(I6="","",IF(I6=E6,"Oui","Non"))

Sheet Étape 5
A1: CAHIER DE RECETTE — Étape 5
A2: 1 tests : 1 OK, 0 en échec selon Claude
A4: N° | B4: Test | C4: Scénario : ce qui est fait et ce qui est attendu | D4: Contrôles faits par Claude (valeur mesurée) | E4: Résultat Claude | F4: Écart constaté par Claude | G4: Catégorie et suite | H4: Résultat testeur | I4: Statut testeur | J4: Testeur | K4: Date | L4: Concorde ? | M4: Commentaire
A5: 47 | B5: etape5/test-gardes.js | C5: Etape 5 : les gardes. Ce que la suite verrouille avant tout, c'est la FENETRE HORAIRE. Une garde va de 20 h a 8 h le lendemain. Si l'analyse retombait sur des journees entieres -- ce que fait la procedure ABC de l'application, qui travaille au jour -- le classement serait celui de l'activite diurne, pas de la garde, tout en restant parfaitement plausible a la lecture. Le jeu d'essai place donc volontairement des ventes DANS la garde et HORS de la garde le meme jour, et verifie que seules les premieres sont comptees. | D5: 58 / 58 conformes ✓ Une garde valide s'enregistre [{"msg":"Garde enregistrée.","data":{"dateDebut":"2030-09-05 20:00:00","libelle":"E2E Nuit du 5 au 6","dureeMinutes":720,"jourDebut":"2030-09-05","heureDebut":"20:00","duree":"12 h","id":"3221133a-34f0-49da-9567-fff01d555cba","dateFin":"2030-09-06 08:00:00","heureFin":"08:00","jourFin":"2030-09-06"},] ✓ Elle porte des bornes a l'heure pres [{"dateDebut":"2030-09-05 20:00:00","libelle":"E2E Nuit du 5 au 6","dureeMinutes":720,"jourDebut":"2030-09-05","heureDebut":"20:00","duree":"12 h","id":"3221133a-34f0-49da-9567-fff01d555cba","dateFin":"2030-09-06 08:00:00","heureFin":"08:00","jourFin":"2030-09-06"}] ✓ Sa duree est calculee [{"dateDebut":"2030-09-05 20:00:00","libelle":"E2E Nuit du 5 au 6","dureeMinutes":720,"jourDebut":"2030-09-05","heureDebut":"20:00","duree":"12 h","id":"3221133a-34f0-49da-9567-fff01d555cba","dateFin":"2030-09-06 08:00:00","heureFin":"08:00","jourFin":"2030-09-06"}] ✓ Une fin anterieure au debut est refusee [{"msg":"La fin de la garde doit être postérieure à son début.","success":false}] ✓ Des bornes egales sont refusees [{"msg":"La fin de la garde doit être postérieure à son début.","success":false}] ✓ Un libelle vide est refuse [{"msg":"Donnez un libellé à la garde.","success":false}] ✓ Une periode deja prise est refusee [{"msg":"Une garde couvre déjà exactement cette période.","success":false}] ✓ La garde figure dans la liste [1 garde(s)] ✓ Le rapport repond [{"garde":{"dateDebut":"2030-09-05 20:00:00","libelle":"E2E Nuit du 5 au 6","dureeMinutes":720,"jourDebut":"2030-09-05","heureDebut":"20:00","duree":"12 h","id":"3221133a-34f0-49da-9567-fff01d555cba","] ✓ Seules les 4 ventes DANS la garde sont comptees [{"lignes":4,"produitsDistincts":3,"marge":7000,"tauxMarge":100,"dureeMinutes":720,"montant":7000,"ventes":4,"montantParHeure":583,"quantite":7}] ✓ Les ventes de jour du 5 et du 6 sont exclues [attendu 7000 (1000+4000+1500+500), obtenu 7000] ✓ La quantite ne retient que la garde [{"lignes":4,"produitsDistincts":3,"marge":7000,"tauxMarge":100,"dureeMinutes":720,"montant":7000,"ventes":4,"montantParHeure":583,"quantite":7}] ✓ Trois produits distincts sur la garde [{"lignes":4,"produitsDistincts":3,"marge":7000,"tauxMarge":100,"dureeMinutes":720,"montant":7000,"ventes":4,"montantParHeure":583,"quantite":7}] ✓ La duree est celle de la garde [{"lignes":4,"produitsDistincts":3,"marge":7000,"tauxMarge":100,"dureeMinutes":720,"montant":7000,"ventes":4,"montantParHeure":583,"quantite":7}] ✓ Le chiffre par heure ramene a une base comparable [7000 / 12 h = 583, obtenu 583] ✓ Les 24 heures en tranches de deux font douze tranches [12] ✓ La premiere tranche part de minuit [00h - 02h | 02h - 04h | 04h - 06h | 06h - 08h | 08h - 10h | 10h - 12h | 12h - 14h | 14h - 16h | 16h - 18h | 18h - 20h | 20h - 22h | 22h - 00h] ✓ La vente de 20h30 tombe dans la tranche 20h - 22h [{"clientsParHeure":0.5,"clients":1,"libelle":"20h - 22h","montant":1000,"ventes":1,"heuresCouvertes":2,"heureDuJour":20,"quantite":2}] ✓ Celle de 23h15 dans 22h - 00h [{"clientsParHeure":0.5,"clients":1,"libelle":"22h - 00h","montant":4000,"ventes":1,"heuresCouvertes":2,"heureDuJour":22,"quantite":1}] ✓ Celle de 03h00 dans 02h - 04h [{"clientsParHeure":0.5,"clients":1,"libelle":"02h - 04h","montant":1500,"ventes":1,"heuresCouvertes":2,"heureDuJour":2,"quantite":3}] ✓ Les heures de jour de la garde sont vides : les ventes de jour du 5 et du 6 ne comptent pas [00h - 02h=0 | 02h - 04h=1500 | 04h - 06h=0 | 06h - 08h=500 | 08h - 10h=0 | 10h - 12h=0 | 12h - 14h=0 | 14h - 16h=0 | 16h - 18h=0 | 18h - 20h=0 | 20h - 22h=1000 | 22h - 00h=4000] ✓ Le total des tranches egale le total de la garde [7000 vs 7000] ✓ La largeur de tranche est parametrable [24] ✓ Le total ne change pas avec la largeur ✓ L'ABC porte sur les produits de la garde [["3 HP KIT GEL/2 + CPR/4 KIT/14 DET","3 HP KIT GEL/2 + CPR/4 KIT/14","4 LIFE RITE START KIDS CPR B/120"]] ✓ Il est trie par montant decroissant [A:4000 | A:2500 | B:500] ✓ Le plus gros produit est en classe A [{"marge":4000,"tauxMarge":100,"classe":"A","cumulPart":57.14,"produitId":"14131942241735077180","libelle":"3 HP KIT GEL/2 + CPR/4 KIT/14 DET","part":57.14,"montant":4000,"cip":"8452598D","stock":0,"quantite":1}] ✓ Les parts cumulent a 100 % [57.14 | 92.86 | 100] ✓ Le produit dominant les journees ne domine pas la garde [3 HP KIT GEL/2 + CPR/4 KIT/14 DET=A/4000 | 3 HP KIT GEL/2 + CPR/4 KIT/14=A/2500 | 4 LIFE RITE START KIDS CPR B/120=B/500] ✓ Son montant est celui de la garde, pas celui des journees [4000 | 2500 | 500] ✓ Le resume donne les trois classes [[{"produits":2,"marge":6500,"tauxMarge":100,"classe":"A","part":92.86,"montant":6500},{"produits":1,"marge":500,"tauxMarge":100,"classe":"B","part":7.14,"montant":500},{"produits":0,"marge":0,"tauxMarge":0,"classe":"C","part":0,"montant":0}]] ✓ Le resume totalise les memes produits [[{"produits":2,"marge":6500,"tauxMarge":100,"classe":"A","part":92.86,"montant":6500},{"produits":1,"marge":500,"tauxMarge":100,"classe":"B","part":7.14,"montant":500},{"produits":0,"marge":0,"tauxMarge":0,"classe":"C","part":0,"montant":0}]] ✓ La comparaison rend les gardes [2] ✓ Elle les classe de la plus ancienne a la plus recente [2030-09-04 20:00:00 | 2030-09-05 20:00:00] ✓ La premiere ligne n'a pas d'ecart [{"clients":0,"libelle":"E2E Nuit precedente","indicateurs":{"caMobile":0,"clients":0,"rates":0,"montant":0,"clientsCredit":0,"caCarte":0,"montantParHe] ✓ L'ecart porte sur le chiffre par heure [{"clients":4,"evolutionPourcentage":0,"ecartParHeure":583,"libelle":"E2E Nuit du 5 au 6","indicateurs":{"caMobile":0,"clients":4,"rates":0,"montant":7000,"clientsCredit":0,"caCarte":0,"montantParHeure] ✓ Une comparaison ciblee ne rend que les gardes demandees [{"total":1,"data":[{"clients":4,"libelle":"E2E Nuit du 5 au 6","indicateurs":{"caMobile":0,"clients":4,"rates":0,"montant":7000,"clientsCredit":0,"caC] ✓ L'edition du rapport aboutit [{"msg":"/data/reports/pdf/garde_2026_10_30_10_16_33.pdf","success":true,"url":"/data/reports/pdf/garde_2026_10_30_10_16_33.pdf"}] ✓ Le PDF est ecrit sur le disque [/data/reports/pdf/garde_2026_10_30_10_16_33.pdf] ✓ L'export ABC repond [{"statut":200,"taille":5632}] ✓ L'export des tranches repond [{"statut":200,"taille":5632}] ✓ Le selecteur de garde est pose sur les ventes terminees ✓ Il liste les gardes enregistrees ✓ Il rappelle les bornes dans le libelle [E2E Nuit du 5 au 6 (2030-09-05 20:00:00 → 2030-09-06 08:00:00)] ✓ Il pose les deux dates [2030-09-05 -> 2030-09-06] ✓ Il pose AUSSI les heures sur un ecran qui les gere [20:00 -> 08:00] ✓ L'ecran a ses onglets : analyse, suivi de l'activite (H2), vendeurs et commandes (H3), comparaison [Analyse de la garde|Suivi de l'activit&eacute;|Vendeurs|Command&eacute;s non vendus|Comparaison] ✓ La liste des gardes est presente ✓ Elle accepte une selection multiple, pour comparer ✓ Les gardes se cochent (retour du 08/09) ✓ Tranches, ABC et resume sont presents ✓ Toutes les actions sont cablees ✓ Le formulaire porte date ET heure pour chaque borne ✓ Il produit des bornes au format attendu [{"id":"","libelle":"","dateDebut":"2026-10-30 20:00","dateFin":"2026-10-30 08:00"}] ✓ Une garde se supprime [{"msg":"Garde supprimée.","success":true}] ✓ Aucune vente n'a ete supprimee avec elle ✓ Aucune erreur JavaScript ✓ Jeu d'essai entierement retire | E5: OK | L5: =IF(I5="","",IF(I5=E5,"Oui","Non"))

Sheet Facturation
A1: CAHIER DE RECETTE — Facturation
A2: 1 tests : 1 OK, 0 en échec selon Claude
A4: N° | B4: Test | C4: Scénario : ce qui est fait et ce qui est attendu | D4: Contrôles faits par Claude (valeur mesurée) | E4: Résultat Claude | F4: Écart constaté par Claude | G4: Catégorie et suite | H4: Résultat testeur | I4: Statut testeur | J4: Testeur | K4: Date | L4: Concorde ? | M4: Commentaire
A5: 48 | B5: facturation/test-cachet-facture.js | C5: CACHET / SIGNATURE des factures du createur de modeles (besoins du 11/10, point 4). Par l'ecran : - un modele dynamique d'essai est cree et rattache, le temps du test, au tiers payant d'une facture du banc ; - sans cachet : la facture porte « LE PHARMACIEN » ; - cachet commun envoye depuis le panneau (PNG) : apercu affiche, la facture porte l'image et plus le texte ; - cachet propre au modele (autre image) : il prime ; retire, le cachet commun revient ; - un fichier qui n'est pas une image (renomme en .png) est refuse, rien n'est enregistre ; - sans le droit du createur de modeles, l'API refuse l'envoi ; aucune fenetre. Tout ce qui est pose est retire : modele, rattachement du tiers payant, cachets (un cachet commun deja en place est sauvegarde et remis). | D5: 11 / 11 conformes ✓ Modèle d'essai créé et rattaché au tiers payant de la facture [{"success":"1","errors":"Tiers payant rattaché au modèle"}] ✓ Sans cachet : la facture porte « LE PHARMACIEN » [] ✓ Fichier qui n'est pas une image : refusé, rien d'enregistré [<span style="color:#c0392b">Seules les images PNG et JPEG sont acceptées.</span>] ✓ Cachet commun enregistré depuis le panneau, aperçu affiché [<span style="color:#1e8449">Cachet enregistré.</span> {"l":120,"h":60}] ✓ Facture : l'image du cachet commun à la place de « LE PHARMACIEN » [120x60] ✓ Cachet propre au modèle : il prime sur le commun [90x90] ✓ Cachet du modèle retiré : le cachet commun revient [120x60] ✓ Panneau : indique que le cachet commun s'applique à ce modèle [Pas de cachet propre à ce modèle : le cachet commun est imprimé.] ✓ Aucune fenêtre [] ✓ Sans le droit du créateur de modèles : envoi refusé par le serveur [{"msg":"Vous n'avez pas le droit de modifier les modèles de facture.","success":false}] ✓ Données retirées (modèle, rattachement, cachets) | E5: OK | L5: =IF(I5="","",IF(I5=E5,"Oui","Non"))

Sheet Filtres des écrans
A1: CAHIER DE RECETTE — Filtres des écrans
A2: 4 tests : 3 OK, 1 en échec selon Claude
A4: N° | B4: Test | C4: Scénario : ce qui est fait et ce qui est attendu | D4: Contrôles faits par Claude (valeur mesurée) | E4: Résultat Claude | F4: Écart constaté par Claude | G4: Catégorie et suite | H4: Résultat testeur | I4: Statut testeur | J4: Testeur | K4: Date | L4: Concorde ? | M4: Commentaire
A5: 49 | B5: filtres/test-etat-stock-filtres.js | C5: ETAT DE STOCK (demande du 13/10) : filtres sur la 1re ligne, actions sur une 2e ligne (tout est visible a 1366 px) ; impression « avec reserve » : NOMS des rayons coches dans le rappel des criteres (avant : leurs identifiants). Lecture seule. | D5: 5 / 5 conformes ✓ Deux lignes : filtres en haut, actions dessous [{"l1Haut":117,"l2Haut":173,"actions":["Imprimer","Imprimer (réserve)","Cr&eacute;er inventaire","Cr&eacute;er suggestion","CSV","EXCEL"],"filtreDansL1":true,"toutVisible":true}] ✓ Actions sur la 2e ligne (Imprimer, réserve, inventaire, suggestion, CSV, EXCEL) [Imprimer|Imprimer (réserve)|Cr&eacute;er inventaire|Cr&eacute;er suggestion|CSV|EXCEL] ✓ Tous les boutons tiennent dans la largeur (1366 px) [{"l1Haut":117,"l2Haut":173,"actions":["Imprimer","Imprimer (réserve)","Cr&eacute;er inventaire","Cr&eacute;er suggestion","CSV","EXCEL"],"filtreDansL1":true,"toutVisible":true}] ✓ Impression avec réserve : les noms des 2 rayons cochés [COMPRIMES / DERMOCOSMETIQUE :: PHARMACIE DE LA CAPITALE BP 771 YAMOUSSOUKRO - - Tel: (+225) 27-24-36-11-66 / 07-08-12-39-58 - Compte Bancaire: BOA CI Dr KRA MICHEL ETAT DE STOCK - RAYON, RESERVE ET TOTAL Rayons : COMPRIMES, DERMOCOSMETIQUE CIP Désignation Emplacement Famille Rayon Réserve ] ✓ Aucune erreur JavaScript | E5: OK | L5: =IF(I5="","",IF(I5=E5,"Oui","Non"))
A6: 50 | B6: filtres/test-filtre-multiple-cazonegeo.js | C6: FILTRE MULTIPLE (maquette validee le 13/10) sur « CA emplacement/famille » (cazonegeomanager). - presentation B par defaut : un bouton « Filtres », panneau a onglets Rayon / Famille / Grossiste ; - cocher 3 rayons : le tableau ne garde que ces 3 rayons, avec les memes montants qu'en les demandant un par un ; - etiquettes sous la barre ; retirer une etiquette relance la recherche ; - rayon ET famille combines ; grossiste ; recherche dans la liste ; « Tout cocher » ne coche que les lignes affichees ; - bouton ⇄ : presentation A (un bouton par axe), memorisee pour l'utilisateur, puis retour a B ; - l'API accepte toujours un seul identifiant (ancien fonctionnement) et refuse sans erreur une saisie piegee ; - aucune erreur JavaScript, aucune fenetre. Seule ecriture : la preference de presentation de l'admin, remise a la fin. | D6: 21 / 21 conformes ✓ Précondition : au moins 3 rayons avec du CA sur 3 mois [35 lignes] ✓ Présentation B par défaut : un bouton « Filtres », anciennes listes masquées [{"presentation":"B","ouvrir":true,"zoneVisible":false,"familleVisible":false}] ✓ Panneau : onglets Rayon / Famille / Grossiste [Rayon|Famille|Grossiste] ✓ Récapitulatif « Votre sélection » : Rayon (3) [Rayon (3)COMPRIMES, DERMOCOSMETIQUE, LAITS ET CEREALES INFANTILES] ✓ Tableau : seulement les 3 rayons cochés [["14521913258936373344","14521913259068223572","14521913259222377963"]] ✓ Montant des 3 rayons = somme des 3 rayons demandés un par un [299660466 / 185112468+78335598+36212400] ✓ Étiquettes sous la barre : 3 [3] ✓ Retirer une étiquette relance la recherche (2 rayons) [["14521913259068223572","14521913259222377963"]] ✓ Rayons ET famille : sous-ensemble des rayons seuls [238912366 <= 299660466] ✓ Grossiste : filtre pris en compte (sous-ensemble du rayon) [180530323 <= 185112468] ✓ Recherche dans la liste : seules les familles qui contiennent « VETE » [VETERINAIRES] ✓ « Tout cocher » ne coche que les lignes affichées [1 / 1] ✓ Bouton ⇄ : présentation A, un bouton par axe avec le résumé [{"presentation":"A","boutons":["Rayon : DERMOCOSMETIQUE, LAITS ET CEREALES INFANTILES ▾","Famille : tous ▾","Grossiste : tous ▾"],"etiquettesVisibles":false}] ✓ Choix mémorisé pour l'utilisateur (préférence A) ✓ Présentation A : la liste d'un seul axe, sans onglets ✓ Réouverture de l'écran : présentation A conservée ✓ Retour à la présentation B ✓ Impression : les noms des rayons et du grossiste cochés [COMPRIMES / DERMOCOSMETIQUE + LABOREX-CI YOP :: Imprimé le 30/10/2026 10:17 PHARMACIE DE LA CAPITALE BP 771 YAMOUSSOUKRO - - Tel: (+225) 27-24-36-11-66 / 07-08-12-39-58 - Compte Bancaire: BOA CI Par : Essai E2E CHIFFRE D'AFFAIRES PAR ZONE GEOGRAPHIQUE Période du 01/07/2026 au 30/10/2026 - 4 tranche] ✓ API : un seul identifiant comme avant [185112468] ✓ API : saisie piégée traitée comme un identifiant inconnu (aucun résultat, pas d'erreur) [{"montantHtGeneral":0,"granularite":"MOIS","data":[],"margeGenerale":0,"totalGeneral":0,"fin":"2026-10-30","tranches":[{] ✓ Aucune erreur JavaScript, aucune fenêtre | E6: OK | L6: =IF(I6="","",IF(I6=E6,"Oui","Non"))
A7: 51 | B7: filtres/test-filtre-multiple-menus.js | C7: FILTRE MULTIPLE dans les 14 autres menus (demande du 13/10). Par ecran, en ouvrant le menu comme l'utilisateur : - le filtre multiple remplace les listes a choix unique (masquees), avec les axes de l'ecran ; - 2 rayons coches + « Rechercher » : la requete de l'ecran porte les 2 rayons ensemble et le serveur repond ; - quand la reponse a un total : total(2 rayons) = total(rayon 1) + total(rayon 2) (un produit n'a qu'un rayon) ; - aucune erreur JavaScript. Lecture seule (la preference de presentation n'est pas touchee). | D7: 62 / 62 conformes ✓ Précondition : 2 rayons avec des produits [14521913259068223572,14521913259188915887] ✓ ArticlesInvendus : filtre multiple à la place des listes (3 axe(s)) [{"axes":3,"masquees":true}] ✓ ArticlesInvendus : la recherche porte les 2 rayons ensemble ✓ ArticlesInvendus : le serveur répond sans erreur [{"s":200,"total":1675,"ko":false}] ✓ ArticlesInvendus : total(2 rayons) = total(rayon 1) + total(rayon 2) [1675 = 1340 + 335] ✓ ArticlesDormants : filtre multiple à la place des listes (3 axe(s)) [{"axes":3,"masquees":true}] ✓ ArticlesDormants : la recherche porte les 2 rayons ensemble ✓ ArticlesDormants : le serveur répond sans erreur [{"s":200,"total":326,"ko":false}] ✓ ArticlesDormants : total(2 rayons) = total(rayon 1) + total(rayon 2) [326 = 236 + 90] ✓ GestionSurstock : filtre multiple à la place des listes (3 axe(s)) [{"axes":3,"masquees":true}] ✓ GestionSurstock : la recherche porte les 2 rayons ensemble ✓ GestionSurstock : le serveur répond sans erreur [{"s":200,"total":464,"ko":false}] ✓ GestionSurstock : total(2 rayons) = total(rayon 1) + total(rayon 2) [464 = 412 + 52] ✓ MargeManager : filtre multiple à la place des listes (3 axe(s)) [{"axes":3,"masquees":true}] ✓ MargeManager : la recherche porte les 2 rayons ensemble ✓ MargeManager : le serveur répond sans erreur [{"s":200,"total":1357,"ko":false}] ✓ MargeManager : total(2 rayons) = total(rayon 1) + total(rayon 2) [1357 = 1144 + 213] ✓ EtatStockManager : filtre multiple à la place des listes (3 axe(s)) [{"axes":3,"masquees":true}] ✓ EtatStockManager : la recherche porte les 2 rayons ensemble ✓ EtatStockManager : le serveur répond sans erreur [{"s":200,"total":3029,"ko":false}] ✓ EtatStockManager : total(2 rayons) = total(rayon 1) + total(rayon 2) [3029 = 2481 + 548] ✓ ArticleVenduBis : filtre multiple à la place des listes (2 axe(s)) [{"axes":2,"masquees":true}] ✓ ArticleVenduBis : la recherche porte les 2 rayons ensemble ✓ ArticleVenduBis : le serveur répond sans erreur [{"s":200,"total":1357,"ko":false}] ✓ ArticleVenduBis : total(2 rayons) = total(rayon 1) + total(rayon 2) [1357 = 1144 + 213] ✓ ArticleVendu : filtre multiple à la place des listes (1 axe(s)) [{"axes":1,"masquees":true}] ✓ ArticleVendu : la recherche porte les 2 rayons ensemble ✓ ArticleVendu : le serveur répond sans erreur [{"s":200,"total":7068,"ko":false}] ✓ ArticleVendu : total(2 rayons) = total(rayon 1) + total(rayon 2) [7068 = 5767 + 1301] ✓ ComparaisonStock : filtre multiple à la place des listes (3 axe(s)) [{"axes":3,"masquees":true}] ✓ ComparaisonStock : la recherche porte les 2 rayons ensemble ✓ ComparaisonStock : le serveur répond sans erreur [{"s":200,"total":3029,"ko":false}] ✓ ComparaisonStock : total(2 rayons) = total(rayon 1) + total(rayon 2) [3029 = 2481 + 548] ✓ EvaluationVenteMoyenneManager : filtre multiple à la place des listes (2 axe(s)) [{"axes":2,"masquees":true}] ✓ EvaluationVenteMoyenneManager : la recherche porte les 2 rayons ensemble ✓ EvaluationVenteMoyenneManager : le serveur répond sans erreur [{"s":200,"total":1623,"ko":false}] ✓ EvaluationVenteMoyenneManager : total(2 rayons) = total(rayon 1) + total(rayon 2) [1623 = 1363 + 260] ✓ SaisiePerimeManager : filtre multiple à la place des listes (3 axe(s)) [{"axes":3,"masquees":true}] ✓ SaisiePerimeManager : la recherche porte les 2 rayons ensemble ✓ SaisiePerimeManager : le serveur répond sans erreur [{"s":200,"total":20,"ko":false}] ✓ SaisiePerimeManager : total(2 rayons) = total(rayon 1) + total(rayon 2) [20 = 5 + 15] ✓ FamilleManager : filtre multiple à la place des listes (1 axe(s)) [{"axes":1,"masquees":true}] ✓ FamilleManager : la recherche porte les 2 rayons ensemble ✓ FamilleManager : le serveur répond sans erreur [{"s":200,"total":3029,"ko":false}] ✓ FamilleManager : total(2 rayons) = total(rayon 1) + total(rayon 2) [3029 = 2481 + 548] ✓ AbcManager : filtre multiple à la place des listes (3 axe(s)) [{"axes":3,"masquees":true}] ✓ AbcManager : la recherche porte les 2 rayons ensemble ✓ AbcManager : le serveur répond sans erreur [{"s":200,"total":1317,"ko":false}] ✓ AbcManager : total(2 rayons) = total(rayon 1) + total(rayon 2) [1317 = 1129 + 188] ✓ FeuilleDeMatchManager : filtre multiple à la place des listes (3 axe(s)) [{"axes":3,"masquees":true}] ✓ FeuilleDeMatchManager : la recherche porte les 2 rayons ensemble ✓ FeuilleDeMatchManager : le serveur répond sans erreur [{"s":200,"total":1317,"ko":false}] ✓ FeuilleDeMatchManager : total(2 rayons) = total(rayon 1) + total(rayon 2) [1317 = 1129 + 188] ✓ AnalyseArticleManager : filtre multiple à la place des listes (3 axe(s)) [{"axes":3,"masquees":true}] ✓ AnalyseArticleManager : la recherche porte les 2 rayons ensemble ✓ AnalyseArticleManager : le serveur répond sans erreur [{"s":200,"total":1628,"ko":false}] ✓ AnalyseArticleManager : total(2 rayons) = total(rayon 1) + total(rayon 2) [1628 = 1368 + 260] ✓ ArticleMvtGrid : filtre multiple à la place des listes (2 axe(s)) [{"axes":2,"masquees":true}] ✓ ArticleMvtGrid : la recherche porte les 2 rayons ensemble ✓ ArticleMvtGrid : le serveur répond sans erreur [{"s":200,"total":1494,"ko":false}] ✓ ArticleMvtGrid : total(2 rayons) = total(rayon 1) + total(rayon 2) [1494 = 1244 + 250] ✓ Aucune erreur JavaScript | E7: OK | L7: =IF(I7="","",IF(I7=E7,"Oui","Non"))
A8: 52 | B8: filtres/test-impressions-filtres.js | C8: IMPRESSIONS ET FILTRE MULTIPLE (demande du 13/10) : chaque impression des menus a filtre multiple rappelle les NOMS des rayons coches (jamais leurs identifiants). 2 rayons coches, periode d'aout a debut octobre. Lecture seule. | E8: Échec | F8: Test arrêté (code 1) avant la fin, sans contrôle en écart | G8: À examiner : Pas encore étudié : test à adapter à la copie ou défaut à confirmer. | L8: =IF(I8="","",IF(I8=E8,"Oui","Non"))

Sheet Inventaire
A1: CAHIER DE RECETTE — Inventaire
A2: 1 tests : 1 OK, 0 en échec selon Claude
A4: N° | B4: Test | C4: Scénario : ce qui est fait et ce qui est attendu | D4: Contrôles faits par Claude (valeur mesurée) | E4: Résultat Claude | F4: Écart constaté par Claude | G4: Catégorie et suite | H4: Résultat testeur | I4: Statut testeur | J4: Testeur | K4: Date | L4: Concorde ? | M4: Commentaire
A5: 53 | B5: inventaire/test-colonnes-inventaire.js | C5: Point 9 : la mise en page des colonnes de l'ecran Inventaire doit survivre a la sortie du menu, dans les deux sens (colonne decochee qui restait masquee, colonne cochee qui restait affichee), et rester propre a l'utilisateur connecte. | D5: 7 / 7 conformes ✓ grille inventaire ouverte avec des colonnes [[{"di":"bl_A_SUPPRIMER","h":false},{"di":"lg_INVENTAIRE_ID","h":true},{"di":"str_NAME","h":false},{"di":"str_DESCRIPTION","h":false},{"di":"lg_USER_ID","h":false},{"di":"dt_CREATED","h":false},{"di":"] ✓ une colonne affichee et une colonne masquee au depart [{"visible":{"di":"str_NAME","h":false},"masquee":{"di":"lg_INVENTAIRE_ID","h":true}}] ✓ la colonne decochee reste masquee au retour dans le menu [str_NAME -> true] ✓ la colonne cochee reste affichee au retour dans le menu [lg_INVENTAIRE_ID -> false] ✓ la mise en page est rangee sous l identifiant de l utilisateur [prestige-90000000000000000001-grille-inventaires | prestige-90000000000000000001-grille-fiche-article-v2] ✓ la presentation d un autre utilisateur n est pas modifiee [{"str_NAME":false,"lg_INVENTAIRE_ID":true}] ✓ aucune erreur JavaScript | E5: OK | L5: =IF(I5="","",IF(I5=E5,"Oui","Non"))

Sheet Journal
A1: CAHIER DE RECETTE — Journal
A2: 12 tests : 10 OK, 2 en échec selon Claude
A4: N° | B4: Test | C4: Scénario : ce qui est fait et ce qui est attendu | D4: Contrôles faits par Claude (valeur mesurée) | E4: Résultat Claude | F4: Écart constaté par Claude | G4: Catégorie et suite | H4: Résultat testeur | I4: Statut testeur | J4: Testeur | K4: Date | L4: Concorde ? | M4: Commentaire
A5: 54 | B5: journal/test-controle-achats-filtre-apres-edition.js | C5: CONTROLE DES ACHATS (LISTE DES BL) : FILTRES APRES LA FENETRE « MISE A JOUR DU BL » (journal du 12/10). « Uncaught TypeError: Me.onRechClick is not a function » (EtatControleManager.js) : l'ecran gardait son instance dans la variable globale Me, que la fenetre de mise a jour d'un BL (cmde_passees/action/edit.js) reprend pour elle (Me = this) ; une fois cette fenetre fermee, chaque filtre appelait onRechClick sur la fenetre. Parcours par les vues, avec un utilisateur qui a le droit P_BTN_UPDATEBL (sans lui, le bouton n'est pas affiche) : le droit est accorde au role de l'utilisateur d'essai avant la connexion, puis retire a la fin. - menu GESTION DES COMMANDES > « Etat de contrôle Achats » ; periode saisie au clavier, bouton Rechercher ; - bouton « Modifier les informations du bon de livraison » de la premiere ligne : la fenetre s'ouvre, fermee par sa croix ; - choix d'un grossiste puis du type de date dans leurs listes : aucune erreur JavaScript, la liste se recharge. | D5: 7 / 7 conformes ✓ Liste des BL de septembre affichée après « Rechercher » [20 bons] ✓ Avec le droit P_BTN_UPDATEBL : bouton « Modifier les informations du BL » affiché sur la ligne ✓ Fenêtre de mise à jour du BL ouverte par le bouton, fermée par sa croix ✓ Après la fenêtre : choix d'un grossiste → la liste se recharge, sans erreur [AFRIC ELITE PHARMA ] ✓ Après la fenêtre : choix du type de date → la liste se recharge, sans erreur [Date d'entrée ] ✓ Aucune erreur JavaScript [] ✓ Droit d'essai retiré, droits du rôle inchangés | E5: OK | L5: =IF(I5="","",IF(I5=E5,"Oui","Non"))
A6: 55 | B6: journal/test-export-journal.js | C6: Point 14 : export Excel du fichier journal. Le bouton existe, l'export porte TOUTES les lignes des criteres et non la seule page affichee, et le fichier est un vrai classeur. | D6: 10 / 10 conformes ✓ ecran Fichier Journal ouvert ✓ bouton Excel present dans la barre du journal [{"present":true,"tooltip":"Exporter le r&eacute;sultat complet vers Excel"}] ✓ le bouton declenche bien un telechargement [fichier_journal_30102026_142651.xlsx] ✓ le fichier porte un nom explicite et l extension xlsx [fichier_journal_30102026_142651.xlsx] ✓ l export repond en 200 [{"status":200,"type":"application/vnd.openxmlformats-officedocument.spreadsheetml.sheet","taille":6970515,"entete":"PK"}] ✓ le fichier est un classeur (signature ZIP des .xlsx) [{"status":200,"type":"application/vnd.openxmlformats-officedocument.spreadsheetml.sheet","taille":6970515,"entete":"PK"}] ✓ le classeur a un contenu [taille=6970515] ✓ la grille reste paginee a l ecran [{"affichees":15,"total":146588}] ✓ le classeur porte toutes les lignes de la periode, pas la page affichee [lignes de donnees=146588 attendu>=146588 page ecran=15] ✓ aucune erreur JavaScript | E6: OK | L6: =IF(I6="","",IF(I6=E6,"Oui","Non"))
A7: 56 | B7: journal/test-infos-client-vente-avant-chargement.js | C7: MODIFICATION DES INFOS CLIENT D'UNE VENTE TIERS PAYANT AVANT LA FIN DU CHARGEMENT (journal du 15/10). « TypeError: can't access property "strFIRSTNAME", client is null » (UpdateVenteClientTpForm.js, changeClientInfos) : la fenetre s'ouvre tout de suite, la vente arrive ensuite ; un clic sur « Modifier infos client » pendant ce temps lisait un client encore vide. Parcours par les vues (vente VO cloturee du banc, lecture seule, chargement de la vente ralenti de 4 s comme un reseau charge), avec le droit P_BTN_UPDATE_VENTE_CLIENT_TP (sans lui le bouton de la ligne n'est pas affiche) : le droit est accorde au role de l'utilisateur d'essai avant la connexion, puis retire a la fin. - menu SERVICE CLIENT > « Vente terminées » ; dates et reference saisies au clavier, bouton rechercher ; - bouton « Modifier info client » de la ligne : pendant le chargement, « Modifier infos client » et « Modifier infos ayant droit » inactifs, un clic ne fait rien, sans erreur ; - vente chargee : les deux boutons actifs ; « Modifier infos client » ouvre la saisie avec le nom du client de la vente (compare, jamais affiche). | D7: 7 / 7 conformes ✓ Jeu d'essai : une vente VO avec client [261028_00001 du 28/10/2026] ✓ Avec le droit : bouton « Modifier info client » affiché sur la ligne de la vente ✓ Pendant le chargement : les deux boutons inactifs, un clic n'ouvre rien [{"client":true,"ayant":true} fenêtres 1 → 1 ] ✓ Vente chargée : les deux boutons actifs [{"client":false,"ayant":false}] ✓ « Modifier infos client » ouvre la saisie avec le nom du client de la vente ✓ Aucune erreur JavaScript [] ✓ Droit d'essai retiré, droits du rôle inchangés | E7: OK | L7: =IF(I7="","",IF(I7=E7,"Oui","Non"))
A8: 57 | B8: journal/test-pilotage-quitte-avant-reponse.js | C8: PILOTAGE QUITTE AVANT LA REPONSE DU SERVEUR (parcours test-saisie-ecrans du 23/10). « TypeError : Cannot read properties of undefined (reading 'down') » dans PilotageCtr.afficherAxe : l'utilisateur ouvre le Pilotage puis passe a un autre ecran avant que les chiffres n'arrivent ; la reponse, arrivee ensuite, etait appliquee a un ecran ferme. Parcours par les vues (admin) : ANALYSE DE GESTION > Pilotage de l'officine, puis tout de suite l'icone « Accueil » de l'en-tete (tableau de bord) ; on attend que la reponse du pilotage soit arrivee : - aucune erreur JavaScript ; - le tableau de bord est toujours affiche, sans message d'erreur. (Quitter par le menu ne declenchait pas l'erreur : l'ecran garde alors sa reference.) Lecture seule. | D8: 4 / 4 conformes ✓ Précondition : le Pilotage est fermé avant que sa réponse n'arrive [{"pilotage":0}] ✓ La réponse du pilotage arrive après le changement d'écran ✓ Pilotage quitté avant sa réponse : aucune erreur JavaScript [] ✓ Le tableau de bord reste affiché, sans message d'erreur [] | E8: OK | L8: =IF(I8="","",IF(I8=E8,"Oui","Non"))
A9: 58 | B9: journal/test-retour-carnet-code-encode.js | C9: RETOUR CARNET DEPOT : CODE LU A LA DOUCHETTE ENVOYE ENCODE (retour du 23/10, meme defaut que vente/findone). La recherche du produit lu (carnet-depot/produits-one/<code>/<tiers-payant>) mettait le code tel quel dans l'adresse : un code avec « / » ou « # » partait coupe ou mal route. Parcours par les vues (admin) : GESTION DES TIERS-PAYANTS > Retour carnet dépôt > bouton de retour, tiers-payant choisi dans la liste, « E2E/12#3 » tape dans « Produit », Entree : - l'appel part avec le code encode (produits-one/E2E%2F12%233/<tiers-payant>) et le serveur repond sans erreur ; - aucune erreur JavaScript. Lecture seule (rien n'est enregistre). La base de travail n'a pas toujours de carnet depot : le test en pose un (type carnet, depot) s'il n'y en a aucun, et le retire a la fin. | D9: 4 / 4 conformes ✓ Tiers-payant choisi dans la liste [E2E-RCC-DEPOT] ✓ Code « E2E/12#3 » envoyé encodé, réponse sans erreur [200 http://localhost:8080/prestige/api/v2/carnet-depot/produits-one/E2E%2F12%233/E2E-RCC-DEPOT] ✓ Aucune erreur JavaScript [] ✓ Carnet dépôt d'essai retiré | E9: OK | L9: =IF(I9="","",IF(I9=E9,"Oui","Non"))
A10: 59 | B10: journal/test-scan-qr-publicitaire.js | C10: QR CODE PUBLICITAIRE SCANNE EN CAISSE (journal du 16/10 : « vente/findone/https://... » en erreur 404, une vingtaine de fois). Le QR de la boite renvoie vers un site internet : ce n'est pas un code produit. Parcours par les vues (admin, aucune vente enregistree) : chaque ecran est ouvert par son menu et son bouton, le geste prealable de l'ecran est fait (depot choisi, client recherche), puis le lien est tape dans son champ « Produit » et Entree, comme une douchette. Le Proforma demande un client : un client d'essai fictif (« E2ESCANQR ») est cree avant et retire a la fin ; aucun client reel n'est lu. - vente (SERVICE CLIENT > Ventes > Nouvelle vente) : aucun appel au serveur avec le lien, message « QR code publicitaire » dans la page (sans fenetre), champ vide ; un vrai code (CIP) scanne ensuite est cherche (la douchette l'ajoute a une vente en cours, retiree a la fin par la route de suppression de l'ecran Ventes) ; - vente depot (SERVICE CLIENT > Vente dépôt > Nouvelle vente, depot choisi), proforma (SERVICE CLIENT > Proforma > Nouveau, client recherche), ajustement (GESTION DU STOCK > Ajustement du Stock > Ajustement rayon), vente en depot (GESTION DES TIERS-PAYANTS > Gestion depots extensions, depot choisi en haut de l'ecran) : meme refus ; - code lu contenant « / » et « # » (retour du 23/10) : dans chaque ecran, il part encode a la recherche du produit (findone/E2E%2F12%233), au lieu d'une adresse coupee ou mal routee ; - aucun ajustement ni vente cree par l'essai. | D10: 11 / 13 conformes ✓ Vente : lien scanné → aucun appel au serveur, « QR code publicitaire » sans fenêtre, champ vidé [{"champ":"","fenetre":false,"texte":true} appels : ] ✓ Vente : un vrai code scanné ensuite est cherché normalement [http://localhost:8080/prestige/api/v1/vente/findone/0000105?_dc=1793370985067] ✗ Vente dépôt : lien scanné → aucun appel au serveur, « QR code publicitaire » sans fenêtre, champ vidé [{"champ":"htt","fenetre":false,"texte":false} appels : ] ✗ Vente dépôt : code avec « / » et « # » envoyé encodé [] ✓ Proforma : lien scanné → aucun appel au serveur, « QR code publicitaire » sans fenêtre, champ vidé [{"champ":"","fenetre":false,"texte":true} appels : ] ✓ Proforma : code avec « / » et « # » envoyé encodé [http://localhost:8080/prestige/api/v1/vente/findone/E2E%2F12%233?_dc=1793371007357] ✓ Ajustement : lien scanné → aucun appel au serveur, « QR code publicitaire » sans fenêtre, champ vidé [{"champ":"","fenetre":false,"texte":true} appels : ] ✓ Ajustement : code avec « / » et « # » envoyé encodé [http://localhost:8080/prestige/api/v1/vente/findone/E2E%2F12%233?_dc=1793371019754] ✓ Vente en dépôt (extensions) : lien scanné → aucun appel au serveur, « QR code publicitaire » sans fenêtre, champ vidé [{"champ":"","fenetre":false,"texte":true} appels : ] ✓ Vente en dépôt (extensions) : code avec « / » et « # » envoyé encodé [http://localhost:8080/prestige/api/v1/vente/findone/E2E%2F12%233?_dc=1793371032832] ✓ Aucune erreur JavaScript [] ✓ Aucun ajustement ni vente créé par l'essai [780/476288 → 780/476288] ✓ Client et dépôt d'essai retirés | E10: Échec | F10: Vente dépôt : lien scanné → aucun appel au serveur, « QR code publicitaire » sans fenêtre, champ vidé [{"champ":"htt","fenetre":false,"texte":false} appels : ] Vente dépôt : code avec « / » et « # » envoyé encodé [] | G10: À examiner : Partie « vente dépôt » en échec deux fois de suite l'après-midi (champ partiellement saisi) ; passait le matin. | L10: =IF(I10="","",IF(I10=E10,"Oui","Non"))
A11: 60 | B11: journal/test-suppression-commande-double.js | C11: SUPPRESSION D'UNE COMMANDE ENVOYEE DEUX FOIS (journal du 16/10, 10:31:44 : deux DELETE dans la meme seconde). Le second appel ne trouvait plus la commande et finissait en erreur 500 (« attempt to create delete event with null entity »), affichee a l'utilisateur dans « Error Message ». Parcours par les vues, deux postes (deux sessions du meme utilisateur) sur GESTION DES COMMANDES > « Commande en cours », reference tapee dans « Recherche » puis Entree, icone « Supprimer » de la ligne : elle devient « Confirmer ? » (confirmation dans le bouton, aucune fenetre), un second clic supprime, le resultat s'affiche dans la page. Les commandes d'essai (une ligne chacune, sinon la liste ne les montre pas) sont creees avant et retirees a la fin. - ergonomie : a 1600 et 1920 px, toutes les icones de la ligne (dont « Supprimer ») sont dans la zone visible de la liste ; a 1366 px, la liste defile horizontalement (molette + Maj) jusqu'a elles ; un clic ne doit jamais dependre d'un defilement qu'un utilisateur ne peut pas faire ; - reference tapee vite puis Entree (douchette, saisie rapide) : la liste montre cette commande ; - confirmation dans le bouton : premier clic -> « Confirmer ? » sans fenetre ; sans second clic, l'icone revient apres 5 s et rien n'est supprime ; un double-clic ne vaut pas confirmation (rien n'est supprime) ; - un poste supprime : « Commande supprimée » dans la page, la commande et sa ligne disparaissent de la liste et de la base ; - liste perimee : le poste 1 supprime, puis le poste 2, qui affiche encore la commande, la supprime a son tour : « Commande supprimée », aucune erreur ; - les deux postes confirment en meme temps : aucun message d'erreur, commande supprimee. | D11: 14 / 14 conformes ✓ Ergonomie 1366 px : toutes les icônes de la ligne, dont « Supprimer », dans la zone visible après défilement horizontal [] ✓ Ergonomie 1600 px : toutes les icônes de la ligne, dont « Supprimer », dans la zone visible [] ✓ Ergonomie 1920 px : toutes les icônes de la ligne, dont « Supprimer », dans la zone visible [] ✓ Référence tapée vite puis Entrée (douchette) : la liste montre la commande ✓ Premier clic sur « Supprimer » : l'icône devient « Confirmer ? », aucune fenêtre ✓ Sans second clic : l'icône revient après 5 s, rien n'est supprimé ✓ Double-clic sur « Supprimer » : ne vaut pas confirmation, rien n'est supprimé ✓ Second clic sur « Confirmer ? » : « Commande supprimée » dans la page, sans fenêtre, commande et ligne supprimées, ligne retirée [ok:✔Commande supprimée : E2ECMDDBL1] ✓ Liste périmée : le poste 1 supprime la commande [ok:✔Commande supprimée : E2ECMDDBL2] ✓ Liste périmée : le poste 2 l'affiche encore et demande sa suppression ✓ Liste périmée : le poste 2 confirme → « Commande supprimée », aucune erreur [ok:✔Commande supprimée : E2ECMDDBL2] ✓ Les deux postes confirment en même temps : aucune erreur, commande et ligne supprimées [ok:✔Commande supprimée : E2ECMDDBL3 || ok:✔Commande supprimée : E2ECMDDBL3] ✓ Aucune erreur JavaScript [] ✓ Commandes d'essai retirées | E11: OK | L11: =IF(I11="","",IF(I11=E11,"Oui","Non"))
A12: 61 | B12: journal/test-tiers-payants-desactives.js | C12: GESTION DES TIERS-PAYANTS > « Tiers payants désactivés » : LISTE VIDE (journal du 18/10). « Échec Ajax HTTP 404 : ../webservices/tierspayantmanagement/tierspayant/ws_data.jsp?str_STATUT=disable » : l'ecran appelait une page qui n'existe pas ; aucun tiers-payant desactive ne pouvait etre retrouve ni reactive. Parcours par les vues : un tiers-payant du banc est desactive le temps du test (puis remis actif). - menu ; la liste montre le tiers-payant desactive, et lui seul parmi les actifs n'y figure pas ; - recherche au clavier sur son nom (Entree) : il reste affiche ; - aucune erreur JavaScript, aucun appel en echec. | D12: 4 / 5 conformes ✗ La liste montre le tiers-payant désactivé [20 ligne(s) ; ] ✓ Et aucun tiers-payant actif [[{"id":"14731203937606255787","statut":"disable"},{"id":"16717114379796404240","statut":"disable"},{"id":"14851114525912947985","statut":"disable"}]] ✓ Recherche sur son nom (Entrée) : il reste affiché [1 ligne(s)] ✓ Aucune erreur JavaScript, aucun appel en échec [] ✓ Tiers-payant remis dans son état | E12: Échec | F12: La liste montre le tiers-payant désactivé [20 ligne(s) ; ] | G12: À examiner : Pas encore étudié : test à adapter à la copie ou défaut à confirmer. | L12: =IF(I12="","",IF(I12=E12,"Oui","Non"))
A13: 62 | B13: journal/test-vente-changer-tiers-payant.js | C13: VENTE TERMINEE > « Modifier info client » > « Modifier le tiers-payant » (journaux du 11/09, 20/09 et 19/10). - « TypeError: can't access property "strFULLNAME", tpRecord.data is undefined » (UpdateVenteClientTpForm.js) : « Valider » sans tiers-payant choisi plantait la fenetre « TIERS-PAYANTS ASSOCIES » ; - « ReferenceError: itemId is not defined » : choisir « AJOUTER UN NOUVEAU TIERS-PAYANT » plantait, la creation d'un tiers-payant depuis la vente n'a jamais pu aboutir. Parcours par les vues (vente VO cloturee du banc avec un tiers-payant), avec le droit P_BTN_UPDATE_VENTE_CLIENT_TP accorde le temps du test : - menu SERVICE CLIENT > « Vente terminées » ; dates et reference saisies au clavier ; « Modifier info client » ; - « Modifier le tiers-payant », puis « Valider » sans choix : la liste est marquee en erreur, la fenetre reste, aucune erreur JavaScript ; - « AJOUTER UN NOUVEAU TIERS-PAYANT » : la saisie s'ouvre ; nom, telephone, adresse, code saisis au clavier ; « Enregistrer » : les deux fenetres se ferment, la ligne du tiers-payant de la vente affiche le nouveau ; - la vente n'est pas enregistree (fenetre fermee sans valider). Donnees retirees a la fin : le tiers-payant cree (nom « E2E TP CHANGE ») et son compte, priorites des comptes du client remises a l'identique, droit d'essai. | D13: 7 / 7 conformes ✓ Jeu d'essai : une vente VO avec tiers-payant [261028_00001 du 28/10/2026, 4 compte(s)] ✓ « Valider » sans tiers-payant choisi : liste marquée en erreur, fenêtre ouverte, aucune erreur JavaScript [] ✓ « AJOUTER UN NOUVEAU TIERS-PAYANT » : la saisie du tiers-payant s'ouvre, sans erreur [] ✓ « Enregistrer » : les deux fenêtres se ferment, la ligne de la vente affiche le nouveau tiers-payant [ANKARA → E2E TP CHANGE] ✓ Tiers-payant créé et rattaché au client ✓ Aucune erreur JavaScript [] ✓ Données d'essai retirées, comptes du client inchangés | E13: OK | L13: =IF(I13="","",IF(I13=E13,"Oui","Non"))
A14: 63 | B14: journal/test-vente-quantite-decimale.js | C14: VENTE : QUANTITE DECIMALE SAISIE DANS LA GRILLE (journal du poste caisse 3, 03/09). « JsonbException : Unable to deserialize property 'qte' ... Integer » sur vente/update/item/vno : la colonne QD de la grille acceptait le point, une quantite 1.5 partait au serveur, qui repondait « erreur interne » et ouvrait un incident au Centre de support. Parcours par les vues (admin, SERVICE CLIENT > Ventes > nouvelle vente, un article) : - clic sur la cellule QD de la ligne, « 1.5 » tape au clavier, Entree : refus avec un message clair (retours du 25/10, point 11), la quantite precedente est gardee, rien de decimal ne part au serveur, aucune erreur serveur ; - une quantite decimale envoyee malgre tout (autre poste, application) est refusee proprement (HTTP 400) avec le nom du champ, sans « erreur interne ». La vente d'essai et le stock de l'article sont remis a la fin. | D14: 5 / 5 conformes ✓ Jeu d'essai : un article en stock [9999157] ✓ QD « 1.5 » tapé dans la grille : refus avec un message clair (25/10), quantité précédente gardée, rien de décimal envoyé [[] qd=1 QuantitéLa quantité doit être un nombre entier : les valeurs décimales (1,5) ne sont pas possibles. La quantité précédente (1) est conservée.OKOuiNonAnnuler] ✓ Quantité décimale envoyée malgré tout : refus 400 qui nomme le champ, pas d'« erreur interne » [400 {"msg":"Valeur saisie invalide pour « qte » : un nombre entier est attendu.","success":false,"total":0}] ✓ Aucune erreur JavaScript [] ✓ Vente d'essai retirée, stock remis | E14: OK | L14: =IF(I14="","",IF(I14=E14,"Oui","Non"))
A15: 64 | B15: journal/test-vente-vendeur-inconnu.js | C15: VENTE : VENDEUR NON RECONNU SIGNALE DES LA SAISIE (retour du 23/10). La liste « Vendeur » reste en saisie libre ; un nom tape qui ne correspond a aucun utilisateur faisait enregistrer la vente au nom de l'utilisateur connecte, sans que personne ne le sache avant la fin. Desormais on le dit juste apres la saisie. Parcours par les vues (admin, SERVICE CLIENT > Ventes > nouvelle vente) : - « ZZZ PERSONNE » tape, Tab : le champ est signale aussitot (avant tout article), avec le message « Vendeur non reconnu » qui dit au nom de qui la vente sera enregistree ; le focus suit son cours (pas de fenetre) ; - le nom complet d'un vendeur tape sans le choisir, Tab : il est reconnu et retenu (son identifiant), plus de signal ; - aucune vente creee par ces saisies, aucune erreur JavaScript. Lecture seule (aucune vente creee). | D15: 5 / 5 conformes ✓ Jeu d'essai : un vendeur avec un nom [01 - ASSALE ABENAN AGNES] ✓ « ZZZ PERSONNE » + Tab : signalé aussitôt « Vendeur non reconnu », au nom de qui la vente sera enregistrée [{"valeur":"ZZZ PERSONNE","invalide":true,"erreur":"Vendeur non reconnu : « ZZZ PERSONNE ». La vente sera enregistrée au nom de l&#39;utilisateur connecté. Choisissez un nom dans la liste pour l&#39;attribuer à un vendeur.","formulaireValide":true,"toast":"Vendeur non reconnu : la vente sera enregist] ✓ Pas de fenêtre, le focus a quitté le champ [combobox-1107-inputEl] ✓ Nom complet d'un vendeur tapé sans le choisir + Tab : reconnu et retenu, plus de signal [{"valeur":"14111258616328087429","invalide":false,"erreur":"","formulaireValide":true,"toast":"","focus":"combobox-1139-inputEl","userAFocus":false}] ✓ Aucune vente créée par ces saisies, aucune erreur JavaScript [] | E15: OK | L15: =IF(I15="","",IF(I15=E15,"Oui","Non"))
A16: 65 | B16: journal/test-vente-vendeur-saisi.js | C16: VENTE : VENDEUR TAPE SANS ETRE CHOISI DANS LA LISTE (journaux du poste caisse 3, 17/08 et 19/08). « TransientPropertyValueException : TPreenregistrement.lgUSERVENDEURID -> TUser » sur vente/add/vno et vente/add/assurance : la liste « Vendeur » est editable ; un nom tape sans etre choisi part tel quel, et la creation de la vente (premier article) rattachait un vendeur qui n'existe pas. L'article n'etait pas ajoute. La cloture, elle, cherche le vendeur en base et retient la caissiere s'il n'existe pas : meme regle a la creation. Parcours par les vues (admin, SERVICE CLIENT > Ventes > nouvelle vente) : - « ZZZ PERSONNE » tape dans « Vendeur », Tab ; - CIP d'un article tape dans la recherche produit, Entree : la vente est creee avec l'article, aucun message d'erreur, aucune erreur JavaScript ; - vendeur enregistre = la caissiere (admin), comme a la cloture. La vente d'essai et le stock de l'article sont remis a la fin. | D16: 6 / 6 conformes ✓ Jeu d'essai : un article en stock [9999951] ✓ Vendeur tapé sans choix (« ZZZ PERSONNE »), article ajouté : vente créée, sans message d'erreur [0e10e725-fc0c-424a-bcdf-0360509b5a12 ; ; ] ✓ L'article est sur la vente [1] ✓ Vendeur enregistré = la caissière (comme à la clôture) [e2e|e2e] ✓ Aucune erreur JavaScript [] ✓ Vente d'essai retirée, stock remis | E16: OK | L16: =IF(I16="","",IF(I16=E16,"Oui","Non"))

Sheet Lot 3
A1: CAHIER DE RECETTE — Lot 3
A2: 3 tests : 2 OK, 1 en échec selon Claude
A4: N° | B4: Test | C4: Scénario : ce qui est fait et ce qui est attendu | D4: Contrôles faits par Claude (valeur mesurée) | E4: Résultat Claude | F4: Écart constaté par Claude | G4: Catégorie et suite | H4: Résultat testeur | I4: Statut testeur | J4: Testeur | K4: Date | L4: Concorde ? | M4: Commentaire
A5: 66 | B5: lot3/test-ergonomie-lot3.js | C5: Lot 3 — ergonomie et navigation. Point 4 : apres generation d'une facture provisoire, retour a la liste, rafraichie. Point 7 : privileges, recherche « contient » declenchee au 3e caractere, temporisee. Point 15 : modeles de message, duplication et variables cliquables. Point 16 : analyse des ajustements triee par nombre d'ajustements decroissant. Point 18 : fiche article, emplacement et famille preselectionnes a la creation. | D5: 28 / 28 conformes ✓ point 16 : l analyse des ajustements repond [status=200 lignes=3] ✓ point 16 : tri par nombre d ajustements decroissant [[5,3,1]] ✓ point 16 : le produit le plus ajuste ouvre la liste, pas le plus gros volume [5 ajustements, qte 5] ✓ point 16 : a egalite, tri alphabetique sur la designation [["3 HP KIT GEL/2 + CPR/4 KIT/14"]] ✓ point 15 : modele source cree [{"msg":"Modèle créé","success":true,"id":"6ef65359-172d-433b-8bdd-4e8d1e1b7d5f"}] ✓ point 15 : la duplication reussit [{"msg":"Modèle dupliqué sous « E2EL3 source (Copie) »","success":true,"libelle":"E2EL3 source (Copie)","id":"452f0207-587a-4880-b6c0-be968b5097a8"}] ✓ point 15 : la copie porte le suffixe « (Copie) » [E2EL3 source (Copie)] ✓ point 15 : la copie est un modele independant du source [452f0207-587a-4880-b6c0-be968b5097a8] ✓ point 15 : dupliquer deux fois ne bute pas sur l unicite du libelle [E2EL3 source (Copie 2)] ✓ point 15 : le modele source est preserve [E2EL3 source ✓ point 15 : la copie reprend le contenu et le canal du source [source=Bonjour {client} copie=Bonjour {client}] ✓ point 15 : la variable est inseree a la position du curseur [Bonjour {client}, merci] ✓ point 15 : chaque variable est rendue cliquable [7 variables] ✓ point 7 : la recherche « contient » trouve par un mot du MILIEU du libelle [motif="E DES" total=29 ] ✓ point 7 : la recherche restreint bien la liste [sans=345 avec=29 ] ✓ point 7 : un fragment absent de tout DEBUT de libelle ramene quand meme des lignes [motif="E DES" total=29 ] ✓ point 7 : l invite annonce un « contient » [{"invite":"Contient... (3 caractères minimum)","present":true}] ✓ point 7 : a deux caracteres aucune recherche n est lancee [0 requete(s)] ✓ point 7 : rien ne part a la frappe meme, la recherche est temporisee [{"immediat":0,"total":1}] ✓ point 7 : au 3e caractere la recherche part, une seule fois [{"immediat":0,"total":1}] ✓ point 7 : cinq frappes rapides ne font qu une requete [1 requete(s)] ✓ point 18 : l emplacement par defaut existe dans le referentiel [["Default"]] ✓ point 18 : la famille par defaut existe dans le referentiel [["SPECIALITES PUBLIQUES"]] ✓ point 18 : l emplacement est preselectionne a DEFAULT [{"ouverte":true,"emplacement":"Default","famille":"SPECIALITES PUBLIQUES"}] ✓ point 18 : la famille est preselectionnee a SPECIALITES PUBLIQUES [{"ouverte":true,"emplacement":"Default","famille":"SPECIALITES PUBLIQUES"}] ✓ point 4 : le retour a la liste des provisoires est cable ✓ point 4 : la liste des factures provisoires est bien affichee [{"ecran":true,"grille":true}] ✓ aucune erreur JavaScript | E5: OK | L5: =IF(I5="","",IF(I5=E5,"Oui","Non"))
A6: 67 | B6: lot3/test-ergonomie-lot3b.js | C6: Lot 3 (suite). Point 3 : ecran de saisie d'une commande — l'icone du code EAN redevient visible, les actions de la fenetre portent un pictogramme explicite et un libelle accessible. Point 8 : produits detailles — quantite obtenue en vert apres le nom, nombre de boites en rouge, contenance rappelee, et boite de message qui ne tronque plus rien. | E6: Échec | F6: Test arrêté (code 1) avant la fin, sans contrôle en écart | G6: À examiner : Pas encore étudié : test à adapter à la copie ou défaut à confirmer. | L6: =IF(I6="","",IF(I6=E6,"Oui","Non"))
A7: 68 | B7: lot3/test-icones-colonnes-action.js | C7: Assainissement de la classe « x-display-hide ». Cette classe n'existe dans aucune feuille de style : elle etait renvoyee pour AFFICHER une icone, et ne fonctionnait que par accident. Elle est remplacee partout par une chaine vide. On verifie ici, sur l'application deployee, que les icones concernees restent visibles et que celles qui doivent etre masquees le sont toujours. | D7: 11 / 11 conformes ✓ la classe fantome a disparu des vues livrees [[]] ✓ la classe fantome n a effectivement aucun effet, elle n est definie nulle part [{"fantomeSansEffet":true,"vraieMasqueBien":true}] ✓ la vraie classe de masquage, elle, masque bien [{"fantomeSansEffet":true,"vraieMasqueBien":true}] ✓ la ligne « visible » affiche bien son icone [{"classe":"x-action-col-icon x-action-col-0 ","affichee":true,"largeur":16}] ✓ la ligne « masquee » n a ni icone ni zone cliquable [{"classe":"x-action-col-icon x-action-col-0 x-hide-display","affichee":false,"largeur":0}] ✓ ecran fiche article : ouvert [{"ouvert":true,"total":0,"visibles":0,"fantomes":0}] ✓ ecran mouvements de caisse : ouvert [{"ouvert":true,"total":0,"visibles":0,"fantomes":0}] ✓ ecran tiers payants : ouvert [{"ouvert":true,"total":80,"visibles":80,"fantomes":0}] ✓ ecran tiers payants : les icones de ligne sont visibles [{"ouvert":true,"total":80,"visibles":80,"fantomes":0}] ✓ ecran tiers payants : aucune icone ne porte la classe fantome [{"ouvert":true,"total":80,"visibles":80,"fantomes":0}] ✓ aucune erreur JavaScript | E7: OK | L7: =IF(I7="","",IF(I7=E7,"Oui","Non"))

Sheet Lot 4
A1: CAHIER DE RECETTE — Lot 4
A2: 2 tests : 2 OK, 0 en échec selon Claude
A4: N° | B4: Test | C4: Scénario : ce qui est fait et ce qui est attendu | D4: Contrôles faits par Claude (valeur mesurée) | E4: Résultat Claude | F4: Écart constaté par Claude | G4: Catégorie et suite | H4: Résultat testeur | I4: Statut testeur | J4: Testeur | K4: Date | L4: Concorde ? | M4: Commentaire
A5: 69 | B5: lot4/test-ca-marge-detail.js | C5: Lot 4 — point 19 : analyse du CA par emplacement et famille. - marge en valeur et en pourcentage, formule unique de « Marge sur produits » ; - detail d'une ligne : produits pris en compte, totaux, impression, export, inventaire. Point 13 : les modes mobile money viennent de la base et non d'une liste codee en dur. | D5: 27 / 27 conformes ✓ point 13 : la liste mobile money vient de la base [rendus=["10","19","7","8","9"] attendus=["10","19","7","8","9"]] ✓ point 13 : aucun mode desactive n est propose [desactives en base=["70","80"] proposes=["10","19","7","8","9"]] ✓ point 13 : l ecran de vente REMPLACE sa liste par celle du serveur [{"liste":["10","19","7","8","9"],"charges":true}] ✓ point 13 : les modes desactives ont disparu de l ecran de vente [["10","19","7","8","9"]] ✓ point 19 : l analyse repond [lignes=36] ✓ point 19 : chaque ligne porte la marge en valeur et en pourcentage [{"total":185112468,"ht":184587451,"achat":122367909,"marge":62219542,"pct":33.7}] ✓ point 19 : la marge suit la formule de « Marge sur produits » [{"q_2026-10":7609,"montantHt":184587451,"familleId":"15423175553778909076","libelle":"COMPRIMES","e_2026-08":-10.4,"marge":62219542,"e_2026-07":null,"total":185112468,"e_2026-09":4.6,"zone":"COMPRIMES","q_2026-09":9295,"zoneId":"14521913258936373344","q_2026-07":10325,"q_2026-08"] ✓ point 19 : le total general de marge est coherent avec les lignes [general=178968416 somme des lignes=178968416] ✓ point 19 : la ligne semee est retrouvee avec ses montants exacts [attendu {"montant":185000,"tva":15000,"achat":135000,"quantite":7,"ht":170000,"marge":35000,"pourcentage":20.6} | obtenu {"total":185000,"tva":15000,"achat":135000,"ht":170000,"marge":35000,"pct":20.6}] ✓ point 19 : le detail d une ligne renvoie ses produits [produits=3] ✓ point 19 : chaque produit porte les six colonnes demandees [{"marge":30000,"pourcentageMarge":33.3,"prixAchat":15000,"montantHt":90000,"produitId":"141263629965927557","prixVente":25000,"montant":100000,"cip":"8452598","designation":"3 HP KIT GEL/2 + CPR/4 KIT/14","achat":60000,"quantite":4}] ✓ point 19 : la somme du detail redonne exactement le total de la ligne [detail=185000 ligne=185000] ✓ point 19 : le detail affiche ses totaux [{"marge":35000,"pourcentageMarge":20.6,"montantHt":170000,"montant":185000,"achat":135000,"quantite":7}] ✓ point 19 : la marge du detail est celle de la ligne [detail=35000 ligne=35000] ✓ point 19 : l export Excel du detail est un classeur valide [{"status":200,"type":"application/octet-stream","taille":3976,"signature":"PK"}] ✓ point 19 : l impression du detail produit un PDF [{"msg":"/data/reports/pdf/detail_ca_ligne_2026_10_30_10_25_01.pdf","success":true,"url":"/data/reports/pdf/detail_ca_ligne_2026_10_30_10_25_01.pdf"}] ✓ point 19 : le PDF a bien ete ecrit [D:\payara5\payara5\glassfish\domains\domain1\applications\prestige\data\reports\pdf\detail_ca_ligne_2026_10_30_10_25_01.pdf] ✓ point 19 : le PDF porte le titre et les criteres de la ligne [octets=2318 texte=4938] ✓ point 19 : le PDF contient bien les produits du detail [cip cherches=8452598,8017017,8074624] ✓ point 19 : le PDF porte les totaux [texte=4938] ✓ point 19 : la creation d inventaire depuis le detail reussit [{"msg":"Inventaire créé : 3 produit(s) en compte.","ignores":[],"success":true,"count":3,"message":"Inventaire reserve-TOUS 30102026-102502548"}] ✓ point 19 : l inventaire porte exactement les produits du detail [[]] ✓ point 19 : un inventaire de plus existe en base [avant=92 apres=93] ✓ point 19 : la colonne Marge est a l ecran [["Zone géographique","S41 (05/10-11/10)","S42 (12/10-18/10)","S43 (19/10-25/10)","S44 (26/10-30/10)","Total","Marge","% marge","Évolution1re → dernière tranche","Détail"]] ✓ point 19 : la colonne % marge est a l ecran [["Zone géographique","S41 (05/10-11/10)","S42 (12/10-18/10)","S43 (19/10-25/10)","S44 (26/10-30/10)","Total","Marge","% marge","Évolution1re → dernière tranche","Détail"]] ✓ point 19 : chaque ligne porte un bouton de detail [{"colonnes":["Zone géographique","S41 (05/10-11/10)","S42 (12/10-18/10)","S43 (19/10-25/10)","S44 (26/10-30/10)","Total","Marge","% marge","Évolution1re → dernière tranche","Détail"],"lignes":36,"actions":1}] ✓ aucune erreur JavaScript | E5: OK | L5: =IF(I5="","",IF(I5=E5,"Oui","Non"))
A6: 70 | B6: lot4/test-recap-caisse-modes.js | C6: Lot 4 — point 22 : récapitulatif caisse / recette. - sous-detail des paiements mobiles, construit selon les modes REELLEMENT presents ; - le total du sous-detail vaut le montant Mobile de la ligne parente ; - onglet « Suivi des modes de reglement » : synthese, courbe, legende et valeurs exactes ; - mise en forme : solde rouge, billetage violet, nombre de clients orange et gras. | D6: 25 / 25 conformes ✓ point 22 : le recapitulatif rend les journees semees [lignes=2] ✓ point 22 : chaque journee porte le detail de ses paiements mobiles [[{"d":"07/05/2021","mobile":80000,"detail":{"WAVE":15000,"MTN":25000,"ORANGE":40000}},{"d":"08/05/2021","mobile":200000,"detail":{"WAVE":80000,"ORANGE":120000}}]] ✓ point 22 : le total du sous-detail vaut le montant Mobile de la ligne [[{"mobile":80000,"somme":80000},{"mobile":200000,"somme":200000}]] ✓ point 22 : le sous-detail suit les modes reellement presents, pas une liste figee [nombres de modes par journee = 2,3] ✓ point 22 : les modes du sous-detail portent leur libelle, pas leur identifiant [[["WAVE","MTN","ORANGE"],["WAVE","ORANGE"]]] ✓ point 22 : le montant mobile total correspond aux encaissements semes [rendu=280000 attendu=280000] ✓ point 22 : le suivi des modes repond [modes=5] ✓ point 22 : chaque mode seme est retrouve avec son montant exact [attendu={"1":800000,"3":60000,"7":160000,"9":25000,"10":95000} rendu=[["1",800000],["7",160000],["10",95000],["3",60000],["9",25000]]] ✓ point 22 : le total general vaut la somme des modes [rendu=1140000 attendu=1140000] ✓ point 22 : les parts sont calculees et totalisent 100 % [[["Especes",70.2],["ORANGE",14],["WAVE",8.3],["Carte Bancaire",5.3],["MTN",2.2]]] ✓ point 22 : le panier moyen par mode est renseigne [[["Especes",2,400000],["ORANGE",2,80000],["WAVE",2,47500],["Carte Bancaire",1,60000],["MTN",1,25000]]] ✓ point 22 : les modes mobiles sont signales comme tels [[["1",false],["7",true],["10",true],["3",false],["9",true]]] ✓ point 22 : la courbe porte une serie par mode et une valeur par tranche [series=5 modes=5 tranches=2] ✓ point 22 : les tranches sans encaissement valent zero et non un trou [[["Especes",[300000,500000]],["ORANGE",[40000,120000]],["WAVE",[15000,80000]],["Carte Bancaire",[0,60000]],["MTN",[25000,0]]]] ✓ point 22 : la somme d une serie vaut le montant de son mode [[["Especes",800000],["ORANGE",160000],["WAVE",95000],["Carte Bancaire",60000],["MTN",25000]]] ✓ point 22 : l ecran s ouvre avec ses deux onglets [["Récapitulatif","Suivi des modes de règlement"]] ✓ point 22 : le tableau du recapitulatif est toujours rempli [lignes=2] ✓ point 22 : chaque journee avec du mobile money affiche son sous-detail sous la ligne (sans clic) [2 ligne(s) de detail affichee(s)] ✓ point 22 : la synthese par mode est remplie [modes=5] ✓ point 22 : la courbe est tracee [true] ✓ point 22 : la courbe porte une legende [true] ✓ point 22 : le solde est affiche en rouge [<span style='color:#c0392b;'>380.000</span>] ✓ point 22 : le billetage est affiche en violet [<span style='color:#7d3c98;'>0</span>] ✓ point 22 : le nombre de clients est en orange et en gras [<span style='color:#e67e22;font-weight:bold;'>1</span>] ✓ aucune erreur JavaScript | E6: OK | L6: =IF(I6="","",IF(I6=E6,"Oui","Non"))

Sheet Application mobile
A1: CAHIER DE RECETTE — Application mobile
A2: 1 tests : 0 OK, 1 en échec selon Claude
A4: N° | B4: Test | C4: Scénario : ce qui est fait et ce qui est attendu | D4: Contrôles faits par Claude (valeur mesurée) | E4: Résultat Claude | F4: Écart constaté par Claude | G4: Catégorie et suite | H4: Résultat testeur | I4: Statut testeur | J4: Testeur | K4: Date | L4: Concorde ? | M4: Commentaire
A5: 71 | B5: mobile/test-info-articles-rapide.js | C5: MOBILE (13/10) : v1/info (analyse article des applications) et v1/checkproduit. Avant : 6 a 7 requetes par produit, ~155 s pour 1 793 produits sur le banc. Apres : requetes groupees. - temps de reponse de v1/info sur tout le catalogue (< 20 s sur le banc) ; - pour un echantillon de produits, chaque information complementaire est recalculee ici avec la requete d'origine (un produit a la fois : ORDER BY ... DESC LIMIT 1) et doit etre identique : derniere vente, dernier achat, dernier inventaire, code geo, classe, stock reserve et seuils ; - stock reserve : deux produits mis en reserve le temps du test (l'un avec 7 en reserve, l'autre sans ligne de reserve -> 0) ; un produit hors reserve n'a ni stock reserve ni seuils. Donnees remises a la fin : reserve et seuils d'origine, lignes d'historique t_famille creees par le declencheur supprimees, ligne de reserve d'essai supprimee. | D5: 9 / 10 conformes ✓ v1/info : tout le catalogue rendu (11650 produits) [200 11650] ✓ v1/info : réponse en moins de 20 s (avant : ~155 s) [11707 ms] ✓ v1/info : valeurs identiques à la requête d'origine (51 produits, 11 informations) [51 ] ✓ v1/info : stock réserve rendu (produit en réserve : 7, seuils 12 / 3) [[7,12,3]] ✓ v1/info : produit en réserve sans ligne de réserve → 0 ✓ v1/info : produit hors réserve sans stock réserve ni seuils [[null,null]] ✓ v1/info?search=CIP : le produit seul, avec son stock réserve [200 2] ✓ v1/checkproduit : stock réserve rendu (7) [200 {"classe":"C","codeGeoArticle":"","dateDernierAchat":"07/10/2026","dateDernierInventaire":"19/07/2026","emplacement":"AMPOULES BUVABLES","familleCip":"8452598","familleId":"141263629965927557","famill] ✗ v1/checkproduit (tout) : réponse en moins de 20 s [58625 ms, 11650] ✓ Données remises (réserve, seuils, historique, ligne d'essai) | E5: Échec | F5: v1/checkproduit (tout) : réponse en moins de 20 s [58625 ms, 11650] | G5: Lenteur (grosse base) : Vérification produit en 51 s pour 20 s attendues : suivi par la session de performance. | L5: =IF(I5="","",IF(I5=E5,"Oui","Non"))

Sheet Performances
A1: CAHIER DE RECETTE — Performances
A2: 11 tests : 8 OK, 3 en échec selon Claude
A4: N° | B4: Test | C4: Scénario : ce qui est fait et ce qui est attendu | D4: Contrôles faits par Claude (valeur mesurée) | E4: Résultat Claude | F4: Écart constaté par Claude | G4: Catégorie et suite | H4: Résultat testeur | I4: Statut testeur | J4: Testeur | K4: Date | L4: Concorde ? | M4: Commentaire
A5: 72 | B5: perf/test-comparaison-stock-export.js | C5: COMPARAISON STOCK : EXPORTS EXCEL ET CSV (journal de l'officine du 15/10). « BLOCAGE DETECTE : requete en traitement depuis 32s : GET /prestige/api/v1/fichearticle/comparaison/excel ». Sur le banc (3 ans de ventes), l'export des articles en stock prenait 327 s : six lectures PAR ARTICLE (consommations, bons de livraison, inventaire, derniere vente) alors que le fichier ne montre que la derniere vente. Ce que le test etablit (lecture seule, par la session de l'ecran) : - export CSV des articles en stock : moins de 20 s, autant de lignes que le total de l'ecran ; - « Derniere vente » de chaque ligne echantillonnee = la derniere vente cloturee de l'article (requete SQL) ; - export Excel : moins de 20 s, fichier Excel valide ; - impression PDF (meme ecran, consommations sur 6 mois, dernier bon, inventaire) : 311 s avant, moins de 40 s, une ligne par article ; consommation du mois et dernier bon d'un echantillon conformes a la base. Le modele PDF de l'officine n'est pas dans le depot : le test pose un modele qui imprime les donnees, et le retire. | E5: Échec | F5: Test arrêté (code 1) avant la fin, sans contrôle en écart | G5: À examiner : Pas encore étudié : test à adapter à la copie ou défaut à confirmer. | L5: =IF(I5="","",IF(I5=E5,"Oui","Non"))
A6: 73 | B6: perf/test-erp-catalogue-export.js | C6: EXPORT DU CATALOGUE VERS L'ERP (GET v1/stock) - audit des exports apres le journal du 15/10. Un article detail cree par l'ecran de deconditionnement n'a pas bool_DECONDITIONNE_EXIST (NULL) : l'export tombait en erreur 500 des qu'un tel article existait (72 sur le banc). Ce que le test etablit (lecture seule) : - reponse 200 en moins de 30 s, un produit par article parent non supprime ; - un article deconditionnable porte son article detail (prix et stock du detail) ; - echantillon : stock officine et nombre de fournisseurs conformes a la base. | D6: 1 / 3 conformes ✗ Réponse 200 en moins de 30 s, un produit par article (193 articles détail sans indicateur) [200, 133642 ms, 22112 / 22112] ✓ Articles déconditionnables : article détail joint [425 / 425] ✗ Échantillon : stock officine et fournisseurs conformes à la base [31 articles ; DUCRAY KERACNYL GLYCOLIC+ CR T/30ML : 0/1 ≠ /1] | E6: Échec | F6: Réponse 200 en moins de 30 s, un produit par article (193 articles détail sans indicateur) [200, 133642 ms, 22112 / 22112] Échantillon : stock officine et fournisseurs conformes à la base [31 articles ; DUCRAY KERACNYL GLYCOLIC+ CR T/30ML : 0/1 ≠ /1] | G6: Lenteur (grosse base) : Catalogue ERP en 120 s pour 30 s attendues : suivi par la session de performance. | L6: =IF(I6="","",IF(I6=E6,"Oui","Non"))
A7: 74 | B7: perf/test-erp-ventes-export.js | C7: EXPORT DES VENTES VERS L'ERP (GET v1/whareouse-vno) - audit des exports apres le journal du 15/10. L'export relisait, pour chaque vente, ses lignes et son paiement, et pour chaque ligne son mouvement de stock : sur le banc, une semaine de ventes depassait 20 min (Hibernate reverifiait avant chaque requete tous les objets deja charges). Ce que le test etablit (lecture seule, session de l'ecran) : - une semaine de ventes en moins de 30 s ; autant de ventes que la base (VNO cloturees, non annulees, montant > 0) ; - echantillon : nombre de lignes, montant paye et mouvements de stock de chaque vente conformes a la base. | D7: 2 / 2 conformes ✓ Une semaine de ventes en moins de 30 s, autant de ventes que la base [10205 ms, 3506 / 3506] ✓ Échantillon : lignes, mouvements de stock et montant payé conformes à la base [22 ventes ; ] | E7: OK | L7: =IF(I7="","",IF(I7=E7,"Oui","Non"))
A8: 75 | B8: perf/test-lignes-bl-mobile.js | C8: LIGNES D'UN BL DEMANDEES EN UNE FOIS (application mobile de reception) : LENTEUR (journal du 21/10, 5,5 s). « Requete lente : GET /prestige/api/v1/commande/bon/items/{id}?page=1&start=0&limit=9999 ». Sur le banc, le plus gros BL (492 lignes) prenait 43 a 47 s : chaque petite requete de la boucle faisait reverifier par Hibernate toutes les lignes deja chargees (temps en carre du nombre de lignes). Meme appel que l'application mobile, session ouverte par la page de connexion : - toutes les lignes en moins de 8 s ; - nombre de lignes et quantite commandee de chaque ligne = base ; - la page de 10 lignes de l'ecran « Gestion des entrees » reste sous 2 s. Lecture seule. | D8: 5 / 5 conformes ✓ Jeu d'essai : un gros BL [445 lignes] ✓ Toutes les lignes (limit=9999) en moins de 8 s [1317 ms] ✓ Nombre de lignes = base [445 / 445 / 445] ✓ Quantité commandée de chaque ligne = base [0 écart(s)] ✓ Page de 10 lignes de l'écran : moins de 2 s [49 ms] | E8: OK | L8: =IF(I8="","",IF(I8=E8,"Oui","Non"))
A9: 76 | B9: perf/test-liste-caisse-export.js | C9: IMPRESSION « LISTE DES CAISSES » (BalancePdfServlet, mode LISTECAISSE) - audit des exports apres le journal du 15/10. Chaque mouvement de caisse etait charge entier, avec, un par un, sa vente liee et les liens de celle-ci : 39 s pour un mois sur le banc (16 565 mouvements). Seules les colonnes utiles sont lues. Ce que le test etablit (lecture seule) : - un mois en moins de 10 s ; - pour chaque caissier, autant de mouvements imprimes que dans la base (hors achats, periode et heures demandees). Le modele de l'officine n'est pas dans le depot : le test pose un modele qui imprime les donnees, et le retire. | E9: Échec | F9: Test arrêté (code 1) avant la fin, sans contrôle en écart | G9: À examiner : Pas encore étudié : test à adapter à la copie ou défaut à confirmer. | L9: =IF(I9="","",IF(I9=E9,"Oui","Non"))
