Workbook

Sheet Mode d'emploi
A1: CAHIER DE RECETTE PRESTIGE
A2: Version testée : branche integration/recette-2026-10-29 (21ddcd3d), déployée sur le poste local (port 8080), copie de l'officine restaurée le 30/10
A4: À quoi sert ce cahier
A5: Chaque ligne est un cas de test. Sa description (existant, étapes, résultats attendus) est tirée uniquement du test automatique correspondant : rien n'y est ajouté. Le nom du fichier du test est rappelé en colonne « Test automatique ».
A7: Comment le remplir
A8: 1. Ouvrir la feuille du module (onglets en bas). La feuille « Synthèse » donne l'avancement par module.
A9: 2. Pour chaque ligne : vérifier l'« Existant » (données et profil nécessaires), suivre les « Étapes » dans l'ordre, comparer avec les « Résultats attendus ».
A10: 3. Les étapes et résultats marqués « (Contrôle technique) » ou « (technique) » sont vérifiés par le test automatique dans la base ou par un appel au serveur : ils ne se voient pas à l'écran. Le testeur peut les laisser à Claude.
A11: 4. Remplir les colonnes jaunes : « Résultat testeur » (OK, KO, Bloqué, Non testé), « Commentaire », « Testeur », « Date ».
A12: 5. Colonne « Résultat Claude » : résultat du test automatique lors de sa dernière exécution par Claude (date et détail à côté). Indiquer dans « Résultat Claude confirmé ? » Oui ou Non après votre propre essai.
A14: Précautions
A15: Toujours tester sur une copie de travail, jamais sur la base de production de l'officine.
... A17: Ne recopier aucune donnée de patient dans les commentaires.

Sheet Synthèse
A1: SYNTHÈSE DE LA RECETTE
A2: Version testée : branche integration/recette-2026-10-29 (21ddcd3d), déployée sur le poste local (port 8080), copie de l'officine restaurée le 30/10
A4: Module | B4: Cas | C4: Claude OK | D4: Claude échec | E4: Claude non joué | F4: Testeur : joués | G4: Testeur OK | H4: Testeur KO | I4: Testeur bloqués | J4: Résultat Claude confirmé | K4: Résultat Claude contesté | L4: % OK testeur
A5: Connexion et sécurité | B5: 16 | C5: 16 | D5: 0 | E5: 0 | F5: =COUNTIF('Connexion et sécurité'!L5:L20,"OK")+COUNTIF('Connexion et sécurité'!L5:L20,"KO")+COUNTIF('Connexion et sécurité'!L5:L20,"Bloqué") | G5: =COUNTIF('Connexion et sécurité'!L5:L20,"OK") | H5: =COUNTIF('Connexion et sécurité'!L5:L20,"KO") | I5: =COUNTIF('Connexion et sécurité'!L5:L20,"Bloqué") | J5: =COUNTIF('Connexion et sécurité'!P5:P20,"Oui") | K5: =COUNTIF('Connexion et sécurité'!P5:P20,"Non") | L5: =IF(F5=0,"",G5/F5)
A6: Ventes | B6: 47 | C6: 46 | D6: 1 | E6: 0 | F6: =COUNTIF('Ventes'!L5:L51,"OK")+COUNTIF('Ventes'!L5:L51,"KO")+COUNTIF('Ventes'!L5:L51,"Bloqué") | G6: =COUNTIF('Ventes'!L5:L51,"OK") | H6: =COUNTIF('Ventes'!L5:L51,"KO") | I6: =COUNTIF('Ventes'!L5:L51,"Bloqué") | J6: =COUNTIF('Ventes'!P5:P51,"Oui") | K6: =COUNTIF('Ventes'!P5:P51,"Non") | L6: =IF(F6=0,"",G6/F6)
A7: Vente en dépôt | B7: 11 | C7: 11 | D7: 0 | E7: 0 | F7: =COUNTIF('Vente en dépôt'!L5:L15,"OK")+COUNTIF('Vente en dépôt'!L5:L15,"KO")+COUNTIF('Vente en dépôt'!L5:L15,"Bloqué") | G7: =COUNTIF('Vente en dépôt'!L5:L15,"OK") | H7: =COUNTIF('Vente en dépôt'!L5:L15,"KO") | I7: =COUNTIF('Vente en dépôt'!L5:L15,"Bloqué") | J7: =COUNTIF('Vente en dépôt'!P5:P15,"Oui") | K7: =COUNTIF('Vente en dépôt'!P5:P15,"Non") | L7: =IF(F7=0,"",G7/F7)
A8: Ordonnances | B8: 21 | C8: 18 | D8: 3 | E8: 0 | F8: =COUNTIF('Ordonnances'!L5:L25,"OK")+COUNTIF('Ordonnances'!L5:L25,"KO")+COUNTIF('Ordonnances'!L5:L25,"Bloqué") | G8: =COUNTIF('Ordonnances'!L5:L25,"OK") | H8: =COUNTIF('Ordonnances'!L5:L25,"KO") | I8: =COUNTIF('Ordonnances'!L5:L25,"Bloqué") | J8: =COUNTIF('Ordonnances'!P5:P25,"Oui") | K8: =COUNTIF('Ordonnances'!P5:P25,"Non") | L8: =IF(F8=0,"",G8/F8)
A9: Clients | B9: 12 | C9: 12 | D9: 0 | E9: 0 | F9: =COUNTIF('Clients'!L5:L16,"OK")+COUNTIF('Clients'!L5:L16,"KO")+COUNTIF('Clients'!L5:L16,"Bloqué") | G9: =COUNTIF('Clients'!L5:L16,"OK") | H9: =COUNTIF('Clients'!L5:L16,"KO") | I9: =COUNTIF('Clients'!L5:L16,"Bloqué") | J9: =COUNTIF('Clients'!P5:P16,"Oui") | K9: =COUNTIF('Clients'!P5:P16,"Non") | L9: =IF(F9=0,"",G9/F9)
A10: Caisse | B10: 14 | C10: 13 | D10: 1 | E10: 0 | F10: =COUNTIF('Caisse'!L5:L18,"OK")+COUNTIF('Caisse'!L5:L18,"KO")+COUNTIF('Caisse'!L5:L18,"Bloqué") | G10: =COUNTIF('Caisse'!L5:L18,"OK") | H10: =COUNTIF('Caisse'!L5:L18,"KO") | I10: =COUNTIF('Caisse'!L5:L18,"Bloqué") | J10: =COUNTIF('Caisse'!P5:P18,"Oui") | K10: =COUNTIF('Caisse'!P5:P18,"Non") | L10: =IF(F10=0,"",G10/F10)
A11: Tiers payants et facturation | B11: 22 | C11: 22 | D11: 0 | E11: 0 | F11: =COUNTIF('Tiers payants et facturation'!L5:L26,"OK")+COUNTIF('Tiers payants et facturation'!L5:L26,"KO")+COUNTIF('Tiers payants et facturation'!L5:L26,"Bloqué") | G11: =COUNTIF('Tiers payants et facturation'!L5:L26,"OK") | H11: =COUNTIF('Tiers payants et facturation'!L5:L26,"KO") | I11: =COUNTIF('Tiers payants et facturation'!L5:L26,"Bloqué") | J11: =COUNTIF('Tiers payants et facturation'!P5:P26,"Oui") | K11: =COUNTIF('Tiers payants et facturation'!P5:P26,"Non") | L11: =IF(F11=0,"",G11/F11)
A12: Commandes et PharmaML | B12: 37 | C12: 36 | D12: 1 | E12: 0 | F12: =COUNTIF('Commandes et PharmaML'!L5:L41,"OK")+COUNTIF('Commandes et PharmaML'!L5:L41,"KO")+COUNTIF('Commandes et PharmaML'!L5:L41,"Bloqué") | G12: =COUNTIF('Commandes et PharmaML'!L5:L41,"OK") | H12: =COUNTIF('Commandes et PharmaML'!L5:L41,"KO") | I12: =COUNTIF('Commandes et PharmaML'!L5:L41,"Bloqué") | J12: =COUNTIF('Commandes et PharmaML'!P5:P41,"Oui") | K12: =COUNTIF('Commandes et PharmaML'!P5:P41,"Non") | L12: =IF(F12=0,"",G12/F12)
A13: Réception et bons de livraison | B13: 21 | C13: 20 | D13: 1 | E13: 0 | F13: =COUNTIF('Réception et bons de livraison'!L5:L25,"OK")+COUNTIF('Réception et bons de livraison'!L5:L25,"KO")+COUNTIF('Réception et bons de livraison'!L5:L25,"Bloqué") | G13: =COUNTIF('Réception et bons de livraison'!L5:L25,"OK") | H13: =COUNTIF('Réception et bons de livraison'!L5:L25,"KO") | I13: =COUNTIF('Réception et bons de livraison'!L5:L25,"Bloqué") | J13: =COUNTIF('Réception et bons de livraison'!P5:P25,"Oui") | K13: =COUNTIF('Réception et bons de livraison'!P5:P25,"Non") | L13: =IF(F13=0,"",G13/F13)
A14: Stock et inventaire | B14: 25 | C14: 23 | D14: 2 | E14: 0 | F14: =COUNTIF('Stock et inventaire'!L5:L29,"OK")+COUNTIF('Stock et inventaire'!L5:L29,"KO")+COUNTIF('Stock et inventaire'!L5:L29,"Bloqué") | G14: =COUNTIF('Stock et inventaire'!L5:L29,"OK") | H14: =COUNTIF('Stock et inventaire'!L5:L29,"KO") | I14: =COUNTIF('Stock et inventaire'!L5:L29,"Bloqué") | J14: =COUNTIF('Stock et inventaire'!P5:P29,"Oui") | K14: =COUNTIF('Stock et inventaire'!P5:P29,"Non") | L14: =IF(F14=0,"",G14/F14)
A15: Fiche article | B15: 16 | C15: 15 | D15: 1 | E15: 0 | F15: =COUNTIF('Fiche article'!L5:L20,"OK")+COUNTIF('Fiche article'!L5:L20,"KO")+COUNTIF('Fiche article'!L5:L20,"Bloqué") | G15: =COUNTIF('Fiche article'!L5:L20,"OK") | H15: =COUNTIF('Fiche article'!L5:L20,"KO") | I15: =COUNTIF('Fiche article'!L5:L20,"Bloqué") | J15: =COUNTIF('Fiche article'!P5:P20,"Oui") | K15: =COUNTIF('Fiche article'!P5:P20,"Non") | L15: =IF(F15=0,"",G15/F15)
A16: Étiquettes | B16: 11 | C16: 11 | D16: 0 | E16: 0 | F16: =COUNTIF('Étiquettes'!L5:L15,"OK")+COUNTIF('Étiquettes'!L5:L15,"KO")+COUNTIF('Étiquettes'!L5:L15,"Bloqué") | G16: =COUNTIF('Étiquettes'!L5:L15,"OK") | H16: =COUNTIF('Étiquettes'!L5:L15,"KO") | I16: =COUNTIF('Étiquettes'!L5:L15,"Bloqué") | J16: =COUNTIF('Étiquettes'!P5:P15,"Oui") | K16: =COUNTIF('Étiquettes'!P5:P15,"Non") | L16: =IF(F16=0,"",G16/F16)
A17: Analyses et statistiques | B17: 27 | C17: 26 | D17: 1 | E17: 0 | F17: =COUNTIF('Analyses et statistiques'!L5:L31,"OK")+COUNTIF('Analyses et statistiques'!L5:L31,"KO")+COUNTIF('Analyses et statistiques'!L5:L31,"Bloqué") | G17: =COUNTIF('Analyses et statistiques'!L5:L31,"OK") | H17: =COUNTIF('Analyses et statistiques'!L5:L31,"KO") | I17: =COUNTIF('Analyses et statistiques'!L5:L31,"Bloqué") | J17: =COUNTIF('Analyses et statistiques'!P5:P31,"Oui") | K17: =COUNTIF('Analyses et statistiques'!P5:P31,"Non") | L17: =IF(F17=0,"",G17/F17)
A18: Pilotage et tableau de bord | B18: 22 | C18: 22 | D18: 0 | E18: 0 | F18: =COUNTIF('Pilotage et tableau de bord'!L5:L26,"OK")+COUNTIF('Pilotage et tableau de bord'!L5:L26,"KO")+COUNTIF('Pilotage et tableau de bord'!L5:L26,"Bloqué") | G18: =COUNTIF('Pilotage et tableau de bord'!L5:L26,"OK") | H18: =COUNTIF('Pilotage et tableau de bord'!L5:L26,"KO") | I18: =COUNTIF('Pilotage et tableau de bord'!L5:L26,"Bloqué") | J18: =COUNTIF('Pilotage et tableau de bord'!P5:P26,"Oui") | K18: =COUNTIF('Pilotage et tableau de bord'!P5:P26,"Non") | L18: =IF(F18=0,"",G18/F18)
A19: Fidélité | B19: 6 | C19: 6 | D19: 0 | E19: 0 | F19: =COUNTIF('Fidélité'!L5:L10,"OK")+COUNTIF('Fidélité'!L5:L10,"KO")+COUNTIF('Fidélité'!L5:L10,"Bloqué") | G19: =COUNTIF('Fidélité'!L5:L10,"OK") | H19: =COUNTIF('Fidélité'!L5:L10,"KO") | I19: =COUNTIF('Fidélité'!L5:L10,"Bloqué") | J19: =COUNTIF('Fidélité'!P5:P10,"Oui") | K19: =COUNTIF('Fidélité'!P5:P10,"Non") | L19: =IF(F19=0,"",G19/F19)
A20: Campagnes et WhatsApp | B20: 15 | C20: 12 | D20: 3 | E20: 0 | F20: =COUNTIF('Campagnes et WhatsApp'!L5:L19,"OK")+COUNTIF('Campagnes et WhatsApp'!L5:L19,"KO")+COUNTIF('Campagnes et WhatsApp'!L5:L19,"Bloqué") | G20: =COUNTIF('Campagnes et WhatsApp'!L5:L19,"OK") | H20: =COUNTIF('Campagnes et WhatsApp'!L5:L19,"KO") | I20: =COUNTIF('Campagnes et WhatsApp'!L5:L19,"Bloqué") | J20: =COUNTIF('Campagnes et WhatsApp'!P5:P19,"Oui") | K20: =COUNTIF('Campagnes et WhatsApp'!P5:P19,"Non") | L20: =IF(F20=0,"",G20/F20)
A21: Ressources humaines et pointage | B21: 14 | C21: 14 | D21: 0 | E21: 0 | F21: =COUNTIF('Ressources humaines et pointage'!L5:L18,"OK")+COUNTIF('Ressources humaines et pointage'!L5:L18,"KO")+COUNTIF('Ressources humaines et pointage'!L5:L18,"Bloqué") | G21: =COUNTIF('Ressources humaines et pointage'!L5:L18,"OK") | H21: =COUNTIF('Ressources humaines et pointage'!L5:L18,"KO") | I21: =COUNTIF('Ressources humaines et pointage'!L5:L18,"Bloqué") | J21: =COUNTIF('Ressources humaines et pointage'!P5:P18,"Oui") | K21: =COUNTIF('Ressources humaines et pointage'!P5:P18,"Non") | L21: =IF(F21=0,"",G21/F21)
A22: Application mobile | B22: 23 | C22: 20 | D22: 3 | E22: 0 | F22: =COUNTIF('Application mobile'!L5:L27,"OK")+COUNTIF('Application mobile'!L5:L27,"KO")+COUNTIF('Application mobile'!L5:L27,"Bloqué") | G22: =COUNTIF('Application mobile'!L5:L27,"OK") | H22: =COUNTIF('Application mobile'!L5:L27,"KO") | I22: =COUNTIF('Application mobile'!L5:L27,"Bloqué") | J22: =COUNTIF('Application mobile'!P5:P27,"Oui") | K22: =COUNTIF('Application mobile'!P5:P27,"Non") | L22: =IF(F22=0,"",G22/F22)
A23: Centre de support et administration | B23: 21 | C23: 17 | D23: 2 | E23: 2 | F23: =COUNTIF('Centre de support et administra'!L5:L25,"OK")+COUNTIF('Centre de support et administra'!L5:L25,"KO")+COUNTIF('Centre de support et administra'!L5:L25,"Bloqué") | G23: =COUNTIF('Centre de support et administra'!L5:L25,"OK") | H23: =COUNTIF('Centre de support et administra'!L5:L25,"KO") | I23: =COUNTIF('Centre de support et administra'!L5:L25,"Bloqué") | J23: =COUNTIF('Centre de support et administra'!P5:P25,"Oui") | K23: =COUNTIF('Centre de support et administra'!P5:P25,"Non") | L23: =IF(F23=0,"",G23/F23)
A24: Ergonomie générale | B24: 32 | C24: 30 | D24: 2 | E24: 0 | F24: =COUNTIF('Ergonomie générale'!L5:L36,"OK")+COUNTIF('Ergonomie générale'!L5:L36,"KO")+COUNTIF('Ergonomie générale'!L5:L36,"Bloqué") | G24: =COUNTIF('Ergonomie générale'!L5:L36,"OK") | H24: =COUNTIF('Ergonomie générale'!L5:L36,"KO") | I24: =COUNTIF('Ergonomie générale'!L5:L36,"Bloqué") | J24: =COUNTIF('Ergonomie générale'!P5:P36,"Oui") | K24: =COUNTIF('Ergonomie générale'!P5:P36,"Non") | L24: =IF(F24=0,"",G24/F24)
A25: Performances | B25: 16 | C25: 14 | D25: 2 | E25: 0 | F25: =COUNTIF('Performances'!L5:L20,"OK")+COUNTIF('Performances'!L5:L20,"KO")+COUNTIF('Performances'!L5:L20,"Bloqué") | G25: =COUNTIF('Performances'!L5:L20,"OK") | H25: =COUNTIF('Performances'!L5:L20,"KO") | I25: =COUNTIF('Performances'!L5:L20,"Bloqué") | J25: =COUNTIF('Performances'!P5:P20,"Oui") | K25: =COUNTIF('Performances'!P5:P20,"Non") | L25: =IF(F25=0,"",G25/F25)
A26: TOTAL | B26: =SUM(B5:B25) | C26: =SUM(C5:C25) | D26: =SUM(D5:D25) | E26: =SUM(E5:E25) | F26: =SUM(F5:F25) | G26: =SUM(G5:G25) | H26: =SUM(H5:H25) | I26: =SUM(I5:I25) | ... K26: =SUM(K5:K25) | L26: =IF(F26=0,"",G26/F26)

Sheet Connexion et sécurité
A1: CAHIER DE RECETTE — CONNEXION ET SÉCURITÉ
A2: Version testée : branche integration/recette-2026-10-29 (21ddcd3d), déployée sur le poste local (port 8080), copie de l'officine restaurée le 30/10
A3: 16 cas — Claude : 16 OK, 0 en échec, 0 non joués
A4: N° | B4: Cas de test | C4: Écran (menu) | D4: Objectif | E4: Existant (avant de commencer) | F4: Étapes | G4: Résultats attendus | H4: Nettoyage / prudence | I4: Test automatique | J4: Résultat Claude | K4: Détail Claude | L4: Résultat testeur | M4: Commentaire testeur | N4: Testeur | O4: Date | P4: Résultat Claude confirmé ?
A5: SEC-01 | B5: Super administrateur : Centre de support réservé, invisible et protégé pour l'admin | C5: Centre de support (sous-menus lus dans l'arbre du menu) ; autres écrans (non précisé dans le test) : contrôles faits par les routes du serveur | D5: Retours du 25/10 (points 5 et 7) : l'administrateur ne voit dans le Centre de support que « Me contacter » et se voit refuser l'audit, la stabilité du serveur et la maintenance ; il ne voit pas le super administrateur (profils, utilisateurs), ne peut ni en créer un ni changer son mot de passe, ni accorder les droits du Centre de support ; le super administrateur a tout. | E5: Comptes d'essai du poste local (outils/poste-local/compte-essai.sql) : le compte de test de profil Administrateur et le compte de support de profil Super Administrateur ; un profil « Caissiere ». Aucune donnée créée (ce qui serait créé par erreur est retiré). | F5: 1. Se connecter en administrateur et ouvrir le Centre de support. 2. (Contrôle technique, fait par le test automatique) : demander l'audit, l'état du serveur et la maintenance. 3. (Contrôle technique, fait par le test automatique) : lire la liste des profils (route REST et ancien écran) et la liste des utilisateurs. 4. (Contrôle technique, fait par le test automatique) : tenter de créer un utilisateur de profil Super Administrateur. 5. (Contrôle technique, fait par le test automatique) : tenter de changer le mot de passe du super administrateur (route REST et ancienne page JSP). 6. (Contrôle technique, fait par le test automatique) : lire le catalogue des droits « CENTRE DE SUPPORT » du profil Caissiere, puis tenter d'accorder le droit des tickets. 7. Se connecter en super administrateur et ouvrir le Centre de support. 8. (Contrôle technique, fait par le test automatique) : demander l'audit, la liste des profils et le catalogue des droits du Centre de support. | G5: 1. (technique) Précondition : compte de test Administrateur et compte de support Super Administrateur présents. 2. Administrateur : Centre de support réduit à « Me contacter ». 3. (technique) Administrateur : audit refusé par le serveur. 4. (technique) Administrateur : stabilité du serveur refusée. 5. (technique) Administrateur : maintenance refusée. 6. (technique) Administrateur : profil Super Administrateur absent des listes de profils (REST et écran historique). 7. (technique) Administrateur : comptes super administrateur absents de la liste des utilisateurs. 8. (technique) Administrateur : création d'un super administrateur refusée, rien de créé. 9. (technique) Administrateur : mot de passe d'un super administrateur non modifiable. 10. (technique) Administrateur : ancienne page (JSP), mot de passe d'un super administrateur non modifiable, sans erreur. 11. (technique) Administrateur : seuls « Centre de support » et « Me contacter » au catalogue des droits du Centre de support. 12. (technique) Administrateur : attribution directe d'un droit du Centre de support refusée. 13. Super administrateur : tout le Centre de support, audit compris. 14. (technique) Super administrateur : audit accessible. 15. (technique) Super administrateur : profil Super Administrateur dans la liste des profils. 16. (technique) Super administrateur : tous les droits du Centre de support au catalogue (au moins 8). 17. (technique) Essais retirés. | H5: Le test supprime l'utilisateur d'essai s'il avait été créé par erreur, retire le droit des tickets s'il avait été accordé, et remet le mot de passe d'essai du compte de support. | I5: securite/test-droits-super-admin.js | J5: OK | K5: Joué le 30/10 15:33 — 17 / 17 conformes
A6: SEC-02 | B6: Gestion de profils : les fenêtres Créer, Modifier et Privilèges sont modales | C6: GESTION DES UTILISATEURS > Gestion de profils | D6: Retours du 25/10, point 3 : dans la gestion de profils, les fenêtres « Créer », « Modifier » et « Attribution des privilèges » voilent l'écran derrière elles (plus de clic possible dessous) et se ferment par leur bouton sans rien enregistrer. | E6: Connexion avec le compte d'essai (administrateur). Au moins un profil existant. Rien n'est créé. | F6: 1. Se connecter avec le compte d'essai. 2. Ouvrir GESTION DES UTILISATEURS > Gestion de profils. 3. Cliquer sur « Créer », regarder l'écran derrière, puis cliquer sur « Annuler ». 4. Cliquer sur l'icône « Modifier » de la première ligne, regarder l'écran derrière, puis cliquer sur « Annuler ». 5. Cliquer sur l'icône « Attribution des privilèges » de la première ligne, regarder l'écran derrière, puis cliquer sur « Fermer ». | G6: 1. « Créer » : fenêtre modale, l'écran derrière est voilé. 2. « Créer » se ferme par « Annuler ». 3. « Modifier » : fenêtre modale, l'écran derrière est voilé. 4. « Modifier » se ferme par « Annuler ». 5. « Attribution des privilèges » : fenêtre modale, l'écran derrière est voilé. 6. « Attribution des privilèges » se ferme par « Fermer ». 7. (technique) Aucun profil ni privilège modifié. 8. Aucune erreur JavaScript, aucune fenêtre du navigateur. | H6: Rien à retirer (lecture seule). | I6: retours/test-profils-fenetres-modales.js | J6: OK | K6: Joué le 30/10 15:33 — 8 / 8 conformes
A7: SEC-03 | B7: Liste des utilisateurs : l'empreinte du mot de passe n'est plus envoyée au navigateur | C7: GESTION DES UTILISATEURS > Utilisateurs | D7: Constat du 17/10 : la liste des utilisateurs renvoyait l'empreinte du mot de passe de chaque compte. Ni la route lue par l'écran, ni l'ancienne route encore lue par deux écrans, ni les trois anciennes routes de privilèges ne doivent la renvoyer ; la grille et la fenêtre « Modifier » fonctionnent toujours. | E7: Connexion avec le compte administrateur de test. Lecture seule : le test ne crée ni ne modifie rien. | F7: 1. Ouvrir GESTION DES UTILISATEURS > Utilisateurs et attendre la liste. 2. (Contrôle technique, fait par le test automatique) : lire les réponses de la liste reçues par le navigateur. 3. (Contrôle technique, fait par le test automatique) : lire l'ancienne route de la liste et les trois anciennes routes de privilèges. 4. Sur la première ligne, cliquer sur l'icône « Modifier » et lire le login ; fermer la fenêtre. | G7: 1. La grille affiche les comptes. 2. (technique) Réponse de la liste lue par l'écran : sans le champ du mot de passe. 3. (technique) Ancienne route ws_data.jsp : sans le champ du mot de passe, toujours des comptes. 4. (technique) Anciennes routes ws_privilege.jsp (3) : sans le champ du mot de passe. 5. « Modifier » : la fenêtre s'ouvre avec le login du compte. 6. (technique) Aucune erreur JavaScript. | H7: Rien à retirer (lecture seule). | I7: securite/test-liste-utilisateurs-sans-mot-de-passe.js | J7: OK | K7: Joué le 30/10 15:33 — 6 / 6 conformes
A8: SEC-04 | B8: Fichier journal : nom du poste, ventes non journalisées, colonnes, alertes, export | C8: MENU PHARMACIEN > Fichier Journal ; SERVICE CLIENT > Vente terminées (menu lu dans la configuration des menus de l'application ; écran décrit par le test : Fichier Journal (menu non précisé dans le test) ; Ventes terminées) | D8: Retours du 10/10 (Q10) : chaque poste porte un nom saisi une fois dans le journal ; les ventes ne sont pas journalisées mais gardent leur poste et leur adresse IP (filtre et détail dans « Ventes terminées ») ; ajustements et suppressions de facture sont journalisés avec poste, adresse IP et application ; alertes d'annulations en série et d'opérations hors horaires ; export Excel enrichi. | E8: Connexion avec le compte de test habituel (administrateur). Un article vendable (prix de 200 à 400) en stock. Le test automatique crée lui-même : une caisse ouverte si l'utilisateur n'en a pas, le stock de l'article porté à 100, quatre lignes de journal datées du 10/06/2025 au poste « E2E-POSTE-ALERTE » (trois annulations à 10:00, 10:05 et 10:12, un ajustement à 05:30), une vente, une prévente, un ajustement de +2 et une facture provisoire « E2E-JRN-FACT » de 12 345 qu'il supprime. Pour un test manuel, préparer ces mêmes éléments. | F8: 1. Se connecter. 2. Ouvrir le Fichier Journal et regarder la liste des types de journal. 3. Dans « Ce poste », saisir « E2E POSTE 7 » et cliquer sur le bouton d'enregistrement du nom. 4. Faire une vente au comptant d'un article et la clôturer. 5. Faire une prévente et la terminer. 6. Ouvrir Ventes terminées ; ouvrir la liste des postes ; filtrer par « E2E POSTE 7 » (Entrée), puis par « E2E-POSTE-INCONNU », puis de nouveau par « E2E POSTE 7 ». 7. Cliquer sur « Voir détail » de la vente et lire le champ « Poste ». 8. Faire un ajustement de stock de +2 sur l'article et le valider. 9. Supprimer la facture provisoire d'essai depuis la liste des factures. 10. Rouvrir le Fichier Journal, chercher sur la date du jour et regarder les colonnes de la ligne d'ajustement. 11. Choisir le poste « E2E-POSTE-ALERTE » et chercher le 10/06/2025. 12. Cliquer sur le bouton des alertes. 13. Lancer l'export Excel du 10/06/2025 pour ce poste. | G8: 1. Le journal ne propose plus de type « Vente » ni « Prévente » (les ventes ne sont pas journalisées). 2. Le nom « E2E POSTE 7 » est mémorisé sur le poste. 3. (technique) La vente clôturée garde le poste de saisie, le poste et l'adresse IP d'encaissement. 4. (technique) La vente clôturée n'ajoute aucune ligne au journal. 5. (technique) La prévente garde son poste de saisie et n'ajoute aucune ligne au journal. 6. Ventes terminées : « E2E POSTE 7 » figure dans la liste des postes. 7. Le filtre par ce poste montre la vente. 8. Le filtre par un autre poste ne la montre pas. 9. Le détail de la vente affiche « Poste » avec l'adresse IP entre parenthèses (le poste de saisie, identique, est masqué). 10. (technique) L'ajustement est journalisé avec « Stock : avant X → après X+2 » et le poste. 11. (technique) La facture est supprimée et la suppression est journalisée avec « Suppression de la facture N° E2E-JRN-FACT, montant 12345 » et le poste. 12. La liste du journal a les colonnes Poste, Adresse IP et Application, renseignées pour l'ajustement (application de type navigateur Chrome). 13. Le filtre par poste montre les 4 lignes de ce poste seulement. 14. Les alertes signalent la série « 3 annulations du 10/06/2025 10:00 au 10/06/2025 10:12 ». 15. Les alertes signalent l'ajustement de 05:30 le 10/06/2025 comme hors horaires. 16. L'export Excel a les colonnes Poste, Adresse IP, Application, Avant / après, et les 4 lignes du poste filtré. 17. Aucune erreur JavaScript. 18. (technique) Ventes et lignes de journal de l'essai retirées. | H8: Le test retire ventes, prévente, règlements, mouvements, ajustement, lignes de journal et facture d'essai, la caisse ouverte par lui, remet le stock d'origine et efface le nom du poste mémorisé. | I8: retours/test-journal-complet.js | J8: OK | K8: Joué le 30/10 15:33 — 18 / 18 conformes
A9: SEC-05 | B9: Page de connexion : informations de l'officine, message d'erreur, blocage après 10 échecs | C9: Page de connexion | D9: Page de connexion du 13/10 : l'ancienne adresse renvoie vers la nouvelle page ; nom de l'application, version et nom de la pharmacie s'affichent ; un mauvais mot de passe donne un message dans la page ; 10 échecs sur un identifiant imposent une attente (écran et téléphone) ; après l'attente, une faute de frappe ne rebloque pas ; la session change à la connexion. | E9: Le compte de test habituel (administrateur) et un identifiant d'essai inexistant (« e2e_inconnu_… »). Aucune donnée écrite : le blocage est gardé en mémoire et expire seul au bout de 30 s. | F9: 1. Ouvrir l'ancienne adresse de la page de connexion (security/index.jsp). 2. Lire le titre, le nom de l'application, la version et le nom de la pharmacie. 3. Saisir le compte de test avec un mauvais mot de passe et cliquer sur « Connexion ». 4. (Contrôle technique, fait par le test automatique) : envoyer 11 tentatives de connexion avec l'identifiant inexistant, puis une tentative par la connexion du téléphone. 5. Saisir l'identifiant inexistant dans la page et cliquer sur « Connexion ». 6. (Contrôle technique, fait par le test automatique) : envoyer 10 mauvais mots de passe pour le compte de test, attendre 31 s, puis envoyer encore un mauvais mot de passe. 7. Se connecter avec le compte de test et son bon mot de passe. 8. Dans un nouvel onglet, rouvrir la page de connexion. | G9: 1. L'ancienne adresse security/index.jsp arrive sur la nouvelle page HTML. 2. (technique) La page est servie sans code JSP. 3. Le nom de l'application, la version et le titre sont affichés. 4. Le nom de la pharmacie est affiché. 5. Mauvais mot de passe : message « incorrect » dans la page. 6. Aucune fenêtre (alerte du navigateur). 7. (technique) Les 9 premiers échecs donnent le message habituel. 8. (technique) Au 10e échec, une attente de 30 s est annoncée (« Trop d'essais »). 9. (technique) Pendant l'attente : refus immédiat avec le temps restant (« Réessayez dans … »). 10. (technique) Le téléphone subit le même blocage. 11. À l'écran, le message de blocage « Trop d'essais » s'affiche. 12. (technique) Un compte réel est bloqué au 10e échec. 13. (technique) L'attente écoulée, une faute de frappe ne rebloque pas : simple message « incorrect ». 14. (technique) Aucune session n'est créée sur la page de connexion avant la connexion. 15. La connexion se fait normalement (arrivée sur l'accueil). 16. (technique) L'identifiant de session est renouvelé à la connexion (un identifiant imposé avant n'est pas repris). 17. Déjà connecté : la page de connexion renvoie directement à l'accueil. 18. Aucune fenêtre pendant tout le parcours. | H9: PRUDENCE : Le test bloque le compte de test pendant 30 s : ne pas lancer d'autre test pendant ce temps. Rien à retirer : l'identifiant d'essai n'existe pas et le blocage expire seul. | I9: securite/test-connexion.js | J9: OK | K9: Joué le 30/10 15:33 — 18 / 18 conformes
A10: SEC-06 | B10: Sessions : pas de session pour les accès anonymes, expiration et retour à la connexion | C10: Page de connexion | D10: Sécurité (13/10) : les routes publiques et pages d'entrée ne créent plus de session ; une connexion ratée non plus ; les sessions expirent après la durée réglée sans requête (720 minutes par défaut) ; un écran dont la session a expiré revient à la connexion avec un message dans la page, sans fenêtre. | E10: Compte d'essai des tests automatiques (administrateur). Le réglage de durée de session (720 minutes par défaut) est ramené à 1 minute pendant le test puis remis à sa valeur d'origine. | F10: 1. (Contrôle technique, fait par le test automatique) : vérifier la présence du réglage de durée de session. 2. (Contrôle technique, fait par le test automatique) : appeler les routes publiques et les pages d'entrée sans être connecté, tenter une connexion ratée, puis une connexion réussie. 3. (Contrôle technique, fait par le test automatique) : ramener la durée de session à 1 minute et attendre une minute. 4. Se connecter avec le compte d'essai. 5. (Contrôle technique, fait par le test automatique) : demander des données, puis provoquer un refus (401) sur une route du téléphone. 6. Ne plus rien faire pendant un peu plus d'une minute. 7. Se reconnecter ; la session est fermée côté serveur ; faire une action à l'écran. 8. (Contrôle technique, fait par le test automatique) : se déconnecter sans session, puis remettre le réglage. | G10: 1. (technique) Le réglage de durée est présent (720 min par défaut). 2. (technique) Routes publiques et pages d'entrée : aucune session créée. 3. (technique) Connexion ratée : aucune session créée. 4. (technique) Connexion réussie : session créée. 5. (technique) Session active : les données répondent. 6. Refus (401) alors que le poste est connecté : l'écran reste ouvert. 7. (technique) Après 1 minute sans requête : la session est expirée (401). 8. Session fermée : l'écran revient à la page de connexion. 9. Le message « session expirée » est affiché dans la page. 10. Aucune fenêtre n'est affichée. 11. (technique) Déconnexion sans session : aucune session créée. 12. (technique) Le réglage est remis à sa valeur d'origine. | H10: PRUDENCE : Pendant le test, la durée de session est d'une minute pour tous les postes : ne pas le lancer pendant que d'autres utilisateurs travaillent. Le test remet le réglage de durée de session à sa valeur d'origine (et attend la minute de cache). | I10: securite/test-sessions.js | J10: OK | K10: Joué le 30/10 15:33 — 12 / 12 conformes
A11: SEC-07 | B11: Connexion par badge (QR) : connexion, refus, journal, limite d'essais | C11: Page de connexion (bouton « Se connecter avec mon badge ») | D11: Demande du 16/10 : se connecter en présentant son badge à la douchette. Le badge doit être actif, non expiré, d'un employé actif rattaché à l'utilisateur ; tout autre cas est refusé sans session ; le secret n'apparaît nulle part ; après 10 échecs le badge est bloqué un moment ; la connexion par mot de passe reste possible. | E11: Compte de test habituel (administrateur). Le test automatique crée lui-même : un employé d'essai « ESSAI Badge connexion » rattaché à cet utilisateur (en détachant le temps du test l'employé déjà rattaché) et un badge actif avec un secret aléatoire. Pour un test manuel, préparer un badge d'essai imprimé pour un employé d'essai rattaché à un utilisateur d'essai. | F11: 1. Ouvrir la page de connexion et cliquer sur « Se connecter avec mon badge ». 2. Présenter le badge à la douchette (lecture puis Entrée). 3. Sur une nouvelle page de connexion, cliquer dans le champ « Identifiant » et présenter le badge directement. 4. Présenter successivement des badges invalides : secret faux, login d'un autre utilisateur, contenu illisible, badge désactivé, badge expiré, employé inactif, connexion par badge coupée (paramètre KEY_CONNEXION_BADGE = 0). 5. Rétablir le badge et le présenter de nouveau. 6. (Contrôle technique, fait par le test automatique) : lire le journal de connexion et les traces du serveur. 7. Se connecter avec l'identifiant et le mot de passe. 8. Présenter 10 fois le badge avec un mauvais secret, puis avec le bon. | G11: 1. Le bouton affiche la zone « Présentez votre badge ». 2. La lecture à la douchette connecte et ouvre l'accueil, avec la session de l'utilisateur du badge. 3. La lecture directe dans « Identifiant » connecte aussi, et le secret lu ne reste pas affiché dans le champ. 4. Refus — secret faux : message « Badge non reconnu », aucune session. 5. Refus — login d'un autre utilisateur : message « Badge non reconnu », aucune session. 6. Refus — contenu illisible : message « Badge non reconnu », aucune session. 7. Refus — badge désactivé : message « Badge non reconnu », aucune session. 8. Refus — badge expiré : message « Badge non reconnu », aucune session. 9. Refus — employé inactif : message « Badge non reconnu », aucune session. 10. Refus — connexion par badge coupée (paramètre KEY_CONNEXION_BADGE = 0) : message « Badge non reconnu », aucune session. 11. Badge rétabli : connexion acceptée. 12. (technique) Le journal de connexion indique « par badge », sans le secret. 13. (technique) Le secret ne figure pas dans les traces du serveur. 14. La connexion par mot de passe fonctionne toujours. 15. Après 10 échecs, le badge est refusé avec un délai d'attente, même avec le bon secret. 16. (technique) Badge et employé d'essai retirés. | H11: PRUDENCE : Le test modifie temporairement le paramètre KEY_CONNEXION_BADGE (connexion par badge coupée) et lit les traces du serveur : à jouer sur un serveur d'essai. Le test retire le badge et l'employé d'essai, rattache de nouveau l'employé d'origine à l'utilisateur et remet le paramètre KEY_CONNEXION_BADGE dans son état. | I11: retours/test-connexion-badge.js | J11: OK | K11: Joué le 30/10 15:33 — 16 / 16 conformes
A12: SEC-08 | B12: Accès sans connexion : routes de gestion et anciennes pages fermées, public conservé | C12: Page de connexion ; le reste sans écran (contrôle technique) | D12: Audit du 12/10 : de faux en-têtes ne valent plus connexion ; les routes de gestion et les anciennes pages JSP ne répondent plus sans session ; ce qui doit rester public (connexion, nom de l'officine, espace produit, avis) le reste ; connecté, les écrans reçoivent toujours leurs données. | E12: Connexion avec le compte de test (administrateur), utilisée seulement pour la partie « connecté ». Le test automatique crée ou modifie lui-même le paramètre « KEY_ENTETES_X_USER_INFO » le temps d'un essai. | F12: 1. (Contrôle technique, fait par le test automatique) : appeler, sans connexion et avec de faux en-têtes d'administrateur, les routes de l'application de vente. 2. (Contrôle technique, fait par le test automatique) : appeler sans connexion, puis avec de faux en-têtes, 18 routes de gestion (CA, TVA, factures, crédits, valorisation, licence…). 3. (Contrôle technique, fait par le test automatique) : appeler sans connexion 9 anciennes pages JSP et servlets. 4. (Contrôle technique, fait par le test automatique) : appeler sans connexion le nom de l'officine, l'espace produit, ses DCI et les avis publics. 5. Ouvrir la page de connexion et regarder le nom de la pharmacie. 6. Se connecter à Prestige. 7. (Contrôle technique, fait par le test automatique) : connecté, appeler une ancienne JSP et les routes lues par les écrans. 8. (Contrôle technique, fait par le test automatique) : mettre le paramètre à 1, attendre une minute et rappeler avec de faux en-têtes ; puis remettre le paramètre et attendre une minute. | G12: 1. (technique) Faux en-têtes d'administrateur refusés. 2. (technique) Catalogue (prix d'achat) refusé avec de faux en-têtes. 3. (technique) Aucune route de gestion lisible sans connexion (18 routes). 4. (technique) Aucune route de gestion lisible avec de faux en-têtes. 5. (technique) Anciennes JSP et servlets refusées sans connexion (9). 6. (technique) Public : nom de l'officine. 7. (technique) Public : espace produit. 8. (technique) Public : DCI de l'espace produit. 9. (technique) Public : avis (jeton faux refusé par le service, pas par le filtre de connexion). 10. Page de connexion : le nom de la pharmacie est affiché. 11. (technique) Connecté : une ancienne JSP répond toujours. 12. (technique) Connecté : les routes des écrans sont toujours servies. 13. (technique) Paramètre à 1 : l'ancien comportement revient (compatibilité). 14. (technique) Paramètre remis : faux en-têtes de nouveau refusés. | H12: PRUDENCE : Pendant environ une minute, le paramètre rouvre l'accès par faux en-têtes : à jouer uniquement sur une base d'essai. Le test remet le paramètre « KEY_ENTETES_X_USER_INFO » à sa valeur d'avant (ou le supprime s'il n'existait pas) et attend une minute pour que l'ancien comportement ne reste pas actif. | I12: securite/test-acces-sans-connexion.js | J12: OK | K12: Joué le 30/10 15:33 — 14 / 14 conformes
A13: SEC-09 | B13: Connexion par badge : lecture déformée par la douchette signalée ou corrigée | C13: Page de connexion, bouton badge et champ « Identifiant » | D13: Retours des 23 et 24/10 : « Badge non reconnu » après le scan d'un badge. La douchette peut déformer la lecture (clavier AZERTY, verrouillage majuscules, douchette restée en QWERTY). L'écran doit le dire clairement sans montrer le secret, et une douchette en QWERTY (avec ou sans majuscules) doit quand même connecter. | E13: Le compte de test (administrateur). Le test automatique crée lui-même : un employé d'essai « ESSAI Badge lecture » relié au compte de test et un badge actif avec son secret (l'éventuel employé déjà relié au compte est détaché le temps du test). Pour un test manuel, préparer : un badge imprimé depuis Ressources humaines (onglet Badges) pour un compte d'essai, et une douchette réglable (AZERTY / QWERTY, majuscules). | F13: 1. Ouvrir la page de connexion. 2. Cliquer sur le bouton badge et scanner un badge dont les séparateurs « | » sont lus comme « µ ». 3. Sur une nouvelle page de connexion, scanner le badge avec le verrouillage majuscules actif (casse inversée). 4. Sur une nouvelle page, scanner un ancien exemplaire du badge (secret qui n'est plus valable). 5. (Contrôle technique, fait par le test automatique) : lire la fin du journal du serveur. 6. Sur une nouvelle page, scanner le bon badge, lu correctement. 7. Sur une nouvelle page, scanner le badge avec une douchette restée en QWERTY sur un poste AZERTY, par le bouton badge. 8. Sur une nouvelle page, faire la même lecture QWERTY dans le champ « Identifiant » puis Entrée. 9. Sur une nouvelle page, scanner avec la douchette en QWERTY et verrouillage majuscules actif, par le bouton badge. 10. Sur une nouvelle page, faire la même lecture QWERTY + majuscules dans le champ « Identifiant » puis Entrée. | G13: 1. « | » remplacé : titre « Lecture du badge déformée », consigne sur la douchette (clavier / AZERTY), aucune session ouverte. 2. Ce qui a été lu est montré (« PRESTIGE-BADGEµ1µ… »), sans le secret du badge. 3. Casse inversée : un message parle des majuscules, aucune session ouverte, le secret n'apparaît pas. 4. Ancien exemplaire lu correctement : « Badge non reconnu » avec la mention qu'il a été réimprimé, aucune session. 5. (technique) Le journal du serveur note la raison du refus (secret), sans le secret. 6. La bonne lecture connecte toujours (arrivée dans l'application). 7. Douchette QWERTY sur poste AZERTY : connexion par le bouton badge. 8. Même lecture dans « Identifiant » : connexion aussi. 9. QWERTY et verrouillage majuscules : connexion par le bouton badge. 10. Même lecture dans « Identifiant » : connexion aussi. 11. (technique) Badge et employé d'essai retirés. | H13: Le test supprime le badge et l'employé d'essai et rattache de nouveau au compte de test l'employé qui l'était avant. | I13: retours/test-connexion-badge-lecture.js | J13: OK | K13: Joué le 30/10 15:33 — 11 / 11 conformes
A14: SEC-10 | B14: Badge sans compte utilisateur ou lecture déformée : messages clairs à la connexion | C14: RESSOURCES HUMAINES > Employés, planning de la semaine, congés et absences, pointages, connexions, pointage mobile (menu lu dans la configuration des menus de l'application ; écran décrit par le test : (menu non précisé dans le test) > Ressources humaines, onglet Badges ; page de connexion) | D14: Un refus « FORMAT » apparaissait dans les traces du serveur. Il faut distinguer un badge imprimé pour un employé sans compte utilisateur (il ne peut pas connecter) d'une lecture déformée (douchette réglée sur un autre clavier), à l'écran comme dans les traces, sans jamais montrer le secret du badge. | E14: Connexion avec le compte administrateur. Le test automatique crée lui-même : un employé d'essai (matricule E2E-BSC-M1) sans compte utilisateur et son badge actif ; pour un test manuel, préparer : un employé sans compte utilisateur avec un badge actif. | F14: 1. Ouvrir l'écran « Ressources humaines » (menu : voir colonne « Écran ») puis l'onglet des badges. 2. Sélectionner la ligne du badge de l'employé d'essai et lire son texte. 3. Cliquer sur le bouton d'impression des badges (libellé non précisé dans le test) et lire le message affiché. 4. Sur une nouvelle page de connexion, scanner le QR du badge sans compte (login vide). 5. Sur une nouvelle page de connexion, scanner le même badge avec une douchette réglée en QWERTY sur un poste AZERTY. 6. (Contrôle technique, fait par le test automatique) : envoyer au serveur la lecture du badge sans login et lire les traces du serveur. | G14: 1. Onglet Badges : la ligne du badge indique « sans compte utilisateur ». 2. L'impression en QR depuis l'écran avertit que le badge est sans compte utilisateur et ne permettra pas de se connecter. 3. Badge sans login : la page de connexion affiche « Badge sans compte utilisateur » et la marche à suivre (réimprimer), sans appel au serveur et sans afficher le secret. 4. Lecture déformée : la page affiche « Lecture du badge déformée » avec ce qui a été lu (ex. « PRESTIGE)BQDGE »), sans le secret. 5. (technique) Les traces du serveur indiquent le refus FORMAT avec « login vide », sans le secret. 6. (technique) Badge et employé d'essai retirés. | H14: PRUDENCE : Le test lit le journal du serveur (traces) : à jouer sur un poste d'essai. Le test supprime le badge et l'employé d'essai. | I14: retours/test-badge-sans-compte.js | J14: OK | K14: Joué le 30/10 15:33 — 6 / 6 conformes
A15: SEC-11 | B15: Une vente ne peut pas être terminée au nom d'un profil « prévente » (deux onglets) | C15: SERVICE CLIENT > Ventes > « Nouvelle vente » | D15: Cas d'officine du 17/10 : une connexion d'un profil « prévente » dans un autre onglet remplaçait l'utilisateur de la session, et la vente commencée par la caissière était terminée au nom de ce profil. Le serveur doit refuser toute clôture (écran, application mobile, dépôt) à un profil prévente, et l'onglet de la caissière doit annoncer le changement de compte. | E15: Connexion avec le compte d'essai (administrateur), caisse ouverte (le test en ouvre une si besoin). Le rôle « Vendeur » existe sans le droit de clôture ; un article en stock (plus de 5 boîtes) avec un CIP de 7 chiffres. Le test automatique crée lui-même : un utilisateur d'essai « e2e-stagiaire » (E2E STAGIAIRE) au rôle « Vendeur », avec une caisse ouverte ; pour un test manuel, préparer : un compte d'essai au rôle « Vendeur » avec une caisse ouverte. | F15: 1. Dans le navigateur, ouvrir un second onglet sur la page de connexion, sans se connecter. 2. Dans le premier onglet, se connecter avec le compte d'essai, ouvrir SERVICE CLIENT > Ventes et cliquer sur « Nouvelle vente ». 3. Saisir le CIP de l'article puis Entrée. 4. Dans le second onglet, se connecter avec le compte « e2e-stagiaire » et regarder le menu. 5. Revenir au premier onglet, saisir le montant reçu et cliquer sur « Terminer la vente » ; lire l'annonce. 6. (Contrôle technique, fait par le test automatique) : rejouer la demande de clôture depuis la session du profil prévente. 7. (Contrôle technique, fait par le test automatique) : depuis cette session, tenter les clôtures de l'application mobile (paiement mobile money avec clôture, ventes en dépôt v1 et v2, dépôt agréé, comptant v2). 8. Dans un nouveau navigateur, se connecter avec le compte d'essai seul, ouvrir SERVICE CLIENT > Ventes, « Nouvelle vente », saisir l'article, le montant reçu et cliquer sur « Terminer la vente ». | G15: 1. (technique) Jeu d'essai : rôle « Vendeur » sans le droit de clôture, article en stock. 2. Onglet administrateur : vente commencée (un article). 3. Onglet 2 : le profil prévente est connecté, sans le menu Ventes. 4. Onglet administrateur : « Changement de compte » est annoncé dans la page (la page se recharge au nom du compte connecté). 5. (technique) La vente n'est pas terminée au nom du profil prévente. 6. (technique) Clôture rejouée depuis la session du profil prévente : refusée (403), vente non terminée. 7. (technique) Application mobile, profil prévente — paiement mobile money avec clôture : refusé (403), vente non terminée. 8. (technique) Application mobile, profil prévente — clôture de vente en dépôt (v1) : refusée (403). 9. (technique) Application mobile, profil prévente — clôture de vente en dépôt agréé (v1) : refusée (403). 10. (technique) Application mobile, profil prévente — clôture de vente en dépôt (v2) : refusée (403). 11. (technique) Application mobile, profil prévente — clôture comptant (v2) : refusée (403). 12. Non-régression : l'administrateur seul termine sa vente normalement (caissier = administrateur). 13. (technique) Données d'essai retirées, stock remis. | H15: Le test supprime les ventes d'essai (règlements, mouvements, recettes), l'utilisateur « e2e-stagiaire », son rôle, ses journaux et les caisses ouvertes pour l'essai, et remet le stock de l'article. | I15: securite/test-cloture-vente-profil-prevente.js | J15: OK | K15: Joué le 30/10 23:29 — 13/13 OK
A16: SEC-12 | B16: Saisies absurdes dans les recherches et filtres : jamais d'erreur interne du serveur | C16: Sans écran (contrôle technique) | D16: Demande du 07/10 : toutes les lectures du serveur sont appelées avec des valeurs absurdes (vide, lettres, négatif, nombre énorme, date impossible, apostrophe, balise, texte très long, caractères spéciaux). Le serveur doit refuser proprement, sans erreur interne, sans dépasser 30 s et sans rien écrire. | E16: Connexion avec le compte d'essai. Le test relève lui-même les lectures dans le code du serveur et écarte celles qui agissent (envoi, synchronisation, exports, etc.). Rien n'est écrit en base. | F16: 1. (Contrôle technique, fait par le test automatique) : relever toutes les lectures de l'API dans le code. 2. Se connecter avec le compte d'essai. 3. (Contrôle technique, fait par le test automatique) : appeler chaque lecture retenue avec chaque jeu de valeurs absurdes, deux appels à la fois. 4. (Contrôle technique, fait par le test automatique) : vérifier la session, les erreurs, les durées, les tables et le Centre de support. | G16: 1. (technique) Le relevé trouve les lectures de l'API (plus de 500). 2. (technique) La session est toujours ouverte après tous les appels. 3. (technique) Aucune erreur interne (HTTP 500), quelle que soit la saisie. 4. (technique) Aucune lecture ne dépasse 30 s. 5. (technique) Aucune table modifiée par les lectures. 6. (technique) Aucune nouvelle erreur au Centre de support. | H16: PRUDENCE : Envoie un très grand nombre d'appels au serveur pendant plusieurs minutes : à jouer sur un poste d'essai, en dehors des heures d'ouverture. Rien à retirer (lecture seule). | I16: retours/test-saisie-api.js | J16: OK | K16: Joué le 30/10 18:38 — 6/6 OK
... A20: SEC-16 | B20: Rappel « date et heure fausses » : serveur, date reculée et horloge du poste | C20: Écran d'accueil après la connexion (rappel affiché en bas de l'écran) | D20: Retours du 25/10, point 2 : quand l'heure du serveur est fausse, quand la date a reculé ou quand l'horloge du poste est fausse, un rappel discret s'affiche en bas de l'écran, avec « Mettre à jour » et « Masquer », sans fenêtre surgissante. | E20: Connexion avec le compte de test (administrateur), une caisse, l'heure d'Internet joignable depuis le serveur. Le test automatique crée lui-même : un réglage d'essai « KEY_HORLOGE_ESSAI_DECALAGE » (serveur en avance d'une heure) et une opération de caisse d'essai datée de dans 2 jours ; il avance l'horloge du navigateur de 3 h pour un second poste. La synchronisation est interceptée : Windows n'est pas touché. | F20: 1. Se connecter à Prestige avec une horloge juste et attendre la vérification. 2. (Contrôle technique, fait par le test automatique) : simuler un serveur en avance d'une heure et relancer la vérification. 3. Cliquer sur « Mettre à jour » dans le rappel, puis sur « Masquer ». 4. (Contrôle technique, fait par le test automatique) : poser une opération de caisse datée de dans 2 jours, puis ouvrir un nouvel onglet de Prestige. 5. Se connecter depuis un poste dont l'horloge est en avance de 3 h. 6. Cliquer sur « Mettre à jour » dans le rappel. 7. (Contrôle technique, fait par le test automatique) : afficher un rappel WhatsApp en bas à droite et relancer la vérification. | G20: 1. (technique) Précondition : horloge du serveur juste, fuseau attendu, heure d'Internet joignable. 2. Horloge juste : aucun rappel. 3. Serveur en avance d'une heure : rappel « la date ou l'heure n'est pas bonne… en avance de 1 h », avec « Mettre à jour » et « Masquer ». 4. « Mettre à jour » : synchronisation demandée au serveur, compte rendu « synchronisée » dans le rappel, bouton « Mis à jour ». 5. « Masquer » retire le rappel. 6. Date reculée (opération datée de dans 2 jours) : signalée (« a reculé »). 7. Horloge du poste en avance de 3 h : « l'horloge de ce poste est en avance de 3 h ». 8. Poste seul en faute : « Mettre à jour » explique comment synchroniser ce poste (« Synchroniser maintenant »), sans appel au serveur. 9. Le rappel s'affiche au-dessus du rappel WhatsApp, sans le recouvrir. 10. Aucune fenêtre surgissante. 11. (technique) Essais retirés. | H20: PRUDENCE : En test manuel, ne pas changer l'heure du serveur ni de Windows : le test automatique simule les écarts et intercepte la synchronisation. Le test supprime le réglage d'essai et l'opération de caisse « E2E-HORLOGE ». | I20: securite/test-horloge.js | J20: OK | K20: Joué le 30/10 15:33 — 11 / 11 conformes

Sheet Ventes
A1: CAHIER DE RECETTE — VENTES
A2: Version testée : branche integration/recette-2026-10-29 (21ddcd3d), déployée sur le poste local (port 8080), copie de l'officine restaurée le 30/10
A3: 47 cas — Claude : 46 OK, 1 en échec, 0 non joués
A4: N° | B4: Cas de test | C4: Écran (menu) | D4: Objectif | E4: Existant (avant de commencer) | F4: Étapes | G4: Résultats attendus | H4: Nettoyage / prudence | I4: Test automatique | J4: Résultat Claude | K4: Détail Claude | L4: Résultat testeur | M4: Commentaire testeur | N4: Testeur | O4: Date | P4: Résultat Claude confirmé ?
A5: VEN-01 | B5: Vente assurance : encours des organismes justes après annulation, modification, refus | C5: (menu non précisé dans le test) > Vente assurance | D5: Reproduire les constats d'audit sur la vente assurance (CR-01 à CR-10, CA-03, CA-09/N5) : l'encours des organismes et des clients doit rester juste après annulation, modification, clôture refusée ou simultanée ; les parts et taux falsifiés, un taux de 250 % ou le retrait d'un tiers payant encaissé doivent être refusés ; une vente ordinaire ne doit pas être enregistrée comme « exclue » ; un changement d'organisme doit déplacer la part, sauf si la vente est déjà facturée. | E5: Connexion avec le compte de test administrateur ; caisse ouverte pour ce compte (créée par le test si besoin) ; au moins un produit à TVA 0 avec du stock. Le test automatique crée lui-même des tiers payants d'essai (copies d'un organisme, compteurs à zéro, certains « exclus » ou « dépôt ») et des clients assurés « ZZAUDIT » ; pour un test manuel, préparer : des organismes d'essai et des clients assurés à 80 % (ou 50 % + 30 %, 70 % + 20 %). | F5: 1. CR-01 : encaisser une vente assurance à 80 %, noter l'encours de l'organisme et du client, puis annuler la vente. 2. CR-02 : encaisser une vente assurance, ouvrir sa modification et la valider sans rien changer. 3. CR-03 : client à deux organismes (50 % et 30 %) ; vendre avec un numéro de bon, puis faire une seconde vente réutilisant le même numéro de bon sur le second organisme et tenter de la clôturer, deux fois. 4. CR-04 : (Contrôle technique, fait par le test automatique) : préparer 6 ventes assurance du même client et les clôturer deux par deux au même instant. 5. CR-07 : (Contrôle technique, fait par le test automatique) : clôturer une vente à 80 % en envoyant une part de 1 F et un taux de 1 %. 6. CR-09 : sur une vente en cours, ajouter un second tiers payant avec un taux de 250 %. 7. CR-10 : sur une vente assurance encaissée, retirer le tiers payant. 8. CA-03 : encaisser une vente sur un organisme « exclu », puis 8 ventes ordinaires ; ensuite 3 ventes sur un carnet dépôt, puis une vente ordinaire. 9. CA-09 : sur une vente encaissée sur l'organisme A, remplacer l'organisme par B. 10. N5 : sur une vente déjà facturée, remplacer l'organisme par un autre. | G5: 1. CR-01 (précondition) : après la vente, l'encours de l'organisme et du client = part du tiers payant. 2. CR-01 : après annulation, l'encours de l'organisme et du client revient à 0. 3. CR-02 (précondition) : la modification s'ouvre. 4. CR-02 : après une modification sans changement, l'encours = une seule part. 5. CR-03 : la clôture est refusée (bon déjà utilisé), aucun encours n'est modifié et aucune ligne tiers payant n'est close. 6. CR-03 : un second essai identique ne recompte rien. 7. CR-04 : (technique) après 3 paires de clôtures simultanées, l'encours = somme des parts des ventes clôturées. 8. CR-07 : (technique) la part de 1 F et le taux de 1 % sont refusés, ou ignorés au profit du calcul du serveur (taux 80 %). 9. CR-09 : l'ajout d'un tiers payant à 250 % est refusé. 10. CR-10 : le retrait du tiers payant d'une vente encaissée est refusé, la ligne reste facturable. 11. CA-03 (précondition) : la vente de l'organisme exclu est enregistrée comme exclue. 12. CA-03 : aucune des 8 ventes ordinaires suivantes n'est enregistrée comme « vente exclue ». 13. CA-03 : une vente ordinaire après des ventes « dépôt » n'est pas enregistrée comme exclue. 14. CA-09 : la part passe de l'organisme A à l'organisme B (encours A → 0, B → part). 15. N5 : changer l'organisme d'une vente déjà facturée est refusé, la ligne facturée reste. 16. Chaque cas se déroule sans exception, et aucune erreur JavaScript n'apparaît. | H5: PRUDENCE : Test de reproduction : une ligne « FAIL » signifie que le défaut est reproduit. Le test retire les tiers payants, clients, ventes et lignes d'essai, et ferme la caisse d'essai s'il l'a créée. | I5: audits/repro-vente-assurance.js | J5: OK | K5: Joué le 30/10 15:33 — 17 / 17 conformes
A6: VEN-02 | B6: Vente comptant : modifications, annulations et clôtures interdites ou cohérentes | C6: (menu non précisé dans le test) > Vente comptant | D6: Reproduire les constats d'audit sur la vente comptant (VC-01 à VC-14, N1, N2) : une vente encaissée ne doit pas changer de quantité, de statut ni de client ; une annulation pendant une modification, la vente du dernier stock deux fois, un paiement insuffisant ou la modification d'une vente annulée doivent être refusés ; l'annulation rend les boîtes au bon lot ; la modification d'une vente d'hier garde une seule date ; une annulation qui échoue n'écrit rien. | E6: Connexion avec le compte de test administrateur ; caisse ouverte pour ce compte (créée par le test si besoin) ; au moins un produit avec du stock ; un autre vendeur actif. Le test automatique crée lui-même : un client « ZZAUDIT VC08 », deux lots d'essai (A épuisé à péremption proche, B à 5 boîtes) sur un produit sans lot, et règle le paramètre FORCER_STOCK_VENTE à 0 ; pour un test manuel, préparer l'équivalent. | F6: 1. VC-01 : encaisser une vente comptant de 2 boîtes, puis tenter de passer la ligne à 5 boîtes. 2. VC-02 : encaisser une vente, puis lancer « Terminer la prévente » dessus. 3. VC-04 : encaisser une vente d'une boîte, ouvrir sa modification, annuler la vente d'origine, puis valider la modification avec un autre vendeur. 4. VC-08 : encaisser une vente pour le client d'essai, puis tenter de la rattacher à un client inconnu. 5. VC-09 : stock du produit à 1, FORCER_STOCK_VENTE à 0 ; préparer deux ventes d'une boîte chacune et les valider l'une après l'autre. 6. VC-11 : vendre 2 boîtes du produit à lots, puis annuler la vente. 7. VC-12 : encaisser une vente, la dater de la veille (préparation faite par le test), puis la modifier et valider la modification avec un autre vendeur. 8. VC-14 : préparer une vente de 2 boîtes et la clôturer en déclarant 1 F reçu et payé. 9. N1 : (Contrôle technique, fait par le test automatique) : retirer la ligne de stock du produit dans l'emplacement, puis annuler la vente. 10. N2 : encaisser une vente, l'annuler, puis tenter d'ouvrir sa modification. | G6: 1. VC-01 (précondition) : la vente de 2 boîtes est encaissée. 2. VC-01 : la modification de quantité est refusée, la ligne reste à 2 boîtes. 3. VC-02 : « Terminer la prévente » est refusé, la vente reste encaissée. 4. VC-04 (précondition) : la modification s'ouvre (copie en cours). 5. VC-04 : l'annulation pendant la modification est refusée, ou la validation de la copie ne réannule pas : une seule annulation, stock = stock de départ − 1, caisse cohérente. 6. VC-08 (précondition) : la vente est rattachée au client d'essai. 7. VC-08 : le changement de client vers un identifiant inconnu est refusé, le client est conservé. 8. VC-09 (précondition) : deux ventes en cours d'une boîte chacune, stock 1. 9. VC-09 : la seconde validation est refusée, le stock ne passe pas sous zéro. 10. VC-11 (précondition) : la vente de 2 boîtes sort du lot B (lot B à 3). 11. VC-11 : l'annulation rend les 2 boîtes au lot B (A = 0, B = 5). 12. VC-12 : toutes les écritures de la modification d'une vente d'hier portent la même date. 13. VC-14 : la clôture qui déclare 1 F payé pour une vente de 2 boîtes est refusée. 14. N1 : (technique) l'annulation qui échoue ne laisse aucune écriture (vente non annulée, aucune copie, aucune contre-passation). 15. N2 : l'ouverture de la modification d'une vente annulée est refusée. 16. Chaque cas se déroule sans exception, et aucune erreur JavaScript n'apparaît. | H6: PRUDENCE : Test de reproduction : une ligne « FAIL » signifie que le défaut est reproduit. Modifie temporairement le paramètre FORCER_STOCK_VENTE (remis à la fin). Le test retire les ventes, le client, les lots d'essai, remet le stock et le paramètre FORCER_STOCK_VENTE à leur valeur, et ferme la caisse d'essai s'il l'a créée. | I6: audits/repro-vente-comptant.js | J6: OK | K6: Joué le 30/10 15:33 — 17 / 17 conformes
A7: VEN-03 | B7: Gestion des différés : relevé du solde par client et filtre « État » | C7: FACTURATION > Gestion des différés (menu lu dans la configuration des menus de l'application ; écran décrit par le test : Gestion des différés (menu non précisé dans le test), onglet « SOLDE ») | D7: Retours du 07/10 et du 09/10 : un onglet « Solde » donne le relevé d'un client sur une période (solde de départ, une ligne par opération, solde de fin de mois) ; un filtre « État » trie les ventes selon leur règlement ; le relevé s'imprime en PDF et s'exporte en Excel avec les mêmes chiffres. | E7: Profil administrateur (compte de test). Le test automatique crée lui-même : un client « ZZDIFFERE Essai », trois ventes en différé (partiellement réglée, non réglée, réglée) et deux règlements en septembre et octobre 2026 ; pour un test manuel, préparer ce jeu. | F7: 1. (Contrôle technique, fait par le test automatique) : demander au serveur le relevé d'octobre 2026, puis septembre-octobre, puis avec des dates inversées et des dates illisibles. 2. (Contrôle technique) : filtrer la liste par État (non réglée, partielle, réglée, non soldés, tous). 3. Ouvrir Gestion des différés (menu : voir colonne « Écran ») et cliquer sur l'onglet « SOLDE ». 4. Saisir du 01/10/2026 au 31/10/2026, choisir le client « ZZDIFFERE Essai », cliquer sur « Rechercher ». 5. Cliquer sur « Imprimer (PDF) » et lire le relevé. 6. Exporter le relevé en Excel. 7. Imprimer avec des dates inversées. | G7: 1. (technique) Solde au début d'octobre = ventes − règlements d'avant (10 000 − 6 000 = 4 000). 2. (technique) Une ligne par opération, solde après chacune, dans l'ordre (vente avant son règlement). 3. (technique) Ligne « Solde fin Octobre 2026 » (totaux du mois). 4. (technique) Date et heure sur chaque opération (première : 03/10/2026 09:00). 5. (technique) Solde final = somme des restes dus des ventes en différé. 6. (technique) Sur deux mois : une ligne de solde par mois, septembre puis octobre. 7. (technique) Dates inversées : refus expliqué (message parlant du début). 8. (technique) Dates illisibles : pas d'erreur serveur. 9. (technique) Filtre État : non réglée (B), partielle (A), réglée (C), non soldés (A, B), tous (A, B, C). 10. Écran : onglet SOLDE, colonnes date et heure / débit / crédit / solde, ligne de fin de mois, résumé. 11. « Imprimer (PDF) » ouvre le relevé avec la période (01/10 au 31/10/2026) et le client de l'écran. 12. PDF : titre et période, client, lignes (ventes, règlement, fin de mois), totaux identiques à l'écran. 13. Export Excel : fichier .xls « releve_differes_2026-10-01_2026-10-31 » avec les opérations du relevé. 14. Impression avec dates inversées : message « pas pu être imprimé », pas de fichier ni d'erreur serveur. 15. Aucune erreur JavaScript. 16. (technique) Jeu d'essai retiré. | H7: Le client, les ventes, les règlements et les mouvements d'essai sont retirés à la fin. | I7: retours/test-differes-solde.js | J7: OK | K7: Joué le 30/10 15:33 — 16 / 16 conformes
A8: VEN-04 | B8: Suppressions de vente : auteur de la suppression et utilisateur qui avait ouvert la vente | C8: SERVICE CLIENT > Produits rétirés et ventes abandonnées ; SERVICE CLIENT > Pre-vente (menu lu dans la configuration des menus de l'application ; écran décrit par le test : Écran des préventes et écran des suppressions de vente (menus non précisés dans le test)) | D8: Évolution 5, point 6 : le mouchard des ventes supprimées garde l'auteur de la suppression (« Système » pour les ventes abandonnées supprimées à minuit) et ajoute l'utilisateur qui avait ouvert la vente ; les deux s'affichent à l'écran et dans l'export Excel. | E8: Profil administrateur (compte de test). Le test automatique crée lui-même un utilisateur d'essai et une vente en attente ouverte par cet utilisateur ; pour un test manuel, faire ouvrir une prévente par un autre utilisateur. | F8: 1. Ouvrir l'écran des suppressions de vente (menu : voir colonne « Écran ») et regarder les colonnes. 2. Ouvrir l'écran des préventes (menu : voir colonne « Écran ») et repérer la vente en attente d'essai. 3. Cliquer sur l'icône de suppression de la ligne et confirmer si une confirmation apparaît. 4. Rouvrir l'écran des suppressions de vente et lire la ligne. 5. Cliquer sur « Exporter (Excel) ». | G8: 1. L'écran des suppressions porte les colonnes « Supprimé par » et « Vente ouverte par ». 2. (technique) L'utilisateur d'origine est prévu dans les données de la liste. 3. La vente en attente posée apparaît dans l'écran des préventes. 4. (technique) La suppression est tracée (une ligne par produit de la vente). 5. (technique) L'auteur de la suppression est conservé : l'opérateur connecté. 6. (technique) L'utilisateur d'origine est celui qui avait ouvert la vente. 7. (technique) Les deux utilisateurs sont bien distincts. 8. (technique) La vente est bien supprimée. 9. L'écran affiche l'auteur de la suppression et l'utilisateur d'origine. 10. Le bouton « Exporter (Excel) » est présent. 11. (technique) L'export Excel répond (avec les deux colonnes d'utilisateur). 12. Aucune erreur JavaScript pendant tout le parcours. 13. (technique) Tout ce que le test a posé est retiré. | H8: La vente d'essai, sa trace de suppression et l'utilisateur d'essai sont retirés à la fin. | I8: retours/test-suppression-vente-origine.js | J8: OK | K8: Joué le 30/10 15:33 — 13 / 13 conformes
A9: VEN-05 | B9: « Modifier » une vente déjà modifiée ouvre l'écran de vente avec la vente chargée | C9: SERVICE CLIENT > Vente terminées | D9: Corriger le défaut signalé le 29/10 : « Modifier » sur une vente issue d'une vente déjà modifiée ouvrait un écran de vente vide, sans message, car le serveur refusait la modification. | E9: Connexion avec le compte de test administrateur ; caisse ouverte pour ce compte (créée par le test si besoin) ; un produit avec du stock et un autre vendeur actif. Le test automatique crée lui-même : une vente comptant d'une boîte encaissée, puis modifiée (copie validée avec un autre vendeur) ; pour un test manuel, préparer : une vente comptant du jour déjà modifiée une fois. | F9: 1. Ouvrir SERVICE CLIENT > « Vente terminées ». 2. Saisir la date du jour en date de début et en date de fin. 3. Saisir la référence de la vente modifiée dans la recherche. 4. Cliquer sur « rechercher ». 5. Sur la ligne de montant positif portant cette référence, cliquer sur l'icône « Modifier ». | G9: 1. (Préparation) La vente est modifiée et sa copie est validée. 2. Le serveur accepte d'ouvrir la modification de la vente déjà modifiée. 3. L'écran de vente s'ouvre avec la vente chargée : la ligne du produit est visible (pas d'écran vide). 4. (technique) Une copie de modification en cours est rattachée à la vente modifiée. 5. Aucune erreur JavaScript n'apparaît. | H9: Le test retire la vente d'essai, ses copies et annulations, et ferme la caisse d'essai s'il l'a créée. | I9: audits/test-ecran-modifier-vente-deja-modifiee.js | J9: OK | K9: Joué le 30/10 15:33 — 6 / 6 conformes
A10: VEN-06 | B10: Vente terminée : modifier le tiers-payant et en créer un nouveau sans plantage | C10: SERVICE CLIENT > Vente terminées | D10: Corrige deux erreurs relevées dans les journaux (11/09, 20/09, 19/10) : « Valider » sans tiers-payant choisi plantait la fenêtre « TIERS-PAYANTS ASSOCIES », et « AJOUTER UN NOUVEAU TIERS-PAYANT » plantait, si bien qu'on ne pouvait jamais créer un tiers-payant depuis la vente. | E10: Connexion avec le compte d'essai. Une vente VO clôturée, non annulée, avec un client et au moins un tiers-payant, dont la référence est unique dans sa journée. Le test accorde lui-même au profil le droit P_BTN_UPDATE_VENTE_CLIENT_TP s'il ne l'a pas ; pour un test manuel, utiliser un profil ayant ce droit. | F10: 1. Se connecter avec le compte d'essai. 2. Ouvrir SERVICE CLIENT > Vente terminées. 3. Saisir au clavier la date de début et la date de fin (jour de la vente) et la référence de la vente, puis cliquer sur « Rechercher ». 4. Sur la ligne de la vente, cliquer sur l'icône « Modifier info client ». 5. Cliquer sur « Modifier le tiers-payant », puis sur « Valider » sans rien choisir. 6. Dans la liste, choisir « AJOUTER UN NOUVEAU TIERS-PAYANT ». 7. Dans la fenêtre « Ajout un tiers-payant », saisir le nom et le nom complet « E2E TP CHANGE », le téléphone « 0102030405 », l'adresse « ESSAI », le code organisme « E2E ». 8. Cliquer sur « Enregistrer ». 9. Fermer la fenêtre de la vente sans valider. | G10: 1. Précondition : une vente VO avec tiers-payant est trouvée. 2. « Valider » sans tiers-payant choisi : la liste est marquée en erreur, la fenêtre « TIERS-PAYANTS ASSOCIES » reste ouverte, aucune erreur JavaScript. 3. « AJOUTER UN NOUVEAU TIERS-PAYANT » ouvre la fenêtre « Ajout un tiers-payant », sans erreur. 4. « Enregistrer » : les deux fenêtres se ferment et la ligne tiers-payant de la vente affiche « E2E TP CHANGE ». 5. (technique) Le tiers-payant est créé et rattaché au client de la vente. 6. Aucune erreur JavaScript. 7. (technique) Données d'essai retirées, priorités des comptes du client inchangées. | H10: Le test supprime le tiers-payant « E2E TP CHANGE » et son compte, remet les priorités des comptes du client et retire le droit accordé pour l'essai. | I10: journal/test-vente-changer-tiers-payant.js | J10: OK | K10: Joué le 30/10 15:33 — 7 / 7 conformes
A11: VEN-07 | B11: Ventes terminées : la liste « Poste » est relue à chaque ouverture | C11: SERVICE CLIENT > Vente terminées | D11: Retours du 25/10, point 4 : la liste « Poste » n'était chargée qu'à l'ouverture de l'écran ; un poste apparu ensuite n'y figurait qu'après réouverture. Elle doit être relue à chaque ouverture de la liste. | E11: Connexion administrateur. Le test automatique crée lui-même, pendant le parcours, une vente d'essai depuis un nouveau poste. Pour un test manuel : faire une vente depuis un autre poste pendant que l'écran est ouvert. | F11: 1. Ouvrir SERVICE CLIENT > Vente terminées. 2. Cliquer sur la flèche de la liste « Poste » et lire les postes proposés ; refermer la liste. 3. (Contrôle technique, fait par le test automatique) : une vente est enregistrée depuis un nouveau poste. 4. Sans quitter l'écran, rouvrir la liste « Poste ». | G11: 1. Première ouverture de la liste : le nouveau poste n'y est pas. 2. Nouvelle ouverture, sans quitter l'écran : le nouveau poste est proposé. 3. Aucune erreur JavaScript, aucune fenêtre du navigateur. 4. (technique) Vente d'essai retirée. | H11: La vente d'essai du nouveau poste est supprimée. | I11: retours/test-ventes-terminees-postes.js | J11: OK | K11: Joué le 30/10 15:33 — 4 / 4 conformes
A12: VEN-08 | B12: Réimpression du ticket d'une vente marquée « copie » (anomalie A8) | C12: SERVICE CLIENT > Vente terminées | D12: Anomalie A8 du rapport du Centre de support du 26/10 : une vente marquée « copie » appelait une route d'impression retirée du serveur (404) et le ticket ne sortait pas. La réimpression doit passer par la route d'impression existante (VNO et VO). | E12: Connexion avec le compte de test. La liste est simulée par le test (deux ventes fictives VNO et VO marquées copie, référence E2EA8COPIE) et les impressions sont interceptées : rien n'est imprimé, aucune donnée lue ni écrite ; pour un test manuel, préparer : une vente terminée VNO et une VO marquées copie. | F12: 1. Ouvrir SERVICE CLIENT > Vente terminées et cliquer sur « Rechercher ». 2. Sur la ligne de la vente VNO marquée copie, cliquer sur l'icône « Réimprimer le ticket » ; fermer le message. 3. Sur la ligne de la vente VO marquée copie, cliquer sur l'icône « Réimprimer le ticket » ; fermer le message. | G12: 1. Vente VNO marquée copie : le ticket part par la route d'impression existante (ticket VNO). 2. Vente VO marquée copie : le ticket part par la route d'impression existante (ticket VO). 3. (technique) Aucune erreur JavaScript. | H12: Rien à retirer : liste simulée, aucune donnée créée. | I12: support/anomalies-centre/test-a8-copie-ticket.js | J12: OK | K12: Joué le 30/10 23:29 — 3/3 PASS
A13: VEN-09 | B13: Ventes terminées : colonne Date unique, « Différé », colonne « P » du poste de saisie | C13: SERVICE CLIENT > Vente terminées (menu lu dans la configuration des menus de l'application ; écran décrit par le test : (menu non précisé dans le test) > Ventes terminées) | D13: Vérifier les colonnes de la liste des ventes terminées (retours du 11/10) : date et heure dans une seule colonne « Date », « Montant différé » renommé « Différé » (écran et Excel), nouvelle colonne « P » du poste de saisie avec infobulle, et tout tient en 1366 points sans défilement horizontal. | E13: Connexion avec le compte de test administrateur, écran de 1366 × 768. Un article vendable entre 200 et 400. Le test automatique met le stock de l'article à 100, ouvre une caisse si besoin et clôture deux ventes comptant d'une boîte : l'une depuis un poste nommé « E2E POSTE ACCUEIL COMPTOIR NUMERO 3 », l'autre sans poste de saisie connu (poste d'encaissement « E2E ENC »). La lecture de l'export Excel demande Python avec xlrd. | F13: 1. (Contrôle technique, fait par le test automatique) : clôturer les deux ventes d'essai. 2. Ouvrir l'écran « Ventes terminées ». 3. Lire les en-têtes de colonnes. 4. Lire la colonne « Date » et la colonne « P » des deux ventes d'essai, et passer la souris sur la colonne « P ». 5. Regarder s'il y a une barre de défilement horizontale et si les actions sont visibles. 6. Cliquer sur le bouton d'export Excel et ouvrir le fichier. | G13: 1. (Précondition) La première vente porte le poste de saisie. 2. La colonne « Heure » a disparu ; il reste une seule colonne « Date ». 3. La colonne « Date » donne date et heure ensemble (jj/mm/aaaa hh:mm). 4. L'en-tête « Différé » remplace « Montant différé ». 5. La colonne « P » vient juste après « Caissier », avec l'infobulle « Poste de saisie ». 6. La colonne « P » affiche le nom du poste de saisie (coupé selon la place). 7. L'infobulle donne le nom entier (« Saisie : … »). 8. Vente sans poste connu : colonne « P » vide, infobulle « Saisie : non connu » et « Encaissement : E2E ENC ». 9. En 1366 points : pas de défilement horizontal, actions visibles. 10. Un nom long est coupé proprement (points de suspension). 11. Export Excel : en-têtes « Différé » et « Poste de saisie ». 12. Export Excel : la vente porte son poste de saisie. 13. Aucune erreur JavaScript n'apparaît. 14. (technique) Les ventes d'essai sont retirées. | H13: PRUDENCE : Met temporairement le stock d'un article à 100 (remis à la fin) et clôture de vraies ventes (retirées à la fin) : à jouer sur une copie de travail. Le test supprime les ventes d'essai (lignes, règlements, recettes, mouvements, suggestions créées), remet le stock de l'article et retire la caisse qu'il a ouverte. | I13: retours/test-ventes-terminees-colonnes.js | J13: OK | K13: Joué le 30/10 15:33 — 14 / 14 conformes
A14: VEN-10 | B14: Libellés « VNO » et « VO » remplacés par « COMPTANT » et « ASSURANCE » à l'affichage | C14: SERVICE CLIENT > Vente terminées (menu lu dans la configuration des menus de l'application ; écran décrit par le test : (non précisé dans le test) > Ventes terminées ; (non précisé dans le test) > Liste de caisse ; (non précisé dans le test) > Visualisation de caisse) | D14: Point 10 du 28/10 : à l'affichage, « VNO » devient « COMPTANT » et « VO » devient « ASSURANCE », sans changer les valeurs enregistrées (les filtres continuent de fonctionner). | E14: Connexion avec le compte d'essai. Des ventes au comptant ou assurance (VNO / VO) dans les 30 derniers jours, et des mouvements en caisse. Lecture seule. | F14: 1. Se connecter avec le compte d'essai. 2. Ouvrir l'écran « Ventes terminées » (menu : voir colonne « Écran »), mettre la date de début à 30 jours en arrière et lancer la recherche. 3. Lire la colonne « Type.Vente ». 4. Ouvrir l'écran « Liste de caisse » et lire la colonne « Type Mouvement ». 5. Ouvrir l'écran « Visualisation de caisse » et lire la colonne « Type Mouvement ». 6. (Contrôle technique, fait par le test automatique) : vérifier la table de correspondance des libellés. | G14: 1. Ventes terminées : la liste contient des ventes VNO ou VO (valeurs enregistrées). 2. Ventes terminées : la colonne « Type.Vente » affiche « COMPTANT » pour VNO et « ASSURANCE » pour VO, et plus jamais « VNO » ni « VO ». 3. Liste de caisse : la colonne « Type Mouvement » n'affiche ni « VNO » ni « VO ». 4. Visualisation de caisse : la colonne « Type Mouvement » n'affiche ni « VNO » ni « VO ». 5. (technique) Correspondances : VNO → COMPTANT, VO → ASSURANCE, ventes N.O. → Ventes comptant, ventes ordonnancées → Ventes assurance ; « Reglements differes » inchangé. 6. Aucune erreur JavaScript. | H14: Rien à retirer (lecture seule). | I14: points-28-10/test-libelles-comptant-assurance.js | J14: OK | K14: Joué le 30/10 15:33 — 6 / 6 conformes
A15: VEN-11 | B15: Points du 29/10 : modification de ventes, périmés, tableau des retours fournisseurs | C15: SERVICE CLIENT > Vente terminées ; GESTION DU STOCK > Recherche périmés ; GESTION DES COMMANDES > Retour fournisseur | D15: Couvre plusieurs retours du 29/10 : modifier une vente issue d'une vente déjà modifiée, « Retour » qui ramène à « Ventes terminées » avec le même critère, colonne d'actions entière en 1366 x 768, refus de modifier une vente à crédit déjà facturée, nombre de lignes en gras dans l'écran de vente, filtres regroupés des périmés, et tableau de bord des retours fournisseurs par utilisateur (filtre, impression, export Excel). | E15: Connexion avec le compte administrateur, écran 1366 x 768. Le test automatique crée lui-même : une vente au comptant d'un produit (stock mis à 100), clôturée puis modifiée (quantité 2) et sa copie clôturée, et une caisse ouverte si besoin ; pour un test manuel, préparer : une vente clôturée déjà modifiée une fois. Il faut aussi une vente à crédit déjà facturée et des retours fournisseurs depuis 2020. | F15: 1. Ouvrir SERVICE CLIENT > Vente terminées. 2. Saisir la référence de la vente issue de la modification dans « Recherche » et cliquer sur « rechercher ». 3. Cliquer sur l'icône « Modifier » (crayon) de cette vente. 4. Dans l'écran de vente, regarder le texte « nombre(s) de ligne(s) ». 5. Si le bandeau d'alerte WhatsApp couvre l'écran, cliquer sur « Masquer ». 6. Cliquer sur le bouton de retour de l'écran de vente (libellé non précisé dans le test). 7. Dans « Ventes terminées », observer la colonne d'actions de la première ligne. 8. Mettre la date de début à il y a 5 ans, rechercher la référence d'une vente à crédit déjà facturée et cliquer sur son icône « Modifier » ; fermer le message par « OK ». 9. Ouvrir GESTION DU STOCK > Recherche périmés et regarder les filtres. 10. Ouvrir GESTION DES COMMANDES > Retour fournisseur, puis l'onglet « Tableau de bord ». 11. Saisir la date de début 01/01/2020 et cliquer sur « Actualiser ». 12. Choisir le premier utilisateur listé dans le filtre utilisateur du tableau. 13. Cliquer sur « Imprimer », puis sur « Export Excel ». 14. Ouvrir l'onglet « Liste des retours », saisir la date de début 01/01/2020 et choisir le même utilisateur dans le filtre utilisateur. | G15: 1. La vente issue d'une vente modifiée est bien clôturée (précondition). 2. « Modifier » charge à l'écran la copie de cette vente avec ses lignes. 3. Le texte « nombre(s) de ligne(s) » est en gras. 4. « Retour » ramène à « Ventes terminées » avec le même critère de recherche (pas aux ventes en attente). 5. (technique) La copie abandonnée est retirée. 6. Colonne d'actions de « Ventes terminées » : aucune icône coupée, pas de défilement horizontal en 1366 x 768. 7. Vente facturée : « Modifier » affiche « La vente ... a été facturée le jj/mm/aaaa (facture n° ...) ». 8. Vente facturée : l'écran de vente ne s'ouvre pas. 9. (technique) Aucune copie n'est créée pour la vente facturée. 10. Recherche périmés : un seul filtre regroupé (grossiste, famille, emplacement), les anciennes listes sont masquées. 11. Tableau de bord : « Retours par utilisateur » affiche le nombre et la part en %. 12. La liste a un filtre utilisateur ; le tableau a « Imprimer » et « Export Excel ». 13. Avec le filtre utilisateur du tableau : cet utilisateur seul, même nombre de retours, 100 %. 14. « Imprimer » ouvre la page d'impression des retours fournisseurs, avec « Utilisateur : » rappelé et une seule ligne. 15. « Export Excel » télécharge un classeur .xlsx non vide. 16. Liste des retours filtrée : seuls les retours de cet utilisateur. 17. (technique) Aucune erreur JavaScript. 18. (technique) Jeu d'essai retiré, stock du produit remis à sa valeur d'origine. | H15: Le test supprime les ventes créées (lignes, règlements, mouvements, modifications), remet le stock d'origine du produit et retire la caisse d'essai s'il l'a ouverte. | I15: points-28-10/test-points-29-10.js | J15: OK | K15: Joué le 30/10 15:33 — 18 / 18 conformes
A16: VEN-12 | B16: Vente modifiée sans aucun changement : pas de validation, retour à la liste | C16: SERVICE CLIENT > Vente terminées ; SERVICE CLIENT > Ventes, bouton « Nouvelle vente » (menu lu dans la configuration des menus de l'application ; écran décrit par le test : Écran « Ventes terminées » puis écran de vente (menu non précisé dans le test)) | D16: Point 7 du 28/10 : quand on ouvre une vente terminée en modification et qu'on la termine sans rien changer, elle ne doit pas être validée (la vente d'origine reste intacte, aucune nouvelle vente). Une vraie modification reste validée. | E16: Connexion avec le compte de test, caisse ouverte (le test en ouvre une si besoin). Un article actif non déconditionné, prix entre 500 et 20 000 (le test met son stock à 100). Le test automatique crée lui-même : une vente au comptant d'une unité de cet article, clôturée. Pour un test manuel, faire et clôturer une vente au comptant d'un article. | F16: 1. Ouvrir l'écran « Ventes terminées ». 2. Saisir la référence de la vente dans le critère de recherche et lancer la recherche. 3. Sur la ligne de la vente, cliquer sur « Modifier » : la copie de la vente s'ouvre à l'écran de vente. 4. Sans rien changer, saisir le montant reçu (= net à payer) et cliquer sur « Terminer la vente » (si un message de recalcul du net à payer apparaît, cliquer sur « OK » et terminer à nouveau). 5. Lire le message puis cliquer sur « OK ». 6. Rouvrir la vente en modification depuis « Ventes terminées » ; changer la quantité de la ligne de 1 à 2. 7. Saisir le montant reçu et cliquer sur « Terminer la vente ». | G16: 1. Précondition : la vente au comptant est clôturée. 2. « Modifier » depuis « Ventes terminées » : une copie de la vente est chargée à l'écran de vente. 3. Validation sans changement : message « Aucun changement détecté, retour à la liste des ventes ». 4. (technique) La vente d'origine n'est pas annulée. 5. (technique) Aucune nouvelle vente clôturée. 6. Après « OK », « Ventes terminées » se rouvre avec le même critère de recherche et la vente dans la liste. 7. (technique) La copie est retirée. 8. Vraie modification (quantité 1 → 2) : validée, la vente d'origine est annulée et la nouvelle vente clôturée. 9. Aucune erreur JavaScript. 10. (technique) Jeu d'essai retiré, stock remis. | H16: Toutes les ventes créées pendant le test (règlements, mouvements, recettes, modifications) sont supprimées, le stock de l'article est remis, et la caisse ouverte par le test est retirée. | I16: points-28-10/test-vente-modifiee-sans-changement.js | J16: OK | K16: Joué le 30/10 23:35 — 10/10 OK
... A51: VEN-47 | B51: Proforma : le deuxième produit s'ajoute sans message « vente clôturée » | C51: Écran de proforma (menu proforma, non précisé dans le test) | D51: Retour du 14/09 : sur une proforma (statut « devis »), l'ajout du deuxième produit était refusé en annonçant une vente clôturée. Le retrait d'une ligne et la remise passent par le même contrôle. | E51: Profil administrateur (compte de test). Au moins un client standard et deux produits en stock. Aucune donnée créée à l'avance ; les proformas posées par le test sont retirées. | F51: 1. (Contrôle technique, fait par le test automatique) : créer une proforma par le serveur avec un premier produit, ajouter un deuxième produit, retirer une ligne. 2. Ouvrir l'écran de proforma (menu non précisé dans le test). 3. Taper le nom d'un client standard dans la recherche client, puis Entrée, et le choisir. 4. Choisir un premier produit, saisir la quantité, Entrée. 5. Choisir un deuxième produit, saisir la quantité, Entrée. 6. (Contrôle technique) : essayer d'ajouter un produit à une vente clôturée. | G51: 1. (technique) Le premier produit crée la proforma. 2. (technique) Elle porte bien le statut « devis ». 3. (technique) Le deuxième produit s'ajoute. 4. (technique) Les deux lignes sont en base, le montant est cumulé. 5. (technique) Une ligne se retire sans message de vente clôturée. 6. Écran : le client est rattaché à la proforma. 7. Écran : le premier produit entre dans la liste, sans message. 8. Écran : le deuxième produit entre aussi, sans message de vente clôturée. 9. (technique) Écran : les deux lignes sont en base. 10. (technique) Une vente clôturée refuse toujours l'ajout, en renvoyant vers « Ventes terminées ». 11. Aucune erreur JavaScript. | H51: Les proformas créées par le test sont retirées à la fin. | I51: retours/test-proforma.js | J51: OK | K51: Joué le 30/10 15:33 — 11 / 11 conformes

Sheet Vente en dépôt
A1: CAHIER DE RECETTE — VENTE EN DÉPÔT
A2: Version testée : branche integration/recette-2026-10-29 (21ddcd3d), déployée sur le poste local (port 8080), copie de l'officine restaurée le 30/10
A3: 11 cas — Claude : 11 OK, 0 en échec, 0 non joués
A4: N° | B4: Cas de test | C4: Écran (menu) | D4: Objectif | E4: Existant (avant de commencer) | F4: Étapes | G4: Résultats attendus | H4: Nettoyage / prudence | I4: Test automatique | J4: Résultat Claude | K4: Détail Claude | L4: Résultat testeur | M4: Commentaire testeur | N4: Testeur | O4: Date | P4: Résultat Claude confirmé ?
A5: DEP-01 | B5: Factures de carnet dépôt : vraies factures, hors facturation ordinaire, suppression simple | C5: GESTION DES TIERS-PAYANTS > Gestion carnet dépôt (menu lu dans la configuration des menus de l'application ; écran décrit par le test : Menu du carnet dépôt (règlement et factures des carnets dépôt ; menu non précisé dans le test)) | D5: Retour du 08/09 : une facture de carnet dépôt est une vraie facture numérotée et définitive, créée depuis le menu du carnet dépôt, absente de la facturation ordinaire, et qui se supprime simplement (ses bons redevenant facturables). | E5: Profil administrateur (compte de test). Un tiers payant réel que le test marque « dépôt » le temps du test, avec des bons non facturés (le test en pose si besoin, avec un client et des comptes d'essai) ; pour un test manuel, un carnet dépôt avec des bons non facturés. | F5: 1. (Contrôle technique, fait par le test automatique) : lire la liste des tiers payants proposés par la facturation ordinaire et par le menu du carnet dépôt. 2. (Contrôle technique) : générer la facture du carnet dépôt depuis son menu, puis l'éditer sans et avec les produits. 3. Ouvrir l'écran du carnet dépôt (menu : voir colonne « Écran ») et regarder la liste des factures. 4. Sur la ligne de la facture, cliquer sur l'imprimante. 5. Ouvrir l'écran de création de facture du carnet dépôt, regarder le sélecteur, puis cliquer sur « Annuler ». 6. (Contrôle technique) : demander la suppression d'une facture ordinaire, d'une facture déjà réglée, puis de la facture de carnet dépôt. | G5: 1. (technique) Jeu d'essai : un carnet dépôt avec des bons non facturés. 2. (technique) La facturation ordinaire ne propose pas le carnet dépôt. 3. (technique) Le menu du carnet dépôt ne propose que les carnets dépôt. 4. (technique) Sans paramètre, la liste reste celle de toujours. 5. (technique) La génération depuis le menu du carnet dépôt répond (1 facture). 6. (technique) La facture est définitive (pas une provisoire). 7. (technique) La facture porte un numéro, le suivant du compteur. 8. (technique) La facture porte tous les bons du jour. 9. (technique) Les bons sont marqués facturés. 10. (technique) Elle figure dans le menu du carnet dépôt. 11. (technique) Elle ne figure pas dans les factures ordinaires. 12. (technique) Elle ne figure pas dans les provisoires. 13. (technique) Édition sans les produits : réponse correcte. 14. (technique) Édition avec les produits : le modèle détaillé répond. 15. Écran : plus de colonne « Statut ». 16. Écran : voir, imprimer et supprimer sur la ligne, chacun dans sa colonne. 17. Écran : le bouton du haut ne sert qu'à la suppression multiple. 18. Écran : l'imprimante de la ligne propose « avec / sans les produits », sans choix de modèle de facture. 19. Écran de création : il ne parle plus de « factures provisoires ». 20. Écran de création : le sélecteur ne propose que les carnets dépôt. 21. Écran de création : « Annuler » ramène au menu du carnet dépôt, onglet FACTURES. 22. (technique) Suppression : une facture ordinaire est refusée. 23. (technique) Suppression : la facture ordinaire est toujours là. 24. (technique) Suppression : une facture déjà réglée est refusée, avec le motif. 25. (technique) Suppression : la facture de carnet dépôt est supprimée. 26. (technique) Suppression : plus de facture ni de lignes en base. 27. (technique) Suppression : les bons redeviennent facturables. 28. Aucune erreur JavaScript. 29. (technique) Jeu d'essai retiré (tiers payant, compteur de numéros). | H5: PRUDENCE : À jouer uniquement sur un serveur d'essai : le test change temporairement le compteur de numéros de facture et le type d'un tiers payant réel (remis à la fin) ; une facture émise pendant le test sur ce serveur pourrait prendre un numéro décalé. La facture générée est supprimée, le tiers payant reprend son état (non dépôt) et le compteur de numéros de facture est remis à sa valeur. | I5: retours/test-point2-depot.js | J5: OK | K5: Joué le 30/10 15:33 — 29 / 29 conformes
A6: DEP-02 | B6: Carnet dépôt : seuls les carnets sont proposés, et choisir un carnet lance la recherche | C6: GESTION DES TIERS-PAYANTS > Gestion carnet dépôt (menu lu dans la configuration des menus de l'application ; écran décrit par le test : Écran « Gerer carnet depot » (menu non précisé dans le test)) | D6: Non-régression après les correctifs du carnet dépôt : l'écran s'ouvre, la liste ne propose que les carnets en dépôt (pas les assurances marquées dépôt), et choisir un carnet déclenche la recherche de l'onglet actif. | E6: Connexion avec le compte de test. Le test automatique crée lui-même, à partir d'un tiers payant existant : un carnet en dépôt « ZZ CARNET TEST » et une assurance marquée dépôt « ZZ ASSURANCE TEST ». Pour un test manuel, préparer ces deux tiers payants. | F6: 1. Ouvrir l'écran « Gerer carnet depot ». 2. Ouvrir la liste des carnets et lire les choix proposés. 3. Choisir « ZZ CARNET TEST » dans la liste. | G6: 1. L'écran « Gerer carnet depot » s'ouvre. 2. La liste des carnets est présente. 3. Seuls les carnets sont proposés (l'assurance « ZZ ASSURANCE TEST » est écartée). 4. La liste contient les carnets en dépôt actifs de la base (plus l'entrée « Tout »). 5. Choisir un carnet lance la recherche. 6. Aucune erreur JavaScript. | H6: Les deux tiers payants d'essai (« ZZ CARNET TEST » et « ZZ ASSURANCE TEST ») sont supprimés. | I6: verif-carnet.js | J6: OK | K6: Joué le 30/10 15:33 — 6 / 6 conformes
A7: DEP-03 | B7: Fiche du client assuré en vente dépôt : grille des complémentaires modifiable et contrôlée | C7: GESTION DES TIERS-PAYANTS > Gestion depots extensions (onglet « Saisir vente dépôt ») | D7: Dans la vente en dépôt, la grille des assurances de la fiche client était restée en lecture seule, et « Associer une assurance » acceptait un taux de 0 % et une priorité déjà prise. La grille doit être modifiable avec les mêmes contrôles que la vente de l'officine. | E7: Profil administrateur (compte de test). Le test automatique crée lui-même : un client d'essai assuré (matricule se terminant par « DEPOTG ») avec une assurance principale A (80 %, priorité 1) et deux complémentaires C (10 %, priorité 2) et F (10 %, priorité 3), plus un tiers payant E non rattaché ; pour un test manuel, préparer un client assuré avec ces trois assurances et un quatrième organisme libre. | F7: 1. Ouvrir GESTION DES TIERS-PAYANTS > Gestion depots extensions. 2. Dans « Type de vente », choisir « ASSURANCE ». 3. Dans la recherche client, taper le nom du client d'essai puis Entrée, et choisir le client dans la liste. 4. Cliquer sur le bouton de modification du client pour ouvrir sa fiche. 5. Dans la grille, cliquer sur la cellule « Taux.Couverture » de l'assurance C et taper 15, Entrée ; cliquer sur la cellule « Numéro/SS » et taper un nouveau matricule, Entrée. 6. Cliquer sur « Enregistrer ». 7. Rouvrir la fiche ; dans la cellule de priorité de C, taper la priorité d'une autre assurance, Entrée. 8. Dans la cellule « Taux.Couverture » de C, taper 150, Entrée. 9. Cliquer sur « Associer une assurance » : choisir l'organisme E, taper 0 dans le taux, cliquer sur « Enregistrer ». 10. Mettre le taux à 1 et la priorité à celle de C, cliquer sur « Enregistrer », puis « Annuler ». 11. Cliquer sur « Enregistrer » dans la fiche du client. | G7: 1. Le taux (15) et le matricule de C sont enregistrés. 2. La priorité déjà portée par une autre assurance est refusée : C garde sa priorité et un message contenant « déjà » s'affiche. 3. Le taux de 150 % est refusé : C garde son taux et un message indique la plage « 1 à 100 ». 4. « Associer une assurance » : le taux de 0 % est refusé, la fenêtre reste ouverte et le champ Taux est marqué en rouge. 5. « Associer une assurance » : la priorité déjà prise est refusée, la fenêtre reste ouverte. 6. (technique) Après « Enregistrer », aucune priorité n'est en double chez le client et l'organisme E n'est pas rattaché. 7. Aucune erreur JavaScript, aucun message d'erreur. | H7: Le client, ses assurances et la vente d'essai sont retirés à la fin. | I7: audits/test-ecran-assurances-client-depot.js | J7: OK | K7: Joué le 30/10 23:29 — 8/8 OK
A8: DEP-04 | B8: Vente en dépôt : les fiches du client assuré et du client carnet se ferment | C8: GESTION DES TIERS-PAYANTS > Gestion depots extensions, onglet « Saisir vente dépôt » | D8: Corriger un défaut où, sur l'écran de vente en dépôt, les boutons « Annuler » et « Enregistrer » de la fiche du client provoquaient une erreur et laissaient la fenêtre ouverte. | E8: Connexion avec le compte de test habituel (administrateur). Le test automatique crée lui-même : un client assuré d'essai « DEPOTW » (tiers payant A à 100 %) et un client carnet d'essai « DEPOTK » (tiers payant K à 100 %, client de type carnet). Pour un test manuel, préparer un client assuré et un client carnet d'essai. | F8: 1. Se connecter (masquer le bandeau d'alerte WhatsApp s'il s'affiche, bouton « Masquer »). 2. Ouvrir GESTION DES TIERS-PAYANTS > Gestion depots extensions, onglet « Saisir vente dépôt ». 3. Choisir le type de vente « ASSURANCE » (ASSURANCE_MUTUELLE), taper le nom du client assuré d'essai dans la recherche client, Entrée, cliquer sur sa ligne si une liste s'affiche. 4. Cliquer sur le bouton de modification du client, puis sur « Annuler ». 5. Choisir le type de vente « CARNET », rechercher le client carnet d'essai de la même façon. 6. Cliquer sur le bouton de modification du client, puis sur « Annuler ». 7. Rouvrir la fiche par le bouton de modification et cliquer sur « Enregistrer ». | G8: 1. Fiche du client assuré : « Annuler » la ferme. 2. Fiche du client carnet : « Annuler » la ferme. 3. Fiche du client carnet : « Enregistrer » l'enregistre et la ferme. 4. (technique) Le client carnet est toujours rattaché au tiers payant K. 5. Aucune erreur JavaScript. | H8: Le test retire les tiers payants, les clients d'essai et la vente ouverte. | I8: audits/test-ecran-fenetres-client-depot.js | J8: OK | K8: Joué le 30/10 23:29 — 6/6 OK
A9: DEP-05 | B9: Dépôts d'extension : stock et valorisation par dépôt, filtres, couleurs, éditions | C9: GESTION DES TIERS-PAYANTS > Gestion depots extensions, onglet « Valorisation » | D9: Évolution 5, point 1 et retours des 17 et 18/09 : consulter depuis l'officine le stock de chaque dépôt d'extension avec sa valorisation, filtrer (recherche, famille, emplacement, stock avec opérateur et valeur, masquer les articles à 0), voir les stocks négatifs en rouge et à zéro en violet, partager les critères entre « Liste des articles » et « Valorisation par emplacement », et éditer en Excel et en PDF paginé. | E9: Connexion avec le compte de test (administrateur, qui voit le sous-menu). Au moins un compte client et 5 articles actifs avec prix d'achat, prix de vente et CIP. Le test automatique crée lui-même : deux dépôts d'extension « DEPOT E2E NORD » (avec 5 articles en stock : 12, 5, 40, 0 et -3) et « DEPOT E2E SUD » (vide). Pour un test manuel, préparer : un dépôt d'extension avec quelques articles dont un à 0 et un négatif, et un dépôt vide. | F9: 1. (Contrôle technique, fait par le test automatique) : vérifier en base que le sous-menu « Gestion depots extensions » est dans GESTION DES TIERS-PAYANTS, avec son privilège, des libellés courts, et qu'il est visible pour l'administrateur. 2. Se connecter et ouvrir GESTION DES TIERS-PAYANTS > Gestion depots extensions, puis l'onglet « Valorisation ». 3. Sans choisir de dépôt, regarder la liste, les boutons d'édition, la case « masquer les articles à 0 », le filtre de stock et les filtres. 4. Ouvrir la liste des dépôts. 5. Choisir « DEPOT E2E NORD ». 6. Choisir « DEPOT E2E SUD », puis revenir à « DEPOT E2E NORD ». 7. Cocher « masquer les articles à 0 », puis la décocher. 8. Dans le filtre de stock, choisir successivement les opérateurs <, =, >, ≠ avec la valeur 0, puis ≥ et ≤ avec la plus grande quantité positive, en validant par Entrée dans la zone de valeur ; puis revenir à « tous ». 9. Choisir dans le filtre emplacement le rayon d'un des articles, puis revenir à « tous ». 10. Saisir le CIP d'un article en stock positif dans la recherche et cliquer sur le bouton de recherche. 11. Cliquer sur « Valorisation par emplacement ». 12. Effacer la recherche et relancer. 13. Imprimer la vue par emplacement. 14. Revenir à « Liste des articles ». 15. Imprimer la liste des articles en PDF ; imprimer aussi avec le filtre stock < 0, puis avec stock ≥ seuil. 16. Exporter en Excel. 17. (Contrôle technique, fait par le test automatique) : demander au serveur le stock et l'édition de l'officine (emplacement 1). 18. Regarder la mise en page de l'écran. | G9: 1. (technique) Le sous-menu « Gestion depots extensions » est posé dans GESTION DES TIERS-PAYANTS, avec le privilège P_SM_DEPOT_EXTENSION. 2. (technique) Le libellé et la description tiennent dans la navigation (25 et 30 caractères au plus). 3. (technique) Le sous-menu est visible pour un profil administrateur. 4. Tant qu'aucun dépôt n'est choisi : liste vide, éditions inactives, message « Choisissez un dépôt… ». 5. « masquer les articles à 0 » est décochée au départ et le filtre de stock est sur « tous ». 6. La zone de valeur du stock est grisée tant qu'aucun opérateur n'est choisi. 7. Le filtre emplacement est présent à côté du filtre famille. 8. Une seule barre de critères pour les deux vues. 9. Les deux vues s'appellent « Liste des articles » et « Valorisation par emplacement ». 10. La liste des dépôts ne propose que les dépôts d'extension actifs, jamais l'officine (dont « DEPOT E2E NORD »). 11. Le stock du dépôt s'affiche en entier : 5 articles, zéro et négatif compris. 12. L'article à zéro est visible par défaut. 13. L'article au stock négatif est visible. 14. Les éditions deviennent actives. 15. La ligne au stock négatif est en rouge. 16. La ligne au stock à zéro est en violet. 17. Une ligne au stock normal n'a aucune des deux couleurs. 18. Les deux couleurs sont réellement appliquées et différentes. 19. La valorisation affichée nomme « DEPOT E2E NORD » et donne la quantité, la valeur d'achat (stock × prix d'achat) et la valeur de vente (stock × prix de vente) des 5 articles. 20. Chaque ligne porte son stock, son prix d'achat et ses deux valorisations (stock × prix d'achat, stock × prix de vente). 21. Le dépôt sans stock s'affiche vide (« DEPOT E2E SUD », « 0 article »), sans le stock du dépôt précédent. 22. Cocher « masquer les articles à 0 » enlève la ligne à zéro et garde le stock négatif. 23. Filtre « stock < 0 » : seuls les stocks négatifs. 24. La case « masquer les articles à 0 » est grisée dès qu'un filtre de stock est posé. 25. Filtre « stock = 0 » : seuls les stocks à zéro. 26. Filtre « stock > 0 » : seuls les stocks positifs. 27. Filtre « stock ≠ 0 » : positifs et négatifs. 28. Filtre « stock ≥ seuil » : le nombre d'articles au-dessus du seuil. 29. Filtre « stock ≤ seuil » : le nombre d'articles sous le seuil. 30. Revenir à « tous » remontre les 5 lignes. 31. La case n'est plus grisée. 32. La zone de valeur est de nouveau grisée. 33. Le filtre emplacement propose les rayons de l'officine. 34. Le filtre emplacement ne garde que les articles de ce rayon. 35. Revenir à « tous » les emplacements remontre les 5 lignes. 36. La recherche par CIP ne garde que cet article, et la valorisation suit. 37. La recherche faite dans la liste vaut pour la vue par emplacement : un seul rayon. 38. Cette ligne porte 1 référence et le nombre d'unités de l'article. 39. Les critères restent visibles et modifiables dans la vue par emplacement. 40. Effacer la recherche remontre tous les emplacements du dépôt. 41. La somme des lignes par emplacement fait le total d'achat du dépôt. 42. La vue par emplacement s'imprime en PDF affiché dans l'onglet. 43. Son édition porte « VALORISATION PAR EMPLACEMENT - DEPOT E2E NORD », les colonnes RÉFÉRENCES et UNITÉS. 44. Son édition est paginée (« Page 1 »). 45. Le bouton Imprimer édite la vue affichée (vue par emplacement). 46. L'export Excel est inactif dans la vue par emplacement. 47. Revenir à la liste des articles recharge les 5 lignes avec les mêmes critères. 48. L'édition PDF de la liste s'affiche dans l'onglet. 49. Le document est un vrai PDF. 50. Le PDF porte « STOCK DU DEPOT - DEPOT E2E NORD », « Dépôt : DEPOT E2E NORD » et rappelle « articles à 0 masqués ». 51. Le PDF porte les colonnes Stock, Val. achat, Val. vente et « TOTAL : 5 article(s) ». 52. Le PDF des articles est paginé. 53. Le PDF avec le filtre négatif rappelle « stock < 0 » et le total des articles négatifs. 54. Le PDF avec opérateur rappelle « stock >= seuil » et le bon total. 55. L'export Excel répond, nommé d'après le dépôt (stock_depot_DEPOT_E2E_NORD). 56. (technique) Demander le stock de l'officine est refusé (ce n'est pas un dépôt d'extension). 57. (technique) L'édition PDF refuse aussi l'officine (erreur 400). 58. (technique) L'édition par emplacement refuse l'officine de la même façon. 59. L'écran est collé au conteneur, sans en-tête en double ni défilement global. 60. Aucune erreur JavaScript pendant tout le parcours. 61. (technique) Tout ce que le test a posé est retiré. | H9: Le test supprime les deux dépôts d'essai et le stock qu'il y avait posé ; les rayons des articles sont seulement lus. | I9: retours/test-depot-extension-stock.js | J9: OK | K9: Joué le 30/10 15:33 — 61 / 61 conformes
A10: DEP-06 | B10: Gestion des dépôts d'extension : un seul écran à quatre onglets, un dépôt choisi en haut | C10: GESTION DES TIERS-PAYANTS > Gestion dépôts extensions | D10: L'officine veut un seul écran pour un dépôt : on choisit le dépôt une fois en haut et les onglets suivent (Saisir vente dépôt, Valorisation simple ou par emplacement, Chiffre d'affaires, Point de caisse). Le menu séparé « Vente du dépôt » disparaît ; chaque onglet a son privilège, sans rien retirer aux utilisateurs le jour de la livraison ; retirer un privilège retire l'onglet et ferme l'accès aux données. | E10: Connexion avec le compte administrateur, dont le rôle porte le privilège du chiffre d'affaires dépôt (P_DEPOT_EXT_CA). Le test automatique crée lui-même : un dépôt d'essai « DEPOT E2E ONGLETS » avec 3 articles répartis dans 2 rayons (stocks 10, 11 et 20) ; pour un test manuel, préparer : un dépôt d'extension avec des articles de deux rayons différents. | F10: 1. (Contrôle technique, fait par le test automatique) : vérifier en base que le menu « Vente du dépôt » n'existe plus, que son privilège est conservé, que le menu est rangé dans GESTION DES TIERS-PAYANTS avec le même identifiant, et que chaque onglet a un privilège porté par tous les rôles qui ouvrent l'écran. 2. Ouvrir GESTION DES TIERS-PAYANTS > Gestion dépôts extensions. 3. Observer les onglets, leurs couleurs et l'onglet ouvert. 4. Ouvrir l'onglet « Valorisation » et choisir le dépôt « DEPOT E2E ONGLETS » dans le sélecteur du haut. 5. Cliquer sur la vue par emplacement. 6. Ouvrir l'onglet « Saisir vente dépôt » et regarder le dépôt et le titre. 7. Remettre la saisie de vente à zéro (comme après une vente validée), puis vider le dépôt choisi en haut ; le choisir de nouveau. 8. Ouvrir l'onglet « Chiffre d'affaires », regarder la période et le bouton d'impression, puis cliquer sur la recherche. 9. Imprimer le chiffre d'affaires. 10. Ouvrir l'onglet « Point de caisse ». 11. Retirer le privilège P_DEPOT_EXT_CA au rôle du compte, se reconnecter dans une nouvelle session et rouvrir l'écran ; puis rendre le privilège. | G10: 1. Il existe des articles du dépôt dans plusieurs rayons. 2. (technique) Le menu séparé « Vente du dépôt » a disparu. 3. (technique) Son privilège P_VENTE_DEPOT_EXTENSION est conservé. 4. (technique) Le menu est dans GESTION DES TIERS-PAYANTS. 5. (technique) Il garde son identifiant et son privilège P_SM_DEPOT_EXTENSION. 6. (technique) Les quatre onglets ont chacun leur privilège. 7. (technique) Tout rôle qui ouvre l'écran garde chacun des quatre onglets (valorisation, vente, chiffre d'affaires, point de caisse). 8. L'écran s'ouvre. 9. Onglets « Saisir vente dépôt | Valorisation | Chiffre d'affaires | Point de caisse », la saisie de vente en premier. 10. L'écran s'ouvre sur la saisie de vente. 11. Chaque onglet a sa propre couleur. 12. C'est le fond de l'onglet qui est coloré, les quatre fonds sont différents. 13. Le libellé est blanc sur les quatre onglets. 14. L'onglet ouvert se distingue des autres (teinte pleine contre teinte claire). 15. (technique) Le serveur indique que l'opérateur a droit aux quatre onglets. 16. Un seul sélecteur de dépôt pilote l'écran. 17. La saisie de vente garde son propre champ dépôt. 18. Le dépôt se choisit une fois en haut de l'écran. 19. La vue simple liste les articles du dépôt (3). 20. La bascule affiche la vue par emplacement. 21. La valorisation est ventilée par rayon, sur au moins 2 lignes. 22. La somme des lignes = exactement le total du dépôt (valeur d'achat et valeur de vente). 23. « Total du dépôt » est rappelé sous la ventilation. 24. Le dépôt choisi en haut est prérenseigné dans la saisie de vente. 25. La saisie de vente est bien l'écran de vente complet (type de vente, contenu). 26. Le dépôt de la vente est en lecture seule et grisé. 27. Il porte le dépôt choisi en haut, et le titre le nomme. 28. Il n'est jamais encadré en erreur. 29. Après une vente validée, le dépôt est conservé, grisé, sans erreur. 30. Le titre nomme toujours le dépôt. 31. Sans dépôt choisi, le titre ne nomme aucun dépôt (« VENTE EN DÉPÔT »). 32. L'onglet Chiffre d'affaires propose une période et ne charge rien tout seul. 33. La période est par défaut celle du jour (début et fin = aujourd'hui). 34. L'impression est inactive avant toute recherche. 35. Colonnes dans l'ordre : type de vente, montant TTC, montant net, marge, nombre de ventes, montant espèces, montant tiers payant. 36. La colonne « règlement » a disparu. 37. Les 6 colonnes de montant ont un total. 38. Après la recherche, le récapitulatif nomme le dépôt et le nombre de vente(s). 39. Une note explique que l'argent est dans la caisse de l'opérateur et que le chiffre appartient au dépôt. 40. Une ligne TOTAL est affichée sous les lignes. 41. Le total du net = la somme des lignes. 42. L'impression devient active après la recherche. 43. Le chiffre d'affaires s'imprime en PDF, affiché dans l'onglet. 44. Le document est un vrai PDF. 45. Sans vente sur la période, l'édition indique « aucune vente sur la période ». 46. (technique) L'édition du chiffre d'affaires est refusée pour l'officine (erreur 400). 47. L'onglet Point de caisse affiche l'écran existant, avec sa grille. 48. Il porte les colonnes de l'écran Point Caisse Dépôt (dont « Caissière » et « Montant Net »). 49. Le dépôt choisi en haut est imposé au point de caisse. 50. (technique) Sans le privilège, le serveur ne propose plus l'onglet Chiffre d'affaires. 51. Sans le privilège, l'onglet est retiré de l'écran (3 onglets restants), pas seulement grisé. 52. L'écran reste utilisable et s'ouvre sur un onglet existant. 53. (technique) Le serveur refuse les données du chiffre d'affaires (« ne donne pas accès »). 54. (technique) L'édition est refusée elle aussi (403). 55. (technique) Le privilège est rendu à la fin du contrôle. 56. (technique) Aucune erreur JavaScript pendant tout le parcours. | H10: PRUDENCE : Retire temporairement le privilège P_DEPOT_EXT_CA au rôle du compte de test, puis le rend. Le test supprime le stock et le dépôt d'essai et rend le privilège P_DEPOT_EXT_CA au rôle du compte. | I10: retours/test-depot-onglets.js | J10: OK | K10: Joué le 30/10 23:29 — 59/59 verifications
A11: DEP-07 | B11: Retour carnet dépôt : un code lu contenant « / » ou « # » est transmis correctement | C11: GESTION DES TIERS-PAYANTS > Retour carnet dépôt | D11: La recherche du produit lu à la douchette dans le retour carnet dépôt mettait le code tel quel dans l'adresse : un code contenant « / » ou « # » partait coupé ou mal routé. | E11: Profil administrateur (compte de test). Au moins un tiers payant de type carnet dépôt ; s'il n'y en a aucun, le test automatique en crée un lui-même. Pour un test manuel, préparer un carnet dépôt. | F11: 1. Ouvrir GESTION DES TIERS-PAYANTS > Retour carnet dépôt. 2. Cliquer sur le bouton de retour (non précisé dans le test pour son libellé exact). 3. Choisir le premier tiers-payant de la liste. 4. Dans le champ « Produit », taper « E2E/12#3 » puis Entrée. | G11: 1. Un tiers-payant est bien choisi dans la liste. 2. (technique) Le code « E2E/12#3 » part encodé (E2E%2F12%233) et le serveur répond sans erreur. 3. Aucune erreur JavaScript. | H11: Rien n'est enregistré ; le carnet dépôt d'essai, s'il a été créé, est retiré. | I11: journal/test-retour-carnet-code-encode.js | J11: OK | K11: Joué le 30/10 15:33 — 4 / 4 conformes
A12: DEP-08 | B12: Vente en dépôt terminée par un profil autorisé, sans refus du serveur | C12: SERVICE CLIENT > Vente dépôt > Nouvelle vente | D12: Vérifier, après le contrôle serveur du 19/10 sur la clôture des ventes en dépôt (réservée aux menus « Vente dépôt », « Gestion depots extensions » ou « Ventes »), qu'un profil autorisé termine toujours une vente en dépôt normalement. | E12: Connexion avec le compte de test administrateur. Un article actif au CIP de 7 chiffres avec plus de 5 en stock. Si la base n'a aucun dépôt, le test automatique crée un dépôt d'essai « DEPOT E2E CLOTURE » ; si aucune caisse n'est ouverte, il ouvre une caisse d'essai. | F12: 1. Ouvrir « SERVICE CLIENT » > « Vente dépôt ». 2. Cliquer sur « Nouvelle vente ». 3. Choisir le premier dépôt de la liste. 4. Cliquer dans le champ produit, taper le CIP de l'article et valider par Entrée. 5. Dans la quantité, saisir 1 et appuyer sur Entrée. 6. Si le champ du montant reçu est affiché, y saisir le montant de la vente. 7. Cliquer sur « Terminer la vente ». | G12: 1. Le dépôt est choisi. 2. L'article est ajouté à la vente en dépôt. 3. La vente en dépôt est terminée ; (technique) le caissier est l'utilisateur connecté et le serveur ne refuse rien. 4. Aucune erreur JavaScript n'apparaît. 5. (technique) Vente retirée, stock remis. | H12: Le test supprime la vente, son règlement, sa recette et ses mouvements, les lignes de stock créées au dépôt, remet le stock de l'article, et retire le dépôt et la caisse d'essai s'il les a créés. | I12: securite/test-vente-depot-cloture.js | J12: OK | K12: Joué le 30/10 23:32 — 5/5 OK
A13: DEP-09 | B13: Vente en dépôt : dépôt demandé avant la saisie, stock et déstockage du dépôt | C13: SERVICE CLIENT > Ventes, bouton « Nouvelle vente » (menu lu dans la configuration des menus de l'application ; écran décrit par le test : (menu non précisé dans le test) > Vente en dépôt) | D13: Évolution 5, point 1 : saisir les ventes d'un dépôt d'extension comme si l'on s'y était connecté, sur un écran dupliqué de l'écran de vente. Le dépôt est demandé avant toute saisie ; la recherche montre le stock du dépôt ; la vente déstocke le dépôt et non l'officine ; l'encaissement va dans la caisse de l'opérateur ; le dépôt est redemandé après chaque vente ; l'écran de vente de l'officine reste inchangé. | E13: Connexion avec le compte de test. Un produit actif avec prix et code CIP, non déconditionné. Le test automatique crée lui-même : un dépôt d'extension « DEPOT E2E VENTE EN DEPOT » avec 40 unités du produit, met le stock officine du produit à 70, et ouvre une caisse d'essai si l'opérateur n'en a pas ; pour un test manuel, préparer : un dépôt d'extension tenant du stock d'un produit, et une caisse ouverte. | F13: 1. (Contrôle technique, fait par le test automatique) : vérifier que l'écran de vente de l'officine et celui du dépôt ne se partagent ni contrôleur ni fenêtres. 2. Ouvrir l'écran « Vente en dépôt » (menu : voir colonne « Écran ») et lire le titre. 3. Tenter de saisir un produit sans avoir choisi de dépôt ; fermer le message. 4. Ouvrir la liste des dépôts et choisir « DEPOT E2E VENTE EN DEPOT ». 5. Rechercher le produit d'essai et lire son stock. 6. (Contrôle technique, fait par le test automatique) : créer une vente de 2 unités du produit, puis la valider en espèces. 7. Après la vente, regarder le sélecteur de dépôt. 8. Ouvrir l'écran de vente habituel de l'officine. | G13: 1. (technique) Les deux contrôleurs (officine et dépôt) coexistent. 2. (technique) Aucun sélecteur de l'officine ne vise l'écran dépôt. 3. (technique) Aucun sélecteur de l'écran dépôt ne vise l'officine. 4. (technique) Les 8 fenêtres du clone existent. 5. (technique) Les 8 fenêtres du clone ont un type distinct de celles de l'officine. 6. L'écran « Vente en dépôt » s'ouvre. 7. Le titre annonce « VENTE EN DÉPÔT ». 8. Le sélecteur de dépôt est présent et vide. 9. Sans dépôt choisi, la saisie est refusée. 10. Un message explique qu'il faut choisir le dépôt. 11. La liste des dépôts d'extension est servie. 12. L'officine ne figure pas dans la liste des dépôts. 13. Le dépôt se choisit dans la liste. 14. (technique) Le contrôleur retient le dépôt choisi. 15. Le titre nomme le dépôt choisi : on ne peut pas confondre les deux écrans. 16. La fiche produit lue avec le dépôt rend le stock du dépôt (40). 17. (technique) La même fiche sans dépôt rend toujours le stock de l'officine (70). 18. (technique) La liste des produits de l'écran dépôt porte le paramètre du dépôt. 19. (technique) La liste des produits de l'officine n'a pas reçu ce paramètre. 20. (technique) La vente se crée depuis l'écran dépôt. 21. (technique) La vente porte le dépôt comme emplacement de vente. 22. (technique) La vente se valide. 23. Le dépôt est déstocké de 2. 24. L'officine n'est pas déstockée. 25. (technique) L'encaissement est dans la caisse de l'opérateur connecté. 26. (technique) Le mouvement du produit est historisé sur le dépôt. 27. Après la vente, le dépôt est redemandé (portée « à chaque vente »). 28. L'écran de vente de l'officine s'ouvre toujours. 29. L'écran de l'officine n'a pas de sélecteur de dépôt. 30. Le titre de l'officine est inchangé (« COMPTANT »). 31. (technique) Aucune erreur de page pendant tout le parcours. | H13: PRUDENCE : Modifie temporairement le stock officine d'un produit réel (remis à la fin) et peut ouvrir une caisse d'essai : à jouer sur un poste d'essai. Le test supprime la vente, ses lignes, règlements, mouvements et recettes, le stock et les références du dépôt, le dépôt d'essai et la caisse d'essai, puis remet le stock officine d'origine du produit. | I13: retours/test-vente-en-depot.js | J13: OK | K13: Joué le 30/10 23:29 — 31/31 verifications
A14: DEP-10 | B14: Chiffre d'affaires du dépôt séparé de l'officine, édition PDF et ventilation du ticket Z | C14: Sans écran (contrôle technique) | D14: Une vente jouée dans un dépôt d'extension laisse son argent dans la caisse de l'opérateur de l'officine. Son chiffre doit compter pour le dépôt et non pour l'officine, sans casser le chiffre de l'officine ; l'édition du chiffre d'affaires du dépôt s'imprime ; le ticket Z de l'opérateur garde le total et nomme la vente du dépôt (ligne « dont vente dépôt »). | E14: Connexion avec le compte administrateur. Le test automatique crée lui-même : un dépôt d'essai « DEPOT E2E CA » avec 60 unités d'un produit, le stock officine de ce produit mis à 80, une caisse ouverte si besoin ; pour un test manuel, préparer : un dépôt d'extension avec du stock et une caisse ouverte pour l'opérateur. | F14: 1. (Contrôle technique, fait par le test automatique) : créer et clôturer une vente au comptant de 3 unités dans le dépôt, réglée en espèces. 2. (Contrôle technique, fait par le test automatique) : créer et clôturer une vente d'officine ordinaire de 2 unités du même produit. 3. (Contrôle technique, fait par le test automatique) : lire la balance du jour du dépôt puis celle de l'officine. 4. (Contrôle technique, fait par le test automatique) : demander l'édition PDF du chiffre d'affaires du dépôt pour le jour. 5. (Contrôle technique, fait par le test automatique) : lire le récapitulatif du ticket Z de l'opérateur pour le jour (00:00 à 23:59). | G14: 1. (technique) La vente en dépôt est validée. 2. (technique) La vente d'officine est validée. 3. (technique) Les deux encaissements sont dans la caisse de l'opérateur, sur l'officine. 4. (technique) La balance du dépôt répond. 5. (technique) La balance de l'officine répond. 6. (technique) Le CA du dépôt = exactement le montant de la vente jouée dans le dépôt. 7. (technique) Le CA de l'officine = seulement sa propre vente ; la vente du dépôt en est retirée. 8. (technique) Les deux CA ne se recouvrent pas : leur somme = le total des deux ventes. 9. L'édition du CA du dépôt est servie en PDF, affichée dans l'onglet. 10. Le fichier est un vrai PDF. 11. L'édition porte « CHIFFRE D'AFFAIRES - DEPOT E2E CA », la période et les colonnes MONTANT TTC, MONTANT NET, MARGE, NBRE VENTES, MONTANT ESP, TIERS PAYANT. 12. L'édition n'a plus de colonne « RÈGLEMENT ». 13. L'édition porte une ligne TOTAL et le montant de la vente du dépôt. 14. L'édition est paginée (« Page 1 ») et rappelle que l'argent est dans la caisse de l'opérateur. 15. (technique) Le ticket Z répond. 16. Le ticket Z nomme la vente en dépôt : ligne « dont vente dépôt » avec le nom du dépôt. 17. Le montant ventilé = celui de la vente en dépôt. 18. Le total du ticket Z est inchangé : il comprend les deux ventes, celle du dépôt comprise. 19. La ventilation ne s'ajoute pas au total : elle en fait partie. 20. (technique) Aucune erreur dans la page. | H14: Le test supprime les deux ventes (lignes, règlements, mouvements), le stock et le dépôt d'essai, la caisse d'essai, et remet le stock officine d'origine. | I14: retours/test-ca-depot.js | J14: OK | K14: Joué le 30/10 15:33 — 20 / 20 conformes
A15: DEP-11 | B15: Vente sur le stock d'un dépôt d'extension, argent dans la caisse de l'opérateur | C15: Sans écran (contrôle technique) | D15: Évolution 5, point 1 (fondations) : une vente peut porter un dépôt d'extension comme lieu de vente. Elle déstocke alors le dépôt et pas l'officine, et l'argent va dans la caisse de l'opérateur connecté ; une vente d'officine reste identique ; un dépôt inconnu est ignoré ; l'annulation rend le stock au dépôt. | E15: Connexion avec le compte d'essai, avec une caisse ouverte (le test en ouvre une si besoin). Un article simple (non déconditionné) en stock à l'officine. Le test automatique crée lui-même : un dépôt d'extension « DEPOT E2E VENTE », 50 boîtes de l'article dans ce dépôt, et fixe le stock officine de l'article à 60 (remis à la fin). | F15: 1. Se connecter avec le compte d'essai. 2. (Contrôle technique, fait par le test automatique) : créer et clôturer une vente comptant de 3 boîtes sans dépôt, comme l'écran de vente. 3. (Contrôle technique, fait par le test automatique) : créer et clôturer la même vente en précisant le dépôt d'essai. 4. (Contrôle technique, fait par le test automatique) : créer des ventes avec un dépôt inconnu, avec l'officine comme dépôt, et avec un dépôt vide. 5. (Contrôle technique, fait par le test automatique) : annuler la vente du dépôt. 6. Ouvrir l'écran de vente. | G15: 1. (technique) Précondition : l'article est tenu par l'officine et par le dépôt. 2. (technique) La vente d'officine se crée comme avant. 3. (technique) Sans dépôt, la vente ne porte aucun lieu de vente. 4. (technique) La vente d'officine se valide. 5. (technique) Elle déstocke l'officine. 6. (technique) Elle ne touche pas le stock du dépôt. 7. (technique) Son mouvement de caisse reste sur l'officine et sur l'opérateur. 8. (technique) Son mouvement produit est historisé sur l'officine. 9. (technique) La vente sur le dépôt se crée. 10. (technique) Elle porte le dépôt comme lieu de vente. 11. (technique) Elle se valide. 12. (technique) Elle déstocke le dépôt. 13. (technique) Elle ne touche pas le stock de l'officine. 14. (technique) Son mouvement produit est historisé sur le dépôt. 15. (technique) L'argent reste dans la caisse de l'opérateur connecté. 16. (technique) Le montant encaissé est celui de la vente. 17. (technique) La référence de la vente est numérotée sur le dépôt. 18. (technique) Un dépôt inconnu est ignoré : vente d'officine. 19. (technique) L'officine donnée comme dépôt est ignorée. 20. (technique) Un dépôt vide est ignoré. 21. (technique) L'annulation de la vente du dépôt aboutit. 22. (technique) L'annulation rend le stock au dépôt. 23. (technique) Elle ne gonfle pas le stock de l'officine. 24. L'écran de vente s'ouvre. 25. L'écran de vente est rendu. 26. Aucune erreur de page pendant le parcours. | H15: Le test supprime les ventes d'essai (et leurs annulations, règlements, mouvements, recettes), le stock et les références du dépôt, le dépôt d'essai et la caisse ouverte pour l'essai, et remet le stock d'origine de l'article à l'officine. | I15: retours/test-vente-contexte-depot.js | J15: OK | K15: Joué le 30/10 15:33 — 26 / 26 conformes

Sheet Ordonnances
A1: CAHIER DE RECETTE — ORDONNANCES
A2: Version testée : branche integration/recette-2026-10-29 (21ddcd3d), déployée sur le poste local (port 8080), copie de l'officine restaurée le 30/10
A3: 21 cas — Claude : 18 OK, 3 en échec, 0 non joués
A4: N° | B4: Cas de test | C4: Écran (menu) | D4: Objectif | E4: Existant (avant de commencer) | F4: Étapes | G4: Résultats attendus | H4: Nettoyage / prudence | I4: Test automatique | J4: Résultat Claude | K4: Détail Claude | L4: Résultat testeur | M4: Commentaire testeur | N4: Testeur | O4: Date | P4: Résultat Claude confirmé ?
A5: ORD-01 | B5: Ordonnancier : médecin, client, détail, recherche, impression, export, inventaire, analyse | C5: Ordonnancier (menu non précisé dans le test), onglets « Registre » et « Analyse » | D5: Corriger quatre défauts de l'ordonnancier : colonne Médecin vide, (+) ouvrant une zone vide, nom du patient absent, et impossibilité de chercher un client, d'imprimer, d'exporter ou de faire un inventaire des produits délivrés. Vérifier aussi le nouvel onglet Analyse. | E5: Connexion avec le compte de test habituel (administrateur). Au moins trois produits avec un code tableau (A, C ou II) et deux clients existants. Le test automatique crée lui-même : un médecin « DOCTEUR ESSAI ORDONNANCIER » (n° d'ordre E2E-9001), trois ventes clôturées du 05/09/2026 rattachées à ce médecin (références E2EORD-REF-1 à 3 ; la première avec deux produits, quantités 2 et 3 ; les autres avec un produit, quantité 2 ; un client servi deux fois), et marque les trois produits comme soumis à ordonnance. Pour un test manuel, préparer ces mêmes ventes sur un jour sans autre vente avec médecin. | F5: 1. Se connecter. 2. Ouvrir l'ordonnancier et choisir la période du 05/09/2026 au 05/09/2026. 3. Lire les colonnes Médecin et Client des trois délivrances. 4. Cliquer sur le (+) de la vente E2EORD-REF-1, puis de E2EORD-REF-3. 5. Chercher le nom du second client, puis la référence « E2EORD-REF-3 », puis « ZZZ-INEXISTANT », puis vider la recherche. 6. Filtrer par le médecin d'essai. 7. Imprimer le registre. 8. Exporter le registre en Excel. 9. Lancer l'inventaire des produits délivrés (contrôle, puis création). 10. Ouvrir l'onglet « Analyse » : lire les indicateurs et les palmarès produits, clients et médecins. 11. Dans l'Analyse, chercher « E2EORD-REF-3 », puis limiter le palmarès à 1. 12. Imprimer puis exporter en Excel l'analyse. 13. (Contrôle technique, fait par le test automatique) : appeler le détail d'une vente inconnue, vérifier la fenêtre de détail et le modèle de données de l'écran. | G5: 1. Les trois délivrances du jour remontent. 2. La colonne Médecin affiche « DOCTEUR ESSAI ORDONNANCIER ». 3. Le numéro d'ordre E2E-9001 suit le médecin. 4. (technique) La liste ne transporte aucun produit (détail chargé à la demande). 5. (technique) Le modèle de données de l'écran ne retient pas de produits. 6. Le détail de E2EORD-REF-1 se charge à la demande et montre 2 produits. 7. Chaque produit porte son code tableau (A, C ou II). 8. Chaque produit porte son CIP, sa quantité et son montant. 9. Le détail de E2EORD-REF-3 montre 1 produit. 10. (technique) Une vente inconnue rend une liste vide, pas une erreur. 11. La fenêtre de détail nomme la vente ouverte (E2EORD-REF-1). 12. (technique) Elle interroge le détail de l'ordonnancier. 13. Elle montre une colonne Tableau. 14. (technique) La même fenêtre sert aux suppressions de vente, sans colonne Tableau. 15. La colonne Client est renseignée sur chaque ligne. 16. La recherche par nom du second client ne rend que E2EORD-REF-2. 17. La recherche par référence ne rend que E2EORD-REF-3. 18. Une recherche sans résultat ne rend rien. 19. Une recherche vide rend les 3 délivrances. 20. Le filtre par médecin rend les 3 délivrances. 21. (technique) Un médecin inconnu ne rend rien. 22. L'édition PDF aboutit. 23. (technique) Le fichier PDF est écrit sur le disque. 24. L'édition porte le titre ORDONNANCIER. 25. L'édition nomme le médecin. 26. L'édition compte une ligne par produit délivré : E2EORD-REF-1 y apparaît 2 fois. 27. L'export Excel répond. 28. L'export Excel n'est pas vide (plus de 2 000 octets). 29. L'export est bien un fichier Excel. 30. Le contrôle d'inventaire compte 3 produits distincts. 31. Le contrôle compte 3 délivrances. 32. (technique) Le contrôle ne crée aucun inventaire. 33. L'inventaire est créé avec 3 produits. 34. L'inventaire porte un nom commençant par « INVENTAIRE ORDONNANCIER ». 35. L'analyse répond. 36. Elle compte 3 délivrances (pas 4 lignes). 37. Elle compte 4 lignes de produit. 38. Elle compte 3 produits distincts. 39. Elle compte 2 clients distincts. 40. Elle compte 1 médecin prescripteur. 41. Elle totalise 9 unités. 42. Elle totalise 5 000 de montant. 43. Le palmarès des produits a 3 lignes. 44. Il est trié par quantité décroissante. 45. Chaque produit du palmarès porte son CIP et son code tableau. 46. Le client servi deux fois compte 2 délivrances. 47. Le médecin totalise les 3 délivrances. 48. Le numéro d'ordre E2E-9001 suit le médecin dans le palmarès. 49. La recherche E2EORD-REF-3 filtre aussi l'analyse : 1 délivrance, 1 produit au palmarès. 50. La limite à 1 coupe le palmarès sans changer les indicateurs (3 produits distincts). 51. L'édition PDF de l'analyse aboutit. 52. (technique) Le PDF de l'analyse est écrit sur le disque. 53. L'export Excel de l'analyse répond et n'est pas vide. 54. L'écran a deux onglets. 55. Les onglets s'appellent « Registre » et « Analyse ». 56. Les filtres (dates, recherche, médecin) valent pour les deux onglets. 57. (technique) La grille du registre est bien identifiée. 58. Les trois palmarès (produits, clients, médecins) sont présents. 59. L'onglet Analyse a ses actions : imprimer, exporter, inventaire, limite du palmarès. 60. Rien n'est calculé tant que l'onglet Analyse n'est pas ouvert. 61. Aucune erreur JavaScript. 62. (technique) Le jeu d'essai est entièrement retiré et les produits retrouvent leur réglage d'origine. | H5: Le test retire les ventes, le médecin et les inventaires « INVENTAIRE ORDONNANCIER » créés, et remet le réglage « soumis à ordonnance » d'origine des trois produits. | I5: etape3/test-ordonnancier.js | J5: OK | K5: Joué le 30/10 15:33 — 62 / 62 conformes
A6: ORD-02 | B6: Passerelle Posos : analyse des interactions avec un serveur Posos simulé | C6: SERVICE CLIENT > Analyse Posologie (menu lu dans la configuration des menus de l'application ; écran décrit par le test : Analyse Posos (menu non précisé dans le test)) | D6: Évolution 5 (point 9) : la passerelle Posos analyse les produits d'une ordonnance ou d'une vente. Sans configuration, un mode démonstration répond ; configurée, elle s'authentifie, n'envoie que les noms des produits et un contexte clinique sans identité du patient, ne laisse jamais sortir le secret, signale les produits non analysés, et une panne ne fait jamais croire qu'il n'y a pas d'alerte. | E6: Connexion avec le compte de test habituel (administrateur). Au moins deux articles actifs avec un prix. Le test automatique démarre lui-même un faux serveur Posos sur le poste (port 18099), écrit temporairement le fichier de configuration posos.properties attendu par l'application (identifiant et secret d'essai), et crée une vente clôturée de référence « E2EPOSOS1 » avec deux articles (quantités 2 et 3). | F6: 1. Se connecter. 2. (Contrôle technique, fait par le test automatique) : lire le statut de la passerelle et l'emplacement attendu du fichier de configuration. 3. (Contrôle technique, fait par le test automatique) : sans fichier de configuration, lire le statut et analyser « DOLIPRANE 500MG CPR B/16 ». 4. (Contrôle technique, fait par le test automatique) : configurer « POSOS_MODE=aucun » et analyser « PARACETAMOL 500 MG ». 5. (Contrôle technique, fait par le test automatique) : configurer l'adresse du faux serveur, l'identifiant et le secret d'essai ; relire le statut. 6. (Contrôle technique, fait par le test automatique) : analyser IBUPROFENE 400 MG COMPRIME (2, « 1 matin et soir »), ASPIRINE 500 MG COMPRIME (1) et TISANE MAISON, avec le contexte : 72 ans, femme, insuffisance rénale ; puis analyser PARACETAMOL 500 MG. 7. (Contrôle technique, fait par le test automatique) : analyser la vente par sa référence E2EPOSOS1. 8. (Contrôle technique, fait par le test automatique) : simuler une panne du serveur Posos (erreur 500) et analyser PARACETAMOL 500 MG. 9. Ouvrir l'écran « Analyse Posos » et lire le bandeau d'état. 10. Ajouter la ligne IBUPROFENE 400 MG COMPRIME (CIP 1234567, quantité 2, « 1 matin et soir »). 11. Cliquer sur « Analyser » et lire la grille des alertes et le message. | G6: 1. (technique) L'application annonce l'emplacement absolu de son fichier « posos.properties ». 2. (technique) Ce fichier est attendu dans le même dossier de configuration que dicisms.properties. 3. (technique) Sans configuration, le statut annonce le mode démonstration. 4. (technique) Le statut dit que le fichier est absent. 5. (technique) Sans configuration, l'analyse vient des règles de démonstration (avertissement « DÉMONSTRATION »), sans aucun appel à Posos. 6. (technique) Avec POSOS_MODE=aucun, aucune analyse n'est tentée et le message dit que Posos n'est « pas configuré ». 7. (technique) La configuration est prise en compte sans redémarrage. 8. (technique) Le statut signale le fichier comme présent. 9. (technique) Le statut ne rend ni le secret ni l'identifiant en clair. 10. (technique) L'identifiant est masqué (« **** ») et le secret n'apparaît que comme « renseigné ». 11. (technique) L'analyse aboutit. 12. (technique) Deux alertes sont rendues, dont une seule majeure. 13. (technique) Les produits concernés par l'alerte sont rendus (IBUPROFENE, ASPIRINE). 14. (technique) Le produit non reconnu (TISANE MAISON) est signalé comme non analysé. 15. (technique) Le jeton est demandé en mode client_credentials. 16. (technique) Le secret part dans l'en-tête d'authentification, jamais dans le corps. 17. (technique) L'analyse est appelée avec le jeton obtenu. 18. (technique) Les produits partent par leur nom. 19. (technique) La posologie saisie est transmise. 20. (technique) Le contexte envoyé est clinique (âge, sexe, insuffisance rénale) et rien n'identifie le patient (ni nom, ni prénom, ni téléphone, ni n° de sécurité sociale). 21. (technique) Le jeton est réutilisé, pas redemandé à chaque analyse. 22. (technique) La vente est analysable par sa référence. 23. (technique) Les deux produits de la vente sont relus en base et renvoyés à l'écran. 24. (technique) Ce sont les noms des produits de la vente qui partent, avec leurs quantités. 25. (technique) Une panne de Posos donne « indisponible » (message mentionnant 500) et non « aucune alerte ». 26. L'écran « Analyse Posos » s'ouvre. 27. Le bandeau annonce que Posos est configuré, avec l'identifiant masqué (« **** »). 28. Le bandeau ne montre aucun secret. 29. Le produit ajouté apparaît dans la liste à analyser. 30. Le bouton « Analyser » est actif et cliquable. 31. L'alerte « Association déconseillée » s'affiche dans la grille, marquée majeure. 32. Le message signale l'alerte majeure (« absolument ») et le produit non analysé TISANE MAISON. 33. Aucune erreur de page. | H6: PRUDENCE : Le test écrit temporairement le fichier de configuration Posos du serveur et démarre un faux serveur Posos local : à jouer uniquement sur un poste d'essai, jamais avec un vrai compte Posos. Le test remet le fichier de configuration Posos d'origine (ou le supprime s'il n'existait pas), retire la vente d'essai et arrête le faux serveur Posos. | I6: retours/test-posos.js | J6: OK | K6: Joué le 30/10 15:33 — 33 / 33 conformes
A7: ORD-03 | B7: Analyse Posos en mode démonstration : alertes, avertissement et produits non couverts | C7: SERVICE CLIENT > Analyse Posologie ; SERVICE CLIENT > Suivi dossier client (menu lu dans la configuration des menus de l'application ; écran décrit par le test : (menu non précisé dans le test) > Analyse posologie ; Ordonnances clients) | D7: Mode démonstration provisoire de l'analyse Posos, activé côté serveur : un bandeau rouge l'annonce, les associations déconseillées et contre-indications sont signalées avec leur source, un produit inconnu des règles est dit « non couvert » sans alerte inventée, et la désactivation remet la passerelle non configurée. | E7: Connexion avec le compte de test. Le test crée lui-même les produits SINTROM 4MG, BRUFEN 400MG et TAHOR 20MG s'ils manquent, une ordonnance Doliprane 1 g + Efferalgan codéine (allaitement) pour un client existant, et ajoute « POSOS_MODE=demonstration » au fichier posos.properties du poste ; pour un test manuel, préparer : ces produits, cette ordonnance et ce réglage. | F7: 1. Ouvrir l'écran « Analyse posologie » (menu : voir colonne « Écran ») et regarder l'état de la passerelle. 2. Dans le champ produit, taper « SINTROM » et choisir SINTROM 4MG CPR SEC B/30. 3. Taper « BRUFEN 400 » et choisir BRUFEN 400MG CPR DRG B/30. 4. Taper « TAHOR 20 » et choisir TAHOR 20MG CPR B/28. 5. Cliquer sur « Analyser » et lire les alertes et le message. 6. Ouvrir les ordonnances clients, ouvrir l'ordonnance d'essai et cliquer sur le bouton d'analyse Posos de la fiche. 7. (Contrôle technique, fait par le test automatique) : retirer la ligne POSOS_MODE et lire l'état de Posos ; puis poser POSOS_MODE=aucun et relire. | G7: 1. Bandeau rouge « MODE DÉMONSTRATION » et bouton « Analyser » actif. 2. Sintrom + Brufen : « Association déconseillée » en tête, risque hémorragique. 3. La conduite à tenir propose le paracétamol et cite « Source : Thésaurus ANSM ». 4. L'avertissement DÉMONSTRATION accompagne le résultat (contenu « NON ENCORE VALIDÉ »). 5. Tahor, inconnu des règles : dit « non couvert », aucune alerte inventée à son sujet. 6. (technique) L'ordonnance Doliprane 1 g + Efferalgan codéine (allaitement) est créée. 7. Fiche : contre-indication (codéine et allaitement) en tête, doublon de paracétamol « Majeure ». 8. Fiche : les alertes majeures sont en rouge, l'avertissement DÉMONSTRATION est affiché. 9. Forme effervescente : le sodium est signalé. 10. (technique) Sans la ligne POSOS_MODE et sans accès Posos : la démonstration reste active d'elle-même. 11. (technique) POSOS_MODE=aucun : la démonstration se désactive, la passerelle se dit non configurée. 12. (technique) Aucune erreur JavaScript. | H7: PRUDENCE : Modifie temporairement le fichier de configuration posos.properties du poste : à jouer sur un poste d'essai. Le test remet le fichier posos.properties d'origine, supprime l'ordonnance d'essai (marquée E2E-DEMO) et retire les produits qu'il a créés. | I7: retours/test-posos-demonstration.js | J7: Échec | K7: Joué le 30/10 15:33 — 11 / 12 conformes Écart : POSOS_MODE=aucun : la démonstration se désactive, la passerelle se dit non configurée [{"mode":"posos","configuree":true}]
A8: ORD-04 | B8: Analyse posologie : équivalents en rayon proposés et remplacement sur l'ordonnance | C8: SERVICE CLIENT > Analyse Posologie ; SERVICE CLIENT > Suivi dossier client (menu lu dans la configuration des menus de l'application ; écran décrit par le test : Écran « Analyse posologie » puis fiche d'ordonnance client (menu non précisé dans le test)) | D8: Demande du 23/09 : quand l'analyse signale une association déconseillée (Sintrom + Brufen), elle recommande le paracétamol et montre dans la colonne « EN RAYON » les produits de paracétamol du catalogue ; sur la fiche d'ordonnance, « Remplacer » change la ligne et vide sa posologie. Une précaution d'espacement ne propose rien. | E8: Connexion avec le compte de test. Le service d'analyse posologie en mode démonstration (le test l'active le temps de l'essai dans sa configuration). Des produits de paracétamol au catalogue. Le test automatique crée lui-même : les produits de la démonstration absents du catalogue (dont SINTROM 4MG et BRUFEN), les liens DCI du paracétamol, et une ordonnance d'essai Sintrom + Brufen. | F8: 1. Ouvrir l'écran « Analyse posologie ». 2. Taper au clavier les produits Sintrom et Brufen et lancer l'analyse. 3. Lire l'alerte, la recommandation et la colonne « EN RAYON ». 4. Ouvrir l'écran des ordonnances clients et ouvrir en modification l'ordonnance d'essai Sintrom + Brufen. 5. Regarder les icônes « produits proposés » des alertes ; cliquer sur celle de l'alerte qui recommande. 6. Dans le panneau, cliquer sur « Remplacer » pour le premier produit proposé. | G8: 1. Analyse posologie : l'alerte AVK + AINS (« Association déconseillée ») recommande le paracétamol. 2. Colonne « EN RAYON » : les produits de paracétamol du catalogue (tous, au plus 8). 3. En stock d'abord ; stock en bleu (ou rouge à 0), prix en rouge. 4. (technique) Précondition : ordonnance Sintrom + Brufen créée. 5. Fiche : l'icône « produits proposés » est active sur l'alerte qui recommande, grisée sur les autres. 6. Le panneau montre les produits proposés, marqués « Proposé (analyse) », et dit quelle ligne sera remplacée. 7. « Remplacer » : le Brufen devient le produit choisi, sa posologie est vidée et le curseur y est placé ; la ligne Sintrom est inchangée. 8. Aucune erreur JavaScript. 9. (technique) Remise en état (configuration, liens DCI, ordonnance de test). | H8: PRUDENCE : Modifie temporairement le fichier de configuration du service d'analyse posologie (mode démonstration) : à jouer uniquement sur un serveur d'essai. La configuration du service d'analyse posologie est remise, les liens DCI, produits et l'ordonnance d'essai sont retirés. | I8: retours/test-posos-equivalents.js | J8: Échec | K8: Joué le 30/10 15:33 — 0 / 2 conformes Écart : Le parcours va au bout [Command failed: mariadb --defaults-extra-file=C:/Users/AIRMAN/AppData/Local/Temp/claude/D--projet-p3-prestige/4660ea01-cd8f-49ab-bd78-f6382d44836c/scratchpad/e2e-1776.cnf --default-character-set=utf8mb4 laborex_v1_db -e INSERT INTO t_famille_dci (lg_FAMILLE_DCI_ID, lg_FAMILLE_ID, lg_DCI_ID, str_STATUT, dt_CREATED, dt_UPDATED) SELECT 'E2E-EQV-0', f.lg_FAMILLE_ID, '', 'enable', NOW(), NOW() FROM t_f] Remise en état (configuration, liens DCI, ordonnance de test)
A9: ORD-05 | B9: Gestion des ordonnances clients : saisie, historique, modification, annulation, droits | C9: SERVICE CLIENT > Suivi dossier client | D9: Évolution 6 (point 2, vague 1) : saisir de bout en bout une ordonnance client, plusieurs par client sans remplacement, historique filtrable, modification qui garde le numéro, annulation qui garde le document, et garantie qu'aucune vente ni aucun mouvement de stock n'est créé. Sans le droit d'écriture, les boutons disparaissent et le serveur refuse. | E9: Compte d'essai des tests automatiques (administrateur), avec les droits de consulter et de saisir les ordonnances (le test retire puis rend le droit d'écriture). Le test automatique crée lui-même : deux clients d'essai « ZZORDOTEST » (type Standard) et « ZZORDOAUTRE » (type Carnet), un médecin d'essai « DOCTEUR ZZORDO ». Pour un test manuel, préparer : ces clients et ce médecin. | F9: 1. (Contrôle technique, fait par le test automatique) : vérifier en base le menu, ses libellés et ses deux droits. 2. Se connecter avec le compte d'essai. 3. Ouvrir SERVICE CLIENT > Suivi dossier client. 4. Cliquer sur « Nouvelle ordonnance ». 5. Rechercher et choisir le client « ZZORDOTEST ». 6. Choisir le prescripteur « DOCTEUR ZZORDO », saisir l'établissement « CHU DE COCODY » et l'observation « Ordonnance de contrôle, à renouveler dans 3 mois. ». 7. Ligne 1 : un article du référentiel, quantité 2, posologie « 1 cp matin et soir », durée « 7 jours ». 8. Ajouter une ligne libre : « SIROP PRESCRIT NON TENU », quantité 1, « 5 ml le soir », « 10 jours ». 9. Cliquer sur « Enregistrer ». 10. Consulter l'historique du client. 11. (Contrôle technique, fait par le test automatique) : enregistrer deux autres ordonnances pour ce client, datées d'hier (« PARACETAMOL PRESCRIT ») et d'avant-hier (« AMOXICILLINE PRESCRITE »). 12. Filtrer l'historique : type de client Carnet, puis Standard ; période = hier ; prescripteur ; recherche par numéro ; recherche « CHU DE COCODY ». 13. Ouvrir la première ordonnance et la modifier : établissement « CHU DE TREICHVILLE », un seul produit « PRODUIT CORRIGÉ », quantité 3, « 2 cp le matin », « 5 jours ». 14. (Contrôle technique, fait par le test automatique) : essayer d'enregistrer sans client, sans date, sans produit, puis datée de demain. 15. Annuler l'ordonnance sans motif, puis avec le motif « Ordonnance saisie sur le mauvais client ». 16. Essayer de modifier l'ordonnance annulée. 17. Regarder l'historique courant, puis avec les ordonnances annulées. 18. Retirer au rôle le droit de saisir les ordonnances, se reconnecter et ouvrir de nouveau l'écran. | G9: 1. (technique) Le menu « Suivi dossier client » est dans SERVICE CLIENT, sous son droit. 2. (technique) Libellé et description restent courts (25 et 30 caractères au plus). 3. (technique) Deux droits distincts : consulter, et saisir / modifier. 4. L'écran s'ouvre. 5. (technique) Le serveur indique que l'opérateur peut consulter et modifier. 6. « Nouvelle ordonnance » ouvre la fiche dans l'écran, sans fenêtre surgissante. 7. La date est préremplie au jour et une ligne de produit est amorcée. 8. Le client se cherche et se choisit dans la fiche. 9. Le prescripteur vient du référentiel des médecins. 10. L'établissement se saisit librement (« CHU DE COCODY »). 11. L'ordonnance est enregistrée avec un numéro lisible ORD-AAAAMM-0001. 12. (technique) Elle porte sa date, son établissement, ses deux produits et son statut. 13. (technique) Le produit prescrit mais non tenu est accepté sans article du référentiel. 14. (technique) Le produit du référentiel garde son libellé recopié et sa quantité prescrite (2). 15. (technique) L'auteur et la date de création sont conservés. 16. L'historique du client montre l'ordonnance, avec le prescripteur, 2 produits et l'auteur de la saisie. 17. (technique) Deux ordonnances de plus sont enregistrées, chacune avec son numéro. 18. (technique) Aucune n'a remplacé les précédentes (3 ordonnances). 19. L'historique va de la plus récente à la plus ancienne. 20. Filtre « Carnet » : aucune ordonnance. 21. Filtre « Standard » : les 3 ordonnances. 22. Filtre de période (hier) : seulement l'ordonnance d'hier. 23. Filtre par prescripteur : seulement son ordonnance. 24. La recherche par numéro trouve le document. 25. La recherche par établissement trouve le document. 26. La fiche rend les produits dans l'ordre de saisie. 27. Le produit référencé a son CIP, le produit libre n'en a pas. 28. La modification est acceptée et garde le numéro. 29. (technique) Les produits sont remplacés (« CHU DE TREICHVILLE », 1 produit « PRODUIT CORRIGÉ ») et le modificateur est tracé. 30. (technique) Sans client : refus. 31. (technique) Sans date : refus. 32. (technique) Sans produit : refus. 33. (technique) Datée de demain : refus (date future). 34. Une annulation sans motif est refusée. 35. L'annulation avec motif est enregistrée. 36. (technique) Le document reste, annulé, avec son motif. 37. (technique) Ses produits restent aussi. 38. Une ordonnance annulée ne peut plus être modifiée. 39. L'historique courant masque l'ordonnance annulée (2 affichées). 40. Elle reste consultable en demandant les annulées (3, dont 1 annulée). 41. (technique) Sans le droit d'écriture, le serveur n'accorde que la consultation. 42. Sans ce droit, « Nouvelle ordonnance » disparaît et « Modifier » / « Annuler » sont grisés sur chaque ligne. 43. (technique) Le serveur refuse l'écriture même appelé directement. 44. (technique) La consultation reste possible. 45. (technique) Le droit est rendu à la fin du contrôle. 46. (technique) Aucune vente n'a été créée par ce menu. 47. (technique) Aucun mouvement de stock n'a été écrit. 48. (technique) Aucune unité de stock n'a bougé. 49. Aucune erreur JavaScript pendant tout le parcours. 50. (technique) Tout ce que le test a posé est retiré. | H9: Le test supprime les ordonnances, les deux clients et le médecin d'essai, et rend le droit d'écriture au rôle. | I9: retours/test-ordonnances-clients.js | J9: OK | K9: Joué le 30/10 15:33 — 50 / 50 conformes
A10: ORD-06 | B10: Ordonnances : fiche client, paramètres et normes, terrains et allergies, consultation | C10: SERVICE CLIENT > Suivi dossier client (menu lu dans la configuration des menus de l'application ; écran décrit par le test : (menu non précisé dans le test) > Ordonnances client (onglets Historique, Fiche client, Terrains, allergies et paramètres)) | D10: Vérifier les retours du 30/09 sur les ordonnances : onglet Fiche client (identité, tuiles des paramètres suivis, terrains et allergies du dossier, saisie des mesures avec normes et IMC, courbe en fenêtre), reprise du dossier sur une ordonnance, consultation en lecture, recherche produit rapide et onglet de paramétrage. | E10: Connexion avec le compte de test administrateur ; les terrains « DIABETE » et « ALLERGIE_PENICILLINE » existent ; 8 paramètres cliniques actifs ; un article actif avec plus de 5 en stock. Le test automatique crée lui-même un client d'essai « ZZFICHE AWA », né le 10/05/1980, téléphone 0707123456 ; pour un test manuel, créer un client d'essai équivalent. | F10: 1. Ouvrir l'écran des ordonnances client. 2. (Contrôle technique, fait par le test automatique) : mesurer la recherche produit des ordonnances avec les 5 premières lettres d'un article. 3. Regarder la fiche ordonnance et la liste des onglets. 4. Ouvrir l'onglet « Fiche client », taper « ZZFICHE » dans la recherche du client et choisir le client au clavier (flèche bas, Entrée). 5. Lire l'identité et les tuiles des paramètres. 6. Cliquer sur la puce du terrain Diabète et celle de l'allergie à la pénicilline, saisir « Iode (examen 2024) » dans les allergies, et enregistrer le dossier. 7. Cliquer sur la tuile « Tension artérielle » ; saisir 150 en systolique du bras gauche et cliquer sur « Ajouter ». 8. Saisir 95 en diastolique, le commentaire « au repos », appuyer sur Entrée ; puis saisir 120 / 80 pour le bras droit et appuyer sur Entrée. 9. Cliquer sur le bouton « Courbe » de la tuile de la tension, lire la fenêtre puis la fermer. 10. Cliquer sur « Glycémie à jeun » et saisir 1,32 + Entrée ; sur « Poids » et saisir 80 + Entrée ; sur « Taille » et saisir 175 + Entrée, puis 1750 + Entrée. 11. Cliquer sur « Glycémie à jeun », retirer la mesure et confirmer par « Oui ». 12. Revenir à l'onglet Historique, cliquer sur « Nouvelle », taper « ZZFICHE » et choisir le client. 13. Saisir le poids 82, rechercher l'article et le choisir au clavier, taper « 1 cp le soir » + Entrée, puis cliquer sur « Enregistrer ». 14. Ouvrir cette ordonnance en consultation. 15. Ouvrir l'onglet « Terrains, allergies et paramètres », cliquer sur « Ajouter un paramètre », taper « ZZFICHE Cholestérol total » et appuyer sur Entrée. | G10: 1. (technique) La recherche produit des ordonnances répond en moins de 300 ms, avec le stock. 2. Le bouton « Ajouter un produit » n'est plus sur la fiche. 3. Onglets : Historique, Fiche client (2e), Analyse des ordonnances, Terrains, allergies et paramètres. 4. La fiche montre l'identité : ZZFICHE AWA, type Standard, 0707123456, né le 10/05/1980, âge en années. 5. Une tuile par paramètre actif (8 au départ), dont « Tension artérielle » et « Glycémie à jeun ». 6. Le dossier enregistre un terrain et une allergie cochés (couleurs terrain / allergie) et l'allergie en texte libre « Iode (examen 2024) ». 7. Tension choisie : champs bras gauche / droit (systolique, diastolique), pas de valeur unique. 8. Après le choix d'un paramètre, le curseur est dans le champ de saisie (bras gauche systolique). 9. Systolique sans diastolique : refus expliqué (« la systolique ET la diastolique »). 10. (technique) Tension enregistrée : bras gauche seul 150/95, puis bras droit seul 120/80. 11. Selon la norme adulte : 150/95 « Élevée », 120/80 « Normale ». 12. La courbe n'est plus dans la page ; un bouton « Courbe » est sur les tuiles qui ont des mesures. 13. Le clic sur « Courbe » ouvre la courbe de la tension dans une fenêtre (points, bande des valeurs normales). 14. La courbe a la bande des valeurs normales « 90 - 139 / 60 - 89 » et 4 points. 15. Paramètre à une valeur : le curseur est dans le champ Valeur, saisie directe au clavier. 16. La taille de 1750 cm est refusée (« hors des valeurs possibles »). 17. Glycémie à jeun 1,32 g/L : « Élevée ». 18. IMC calculé (80 kg, 175 cm) : 26,1, « Surpoids ». 19. Poids et taille n'affichent plus « Pas de norme » mais renvoient à l'IMC (« IMC 26,1 · Surpoids »). 20. La mesure erronée de glycémie est retirée. 21. Sur la nouvelle ordonnance, les terrains et allergies du dossier sont cochés et les allergies en texte libre (Iode) rappelées. 22. (technique) Le poids saisi sur l'ordonnance (82) rejoint le suivi du client, lié à l'ordonnance. 23. En consultation : le contexte est en texte (né le 10/05/1980, poids 82 kg, Diabète), sans case ni champ à cocher, sans « Grossesse ». 24. Onglet paramétrage : terrains avec catégorie (3 allergies), paramètres avec leurs normes (tension : 3 tranches d'âge). 25. « Ajouter un paramètre » le crée aussitôt, actif. 26. Aucune erreur JavaScript n'apparaît. 27. (technique) Remise en état : client, mesures, dossier, ordonnance et paramètre de test retirés. | H10: Le test supprime le paramètre « ZZFICHE Cholestérol total », le client d'essai ZZFICHE, ses mesures, terrains, dossier, compte et ordonnances. | I10: retours/test-ordonnances-fiche-client.js | J10: OK | K10: Joué le 30/10 15:33 — 27 / 27 conformes
A11: ORD-07 | B11: Ordonnance : création rapide d'un client, d'un prescripteur et d'un établissement | C11: SERVICE CLIENT > Suivi dossier client (menu lu dans la configuration des menus de l'application ; écran décrit par le test : (menu non précisé dans le test) > Ordonnances clients) | D11: Depuis la fiche d'une nouvelle ordonnance, « Nouveau client » ouvrait une fenêtre vide. Il doit ouvrir une fenêtre de création remplie avec le nom tapé, créer un client Standard et le choisir ; on doit aussi pouvoir créer rapidement un prescripteur (sans doublon) et un établissement, puis enregistrer l'ordonnance sur eux. | E11: Connexion avec le compte de test. Aucun client nommé « ZZNCLIENT » ni prescripteur « ZZDOCTEUR ». Le test crée par l'écran : un client « ZZNCLIENT ESSAI... », un prescripteur « ZZDOCTEUR Awa », un établissement « Clinique ZZ Essai » et une ordonnance ; pour un test manuel, utiliser ces mêmes données d'essai. | F11: 1. Ouvrir l'écran des ordonnances clients (menu : voir colonne « Écran »). 2. Cliquer sur « Nouvelle » ; dans le champ client, taper « ZZNCLIENT ». 3. Cliquer sur « Nouveau client ». 4. Cliquer sur « Créer le client » sans remplir le prénom ni le téléphone ; fermer le message. 5. Saisir un prénom, le téléphone 0707070707, choisir le sexe F, puis cliquer sur « Créer le client ». 6. Dans le champ prescripteur, taper « ZZDOCTEUR » et cliquer sur le bouton de nouveau prescripteur. 7. Saisir le prénom « Awa » et la spécialité « Pédiatre », puis cliquer sur le bouton de création du prescripteur. 8. (Contrôle technique, fait par le test automatique) : redemander la création du prescripteur « zzdocteur awa ». 9. Cliquer sur le bouton de nouvel établissement, saisir « Clinique ZZ Essai » et cliquer sur « Ajouter ». 10. Saisir un produit sur la première ligne, une observation, puis cliquer sur « Enregistrer ». | G11: 1. « Nouveau client » ouvre une fenêtre de création remplie (pas la fenêtre vide de la caisse). 2. Le nom tapé dans la recherche (ZZNCLIENT) est repris. 3. Sans prénom ni téléphone : création refusée, avec un message indiquant les champs obligatoires. 4. (technique) Client créé de type Standard, avec le téléphone 0707070707 et le sexe F. 5. Le client créé est choisi dans la fiche, la fenêtre se referme, le sexe passe au contexte clinique. 6. Prescripteur : « Nouveau » ouvre la saisie rapide avec le nom ZZDOCTEUR repris. 7. Prescripteur créé (prénom AWA, spécialité Pédiatre, actif) et choisi dans la fiche. 8. (technique) Même nom et prénom : pas de doublon, le prescripteur existant est rendu. 9. L'établissement « CLINIQUE ZZ ESSAI » est ajouté et posé dans la fiche. 10. (technique) L'ordonnance est enregistrée sur le nouveau client, avec le prescripteur et l'établissement créés. 11. (technique) Aucune erreur JavaScript. 12. (technique) Client et ordonnance de test retirés. | H11: Le test supprime le client d'essai (et son compte), ses ordonnances et le prescripteur ZZDOCTEUR. | I11: retours/test-ordonnances-nouveau-client.js | J11: OK | K11: Joué le 30/10 15:33 — 12 / 12 conformes
A12: ORD-08 | B12: Ordonnances : reste à délivrer dans l'historique, la fiche et le signalement du client | C12: SERVICE CLIENT > Suivi dossier client (menu lu dans la configuration des menus de l'application ; écran décrit par le test : (menu non précisé dans le test) > Ordonnances clients) | D12: Une ligne est due quand sa quantité servie est renseignée et inférieure à la prescription ; une ligne à renseigner ou une ordonnance annulée n'a pas de reste. L'historique montre et filtre le reste, la fiche le montre par ligne, et dès que le client est choisi la fiche signale ses autres ordonnances dues, avec un lien « Voir ». | E12: Connexion avec le compte de test. Le test automatique crée lui-même : un client « ZZRESTEDU E2E » et 4 ordonnances : A (il y a 10 jours, ligne 1 : 3 prescrits, 1 servi ; ligne 2 servie), B (à renseigner), C (2 prescrits, 0 servi), D (annulée, 4 prescrits, 1 servi) ; pour un test manuel, préparer : ce même client et ces 4 ordonnances. | F12: 1. Ouvrir l'écran des ordonnances clients (menu : voir colonne « Écran »). 2. Taper « ZZRESTEDU » dans la recherche de l'historique et lire la colonne RESTE. 3. Cocher « Avec un reste à délivrer ». 4. Cocher l'affichage des annulées. 5. Cliquer sur « Réinitialiser ». 6. (Contrôle technique, fait par le test automatique) : lire le reste du client par le serveur. 7. Cliquer sur « Nouvelle », taper « ZZRESTEDU » dans le client, choisir le client avec Flèche bas puis Entrée. 8. Cliquer sur le lien « Voir » du bandeau, puis confirmer par « Oui ». 9. Dans l'historique filtré, cliquer sur l'icône de consultation de l'ordonnance A. | G12: 1. (technique) Quatre ordonnances créées, dont une annulée. 2. Colonne RESTE : A « 2 à servir », C « 2 à servir », B rien. 3. L'ordonnance annulée n'apparaît pas (masquée par défaut). 4. « Avec un reste à délivrer » : seulement A et C. 5. Même avec les annulées affichées, l'annulée n'a pas de reste (toujours A et C). 6. « Réinitialiser » décoche le filtre du reste et celui des annulées. 7. (technique) Reste du client : 2 ordonnances, 4 à servir, la plus ancienne d'abord (A puis C). 8. Client choisi : bandeau « 2 autre(s) ordonnance(s) avec un reste à délivrer — 4 à servir. Voir ». 9. « Voir » avec une saisie en cours : confirmation « Abandonner la saisie ». 10. L'historique s'ouvre filtré sur ce client et son reste à délivrer (A et C). 11. Fiche de A : colonne RESTE par ligne (2 pour la première, rien pour la ligne servie). 12. Fiche de A : seule l'autre ordonnance due (C) est signalée : « 1 autre(s) ordonnance(s) », « 2 à servir ». 13. (technique) Aucune erreur JavaScript. 14. (technique) Jeu d'essai retiré. | H12: Le test supprime le client d'essai E2E-RS-CLIENT et ses ordonnances. | I12: retours/test-ordonnances-reste.js | J12: OK | K12: Joué le 30/10 15:33 — 14 / 14 conformes
A13: ORD-09 | B13: Ordonnances clients : consultation sans erreur, présentation, saisie au clavier, pièces | C13: SERVICE CLIENT > Suivi dossier client (menu lu dans la configuration des menus de l'application ; écran décrit par le test : (non précisé dans le test) : écran des ordonnances clients (historique et fiche)) | D13: Retours du 30/09 : plus d'erreur « getId » en consultant ou modifiant une ordonnance ; fiche en présentation B (patient à gauche, ordonnance à droite, N° dans le titre, un seul bouton « Retour à l'historique » avec confirmation si saisie en cours) ; curseur placé au bon endroit ; créations rapides en fenêtre ; info-bulles des alertes qui restent ; actions Voir / Télécharger / Retirer sur chaque pièce ; recherche de l'historique pendant la frappe, en « contient ». | E13: Connexion avec le compte de test (administrateur). Un type de client « Standard » et un article « DOLIPRANE 1G… » avec plus de 5 unités en stock. Le test automatique crée lui-même : un client d'essai « ZZTRENTESEPT E2E » et trois ordonnances de 3, 1 et 2 lignes pour lui ; pendant le parcours, un prescripteur « ZZTRENTEDOC » et un établissement « CLINIQUE ZZ TRENTE ». Pour un test manuel, préparer : un client d'essai avec trois ordonnances de 3, 1 et 2 lignes, et un petit fichier PDF. | F13: 1. Se connecter et ouvrir l'écran des ordonnances clients. 2. Dans la recherche de l'historique, taper « TRENTESE » sans appuyer sur Entrée. 3. Consulter l'ordonnance de 3 lignes, cliquer dans une cellule des produits, revenir à l'historique, puis consulter l'ordonnance d'1 ligne ; revenir. 4. Modifier l'ordonnance de 3 lignes, cliquer dans une cellule, puis cliquer sur l'icône de retrait (première colonne) d'une ligne ; revenir (Oui) et consulter l'ordonnance de 2 lignes. 5. Regarder la fiche consultée : titre de section, place du patient, boutons, texte du contexte clinique, première colonne. 6. Revenir à l'historique et cliquer sur « Nouvelle ». 7. Taper « ZZTRENTESEPT », choisir le client avec la flèche bas et Entrée. 8. Cliquer sur « Retour à l'historique », lire la question et répondre Non. 9. Dans la recherche produit, taper le début du nom de l'article DOLIPRANE, choisir avec flèche bas + Entrée, taper « 1 cp 3 fois par jour » et Entrée. 10. Dans la recherche produit, taper « Préparation magistrale ZZ » et valider par Entrée. 11. Choisir le sexe F. 12. Cliquer sur « + » du prescripteur, taper « ZZTRENTEDOC » et Entrée. 13. Cliquer sur « + » de l'établissement, saisir « Clinique ZZ trente » et valider. 14. Cliquer sur « + » du client, puis « Annuler ». 15. Cliquer sur « Enregistrer ». 16. Lancer l'analyse de l'ordonnance, survoler une cellule d'alerte pendant 7 secondes, puis sortir la souris. 17. Joindre le fichier PDF comme pièce. 18. Sur la ligne de la pièce, cliquer sur « Voir », puis fermer l'onglet ouvert. 19. Sur la ligne de la pièce, cliquer sur « Retirer » et répondre Oui. 20. Cliquer sur « Retour à l'historique ». | G13: 1. La recherche part pendant la frappe, sans Entrée, et trouve les 3 ordonnances du client ZZTRENTESEPT. 2. Consulter, cliquer une cellule, revenir, consulter une autre : aucune erreur « getId » (la seconde ordonnance montre 1 ligne). 3. Modifier, retirer une ligne, revenir, consulter : aucune erreur « getId » (l'ordonnance montre 2 lignes). 4. L'icône de retrait (première colonne) retire bien la ligne (2 lignes restent). 5. Le N° de l'ordonnance est dans le titre de la section. 6. Présentation B : le patient et son contexte clinique (dont l'âge) à gauche, l'ordonnance à droite. 7. Un seul bouton « Retour à l'historique », plus d'« Abandonner ». 8. Contexte clinique : « … aucune donnée du client ne sort », sans nom de technologie. 9. Le retrait d'une ligne est en première colonne. 10. Fiche neuve : titre « Nouvelle ordonnance ». 11. Après le choix du client, le curseur est dans la recherche produit. 12. Le type du client (Standard) s'affiche sous son nom. 13. Saisie en cours : « Retour à l'historique » demande « Abandonner la saisie… ». 14. « Non » : on reste sur la fiche, la saisie est gardée. 15. Le produit choisi remplit la ligne vide (pas de ligne en plus). 16. Le curseur est ensuite dans la posologie. 17. Texte libre + Entrée : ligne « PRÉPARATION MAGISTRALE ZZ » hors référentiel. 18. Après le choix du sexe, le curseur est dans la recherche produit. 19. « + » prescripteur : fenêtre de création, curseur dans le nom. 20. Entrée crée le prescripteur, la fenêtre se ferme, il est choisi (ZZTRENTEDOC), le curseur revient à la recherche produit. 21. « + » établissement : fenêtre, « CLINIQUE ZZ TRENTE » ajouté et posé dans la fiche. 22. « + » client : fenêtre, « Annuler » la ferme. 23. Après enregistrement, le titre indique « N° … » et « enregistrée ». 24. Analyse : chaque colonne de texte des alertes porte son info-bulle. 25. L'info-bulle est encore là après 7 secondes (elle reste tant que la souris est dessus). 26. Hors de l'écran des ordonnances, le délai d'origine des info-bulles est remis. 27. Pièces : Voir, Télécharger et Retirer sur la ligne de la pièce, plus de boutons en haut. 28. « Voir » de la ligne ouvre la pièce dans un onglet. 29. « Retirer » de la ligne demande confirmation puis retire la pièce. 30. Rien de changé depuis l'enregistrement : retour direct à l'historique, sans question. 31. Aucune erreur JavaScript pendant tout le parcours. 32. (technique) Jeu d'essai retiré. | H13: Le test supprime les ordonnances, lignes et pièces (fichiers compris) du client d'essai, le client d'essai et le prescripteur « ZZTRENTEDOC ». | I13: retours/test-ordonnances-3009.js | J13: OK | K13: Joué le 30/10 15:33 — 32 / 32 conformes
A14: ORD-10 | B14: Pièces justificatives des ordonnances : dépôt, consultation, refus, retrait, droits | C14: SERVICE CLIENT > Suivi dossier client (menu lu dans la configuration des menus de l'application ; écran décrit par le test : (non précisé dans le test) : écran des ordonnances clients, fiche d'ordonnance, zone des pièces) | D14: Évolution 6, point 2 : joindre une ou plusieurs pièces (images, PDF, documents numérisés) à une ordonnance client, les voir et les télécharger depuis la fiche. Les fichiers interdits, vides ou trop gros sont refusés, un nom ou un chemin piégé n'écrit ni ne lit ailleurs, une pièce se retire sans supprimer l'ordonnance, et sans le droit d'écriture on ne peut que consulter. | E14: Connexion avec le compte de test (administrateur, qui a le droit P_ORDONNANCE_CLIENT_MAJ). Un type de client « Standard ». Le test automatique crée lui-même : un client d'essai « ZZPIECETEST E2E », une ordonnance d'une ligne pour lui, et des fichiers d'essai (un PDF, une image PNG, un .exe, un PDF vide, un PDF de 10 Mo + 1 octet). Pour un test manuel, préparer : un client d'essai avec une ordonnance enregistrée et ces fichiers. | F14: 1. Se connecter et ouvrir l'écran des ordonnances clients. 2. Cliquer sur « Nouvelle » et regarder la zone des pièces, puis cliquer sur « Retour à l'historique ». 3. Ouvrir la fiche de l'ordonnance d'essai. 4. Choisir le fichier « ordonnance-scan.pdf » et cliquer sur le bouton pour joindre la pièce. 5. Choisir « photo-ordonnance.png » et le joindre. 6. (Contrôle technique, fait par le test automatique) : vérifier en base le chemin enregistré et sur le disque la présence des fichiers. 7. Voir la pièce PDF, puis la télécharger. 8. (Contrôle technique, fait par le test automatique) : tenter de déposer le .exe, le PDF vide, le PDF trop gros, puis un PDF au nom piégé (remontée de dossiers et chemin absolu). 9. (Contrôle technique, fait par le test automatique) : trafiquer en base le chemin d'une pièce vers un fichier système et la demander. 10. Retirer une pièce. 11. (Contrôle technique, fait par le test automatique) : vieillir d'un jour un fichier orphelin dans le dossier des pièces et lancer la purge. 12. (Contrôle technique, fait par le test automatique) : annuler l'ordonnance puis tenter d'y joindre une pièce, et lister ses pièces. 13. (Contrôle technique, fait par le test automatique) : retirer le droit P_ORDONNANCE_CLIENT_MAJ au rôle du compte de test, se reconnecter, rouvrir la fiche, tenter un dépôt et une consultation, puis rendre le droit. | G14: 1. (technique) Précondition : une ordonnance à garnir est créée. 2. Sur une saisie non enregistrée, la zone de pièces dit « Enregistrez… » et reste inactive. 3. La pièce déposée apparaît dans la liste avec son nom, son type (application/pdf), sa taille et son auteur. 4. Plusieurs pièces cohabitent sur la même ordonnance (dont une image PNG). 5. (technique) La base ne contient qu'un chemin relatif, rangé par mois (ordonnances/AAAA/MM/). 6. (technique) Les fichiers sont réellement écrits sur le disque, sous la racine de stockage. 7. (technique) Le nom sur disque est l'identifiant de la pièce, pas le nom d'origine. 8. La pièce est affichée dans l'onglet avec son vrai type et sous son nom d'origine. 9. C'est bien le fichier déposé qui revient (un PDF). 10. Le téléchargement rend le même document en pièce attachée, sous son nom d'origine. 11. Un fichier exécutable est refusé, et le message dit ce qui est accepté. 12. Un fichier vide est refusé (« vide »). 13. Un fichier de plus de 10 Mo est refusé, avec la taille et la limite dans le message. 14. (technique) Un nom de fichier qui remonte l'arborescence est désarmé. 15. (technique) Rien n'est écrit hors du dossier des pièces. 16. Le nom conservé est le nom de fichier seul (« evasion.pdf »), sans son chemin. 17. (technique) Un chemin trafiqué en base n'est pas suivi : le service ne lit pas les fichiers du serveur. 18. (technique) Précondition : le fichier de la pièce à retirer existe. 19. Une pièce se retire. 20. (technique) Sa ligne et son fichier ont disparu. 21. (technique) L'ordonnance reste intacte. 22. Les deux autres pièces sont toujours là. 23. (technique) La purge supprime le fichier orphelin. 24. (technique) La purge ne touche pas aux fichiers rattachés à une ordonnance. 25. (technique) On ne joint plus de pièce à une ordonnance annulée (message « annulée »). 26. (technique) Les pièces d'une ordonnance annulée restent consultables. 27. Sans le droit d'écriture, la zone de dépôt disparaît et le retrait de la ligne est grisé. 28. Sans le droit d'écriture, « Voir » reste actif sur la ligne. 29. (technique) Sans le droit, le service refuse le dépôt même appelé directement. 30. (technique) Sans le droit, la consultation des pièces reste possible. 31. (technique) Le droit est rendu à la fin du contrôle. 32. Aucune erreur JavaScript pendant tout le parcours. 33. (technique) Tout ce que le test a posé est retiré (lignes et fichiers). | H14: PRUDENCE : Retire temporairement un droit au rôle du compte de test (rendu ensuite) et lance la purge des fichiers de pièces orphelins du stockage du poste : à jouer sur un poste d'essai. Le test supprime les pièces (fichiers compris), l'ordonnance et le client d'essai, ses fichiers temporaires, et rend le droit P_ORDONNANCE_CLIENT_MAJ au rôle du compte de test. | I14: retours/test-ordonnances-pieces.js | J14: OK | K14: Joué le 30/10 15:33 — 33 / 33 conformes
A15: ORD-11 | B15: Ordonnance : équivalents par DCI proposés pour un produit en rupture | C15: SERVICE CLIENT > Suivi dossier client (menu lu dans la configuration des menus de l'application ; écran décrit par le test : (non précisé dans le test) : écran des ordonnances clients, nouvelle ordonnance) | D15: Évolution du 23/09 : dans une ordonnance, un produit en rupture affiche de lui-même ses équivalents de même DCI, les équivalents directs avant ceux « à adapter » (avec la raison), sans autre voie d'administration ; « Remplacer » change le produit en gardant la posologie ; la lévothyroxine est signalée « substitution à éviter » et un produit sans DCI n'a aucune proposition devinée. | E15: Connexion avec le compte de test (administrateur). Les articles « DOLIPRANE 500MG CPR B/16 », DOLIPRANE effervescent, « DOLIPRANE 1G CPR B/8 », « DOLIPRANE 200MG SUPPO B/10 », « EFFERALGAN 500MG GEL B/16 ANF », « EFFERALGAN 500MG CPR SEC B/16 », « LEVOTHYROX 75MCG CPR SEC B/30 », « LEVOTHYROXINE GH 75MCG CPR B/30 » et « FERCEFOL CPR B/30 ». Le test pose lui-même les liens DCI (paracétamol, lévothyroxine) manquants, marqués « E2E-SUB- », et met à 0 le stock de « DOLIPRANE 500MG CPR B/16 » le temps du test. | F15: 1. Se connecter, ouvrir l'écran des ordonnances clients et cliquer sur « Nouvelle ». 2. Dans la cellule produit de la première ligne, taper « DOLIPRANE 500MG CPR » et choisir « DOLIPRANE 500MG CPR B/16 » ; saisir la posologie « 1 cp 3 fois par jour » et Entrée. 3. Lire le message et la liste des équivalents qui s'affichent, regarder les couleurs du stock et du prix. 4. Cliquer sur « Remplacer » sur le premier équivalent. 5. Ajouter une ligne, taper « LEVOTHYROX 75 » et choisir « LEVOTHYROX 75MCG CPR SEC B/30 », puis cliquer sur l'icône des équivalents de la ligne. 6. Ajouter une ligne, taper « FERCEFOL » et choisir « FERCEFOL CPR B/30 », puis cliquer sur l'icône des équivalents de la ligne. | G15: 1. (technique) Précondition : au moins 5 candidats paracétamol liés, le produit d'origine en rupture. 2. Produit en rupture choisi : les équivalents s'affichent d'eux-mêmes, le message parle de la rupture et de PARACETAMOL. 3. Autant de propositions que de produits paracétamol en base, moins le suppositoire (voie rectale). 4. Les équivalents directs viennent d'abord, puis « à adapter ». 5. Efferalgan 500 gélule et comprimé sécable : équivalents directs. 6. Effervescent et 1 g : « à adapter », avec la raison (sodium ; « 1000 mg au lieu de 500 mg »). 7. Vente à l'unité (DET) : signalée (« unité ») et rangée après les boîtes. 8. Le suppositoire n'est pas proposé. 9. Stock et prix visibles en couleur (bleu / rouge). 10. « Remplacer » : la ligne prend le produit choisi et garde sa posologie « 1 cp 3 fois par jour » ; la liste des équivalents se ferme. 11. Lévothyroxine : « substitution à éviter », marge thérapeutique étroite. 12. Produit sans DCI : aucune proposition, message « Aucune DCI… ». 13. Aucune erreur JavaScript. 14. (technique) Remise en état : liens DCI d'essai retirés, stock remis. | H15: Le test supprime les liens produit-DCI et les DCI d'essai qu'il a créés et remet le stock du produit d'origine. L'ordonnance en saisie n'est pas enregistrée. | I15: retours/test-ordonnances-substituts.js | J15: OK | K15: Joué le 30/10 18:12 — 14/14 controles OK
A16: ORD-12 | B16: Ordonnances : historique revu et scan d'ordonnance (saisie assistée, lecture auto) | C16: SERVICE CLIENT > Suivi dossier client (menu lu dans la configuration des menus de l'application ; écran décrit par le test : (non précisé dans le test) > Ordonnances clients (écran « SUIVI DOSSIER CLIENT ») (Historique et écran de scan)) | D16: Retours du 30/09 : historique revu (onglets, critères en puces, boutons à gauche, compteurs cliquables, colonnes regroupées) et scan d'une ordonnance : saisie assistée sans lecture automatique, puis lecture automatique par le service Posos (simulé), avec ligne incertaine en orange et possibilité d'écarter le scan. | E16: Connexion avec le compte d'essai (administrateur). Un article réel en stock. Le test fabrique lui-même deux photos d'ordonnance « papier », crée un client « ZZSCAN KOFFI » et un prescripteur « Dr ZZSCANDOC », et remplace le temps du test la configuration Posos du poste par un faux service local ; pour un test manuel, préparer deux photos d'ordonnance et un service de lecture d'essai. | F16: 1. Se connecter avec le compte d'essai. 2. Ouvrir l'écran des ordonnances clients (menu : voir colonne « Écran ») et regarder l'historique : onglets, puces de type de client, boutons, compteurs, colonnes. 3. Cliquer sur le compteur « avec un reste ». 4. Cliquer sur la puce « 7 jours », puis sur la puce « Standard ». 5. Cliquer sur « Réinitialiser ». 6. Cliquer sur « Scanner une ordonnance » et déposer la première photo. 7. Regarder le message, les boutons « Lire l'ordonnance » et « Créer l'ordonnance · Ctrl+Entrée », et la file des scans ; utiliser le zoom + et la rotation. 8. Rechercher l'article par son premier mot, le choisir, taper la posologie « 1 cp matin et soir » puis Entrée ; cliquer deux fois sur + et une fois sur − de la quantité. 9. Appuyer sur Ctrl+Entrée sans client ni nom. 10. Saisir le nom « ZZSCAN », les prénoms « AWA », la date de naissance « 12/04/19 », puis Ctrl+Entrée. 11. (Contrôle technique, fait par le test automatique) : envoyer un fichier Word comme scan. 12. (Le test automatique branche un faux service de lecture Posos local.) Rouvrir le scan et déposer la seconde photo. 13. Lire les lignes lues, le patient, le prescripteur et le message. 14. Cliquer sur « Écarter ce scan » et confirmer par « Oui ». 15. (Contrôle technique, fait par le test automatique) : lire le journal du serveur. | G16: 1. Historique : onglets segmentés, type de client en puces (« Tous » + au moins 3 types, « Tous » enfoncé), liste déroulante cachée. 2. « Nouvelle ordonnance » puis « Scanner une ordonnance » à gauche, compteurs à côté (ordonnances, reste à délivrer, à renouveler). 3. Colonnes regroupées : « N° / DATE » en premier, plus de colonnes TYPE, ÉTABLISSEMENT ni SAISIE. 4. Compteur « avec un reste » cliqué : le filtre est posé et le compteur s'allume. 5. Puce « 7 jours » : la période des 7 derniers jours est posée et la recherche relancée. 6. Puce « Standard » : le type de client est filtré. 7. « Réinitialiser » : filtres, type et période effacés, « Tous » enfoncé. 8. « Scanner une ordonnance » ouvre l'écran de scan. 9. Photo déposée : scan « à traiter », source poste, image PNG affichée à gauche. 10. Sans lecture branchée : saisie assistée annoncée (« non branchée »), « Lire » et « Créer » grisés, le scan est dans la file et sélectionné. 11. Zoom (× 1,25) et rotation (90°) de l'image. 12. Produit ajouté par la recherche, avec son stock ; posologie saisie ; quantité 1. 13. Les boutons − / + règlent la quantité (résultat : 2). 14. Ctrl+Entrée sans client ni nom : refus expliqué (créer un nouveau client standard). 15. Ctrl+Entrée : client STANDARD créé (né le 12/04/2019), ordonnance à 1 produit (quantité 2), scan joint en pièce. 16. (technique) Le scan est « traité » et lié à l'ordonnance. 17. La fiche de l'ordonnance créée s'ouvre, avec le scan en pièce et la date de naissance 12/04/2019. 18. (technique) Un fichier qui n'est ni photo ni PDF est refusé. 19. Lecture automatique : le produit lu est rapproché du catalogue, posologie « 2 fois par jour » et quantité 3 reprises. 20. Ligne illisible : gardée telle que lue, à vérifier, en orange ; message « 1 à vérifier ». 21. Patient lu et déjà client : il est choisi (type Standard et téléphone affichés, 7 ans), pas de nouveau client ; prescripteur retrouvé ; « Lire » actif. 22. (technique) Le service de lecture a reçu le document, avec le jeton. 23. (technique) La lecture est gardée en base (pas de nouvel appel à la réouverture). 24. « Écarter ce scan » : le scan quitte la file (il reste tracé, statut écarté). 25. (technique) Les journaux du serveur ne contiennent ni le jeton, ni le document, ni le nom du patient. 26. Aucune erreur JavaScript. 27. (technique) La configuration Posos du poste est remise telle quelle. 28. (technique) Clients, ordonnances et scans de test retirés. | H16: PRUDENCE : Remplace temporairement le fichier de configuration Posos du poste par un faux service local (remis à la fin) : à jouer uniquement sur un poste d'essai. Le test remet le fichier de configuration Posos d'origine, supprime les clients « ZZSCAN », leurs ordonnances, pièces et scans (et les fichiers sur le disque), et le prescripteur d'essai. | I16: retours/test-ordonnances-scan.js | J16: OK | K16: Joué le 30/10 15:33 — 28 / 28 conformes
... A25: ORD-21 | B25: Analyse posologie : interaction unitaire et historique sans nom de produit | C25: Sans écran (contrôle technique) | D25: Demandes serveur des applications mobiles, point 35 : une route vérifie l'interaction entre deux produits du catalogue, et chaque analyse laisse une ligne d'historique (source, nombres, gravité, mode) sans aucun nom de produit. L'historique est réservé au droit Posos. | E25: Connexion avec le compte de test (droit Posos). Le service d'analyse posologie en mode démonstration (activé par le test le temps de l'essai). Le test crée lui-même les produits de la démonstration s'ils manquent (Sintrom, Brufen). | F25: 1. (Contrôle technique, fait par le test automatique) : demander l'interaction Sintrom + Brufen (par identifiant et par CIP), puis avec un produit inconnu. 2. (Contrôle technique, fait par le test automatique) : lancer une analyse en saisie libre comme l'écran. 3. (Contrôle technique, fait par le test automatique) : lire l'historique des analyses. 4. (Contrôle technique, fait par le test automatique) : sans le droit Posos, lire l'historique et demander une interaction. | G25: 1. (technique) Interaction Sintrom + Brufen (identifiant et CIP) : « Association déconseillée ». 2. (technique) Produit inconnu : refus 400 (produit inconnu). 3. (technique) Analyse de l'écran (saisie libre) : inchangée, alertes rendues. 4. (technique) Historique : route unitaire et écran tracés (source, nombre de produits, alertes, gravité, mode). 5. (technique) Historique : total des alertes rendu. 6. (technique) Aucun nom de produit gardé dans l'historique. 7. (technique) Une ligne par analyse (2), l'inconnu refusé avant. 8. (technique) Sans le droit Posos : historique et interaction refusés (403). 9. (technique) Remise en état (configuration, historique du test, produits). | H25: PRUDENCE : Modifie temporairement le fichier de configuration du service d'analyse posologie (mode démonstration) : à jouer uniquement sur un serveur d'essai. La configuration du service d'analyse posologie est remise ; les lignes d'historique du test et les produits créés sont retirés. | I25: retours/test-posos-historique.js | J25: Échec | K25: Joué le 30/10 15:33 — 8 / 9 conformes Écart : Remise en état (configuration, historique du test, produits)

Sheet Clients
A1: CAHIER DE RECETTE — CLIENTS
A2: Version testée : branche integration/recette-2026-10-29 (21ddcd3d), déployée sur le poste local (port 8080), copie de l'officine restaurée le 30/10
A3: 12 cas — Claude : 12 OK, 0 en échec, 0 non joués
A4: N° | B4: Cas de test | C4: Écran (menu) | D4: Objectif | E4: Existant (avant de commencer) | F4: Étapes | G4: Résultats attendus | H4: Nettoyage / prudence | I4: Test automatique | J4: Résultat Claude | K4: Détail Claude | L4: Résultat testeur | M4: Commentaire testeur | N4: Testeur | O4: Date | P4: Résultat Claude confirmé ?
A5: CLI-01 | B5: Fiche client : compléter date de naissance et sexe ; suivi de consommation par vente | C5: (menu non précisé dans le test) > Fiche client (fenêtre de la gestion des clients) | D5: Pour un client sans date de naissance ni sexe, la fiche propose de les compléter et les enregistre sans fenêtre, sans jamais écraser ce qui est déjà renseigné, en refusant une date future. Le suivi de consommation propose « Par vente » (par défaut, ventes des 12 derniers mois) et « Par produit » (vue d'avant). | E5: Connexion avec le compte administrateur. Le test automatique crée lui-même : un client d'essai « ZZFICHE Identite » sans date de naissance ni sexe ; pour un test manuel, préparer : un tel client. Il faut aussi un client ayant des ventes clôturées sur les 12 derniers mois (lu sans modification). | F5: 1. Ouvrir la fiche du client d'essai « ZZFICHE Identite ». 2. Dans le bloc pour compléter l'identité, saisir la date de naissance 01/01/2099 et cliquer sur le bouton d'enregistrement du bloc. 3. Saisir la date de naissance 12/05/1975, choisir le sexe « M », puis cliquer sur le bouton d'enregistrement du bloc. 4. Observer la fiche après l'enregistrement. 5. (Contrôle technique, fait par le test automatique) : envoyer directement au serveur une autre date (01/01/1990) et le sexe F pour ce client. 6. Fermer la fiche et ouvrir celle d'un client ayant des ventes sur les 12 derniers mois. 7. Regarder le suivi de consommation, puis cliquer sur « Par produit ». | G5: 1. Pour un client sans date ni sexe, la fiche affiche un bloc avec les champs date de naissance et sexe. 2. La date future 01/01/2099 est refusée : rien n'est enregistré. 3. (technique) La fiche client enregistre 12/05/1975 et le sexe M. 4. Le bloc disparaît ; l'identité affiche 12/05/1975, l'âge et « Masculin ». 5. (technique) Les valeurs déjà renseignées ne sont pas écrasées (toujours 12/05/1975 et M). 6. Il existe un client avec des ventes sur les 12 derniers mois. 7. Le choix « Par vente / Par produit » est présent, « Par vente » sélectionné par défaut. 8. « Par vente » : colonnes Date, Ticket, Montant, Produits ; une ligne par vente (au plus 50). 9. « Par produit » : colonnes Produit, Achats, Fréquence (vue d'avant), avec des lignes. 10. Aucune fenêtre surgissante, aucune erreur JavaScript. 11. (technique) Le client d'essai est retiré. | H5: Le test supprime le client d'essai (fiche, compte et dossier). | I5: client/test-fiche-client-identite-conso.js | J5: OK | K5: Joué le 30/10 15:33 — 11 / 11 conformes
A6: CLI-02 | B6: Corriger le nom du client d'un différé depuis un bandeau, sans fenêtre | C6: FACTURATION > Gestion des différés (menu lu dans la configuration des menus de l'application ; écran décrit par le test : (menu non précisé dans le test) > Gestion des différés) | D6: Permettre (besoins du 11/10, point 3) de corriger le nom d'un client en différé saisi par erreur (« MOUSSA » au lieu de « INOUSSA ») : fiche client et nom recopié sur ses ventes corrigés, sans toucher à une vente portant un autre nom ; refus propres des saisies invalides. | E6: Connexion avec le compte de test administrateur. Le test automatique crée lui-même : un client d'essai « MOUSSA ALI » avec un compte client, une vente en différé de 5 000 (05/10/2026), une vente comptant de 1 500 à son nom (06/10/2026), une vente de 1 000 portant le nom d'un autre porteur « AUTRE PORTEUR » (07/10/2026), et un client « ZZSANS DIFFERE » sans différé ; pour un test manuel, préparer l'équivalent. | F6: 1. Se connecter à Prestige avec le compte administrateur. 2. (Contrôle technique, fait par le test automatique) : lire la fiche du client d'essai, puis tenter des corrections invalides (nom vide, nom de 51 caractères, client inconnu, client sans différé). 3. Ouvrir l'écran « Gestion des différés » (menu : voir colonne « Écran »). 4. Saisir la période du 01/10/2026 au 31/10/2026, choisir le client « MOUSSA ALI » et cliquer sur « Rechercher ». 5. Regarder le bandeau « Corriger le client » sous la liste. 6. Cliquer sur la ligne du différé. 7. Dans le champ du nom du bandeau, remplacer le nom par « inoussa » et appuyer sur Entrée. | G6: 1. (technique) La lecture de la fiche donne le nom et les prénoms séparés, et le droit de modifier. 2. (technique) Nom vide : refus expliqué (message parlant du nom). 3. (technique) Nom trop long (51 caractères) : refus expliqué (limite de 50). 4. (technique) Client inconnu : refus. 5. (technique) Client sans différé : refus (la correction ne vaut que pour les différés). 6. (technique) Aucun refus n'a rien changé. 7. Le bandeau « Corriger le client » est sous la liste, inactif tant qu'aucune ligne n'est choisie. 8. La ligne choisie, le nom « MOUSSA » et les prénoms « ALI » sont repris dans le bandeau, sans fenêtre. 9. Après Entrée, un message s'affiche dans le bandeau et la liste se recharge avec « INOUSSA ALI ». 10. (technique) La fiche client est corrigée, en majuscules : « INOUSSA ALI ». 11. (technique) Le nom recopié est corrigé sur ses ventes (différée et comptant) qui portaient l'ancien nom. 12. (technique) La vente portant le nom d'un autre porteur est inchangée. 13. Aucune erreur JavaScript n'apparaît. 14. (technique) Le jeu d'essai est retiré. | H6: Le test supprime les clients, le compte client, les ventes et le différé d'essai. | I6: retours/test-differe-nom-client.js | J6: OK | K6: Joué le 30/10 15:33 — 14 / 14 conformes
A7: CLI-03 | B7: Création d'un client standard avec date de naissance et sexe facultatifs | C7: GESTION DES TIERS-PAYANTS > Clients (menu lu dans la configuration des menus de l'application ; écran décrit par le test : (non précisé dans le test) > Clients (fenêtre « Créer client standard »)) | D7: Retours du 13/10, point 14 : la fenêtre « Créer client standard » doit proposer la date de naissance et le sexe, facultatifs, avec un enchaînement des champs par la touche Entrée, une mise en page aérée et le refus d'une date de naissance dans le futur. | E7: Connexion avec le compte d'essai (administrateur). Le test automatique crée lui-même ses clients d'essai (prénom commençant par « E2ECSNAISS ») ; pour un test manuel, utiliser des noms d'essai faciles à retrouver et à supprimer. | F7: 1. Se connecter avec le compte d'essai (administrateur). 2. Ouvrir l'écran « Clients » (menu : voir colonne « Écran »). 3. Cliquer sur le bouton « … client standard » (Créer client standard). 4. Regarder les champs Date de naissance et Sexe, et l'écart entre le champ Nom et le haut du cadre. 5. Saisir le nom « E2ECSNAISSA », Entrée, les prénoms « Avec Date », Entrée, le téléphone « 0708473791 », Entrée. 6. Saisir la date de naissance « 15/03/1980 », choisir le sexe F, puis appuyer sur Entrée depuis la date. 7. Appuyer sur Entrée (le bouton Enregistrer a le focus). 8. Rouvrir la fenêtre, saisir nom « E2ECSNAISSB », prénoms « Sans Date », téléphone « 0708473792 », sans date ni sexe, et cliquer sur « Enregistrer ». 9. Rouvrir la fenêtre, saisir nom « E2ECSNAISSC », prénoms « Futur », téléphone « 0708473793 », date de naissance « 01/01/2099 », Tab, puis cliquer sur « Enregistrer ». 10. (Contrôle technique, fait par le test automatique) : envoyer directement au serveur une création avec la date 2099-01-01 et un sexe inconnu « X ». 11. Fermer la fenêtre. | G7: 1. Les champs Date de naissance et Sexe sont proposés et facultatifs. 2. Le premier champ (Nom) n'est plus collé au haut du cadre (au moins 12 pixels d'écart). 3. Entrée fait passer du téléphone à la date de naissance. 4. Entrée fait passer de la date de naissance au bouton Enregistrer. 5. Le client est créé avec sa date de naissance 15/03/1980, le sexe F, le type client standard et le téléphone 0708473791. 6. Le client créé sans date ni sexe est enregistré comme avant (date et sexe vides, téléphone 0708473792). 7. Une date de naissance dans le futur est refusée à l'écran (champ en erreur) et rien n'est créé. 8. (technique) Une date future ou un sexe inconnu sont refusés par le serveur, rien n'est créé. 9. Aucune erreur JavaScript. 10. (technique) Les clients d'essai sont retirés. | H7: Le test supprime les clients d'essai « E2ECSNAISS… » et leurs comptes. | I7: client/test-client-standard-naissance.js | J7: OK | K7: Joué le 30/10 15:33 — 10 / 10 conformes
A8: CLI-04 | B8: Gestion des clients : barre d'outils (filtre, recherche, bouton Importer unique) | C8: GESTION DES TIERS-PAYANTS > Clients (menu lu dans la configuration des menus de l'application ; écran décrit par le test : (non précisé dans le test) > Clients) | D8: Retours du 13/10, point 15 : dans la gestion des clients, le filtre « Type client » ne doit plus se confondre avec le champ de recherche, et un seul bouton « Importer » doit proposer les deux imports (colonnes au choix / fichier modèle). | E8: Connexion avec le compte d'essai (administrateur). Des clients existants dont le nom contient la lettre A. Lecture seule. | F8: 1. Se connecter avec le compte d'essai (administrateur). 2. Ouvrir l'écran « Clients » (menu : voir colonne « Écran »). 3. Regarder la barre d'outils : le filtre « Type client », le champ de recherche et son texte d'aide, les boutons d'import. 4. Cliquer sur « Importer » et regarder les choix proposés. 5. Choisir l'import par colonnes au choix, puis fermer la fenêtre. 6. Cliquer sur « Importer » et choisir l'import par fichier modèle (historique), puis fermer la fenêtre. 7. Saisir « A » dans la recherche et lancer la recherche. | G8: 1. Le filtre « Type client » et le champ de recherche sont bien séparés (écart visible d'au moins 12 pixels). 2. Le champ de recherche indique ce qu'il cherche (nom, numéro ou client). 3. Il n'y a qu'un seul bouton « Importer ». 4. Son menu propose exactement deux imports : l'un par colonnes, l'autre par fichier modèle (historique). 5. « Colonnes au choix » ouvre l'assistant d'import. 6. « Fichier modèle » ouvre l'import historique (une fenêtre s'ouvre). 7. La recherche fonctionne toujours (au moins un client trouvé). 8. Aucune erreur JavaScript. | H8: Rien à retirer (lecture seule). | I8: client/test-gestion-clients-barre.js | J8: OK | K8: Joué le 30/10 18:31 — 8/8 OK
A9: CLI-05 | B9: Création d'un client standard : nom, prénoms et téléphone unique, saisie au clavier | C9: GESTION DES TIERS-PAYANTS > Clients (menu lu dans la configuration des menus de l'application ; écran décrit par le test : Liste des clients (menu non précisé dans le test), bouton « Créer client standard ») | D9: Créer rapidement un client standard (nom, prénoms, téléphone). Le numéro a désormais sa propre colonne (il était rangé dans l'adresse), il est normalisé à dix chiffres et unique parmi les clients standards seulement. La fenêtre s'enchaîne à la touche Entrée comme l'écran de vente. | E9: Profil administrateur (compte de test). Le test choisit lui-même deux numéros de téléphone qu'aucun client ne porte (commençant par 07 et 05) et crée des clients d'essai « E2ESTANDARD... » et « E2ECS-CLAVIER » ; pour un test manuel, choisir deux numéros libres et disposer de deux clients non standards (assurance) pour le contrôle de non-régression. | F9: 1. Ouvrir la liste des clients (menu : voir colonne « Écran »). 2. Vérifier la colonne « Téléphone », le bouton « Créer client standard » à côté de « Créer » et le filtre « Type client ». 3. Cliquer sur « Créer client standard ». 4. Saisir un nom, des prénoms et le premier numéro libre écrit avec des séparateurs ; cliquer sur « Enregistrer ». 5. Recréer un client avec le même numéro, puis avec le même numéro écrit autrement (« +225 07-08-... »), puis avec le second numéro libre. 6. Ouvrir la fenêtre et cliquer sur « Enregistrer » sans rien saisir. 7. Saisir un numéro commençant par 02 (ex. 0208473750). 8. (Contrôle technique, fait par le test automatique) : donner le même numéro à deux clients non standards. 9. Rechercher le client créé par son numéro dans la liste. 10. Ouvrir la fenêtre ; taper « E2ECS-CLAVIER » puis Entrée, « Awa » puis Entrée, « 0708473777 » puis Entrée, Entrée sur la date de naissance laissée vide, puis Entrée sur le bouton « Enregistrer ». | G9: 1. Une colonne « Téléphone » figure dans la liste des clients. 2. Le bouton de création allégée est à côté du bouton « Créer ». 3. Le filtre « Type client » propose « Client standard » et « Tous les types ». 4. La fenêtre demande nom, prénoms et téléphone ; date de naissance et sexe sont facultatifs. 5. Le client standard est créé et la fenêtre se referme. 6. (technique) Le numéro est enregistré normalisé, sans les séparateurs. 7. (technique) Le client est de type standard et actif. 8. (technique) Son compte client est créé, comme avec le formulaire complet. 9. (technique) Le numéro n'est plus rangé dans le champ Adresse. 10. Un numéro déjà porté par un client standard est refusé. 11. Le message nomme le client qui détient le numéro. 12. Le second client n'est pas créé. 13. Le même numéro écrit autrement est refusé aussi. 14. Un autre numéro est accepté. 15. Une saisie vide est refusée à l'écran, la fenêtre reste ouverte. 16. Un numéro qui ne commence pas par 01, 05 ou 07 est refusé à l'écran. 17. (technique) Deux clients non standards peuvent partager un numéro (aucune régression pour l'assurance). 18. La recherche par numéro retrouve le client et la liste affiche son téléphone. 19. À l'ouverture, le curseur est dans le champ Nom. 20. Entrée depuis le Nom passe aux Prénoms. 21. Entrée depuis les Prénoms passe au Téléphone. 22. Entrée depuis le Téléphone passe à la date de naissance (facultative). 23. Entrée depuis la date de naissance vide passe au bouton « Enregistrer ». 24. Arriver sur le bouton n'enregistre rien : la fenêtre reste ouverte. 25. Aucun client n'a encore été créé à ce stade. 26. La fenêtre porte la zone d'animation de l'écran de vente. 27. Le champ actif « bat » comme dans la vente. 28. Le bouton « Enregistrer » bat quand le curseur l'atteint. 29. Entrée sur le bouton enregistre le client (la fenêtre se ferme). 30. Le client saisi entièrement au clavier est bien créé. 31. Le battement s'allume sur le bouton et s'éteint dès qu'on revient dans un champ. 32. Aucune erreur JavaScript pendant tout le parcours. 33. (technique) Tout ce que le test a posé est retiré. | H9: Les clients d'essai et leurs comptes sont retirés à la fin. | I9: retours/test-client-standard.js | J9: OK | K9: Joué le 30/10 23:29 — 33/33 controles OK
A10: CLI-06 | B10: Import de clients : choix des colonnes, contrôle ligne à ligne, droit requis | C10: GESTION DES TIERS-PAYANTS > Clients (menu lu dans la configuration des menus de l'application ; écran décrit par le test : Écran de gestion des clients, bouton « Importer » (menu non précisé dans le test)) | D10: Évolution 5, point 3 : l'ancien import lisait les colonnes à position fixe sans contrôle. Le nouvel import fait désigner les colonnes, juge chaque ligne séparément, rend son rapport avant d'écrire et n'est ouvert qu'aux profils ayant le droit « P_IMPORT_CLIENTS » (l'import historique suit le même droit). | E10: Un profil portant le droit « P_IMPORT_CLIENTS » (administrateur). Un client standard existant ayant déjà un numéro de téléphone (pour le cas « déjà en base »). Le test automatique crée lui-même : un opérateur d'essai sans ce droit (rôle Caisse/Commande/Stock) et un fichier CSV volontairement difficile : colonnes TELEPHONE;PRENOMS;NOM dans un ordre inattendu, une ligne sans téléphone, un numéro invalide (« pas-un-numero »), un doublon interne, un numéro déjà en base, une ligne vide, un numéro écrit avec des espaces. Pour un test manuel, préparer le même fichier et un opérateur sans le droit. | F10: 1. Se connecter avec l'opérateur d'essai sans le droit. 2. Ouvrir l'écran de gestion des clients et chercher le bouton « Importer ». 3. (Contrôle technique, fait par le test automatique) : appeler directement le service d'import, puis celui de l'import historique, avec ce profil. 4. Se connecter avec le profil portant le droit et ouvrir l'écran de gestion des clients. 5. Cliquer sur « Importer » : vérifier la présence de l'import historique et du nouvel import. 6. Ouvrir le nouvel import, choisir le fichier CSV d'essai et lancer la lecture des colonnes. 7. Vérifier les colonnes proposées puis lancer le contrôle (libellé du bouton non précisé dans le test). 8. Lire le rapport ligne à ligne. 9. Cliquer sur le bouton d'import. 10. Relancer le contrôle avec le même fichier. | G10: 1. (technique) Un profil sans le droit n'est pas autorisé à importer. 2. Le bouton d'import lui reste caché. 3. (technique) Le service d'import refuse ce profil même appelé directement. 4. L'import historique lui est caché aussi : les deux imports suivent le même droit. 5. (technique) Le service d'import historique refuse ce profil. 6. (technique) Un profil portant le droit est autorisé. 7. Le bouton d'import lui est proposé, à côté de l'import historique. 8. L'import historique est conservé et proposé à ce profil. 9. À l'ouverture, seules les étapes déjà possibles sont actives (colonnes et import désactivés). 10. Les colonnes du fichier sont rendues telles qu'elles sont, avec un échantillon. 11. Le séparateur « ; » est détecté et annoncé. 12. L'étape des colonnes s'active après la lecture. 13. (technique) Le fichier n'est envoyé qu'une fois : un jeton le désigne pour les étapes suivantes. 14. Les colonnes sont pré-désignées d'après les titres, malgré leur ordre inattendu. 15. (technique) Le contrôle n'écrit rien en base. 16. Le rapport annonce 3 lignes retenues et 4 rejetées. 17. La ligne sans téléphone est rejetée avec son motif. 18. Le numéro invalide est rejeté avec son motif. 19. Le doublon interne au fichier est rejeté en indiquant à quelle ligne. 20. Le numéro déjà attribué en base est rejeté. 21. La ligne entièrement vide est ignorée et non rejetée. 22. Le numéro saisi avec des séparateurs est normalisé. 23. Le bouton d'import ne s'active qu'une fois le contrôle fait. 24. L'import annonce « 3 client(s) créé(s) ». 25. Le bouton d'import se désactive après écriture (pas de double import). 26. (technique) Exactement les trois lignes retenues sont créées, avec leur numéro normalisé. 27. (technique) Les clients importés sont des clients standards actifs. 28. (technique) Chaque client importé a son compte client, comme par le formulaire. 29. (technique) Les prénoms viennent bien de la colonne désignée. 30. Rejouer le même fichier ne retient plus aucune ligne. 31. Aucune erreur JavaScript pendant tout le parcours. 32. (technique) Tout ce que le test a posé est retiré (clients importés, opérateur d'essai). | H10: Les clients importés et l'opérateur d'essai sont supprimés ; le fichier d'essai est effacé. | I10: retours/test-import-clients.js | J10: OK | K10: Joué le 30/10 21:10 — 32/32 controles OK
A11: CLI-07 | B11: Fiche client en fenêtre depuis les clients et la vente ; disposition de l'analyse article | C11: GESTION DES TIERS-PAYANTS > Clients ; SERVICE CLIENT > Ventes, bouton « Nouvelle vente » ; ANALYSE DE GESTION > Matrice marge × rotation, produits achetés ensemble et suivi des équivalences (menu lu dans la configuration des menus de l'application ; écran décrit par le test : Clients (non précisé dans le test) ; vente (non précisé dans le test) ; Analyse article (non précisé dans le test)) | D11: Retours du 10/10 : la fiche client (celle des Ordonnances) s'ouvre en fenêtre depuis la gestion des clients et depuis la vente via un bouton « FICHE CLIENT » visible seulement quand un client est sur la vente (point 14) ; l'analyse article a ses critères sur une ligne et ses actions à droite des onglets (point 11). | E11: Compte d'essai des tests automatiques (administrateur). Au moins un client actif avec un prénom. Écran de 1 366 × 768. Lecture seule. | F11: 1. Se connecter avec le compte d'essai. 2. Ouvrir l'écran « Clients » (menu : voir colonne « Écran »). 3. Sur la ligne d'un client, cliquer sur l'action « Fiche client », puis fermer la fenêtre. 4. Ouvrir l'écran de vente (menu : voir colonne « Écran ») sans client. 5. Mettre un client sur la vente. 6. Cliquer sur « FICHE CLIENT », puis fermer la fenêtre. 7. Retirer le client de la vente. 8. Ouvrir l'écran « Analyse article » (menu : voir colonne « Écran ») et regarder la disposition. | G11: 1. Chaque ligne de la liste des clients a une action « Fiche client ». 2. La fiche client s'ouvre en fenêtre modale, titrée « Fiche client », sur ce client. 3. Vente sans client : le bouton « FICHE CLIENT » est masqué. 4. Client posé sur la vente : « FICHE CLIENT » est visible. 5. Le clic ouvre la fiche de ce client en fenêtre. 6. Client retiré : le bouton est de nouveau masqué. 7. Analyse article : une seule ligne de critères ; « Analyser » vient après le seuil de marge et le seuil de rotation. 8. Analyse article : les boutons inventaire, Excel et Imprimer sont à droite sur la ligne des onglets. 9. Aucune erreur JavaScript. | H11: Rien à retirer (lecture seule). | I11: retours/test-fiche-client-fenetre.js | J11: OK | K11: Joué le 30/10 15:33 — 9 / 9 conformes
