Workbook

Sheet Mode d'emploi
A1: Cahier de recette : corrections des audits de code
A3: Version testée | B3: Branche PRES-/audits-code-dffa0a, commit 9b02b3c7 (26/10/2026). WAR : target/prestige.war construit à partir de ce commit. Il ne contient pas les commits récents de la branche principale (droits, horloge, bornes, téléphone de la vente).
A4: Référence | B4: docs/notices/CONFIRMATION_AUDITS_CODE_2026-10-25.md : fiches par constat (§3), corrections (§9), règle de remise de la vente assurance (§9.5).
A5: Base | B5: Une copie de travail uniquement, jamais une base de production. Les données d'essai sont à retirer après la recette.
A6: Préparation | B6: Caisse ouverte pour l'utilisateur de test. Pour les remises : une remise de 10 % avec sa grille VO et VNO, un produit remisable et un produit non remisable (code remise vide). Pour l'assurance : un organisme à 80 % et un à 95 %, un client assuré. Pour les différés : un client et une vente comptant de 2 boîtes en différé. Pour le carnet : un carnet dépôt avec un solde de 5 000 F.
A7: Deux postes | B7: Plusieurs cas demandent deux postes ou deux onglets ouverts en même temps (VC-01, VC-02, VC-04, VC-09, DIF-01, F1, F2, F3).
A8: Appel direct | B8: Quelques cas ne sont pas atteignables par l'écran (l'écran les bloque) : ils se jouent par un appel REST, comme l'appli mobile ou un écran resté ouvert. Le test automatique cité les joue.
A9: Colonnes à remplir | B9: Onglet « Cas de recette », colonnes en jaune : Résultat obtenu, Statut, Testeur, Date, Commentaire. Le statut se choisit dans la liste : OK, KO, Bloqué, Non joué.
A10: Synthèse | B10: L'onglet « Synthèse » se calcule seul à partir des statuts.
A11: Tests automatiques | B11: Colonne « Test automatique » : script Playwright du dépôt (src/test/e2e/...), lancé seul, un à la fois : node src/test/e2e/audits/repro-vente-comptant.js. Une ligne FAIL = défaut présent.
A12: Restent en échec | B12: VC-12 et VC-16 (cas « hier ») : décision métier en attente sur la date des écritures. Voir l'onglet « Décisions ».
A14: Exemple de saisie
A15: Résultat obtenu | B15: Refus « vente non modifiable » ; vente 6 950 F, stock 98
A16: Statut | B16: OK
A17: Testeur | B17: Initiales du testeur
A18: Date | B18: 27/10/2026
A19: Commentaire | B19: Joué sur deux onglets du même poste

Sheet Cas de recette
A1: N° | B1: Module | C1: Constat | D1: Gravité | E1: Titre | F1: Données / préconditions | G1: Procédure | H1: Résultat attendu (après correction) | I1: Constaté avant correction | J1: Test automatique | K1: Résultat obtenu | L1: Statut | M1: Testeur | N1: Date | O1: Commentaire
A2: 1 | B2: Vente comptant | C2: VC-01 | D2: A | E2: Ligne d'une vente encaissée modifiable | F2: Produit à 3 475 F, stock 100. Vente comptant de 2 boîtes. | G2: 1. Ouvrir la même prévente sur deux postes (ou deux onglets). 2. Poste B : encaisser la vente en espèces. 3. Poste A, resté ouvert : passer la quantité de la ligne à 5 dans la grille. | H2: La modification est refusée avec un message (vente non modifiable). La vente reste à 2 boîtes, 6 950 F ; stock 98. | I2: Modification acceptée : ligne à 5 boîtes, vente 17 375 F, stock 98, caisse 6 950 F. | J2: repro-vente-comptant.js (VC-01) | K2: Réussi : VC-01 précondition : vente comptant de 2 boîtes encaissée [4c8ce3c2-ce74-43c6-a51e-0bc9b63a8b34] Réussi : VC-01 attendu : modifier la quantité d'une ligne d'une vente encaissée est refusé, ligne inchangée (2 boîtes) [réponse {"msg":"Cette vente (N° 261026_00268) a été clôturée le 26/10/2026 19:36 : elle ne peut plus être modifiée ici. Pour retirer un produit, passez par « Ventes ter ; ligne après = qté|montant 2|6950 ; vente {"statut":"is_Closed","annulee":false,"prix":6950,"remise":0,"partClient":0,"tva":0,"client":"NU… | L2: OK | M2: Claude (tests automatiques) | N2: 26/10/2026 | O2: Test automatique repro-vente-comptant.js, 26/10/2026 19:35-19:45 : 2 réussi(s), 0 en échec
A3: 2 | B3: Vente comptant | C3: VC-02 | D3: A | E3: « Terminer la prévente » sur une vente encaissée | F3: Vente comptant d'une boîte, encaissée sur un autre poste. | G3: 1. Poste A : ouvrir la prévente. 2. Poste B : encaisser cette vente. 3. Poste A : cliquer « Terminer la prévente ». | H3: Refus. La vente reste clôturée et dans la caisse du jour. | I3: Succès : la vente repassait « en cours » et sortait de la caisse du jour. | J3: repro-vente-comptant.js (VC-02) | K3: Réussi : VC-02 attendu : « Terminer la prévente » sur une vente encaissée est refusé, statut is_Closed conservé [réponse {"msg":"Cette vente (N° 261026_00269) a été clôturée le 26/10/2026 19:36 : elle ne peut plus être modifiée ici. Pour ret ; statut après is_Closed ; transactions de caisse 1] | L3: OK | M3: Claude (tests automatiques) | N3: 26/10/2026 | O3: Test automatique repro-vente-comptant.js, 26/10/2026 19:35-19:45 : 1 réussi(s), 0 en échec
A4: 3 | B4: Vente comptant | C4: VC-04 | D4: A | E4: Annulation pendant une modification | F4: Vente comptant d'une boîte à 3 475 F, encaissée. | G4: 1. Poste A : Ventes terminées → Modifier (la copie s'ouvre). 2. Poste B : Ventes terminées → Annuler la même vente. 3. Poste A : valider la copie. | H4: L'annulation du poste B est refusée tant que la modification est ouverte. La copie se valide normalement ; une seule vente active ; stock et caisse justes. | I4: Tout accepté : l'origine annulée 3 fois, stock 97 → 97, caisse nette 0 F. | J4: repro-vente-comptant.js (VC-04) | K4: Réussi : VC-04 précondition : modification ouverte (copie en cours) [{"msg":"Opération effectuée avec success","data":{"lgPREENREGISTREMENTID":"a923845f-86f8-4a9b-a563-9b98c08518bd","intPRICE":3475,"intPRICEREMISE":0,"strREF":"26] Réussi : VC-04 attendu : annuler la vente pendant sa modification est refusé, ou la clôture de la copie ne la réannule pas (une seule annulation ; stock = stock de départ − 1 car la copie est vendue) [annulation {"msg":"Cette vente est en cours de modification : terminez ou abandonnez la mod ; clôture copie {"s":true,"m":"Opération effectuée avec success"} ; annulations de l'origine 1 ; stock départ 97 → fin 96 ; somme caiss… | L4: OK | M4: Claude (tests automatiques) | N4: 26/10/2026 | O4: Test automatique repro-vente-comptant.js, 26/10/2026 19:35-19:45 : 2 réussi(s), 0 en échec
A5: 4 | B5: Vente comptant | C5: VC-05 | D5: A | E5: TVA doublée avec une remise | F5: Remise de 10 % sur un produit TVA 18 % (par exemple 3 270 F). | G5: 1. Vente comptant du produit. 2. Choisir la remise, puis « Net à payer ». 3. Encaisser. 4. Comparer la TVA de la vente (ticket Z, mouvement de caisse) à la somme des TVA des lignes. | H5: TVA de la vente = somme des TVA des lignes. | I5: TVA de la vente 998 pour 499 sur les lignes. | J5: repro-remise-caisse.js (VC-05) | K5: Réussi : VC-05 attendu : TVA de la vente = somme des TVA des lignes [clôture true ; TVA en-tête 499 ; somme des lignes 499 ; TVA du mouvement de caisse 499] | L5: OK | M5: Claude (tests automatiques) | N5: 26/10/2026 | O5: Test automatique repro-remise-caisse.js, 26/10/2026 19:35-19:45 : 1 réussi(s), 0 en échec
A6: 5 | B6: Vente comptant | C6: VC-06 | D6: A | E6: Net demandé sans remise : remise conservée | F6: Vente comptant avec la remise de 10 % posée. | G6: 1. Poser la remise. 2. Demander le net sans remise (cas de l'appli mobile). 3. Encaisser au plein tarif. | H6: La vente n'enregistre aucune remise (remise = 0). | I6: Encaissé au plein tarif, mais remise de 327 F enregistrée. | J6: repro-remise-caisse.js (VC-06) | K6: Réussi : VC-06 attendu : une vente encaissée au net sans remise n'enregistre pas de remise (remise de la vente = 0) [net demandé sans remiseId 3270 (plein tarif 3270) ; clôture true ; remise enregistrée sur la vente 0 ; transaction montant|remise|payé 3270|0|3270] | L6: OK | M6: Claude (tests automatiques) | N6: 26/10/2026 | O6: Test automatique repro-remise-caisse.js, 26/10/2026 19:35-19:45 : 1 réussi(s), 0 en échec
A7: 6 | B7: Vente comptant | C7: VC-07 | D7: A | E7: Remise enregistrée différente de la remise encaissée | F7: Vente comptant avec la remise de 10 % (produit à 3 270 F). | G7: 1. Poser la remise, Net à payer. 2. Noter la remise affichée et le net. 3. Encaisser, puis consulter la vente. | H7: Remise enregistrée = remise affichée ; prix − remise = net payé. | I7: Remise affichée 325, enregistrée 327 ; payé 2 945 pour prix − remise = 2 943. | J7: repro-remise-caisse.js (VC-05/VC-07) | K7: Réussi : VC-05/07 précondition : remise de 10 % posée et appliquée (prix 3270 F, TVA 18 %) [pose {"msg":"Opération effectuée avec success","success":true,"http":200} ; net {"margeUg":0,"montant":3270,"montantAccount":0,"restructuring":false,"remise":325,"cmuAmount":0,"montantTva":499,"montantNet":2945,"marge":198,"montantTtcUg":0,"montantTvaUg":0,"montantTp":0,"tiersPay] Réussi : VC-07 attendu : la remise enregistrée est celle affichée et encaissée (prix − remise = net payé) [remise affichée 325 ; net affiché 2945 ; remise enregistrée (vente) 325 ; prix − remise enregistrée 2945 ; transaction remise|net|payé 325|2945|2945] | L7: OK | M7: Claude (tests automatiques) | N7: 26/10/2026 | O7: Test automatique repro-remise-caisse.js, 26/10/2026 19:35-19:45 : 2 réussi(s), 0 en échec
A8: 7 | B8: Vente comptant | C8: VC-08 | D8: D | E8: Client d'une vente encaissée remplacé | F8: Vente encaissée pour un client. | G8: Appel direct (appli mobile) : POST vente/update/client avec un identifiant de client inconnu. | H8: Vente encaissée : refus, client inchangé. Sur une vente en cours, un client inconnu laisse le client inchangé (réponse succès, pour l'appli mobile). | I8: Succès et client de la vente vidé (NULL). | J8: repro-vente-comptant.js (VC-08) | K8: Réussi : VC-08 précondition : vente encaissée rattachée au client d'essai [{"statut":"is_Closed","annulee":false,"prix":3475,"remise":0,"partClient":0,"tva":0,"client":"ZZAUDIT-CL-VC08"}] Réussi : VC-08 attendu : changer le client d'une vente encaissée (identifiant inconnu) est refusé, client conservé [réponse {"msg":"Cette vente (N° 261026_00272) a été clôturée le 26/10/2026 19:36 : elle ne peut plus être modifiée ici. Pour ret ; client après ZZAUDIT-CL-VC08] | L8: OK | M8: Claude (tests automatiques) | N8: 26/10/2026 | O8: Test automatique repro-vente-comptant.js, 26/10/2026 19:35-19:45 : 2 réussi(s), 0 en échec
A9: 8 | B9: Vente comptant | C9: VC-09 | D9: A | E9: Stock négatif à la validation | F9: Paramètre FORCER_STOCK_VENTE = 0, produit avec stock 1. | G9: 1. Poste A et poste B saisissent chacun 1 boîte du produit. 2. Valider sur A, puis sur B. | H9: La seconde validation est refusée (stock insuffisant). Stock final 0. | I9: Les deux validations passent, stock −1. | J9: repro-vente-comptant.js (VC-09) | K9: Réussi : VC-09 précondition : deux ventes en cours de 1 boîte chacune, stock 1, FORCER_STOCK_VENTE = 0 [af947d3d-f2fb-4a6e-9ca2-35af72429c04 / dda46ad3-e694-45c6-a19a-aa1e47c77f64] Réussi : VC-09 attendu : la seconde validation est refusée, le stock ne passe pas sous zéro [clôture 1 true ; clôture 2 {"s":false,"m":"Impossible de valider la vente : stock insuffisant pour A CIN 500MG CPR PELL B/3 (une autre vente l'a peut-être pris entre-temps). Veuillez modifier la vente."} ; stock final 0] | L9: OK | M9: Claude (tests automatiques) | N9: 26/10/2026 | O9: Test automatique repro-vente-comptant.js, 26/10/2026 19:35-19:45 : 2 réussi(s), 0 en échec
A10: 9 | B10: Vente comptant | C10: VC-11 | D10: A | E10: Annulation : stock rendu au mauvais lot | F10: Lot A (péremption proche) épuisé, lot B (péremption lointaine) à 5. Vente de 2 boîtes, sortie du lot B. | G10: 1. Annuler la vente. 2. Consulter les lots du produit. | H10: Les 2 boîtes reviennent au lot B : A = 0, B = 5. | I10: A = 2, B = 3. | J10: repro-vente-comptant.js (VC-11) | K10: Réussi : VC-11 précondition : lot A (péremption proche) épuisé, lot B à 5 ; la vente de 2 boîtes sort du lot B [ZZAUDIT-LOT-A=0,ZZAUDIT-LOT-B=3] Réussi : VC-11 attendu : l'annulation rend les 2 boîtes au lot B d'où elles sont sorties (A=0, B=5) [annulation true ; lots après annulation ZZAUDIT-LOT-A=0,ZZAUDIT-LOT-B=5] | L10: OK | M10: Claude (tests automatiques) | N10: 26/10/2026 | O10: Test automatique repro-vente-comptant.js, 26/10/2026 19:35-19:45 : 2 réussi(s), 0 en échec
A11: 10 | B11: Vente comptant | C11: VC-12 | D11: A | E11: Modification d'une vente de la veille : dates mélangées | F11: Vente encaissée datée de la veille. | G11: 1. Ventes terminées → Modifier la vente sans rien changer. 2. Valider. 3. Comparer les dates de la transaction, de la contre-passation, de la recette et du mouvement de stock. | H11: DÉCISION EN ATTENTE (date de l'opération ou de la saisie) : non corrigé. À jouer pour constat seulement. | I11: Transaction et contre-passation datées de la veille ; recette et stock du jour. | J11: repro-vente-comptant.js (VC-12) : reste en échec tant que la décision n'est pas prise | K11: ÉCHEC : VC-12 attendu : toutes les écritures de la modification d'une vente d'hier portent la même date [clôture copie true ; transaction de la copie 2026-10-25 ; contre-passation 2026-10-25,2026-10-25 ; recette de la copie 2026-10-26 ; mouvement de stock de la copie 2026-10-26 ; aujourd'hui 2026-10-26] | L11: KO | M11: Claude (tests automatiques) | N11: 26/10/2026 | O11: Test automatique repro-vente-comptant.js, 26/10/2026 19:35-19:45 : 0 réussi(s), 1 en échec. Écart attendu : décision métier en attente sur la date des écritures (onglet Décisions), rien n'a été changé
A12: 11 | B12: Vente comptant | C12: VC-14 | D12: A | E12: Montant payé du poste pris tel quel | F12: Vente comptant de 6 950 F. | G12: Appel direct : clôture avec « montant payé = 1 » (l'écran bloque ce cas). | H12: Clôture refusée : les règlements ne couvrent pas le net (tolérance 5 F). | I12: Acceptée : transaction et recette à 1 F. | J12: repro-vente-comptant.js (VC-14) | K12: Réussi : VC-14 attendu : une clôture qui déclare 1 F payé pour une vente de 6950 F est refusée [clôture {"s":false,"m":"Le montant réglé (1 F) est inférieur au net de la vente (6950 F) : vérifiez les montants saisis, ou choisissez le règlement en différé."} ; transaction montant|net|payé|réglé ; recette aucune] | L12: OK | M12: Claude (tests automatiques) | N12: 26/10/2026 | O12: Test automatique repro-vente-comptant.js, 26/10/2026 19:35-19:45 : 1 réussi(s), 0 en échec
... A55: 54 | B55: Différés | C55: DIF-09 | D55: D | E55: Ventilation dans l'ordre des clics | F55: Deux ventes différées du même client, une ancienne et une récente. | G55: Faire un règlement partiel en cochant la récente puis l'ancienne. | H55: La plus ancienne est soldée en premier. | I55: La récente était soldée, l'ancienne restait due. | J55: repro-differes.js (DIF-09) | K55: Réussi : DIF-09 attendu : un règlement partiel solde d'abord la vente la plus ancienne [reste de l'ancienne 0 ; reste de la récente 2755] | L55: OK | M55: Claude (tests automatiques) | N55: 26/10/2026 | O55: Test automatique repro-differes.js, 26/10/2026 19:35-19:45 : 1 réussi(s), 0 en échec
A56: 55 | B56: Différés | C56: DIF-10 | D56: Af | E56: Valider à 0 F sans message | F56: Dette à régler. | G56: Écran « Faire un règlement » : valider sans saisir de montant reçu. | H56: Message « Saisissez le montant reçu. » | I56: Rien ne se passait (non joué à l'écran avant correction). | J56: Contrôle à l'écran uniquement | L56: Non joué | M56: Claude (tests automatiques) | N56: 26/10/2026 | O56: Aucun test automatique pour ce cas : à jouer à l'écran.. Contrôle à l'écran seulement (message « Saisissez le montant reçu. ») : non automatisé, à vérifier à l'écran
A57: 56 | B57: Non-régression | C57: NR-01 | D57: — | E57: Annulation simple et double annulation | F57: Vente comptant encaissée. | G57: Annuler la vente ; tenter une seconde annulation (autre poste). | H57: Une seule annulation ; stock rendu une fois ; la seconde est refusée. | I57: — | J57: retours/test-annulation-vente-double.js | K57: 11 contrôle(s) réussi(s), 0 en échec. | L57: OK | M57: Claude (tests automatiques) | N57: 26/10/2026 | O57: Test automatique test-annulation-vente-double.js, 26/10/2026 19:35-19:45 : 11 réussi(s), 0 en échec
A58: 57 | B58: Non-régression | C58: NR-02 | D58: — | E58: Différés : modification, règlement, solde, nom du client | F58: Ventes différées d'essai. | G58: Parcours complets « Gestion des différés » : modifier, régler (espèces, mobile money), relevé, PDF, Excel. | H58: Solde du relevé = somme des restes dus ; PDF et Excel conformes à l'écran. | I58: — | J58: retours/test-differes-*.js, test-differe-nom-client.js | K58: 54 contrôle(s) réussi(s), 2 en échec. ÉCHEC : Bouton « Imprimer (PDF) » : ouvre le relevé avec la période et le client de l'écran ÉCHEC : PDF : titre et période, client, lignes (ventes, règlement, fin de mois), totaux = écran | L58: Bloqué | M58: Claude (tests automatiques) | N58: 26/10/2026 | O58: Test automatique test-differes-modification, test-differes-reglement, test-differes-solde, test-differe-nom-client.js, 26/10/2026 19:35-19:45 : 54 réussi(s), 2 en échec. Environnement du poste : les 2 échecs portent sur l'ouverture du PDF par le navigateur de test (Chromium sans écran télécharge le PDF au lieu d'exposer son adresse). Le PDF produit par le serveur a été lu à part le 26/10 : titre, client, lignes et totaux conformes à l'écran
A59: 58 | B59: Non-régression | C59: NR-03 | D59: — | E59: Mouvements de caisse | F59: Caisse ouverte. | G59: Écran Mouvements de caisse : filtres, saisie d'une entrée et d'une sortie. | H59: Trois types proposés ; filtres et saisie corrects. | I59: — | J59: caisse/test-mvt-caisse.js | K59: 11 contrôle(s) réussi(s), 0 en échec. | L59: OK | M59: Claude (tests automatiques) | N59: 26/10/2026 | O59: Test automatique test-mvt-caisse.js, 26/10/2026 19:35-19:45 : 11 réussi(s), 0 en échec
A60: 59 | B60: Non-régression | C60: NR-04 | D60: — | E60: Vente au détail avec déconditionnement | F60: Produit au détail avec sa boîte parente. | G60: Vente au comptant de 3 unités avec 2 en rayon. | H60: Boîte ouverte, stock et historique cohérents. | I60: — | J60: vente/test-historique-deconditionnement.js (partie dépôt : poste avec un dépôt de type 2) | K60: 9 contrôle(s) réussi(s), 6 en échec. ÉCHEC : Jeu d'essai : produit au détail (boîte de 14) et dépôt trouvés [8452598D ] ÉCHEC : B. Vente au dépôt de 3 (2 en rayon) validée [{"msg":"Erreur: Echec de validation de la vente","success":false}] ÉCHEC : B. Officine : ligne de vente au dépôt part du stock après ouverture (16 → 13) [[]] ÉCHEC : B. Officine : dernière ligne = stock réel [undefined / 2] ÉCHEC : B. Dépôt : entrée en stock en hausse (0 → 3) [[]] ÉCHEC : B. Dépôt : dernière ligne = stock réel du dépôt [undefined / 0] | L60: Bloqué | M60: Claude (tests automatiques) | N60: 26/10/2026 | O60: Test automatique test-historique-deconditionnement.js, 26/10/2026 19:35-19:45 : 9 réussi(s), 6 en échec. Environnement du poste : la partie A (officine) passe en entier ; la partie B demande un dépôt de type 2, absent de la base de test (0 dépôt)
A61: 60 | B61: Non-régression | C61: NR-05 | D61: — | E61: Vente assurance : deuxième assurance, changement de tiers payant | F61: Client à deux assurances. | G61: Modifier la deuxième assurance d'une vente ; changer le tiers payant d'une vente. | H61: La première assurance et la référence du bon sont intactes ; un échec ne laisse rien à moitié. | I61: — | J61: vente/test-deuxieme-assurance.js, journal/test-vente-changer-tiers-payant.js | K61: 21 contrôle(s) réussi(s), 0 en échec. | L61: OK | M61: Claude (tests automatiques) | N61: 26/10/2026 | O61: Test automatique test-deuxieme-assurance, test-vente-changer-tiers-payant.js, 26/10/2026 19:35-19:45 : 21 réussi(s), 0 en échec
A62: 61 | B62: Non-régression | C62: NR-06 | D62: — | E62: Facturation des carnets dépôt | F62: Carnet dépôt avec des ventes. | G62: Gérer carnet dépôt → onglet FACTURES, créer, voir, imprimer. | H62: Factures créées et imprimées avec le détail des médicaments. | I62: — | J62: carnet-depot/test-facturation-carnet-depot.js | K62: 33 contrôle(s) réussi(s), 0 en échec. | L62: OK | M62: Claude (tests automatiques) | N62: 26/10/2026 | O62: Test automatique test-facturation-carnet-depot.js, 26/10/2026 19:35-19:45 : 33 réussi(s), 0 en échec
A63: 62 | B63: Non-régression | C63: NR-07 | D63: — | E63: Crédit client et mode de règlement client | F63: Client avec crédit. | G63: Vente à crédit ; réglage du mode de règlement du client. | H63: Crédit et modes conformes. | I63: — | J63: vente/test-client-credit-course.js, vente/test-mode-reglement-client.js | K63: 33 contrôle(s) réussi(s), 0 en échec. | L63: OK | M63: Claude (tests automatiques) | N63: 26/10/2026 | O63: Test automatique test-client-credit-course, test-mode-reglement-client.js, 26/10/2026 19:35-19:45 : 33 réussi(s), 0 en échec

Sheet Synthèse
A1: Module | B1: Cas | C1: OK | D1: KO | E1: Bloqué | F1: Non joué | G1: % OK
A2: Vente comptant | B2: =COUNTIF('Cas de recette'!$B$2:$B$63,A2) -> 13 | C2: =COUNTIFS('Cas de recette'!$B$2:$B$63,A2,'Cas de recette'!$L$2:$L$63,"OK") -> 12 | D2: =COUNTIFS('Cas de recette'!$B$2:$B$63,A2,'Cas de recette'!$L$2:$L$63,"KO") -> 1 | E2: =COUNTIFS('Cas de recette'!$B$2:$B$63,A2,'Cas de recette'!$L$2:$L$63,"Bloqué") -> 0 | F2: =COUNTIFS('Cas de recette'!$B$2:$B$63,A2,'Cas de recette'!$L$2:$L$63,"Non joué") -> 0 | G2: =IF(B2=0,0,C2/B2) -> 0.92307692
A3: Caisse | B3: =COUNTIF('Cas de recette'!$B$2:$B$63,A3) -> 1 | C3: =COUNTIFS('Cas de recette'!$B$2:$B$63,A3,'Cas de recette'!$L$2:$L$63,"OK") -> 0 | D3: =COUNTIFS('Cas de recette'!$B$2:$B$63,A3,'Cas de recette'!$L$2:$L$63,"KO") -> 1 | E3: =COUNTIFS('Cas de recette'!$B$2:$B$63,A3,'Cas de recette'!$L$2:$L$63,"Bloqué") -> 0 | F3: =COUNTIFS('Cas de recette'!$B$2:$B$63,A3,'Cas de recette'!$L$2:$L$63,"Non joué") -> 0 | G3: =IF(B3=0,0,C3/B3) -> 0
A4: Vente assurance | B4: =COUNTIF('Cas de recette'!$B$2:$B$63,A4) -> 15 | C4: =COUNTIFS('Cas de recette'!$B$2:$B$63,A4,'Cas de recette'!$L$2:$L$63,"OK") -> 15 | D4: =COUNTIFS('Cas de recette'!$B$2:$B$63,A4,'Cas de recette'!$L$2:$L$63,"KO") -> 0 | E4: =COUNTIFS('Cas de recette'!$B$2:$B$63,A4,'Cas de recette'!$L$2:$L$63,"Bloqué") -> 0 | F4: =COUNTIFS('Cas de recette'!$B$2:$B$63,A4,'Cas de recette'!$L$2:$L$63,"Non joué") -> 0 | G4: =IF(B4=0,0,C4/B4) -> 1
A5: Carnet | B5: =COUNTIF('Cas de recette'!$B$2:$B$63,A5) -> 6 | C5: =COUNTIFS('Cas de recette'!$B$2:$B$63,A5,'Cas de recette'!$L$2:$L$63,"OK") -> 6 | D5: =COUNTIFS('Cas de recette'!$B$2:$B$63,A5,'Cas de recette'!$L$2:$L$63,"KO") -> 0 | E5: =COUNTIFS('Cas de recette'!$B$2:$B$63,A5,'Cas de recette'!$L$2:$L$63,"Bloqué") -> 0 | F5: =COUNTIFS('Cas de recette'!$B$2:$B$63,A5,'Cas de recette'!$L$2:$L$63,"Non joué") -> 0 | G5: =IF(B5=0,0,C5/B5) -> 1
A6: Facturation | B6: =COUNTIF('Cas de recette'!$B$2:$B$63,A6) -> 4 | C6: =COUNTIFS('Cas de recette'!$B$2:$B$63,A6,'Cas de recette'!$L$2:$L$63,"OK") -> 4 | D6: =COUNTIFS('Cas de recette'!$B$2:$B$63,A6,'Cas de recette'!$L$2:$L$63,"KO") -> 0 | E6: =COUNTIFS('Cas de recette'!$B$2:$B$63,A6,'Cas de recette'!$L$2:$L$63,"Bloqué") -> 0 | F6: =COUNTIFS('Cas de recette'!$B$2:$B$63,A6,'Cas de recette'!$L$2:$L$63,"Non joué") -> 0 | G6: =IF(B6=0,0,C6/B6) -> 1
A7: Liens assurance | B7: =COUNTIF('Cas de recette'!$B$2:$B$63,A7) -> 5 | C7: =COUNTIFS('Cas de recette'!$B$2:$B$63,A7,'Cas de recette'!$L$2:$L$63,"OK") -> 5 | D7: =COUNTIFS('Cas de recette'!$B$2:$B$63,A7,'Cas de recette'!$L$2:$L$63,"KO") -> 0 | E7: =COUNTIFS('Cas de recette'!$B$2:$B$63,A7,'Cas de recette'!$L$2:$L$63,"Bloqué") -> 0 | F7: =COUNTIFS('Cas de recette'!$B$2:$B$63,A7,'Cas de recette'!$L$2:$L$63,"Non joué") -> 0 | G7: =IF(B7=0,0,C7/B7) -> 1
A8: Différés | B8: =COUNTIF('Cas de recette'!$B$2:$B$63,A8) -> 11 | C8: =COUNTIFS('Cas de recette'!$B$2:$B$63,A8,'Cas de recette'!$L$2:$L$63,"OK") -> 10 | D8: =COUNTIFS('Cas de recette'!$B$2:$B$63,A8,'Cas de recette'!$L$2:$L$63,"KO") -> 0 | E8: =COUNTIFS('Cas de recette'!$B$2:$B$63,A8,'Cas de recette'!$L$2:$L$63,"Bloqué") -> 0 | F8: =COUNTIFS('Cas de recette'!$B$2:$B$63,A8,'Cas de recette'!$L$2:$L$63,"Non joué") -> 1 | G8: =IF(B8=0,0,C8/B8) -> 0.90909091
A9: Non-régression | B9: =COUNTIF('Cas de recette'!$B$2:$B$63,A9) -> 7 | C9: =COUNTIFS('Cas de recette'!$B$2:$B$63,A9,'Cas de recette'!$L$2:$L$63,"OK") -> 5 | D9: =COUNTIFS('Cas de recette'!$B$2:$B$63,A9,'Cas de recette'!$L$2:$L$63,"KO") -> 0 | E9: =COUNTIFS('Cas de recette'!$B$2:$B$63,A9,'Cas de recette'!$L$2:$L$63,"Bloqué") -> 2 | F9: =COUNTIFS('Cas de recette'!$B$2:$B$63,A9,'Cas de recette'!$L$2:$L$63,"Non joué") -> 0 | G9: =IF(B9=0,0,C9/B9) -> 0.71428571
A10: Total | B10: =SUM(B2:B9) -> 62 | C10: =SUM(C2:C9) -> 57 | D10: =SUM(D2:D9) -> 2 | E10: =SUM(E2:E9) -> 2 | F10: =SUM(F2:F9) -> 1 | G10: =IF(B10=0,0,C10/B10) -> 0.91935484
A12: Calculé à partir de la colonne Statut de l'onglet « Cas de recette ».

Sheet Décisions
A1: Sujet | B1: Constats | C1: État dans cette version | D1: Décision à prendre | E1: Décision prise | F1: Par | G1: Date
A2: Date des écritures de caisse | B2: VC-12, VC-16 | C2: Seules les dates futures sont refusées. Une modification d'une vente de la veille et un mouvement daté d'hier gardent des dates différentes selon l'écriture. | D2: Date de l'opération réelle, ou date de la saisie ?
A3: Vente différée réglée puis modifiée | B3: DIF-03 | C3: Refus (pas d'avoir), choisi par défaut. | D3: Refuser, ou reporter avec un avoir ?
A4: Annulation d'une vente déjà réglée | B4: D2 | C4: Refus (pas d'avoir), choisi par défaut. | D4: Refuser, ou créer un avoir ?
A5: Encours à la facturation | B5: F5 | C5: L'encours est recalculé depuis les bons non facturés. | D5: Remise à zéro, ou diminution du montant facturé ?
A6: Remise de la vente assurance | B6: CR-06 | C6: Tranché le 26/10 : remise sur la part client de chaque produit, plafond réparti au prorata. | D6: —
A7: Appli mobile | B7: VC-06, VC-08, VC-14, CR-07 | C7: Le serveur refuse désormais les montants incohérents envoyés par le poste. | D7: Vérifier avec l'appli mobile et fixer le calendrier.
A8: Encours sans verrou | B8: CR-04 | C8: Non corrigé : non reproduit (3 paires de clôtures simultanées justes). | D8: Faut-il ajouter un verrou malgré tout ?
