Workbook

Sheet Mode d'emploi
A1: Cahier de recette : points à revoir (retours du 28/10/2026)
A3: Version testée | B3: Branche PRES-/audits-code-dffa0a, commit 44378ec9 (28/10/2026 au soir). Serveur de recette domain3 : http://localhost:10090/prestige, base laborex_audit (copie de laborex_v1_db, envois SMS, e-mail, WhatsApp et PharmaML coupés). domain1 et laborex_v1_db ne sont pas touchés.
A4: Référence | B4: docs/notices/RETOURS_RECETTE_2026-10-28.md (réponses détaillées, résultats des tests) ; sorties des tests : docs/notices/preuves-audits-2026-10-25/retours-ecran-2026-10-28/.
A5: Contenu | B5: Les points relevés lors de ta recette du 28/10 : corrections à vérifier à l'écran, cas dont le test doit être refait par l'écran, non-régressions demandées, et constats nouveaux.
A6: Règle des tests | B6: Chaque procédure se joue comme un utilisateur : menus, clavier, boutons visibles. Aucun appel direct au serveur. Seule la préparation des données peut se faire autrement.
A7: Colonne « Test automatique » | B7: Nom du test d'écran et son résultat sur domain3 : ancienne version (6724b004) → version corrigée. « aucun » : pas encore de test, à jouer à la main.
A8: À remplir | B8: Résultat obtenu, Statut (OK, KO, Bloqué, Non joué), Testeur, Date, Commentaire. La feuille « Synthèse » se calcule seule à partir du statut.
A9: Gravité | B9: A : argent, stock ou dette faux, ou donnée perdue. B : écran ou donnée incohérente sans perte. C : confort, affichage.
A10: Questions | B10: La feuille « Questions et décisions » liste ce qui attend ta réponse.

Sheet Cas de recette
A1: N° | B1: Module | C1: Réf. | D1: Gravité | E1: Titre | F1: Données / préconditions | G1: Procédure | H1: Résultat attendu | I1: Constaté avant correction | J1: Test automatique | K1: Résultat obtenu | L1: Statut | M1: Testeur | N1: Date | O1: Commentaire
A2: 1 | B2: Vente assurance | C2: CA-09 | D2: A | E2: Changement d'organisme d'une vente terminée : encours affiché | F2: Client assuré chez A (90 %, principale) et C (10 %). Une vente assurance encaissée sur A seul. Organisme B non rattaché au client. | G2: 1. GESTION DES TIERS-PAYANTS > Tiers-payants : rechercher A puis B, noter la colonne « Encours ». 2. SERVICE CLIENT > Vente terminées : dates et n° de la vente, « rechercher ». 3. Icône « Modifier info client » de la ligne. 4. « Modifier le tiers-payant », choisir B, « Valider ». 5. « Enregistrer », répondre « Non » à l'impression. 6. Revenir dans « Tiers-payants » et relire A et B. | H2: L'encours de A baisse de la part de la vente ; celui de B monte de la part du nouveau bon (à 1 F près, voir le cas 15). | I2: B : 0 → 0. Le bon recréé pour B avait un reste dû vide, ignoré par l'écran. | J2: test-ecran-modifier-tp-vente-encours.js : 7/9 → 9/9 (A 2 551 → 0, B 0 → 2 552)
A3: 2 | B3: Facturation | C3: CA-09 | D3: A | E3: Bon d'une vente modifiée : facturé et réglé | F3: Vente du cas 1, portée par B après modification. | G3: 1. Facturer l'organisme B sur la période de la vente. 2. Vérifier que le bon de la vente figure dans la facture. 3. Faire un règlement de la facture (montant total). 4. Relire le reste de la facture et l'encours de B. | H3: Le bon est facturé ; le règlement le solde ; reste de la facture 0 ; l'encours de B redescend. | I3: Un bon sans reste dû était écarté du règlement (constaté en base, pas joué à l'écran). | J3: aucun
A4: 3 | B4: Données | C4: CA-09 | D4: B | E4: Reprise des anciens bons sans reste dû (script manuel) | F4: Sur une copie de base seulement, après sauvegarde. Script : outils/sql/corriger-reste-bons-modifies.sql. | G4: 1. Lancer la partie « 0. Constat » seule, noter les trois nombres. 2. Lancer tout le script. 3. Lire le contrôle de la partie 4. 4. Dans « Tiers-payants », relire l'encours d'un organisme concerné. | H4: Contrôle : 0 bon restant. L'encours des organismes concernés inclut ces bons. | I4: laborex_v1_db du 28/10 : 872 bons facturés, 179 non facturés, 15 de ventes annulées, sans reste dû. | J4: aucun (script non exécuté)
A5: 4 | B5: Fiche client | C5: M3, point 21 | D5: A | E5: Changement de l'assurance principale depuis l'écran de vente | F5: Client assuré : A 90 % (principale, priorité 1), C 10 % (priorité 2). Organisme B non rattaché. | G5: 1. SERVICE CLIENT > Ventes > nouvelle vente, type « Assurance ». 2. Taper le nom du client, Entrée. 3. Icône de modification du client (à côté de son nom). 4. « Assurance » : taper B, la choisir, « Enregistrer ». 5. Rouvrir la fiche et lire la grille « Infos Assurance Complémentaire ». | H5: B est la principale. A reste rattachée et active, à une priorité libre (3). Aucune priorité en double. | I5: A était supprimée (priorité −1). | J5: test-ecran-assurances-client-priorites.js : 8/13 → 13/13
A6: 5 | B6: Fiche client | C6: M3 | D6: A | E6: « Associer une assurance » : priorité proposée | F6: Client du cas 4, après le cas 4 (priorités 2 et 3 prises). | G6: 1. Ouvrir la fiche du client. 2. « Associer une assurance ». 3. Lire le champ « Priorité » sans le toucher. 4. Choisir un organisme D, taux 10, « Enregistrer », puis « Enregistrer » dans la fiche. | H6: La priorité proposée est la première libre (4 ici). D est enregistrée à cette priorité ; aucune priorité en double. | I6: Toujours 2 proposé : C et D se retrouvaient toutes deux en priorité 2 (ton constat). | J6: test-ecran-assurances-client-priorites.js : 8/13 → 13/13
A7: 6 | B7: Fiche client | C7: M3 | D7: A | E7: Priorité saisie déjà prise par une autre assurance | F7: Client avec C en priorité 2. | G7: 1. Fiche du client > « Associer une assurance ». 2. Choisir un organisme E, taux 10, remplacer la priorité par 2. 3. « Enregistrer » deux fois. 4. Rouvrir la fiche. | H7: C garde la priorité 2 ; E prend la première priorité libre. Aucune priorité en double. | I7: La priorité saisie était enregistrée telle quelle : doublon. | J7: repro-assurances-liens.js (P21-b) : 15/15 (par le serveur, pas par l'écran)
A8: 7 | B8: Fiche client | C8: Retours 28/10 | D8: B | E8: Taux, matricule et priorité modifiables dans la grille des complémentaires | F8: Client avec au moins une assurance complémentaire. | G8: 1. Ouvrir la fiche du client depuis l'écran de vente. 2. Cliquer dans la cellule « Taux.Couverture » d'une complémentaire, taper 15, Entrée. 3. Même chose pour « Numéro/SS » puis « RC » (priorité). 4. « Enregistrer », rouvrir la fiche. | H8: Les nouvelles valeurs sont gardées. Priorité acceptée de 2 à 4 seulement. Aucune priorité en double. | I8: Cellules non modifiables ; le serveur ignorait les changements d'une assurance déjà rattachée. | J8: test-ecran-assurances-client-priorites.js, étape 3 : 13/13
A9: 8 | B9: Ventes terminées | C9: M3 | D9: B | E9: Nouvel organisme créé depuis « Modifier info client » | F9: Vente assurance terminée d'un client qui a déjà deux assurances (priorités 1 et 2). | G9: 1. Vente terminées > « Modifier info client ». 2. « Modifier le tiers-payant » > « AJOUTER UN NOUVEAU TIERS-PAYANT ». 3. Saisir nom, téléphone, adresse, code ; « Enregistrer ». 4. Ouvrir la fiche du client et lire les priorités. | H9: Le nouvel organisme est rattaché au client à une priorité libre ; aucune priorité en double. | I9: Non mesuré avant. | J9: test-vente-changer-tiers-payant.js : 7/7 (ne contrôle pas les priorités)
A10: 9 | B10: Données | C10: M3 | D10: B | E10: Client de recette déjà en double (priorité 2 portée deux fois) | F10: Ton client de test du 28/10 (68dcd776-…), deux liens actifs en priorité 2 sur laborex_v1_db (ou sa copie laborex_audit). | G10: 1. Écran de vente, type Assurance, choisir ce client. 2. Ouvrir sa fiche, ne rien changer, « Enregistrer ». 3. Rouvrir la fiche. | H10: Les priorités sont devenues uniques (l'assurance la plus ancienne garde la 2). | I10: Doublon en base depuis le 28/10 14:01. | J10: aucun
A11: 10 | B11: Fiche article | C11: VC-11 | D11: C | E11: Stock restant du lot dans « Voir les lots / péremptions » | F11: Précondition : la version de « Recherche périmés » de la branche claude/new-session-xm8ptu est intégrée (elle fournit la quantité restante). Un produit avec un lot dont une partie est vendue. | G11: 1. GESTION DU STOCK > Fiche Article : taper le CIP, Entrée. 2. Sur la ligne, « Voir les lots / péremptions » (icône ou menu « Autres actions »). 3. Lire les colonnes du lot. | H11: Colonnes « Quantité saisie » puis « Quantité restante lot », avec le stock restant du lot. | I11: Aucune colonne de stock restant. | J11: test-fiche-article-qte-restante-lot.js : 2/4 → 3/4 (sans la version retenue de « Recherche périmés », la colonne affiche 0)
A12: 11 | B12: Recherche périmés | C12: VC-11 | D12: C | E12: Colonnes « Quantité saisie » et « Quantité restante », exports | F12: Version de la branche claude/new-session-xm8ptu (décision du 28/10). | G12: 1. Menu « Recherche périmés » : rechercher un produit à lot entamé. 2. Lire les deux colonnes. 3. Exporter en CSV puis en Excel. | H12: Grille : quantité saisie et quantité restante du lot. Exports : les deux colonnes. | I12: Une seule colonne « Qunatité » (quantité reçue). | J12: aucun sur cette branche (version de la session principale ; exports CSV et Excel à compléter par elle)
A13: 12 | B13: Ventes terminées | C13: DIF-02 / DIF-03 | D13: A | E13: Bouton « Modifier » sur une vente différée | F13: Utilisateur avec le droit « modification de vente ». Ta vente différée 261028_00002 (non annulée) et 261028_00003 (annulée). | G13: 1. SERVICE CLIENT > Vente terminées : date du 28/10. 2. Regarder la colonne des actions sur 261028_00002, puis sur 261028_00003, puis sur une vente comptant. | H13: Bouton présent sur 261028_00002 et sur la vente comptant ; absent sur 261028_00003 (annulée). | I13: Tu n'as pas vu le bouton : vente concernée inconnue (voir Questions). | J13: aucun (les tests DIF appelaient l'adresse du bouton : à refaire par l'écran)
... A20: 19 | B20: Vente assurance | C20: CA-03 | D20: A | E20: Organisme exclu : seules ses ventes sont exclues | F20: Un organisme marqué « exclure » dans « Gérer les tp à exclure », un organisme ordinaire, un client chez chacun. | G20: 1. Vente assurance encaissée sur l'organisme exclu. 2. Vente assurance encaissée sur l'organisme ordinaire. 3. Ouvrir le suivi des tiers payants exclus. | H20: Seule la première vente apparaît comme exclue. | I20: Les ventes suivantes étaient inscrites à tort comme exclues. | J20: repro-vente-assurance.js (CA-03) : OK par le serveur ; à refaire par l'écran

Sheet Synthèse
A1: Module | B1: Cas | C1: OK | D1: KO | E1: Bloqué | F1: Non joué | G1: % OK
A2: Vente assurance | B2: =COUNTIF('Cas de recette'!$B$2:$B$20,A2) -> 5 | C2: =COUNTIFS('Cas de recette'!$B$2:$B$20,A2,'Cas de recette'!$L$2:$L$20,"OK") -> 0 | D2: =COUNTIFS('Cas de recette'!$B$2:$B$20,A2,'Cas de recette'!$L$2:$L$20,"KO") -> 0 | E2: =COUNTIFS('Cas de recette'!$B$2:$B$20,A2,'Cas de recette'!$L$2:$L$20,"Bloqué") -> 0 | F2: =B2-C2-D2-E2 -> 5 | G2: =IF(B2=0,0,C2/B2) -> 0
A3: Facturation | B3: =COUNTIF('Cas de recette'!$B$2:$B$20,A3) -> 1 | C3: =COUNTIFS('Cas de recette'!$B$2:$B$20,A3,'Cas de recette'!$L$2:$L$20,"OK") -> 0 | D3: =COUNTIFS('Cas de recette'!$B$2:$B$20,A3,'Cas de recette'!$L$2:$L$20,"KO") -> 0 | E3: =COUNTIFS('Cas de recette'!$B$2:$B$20,A3,'Cas de recette'!$L$2:$L$20,"Bloqué") -> 0 | F3: =B3-C3-D3-E3 -> 1 | G3: =IF(B3=0,0,C3/B3) -> 0
A4: Données | B4: =COUNTIF('Cas de recette'!$B$2:$B$20,A4) -> 2 | C4: =COUNTIFS('Cas de recette'!$B$2:$B$20,A4,'Cas de recette'!$L$2:$L$20,"OK") -> 0 | D4: =COUNTIFS('Cas de recette'!$B$2:$B$20,A4,'Cas de recette'!$L$2:$L$20,"KO") -> 0 | E4: =COUNTIFS('Cas de recette'!$B$2:$B$20,A4,'Cas de recette'!$L$2:$L$20,"Bloqué") -> 0 | F4: =B4-C4-D4-E4 -> 2 | G4: =IF(B4=0,0,C4/B4) -> 0
A5: Fiche client | B5: =COUNTIF('Cas de recette'!$B$2:$B$20,A5) -> 4 | C5: =COUNTIFS('Cas de recette'!$B$2:$B$20,A5,'Cas de recette'!$L$2:$L$20,"OK") -> 0 | D5: =COUNTIFS('Cas de recette'!$B$2:$B$20,A5,'Cas de recette'!$L$2:$L$20,"KO") -> 0 | E5: =COUNTIFS('Cas de recette'!$B$2:$B$20,A5,'Cas de recette'!$L$2:$L$20,"Bloqué") -> 0 | F5: =B5-C5-D5-E5 -> 4 | G5: =IF(B5=0,0,C5/B5) -> 0
A6: Ventes terminées | B6: =COUNTIF('Cas de recette'!$B$2:$B$20,A6) -> 2 | C6: =COUNTIFS('Cas de recette'!$B$2:$B$20,A6,'Cas de recette'!$L$2:$L$20,"OK") -> 0 | D6: =COUNTIFS('Cas de recette'!$B$2:$B$20,A6,'Cas de recette'!$L$2:$L$20,"KO") -> 0 | E6: =COUNTIFS('Cas de recette'!$B$2:$B$20,A6,'Cas de recette'!$L$2:$L$20,"Bloqué") -> 0 | F6: =B6-C6-D6-E6 -> 2 | G6: =IF(B6=0,0,C6/B6) -> 0
A7: Fiche article | B7: =COUNTIF('Cas de recette'!$B$2:$B$20,A7) -> 1 | C7: =COUNTIFS('Cas de recette'!$B$2:$B$20,A7,'Cas de recette'!$L$2:$L$20,"OK") -> 0 | D7: =COUNTIFS('Cas de recette'!$B$2:$B$20,A7,'Cas de recette'!$L$2:$L$20,"KO") -> 0 | E7: =COUNTIFS('Cas de recette'!$B$2:$B$20,A7,'Cas de recette'!$L$2:$L$20,"Bloqué") -> 0 | F7: =B7-C7-D7-E7 -> 1 | G7: =IF(B7=0,0,C7/B7) -> 0
A8: Recherche périmés | B8: =COUNTIF('Cas de recette'!$B$2:$B$20,A8) -> 1 | C8: =COUNTIFS('Cas de recette'!$B$2:$B$20,A8,'Cas de recette'!$L$2:$L$20,"OK") -> 0 | D8: =COUNTIFS('Cas de recette'!$B$2:$B$20,A8,'Cas de recette'!$L$2:$L$20,"KO") -> 0 | E8: =COUNTIFS('Cas de recette'!$B$2:$B$20,A8,'Cas de recette'!$L$2:$L$20,"Bloqué") -> 0 | F8: =B8-C8-D8-E8 -> 1 | G8: =IF(B8=0,0,C8/B8) -> 0
A9: Vente différée | B9: =COUNTIF('Cas de recette'!$B$2:$B$20,A9) -> 2 | C9: =COUNTIFS('Cas de recette'!$B$2:$B$20,A9,'Cas de recette'!$L$2:$L$20,"OK") -> 0 | D9: =COUNTIFS('Cas de recette'!$B$2:$B$20,A9,'Cas de recette'!$L$2:$L$20,"KO") -> 0 | E9: =COUNTIFS('Cas de recette'!$B$2:$B$20,A9,'Cas de recette'!$L$2:$L$20,"Bloqué") -> 0 | F9: =B9-C9-D9-E9 -> 2 | G9: =IF(B9=0,0,C9/B9) -> 0
A10: Vente comptant | B10: =COUNTIF('Cas de recette'!$B$2:$B$20,A10) -> 1 | C10: =COUNTIFS('Cas de recette'!$B$2:$B$20,A10,'Cas de recette'!$L$2:$L$20,"OK") -> 0 | D10: =COUNTIFS('Cas de recette'!$B$2:$B$20,A10,'Cas de recette'!$L$2:$L$20,"KO") -> 0 | E10: =COUNTIFS('Cas de recette'!$B$2:$B$20,A10,'Cas de recette'!$L$2:$L$20,"Bloqué") -> 0 | F10: =B10-C10-D10-E10 -> 1 | G10: =IF(B10=0,0,C10/B10) -> 0
A11: Total | B11: =SUM(B2:B10) -> 19 | C11: =SUM(C2:C10) -> 0 | D11: =SUM(D2:D10) -> 0 | E11: =SUM(E2:E10) -> 0 | F11: =SUM(F2:F10) -> 19 | G11: =IF(B11=0,0,C11/B11) -> 0

Sheet Questions et décisions
A1: Sujet | B1: Cas | C1: Question | D1: Réponse / décision | E1: Par | F1: Date
A2: Bouton « Modifier » des différés | B2: DIF-02, DIF-03 | C2: Sur quelle vente le bouton manquait-il : 261028_00002 ou 261028_00003 (annulée) ? Apparaît-il sur les autres ventes avec le même utilisateur ?
A3: Acompte d'une différée modifiée | B3: DIF-02 | C3: La copie doit-elle reprendre automatiquement le montant déjà reçu, ou la caissière le ressaisit-elle (comportement actuel) ?
A4: Écart d'1 F | B4: Constat 28/10 | C4: À la modification de l'organisme : garder la part de la vente, ou accepter le recalcul ?
A5: Script de reprise des bons | B5: CA-09 | C5: Sur quelles bases, quand et par qui exécuter outils/sql/corriger-reste-bons-modifies.sql ?
A6: Priorité saisie déjà prise | B6: M3 | C6: Aujourd'hui l'assurance la plus ancienne garde la priorité et la nouvelle passe à la suivante. Faut-il au contraire donner raison à la saisie et décaler l'autre ?
A7: Vente en dépôt | B7: Retours 28/10 | C7: La grille des complémentaires doit-elle aussi devenir modifiable dans la fiche client de la vente en dépôt ?
A8: Serveur domain3 | B8: — | C8: Garder domain3 et la copie laborex_audit après ta recette, ou les supprimer ?
