Workbook

Sheet Synthèse
B2: CAHIER DE RECETTE — Évolutions Prestige
B3: Application pharmacie Prestige — branche claude/evolution-branch-setup-fs37ds
B5: Projet | C5: Prestige — Lot d'évolutions (12 points)
B6: Version / Branche | C6: claude/evolution-branch-setup-fs37ds
B7: Date de recette
B8: Testeur
B9: Environnement | C9: Officine / Dépôt — préciser (recette / pré-prod / prod)
B10: Navigateur
B11: Statut global
B13: LÉGENDE STATUT
B14: OK | C14: Conforme au résultat attendu
B15: KO | C15: Non conforme / anomalie
B16: Bloqué | C16: Test non exécutable (dépendance/pré-requis)
B17: N/A | C17: Non applicable dans ce contexte
B19: PRÉ-REQUIS & POINTS D'ATTENTION
B20: • Recompiler et déployer le back-end (build Maven habituel) : modifications Java sur grossiste, articles invendus, valorisation, suivi UG.
B21: • Point 1 (Evolution Stock) : ajouter le sous-menu « Evolution Stock » sous « Gestion du Stock » avec id/xtype = evolutionstock (admin MenuManager / BDD).
B22: • Vider le cache navigateur après déploiement (fichiers JS ExtJS et dashboard.html).
B23: • Se connecter avec un profil Pharmacien pour recetter le point 4 (dashboard d'accueil).
B24: • Disposer d'un jeu de données : grossistes, produits avec stock UG, inventaire, bons de livraison, ventes VO.
B26: SYNTHÈSE PAR POINT
B27: Point | C27: Intitulé | D27: Nb cas | E27: OK | F27: KO | G27: Bloqué / N/A
B28: 1 | C28: Menu Evolution Stock (courbe valorisation) | D28: =COUNTIF(Recette!$B:$B,$B28) | E28: =COUNTIFS(Recette!$B:$B,$B28,Recette!$I:$I,"OK") | F28: =COUNTIFS(Recette!$B:$B,$B28,Recette!$I:$I,"KO") | G28: =COUNTIFS(Recette!$B:$B,$B28,Recette!$I:$I,"Bloqué")+COUNTIFS(Recette!$B:$B,$B28,Recette!$I:$I,"N/A")
B29: 2 | C29: Ventes terminées — date future interdite | D29: =COUNTIF(Recette!$B:$B,$B29) | E29: =COUNTIFS(Recette!$B:$B,$B29,Recette!$I:$I,"OK") | F29: =COUNTIFS(Recette!$B:$B,$B29,Recette!$I:$I,"KO") | G29: =COUNTIFS(Recette!$B:$B,$B29,Recette!$I:$I,"Bloqué")+COUNTIFS(Recette!$B:$B,$B29,Recette!$I:$I,"N/A")
B30: 3 | C30: Gestion des Utilisateurs (titre + IDS/langue) | D30: =COUNTIF(Recette!$B:$B,$B30) | E30: =COUNTIFS(Recette!$B:$B,$B30,Recette!$I:$I,"OK") | F30: =COUNTIFS(Recette!$B:$B,$B30,Recette!$I:$I,"KO") | G30: =COUNTIFS(Recette!$B:$B,$B30,Recette!$I:$I,"Bloqué")+COUNTIFS(Recette!$B:$B,$B30,Recette!$I:$I,"N/A")
B31: 4 | C31: Dashboard accueil — valorisation + nom pharmacien | D31: =COUNTIF(Recette!$B:$B,$B31) | E31: =COUNTIFS(Recette!$B:$B,$B31,Recette!$I:$I,"OK") | F31: =COUNTIFS(Recette!$B:$B,$B31,Recette!$I:$I,"KO") | G31: =COUNTIFS(Recette!$B:$B,$B31,Recette!$I:$I,"Bloqué")+COUNTIFS(Recette!$B:$B,$B31,Recette!$I:$I,"N/A")
B32: 5 | C32: Grossiste — colonnes + champs PharmaML | D32: =COUNTIF(Recette!$B:$B,$B32) | E32: =COUNTIFS(Recette!$B:$B,$B32,Recette!$I:$I,"OK") | F32: =COUNTIFS(Recette!$B:$B,$B32,Recette!$I:$I,"KO") | G32: =COUNTIFS(Recette!$B:$B,$B32,Recette!$I:$I,"Bloqué")+COUNTIFS(Recette!$B:$B,$B32,Recette!$I:$I,"N/A")
B33: 6 | C33: Commande — str_CODE_REMISE = 0 | D33: =COUNTIF(Recette!$B:$B,$B33) | E33: =COUNTIFS(Recette!$B:$B,$B33,Recette!$I:$I,"OK") | F33: =COUNTIFS(Recette!$B:$B,$B33,Recette!$I:$I,"KO") | G33: =COUNTIFS(Recette!$B:$B,$B33,Recette!$I:$I,"Bloqué")+COUNTIFS(Recette!$B:$B,$B33,Recette!$I:$I,"N/A")
B34: 7 | C34: Facturation — mise en évidence ligne survolée | D34: =COUNTIF(Recette!$B:$B,$B34) | E34: =COUNTIFS(Recette!$B:$B,$B34,Recette!$I:$I,"OK") | F34: =COUNTIFS(Recette!$B:$B,$B34,Recette!$I:$I,"KO") | G34: =COUNTIFS(Recette!$B:$B,$B34,Recette!$I:$I,"Bloqué")+COUNTIFS(Recette!$B:$B,$B34,Recette!$I:$I,"N/A")
B35: 8 | C35: Inventaire — chargement des articles | D35: =COUNTIF(Recette!$B:$B,$B35) | E35: =COUNTIFS(Recette!$B:$B,$B35,Recette!$I:$I,"OK") | F35: =COUNTIFS(Recette!$B:$B,$B35,Recette!$I:$I,"KO") | G35: =COUNTIFS(Recette!$B:$B,$B35,Recette!$I:$I,"Bloqué")+COUNTIFS(Recette!$B:$B,$B35,Recette!$I:$I,"N/A")
B36: 9 | C36: Entrée stock — confirmation UG + focus recherche | D36: =COUNTIF(Recette!$B:$B,$B36) | E36: =COUNTIFS(Recette!$B:$B,$B36,Recette!$I:$I,"OK") | F36: =COUNTIFS(Recette!$B:$B,$B36,Recette!$I:$I,"KO") | G36: =COUNTIFS(Recette!$B:$B,$B36,Recette!$I:$I,"Bloqué")+COUNTIFS(Recette!$B:$B,$B36,Recette!$I:$I,"N/A")
B37: 10 | C37: Emplacements — impression portrait | D37: =COUNTIF(Recette!$B:$B,$B37) | E37: =COUNTIFS(Recette!$B:$B,$B37,Recette!$I:$I,"OK") | F37: =COUNTIFS(Recette!$B:$B,$B37,Recette!$I:$I,"KO") | G37: =COUNTIFS(Recette!$B:$B,$B37,Recette!$I:$I,"Bloqué")+COUNTIFS(Recette!$B:$B,$B37,Recette!$I:$I,"N/A")
B38: 11 | C38: Articles invendus — date dernière entrée + filtre mois | D38: =COUNTIF(Recette!$B:$B,$B38) | E38: =COUNTIFS(Recette!$B:$B,$B38,Recette!$I:$I,"OK") | F38: =COUNTIFS(Recette!$B:$B,$B38,Recette!$I:$I,"KO") | G38: =COUNTIFS(Recette!$B:$B,$B38,Recette!$I:$I,"Bloqué")+COUNTIFS(Recette!$B:$B,$B38,Recette!$I:$I,"N/A")
B39: 12 | C39: Unités gratuites — 2 onglets + Suivi UG | D39: =COUNTIF(Recette!$B:$B,$B39) | E39: =COUNTIFS(Recette!$B:$B,$B39,Recette!$I:$I,"OK") | F39: =COUNTIFS(Recette!$B:$B,$B39,Recette!$I:$I,"KO") | G39: =COUNTIFS(Recette!$B:$B,$B39,Recette!$I:$I,"Bloqué")+COUNTIFS(Recette!$B:$B,$B39,Recette!$I:$I,"N/A")
C40: TOTAL | D40: =SUM(D28:D39) | E40: =SUM(E28:E39) | F40: =SUM(F28:F39) | G40: =SUM(G28:G39)

Sheet Recette
A1: N° | B1: Point | C1: Fonctionnalité | D1: Type | E1: Pré-requis | F1: Étapes de test | G1: Résultat attendu | H1: Résultat obtenu | I1: Statut | J1: Sévérité | K1: Commentaire / Anomalie
A2: R1-01 | B2: 1 | C2: Ouverture de l'écran | D2: Nominal | E2: Sous-menu evolutionstock ajouté | F2: Menu Gestion du Stock → Evolution Stock. | G2: L'écran s'ouvre avec 2 champs date (Du = J-30, Au = aujourd'hui), boutons Rechercher et Imprimer, une courbe et une grille.
A3: R1-02 | B3: 1 | C3: Recherche période | D3: Nominal | E3: Écran ouvert | F3: Saisir Du et Au sur une période avec données, cliquer Rechercher. | G3: La courbe (valeur d'achat) et la grille (Date, Valeur d'achat, Valeur de vente) se remplissent ; la valeur d'achat moyenne s'affiche.
A4: R1-03 | B4: 1 | C4: Tooltip courbe | D4: Nominal | E4: Recherche effectuée | F4: Survoler un point de la courbe. | G4: Une infobulle affiche la date et la valeur d'achat du point.
A5: R1-04 | B5: 1 | C5: Validation dtStart<=dtEnd | D5: Limite | E5: Écran ouvert | F5: Mettre Du postérieur à Au, cliquer Rechercher. | G5: Message « La date de début doit être antérieure ou égale à la date de fin » ; aucun chargement.
A6: R1-05 | B6: 1 | C6: Dates obligatoires | D6: Limite | E6: Écran ouvert | F6: Vider une des deux dates, cliquer Rechercher. | G6: Message d'information demandant de renseigner les deux dates.
A7: R1-06 | B7: 1 | C7: Impression | D7: Nominal | E7: Recherche effectuée | F7: Cliquer Imprimer. | G7: Fenêtre imprimable portrait avec titre, période et tableau (date, valeur achat, valeur vente).
A8: R1-07 | B8: 1 | C8: API retourne la date | D8: Nominal | E8: - | F8: Vérifier la réponse de ../api/v1/valorisation/all (console réseau). | G8: Chaque élément contient un champ « date » (format AAAA-MM-JJ) en plus de valeurAchat/valeurVente.
A9: R2-01 | B9: 2 | C9: Ouverture modif date | D9: Nominal | E9: Une vente VO existante | F9: Ventes terminées → clic « Modifier la date » sur une vente éligible. | G9: La fenêtre « Modification de la date de vente » s'ouvre.
A10: R2-02 | B10: 2 | C10: Date future interdite | D10: Limite | E10: Fenêtre ouverte | F10: Sélectionner une date supérieure à aujourd'hui. | G10: Le champ passe en erreur (« La date ne doit pas dépasser la date du jour ») ; enregistrement bloqué.
A11: R2-03 | B11: 2 | C11: Date du jour/passée | D11: Nominal | E11: Fenêtre ouverte | F11: Sélectionner aujourd'hui ou une date passée + heure, Enregistrer. | G11: Enregistrement accepté ; proposition d'impression du ticket.
A12: R2-04 | B12: 2 | C12: Non-régression | D12: Régression | E12: - | F12: Rejouer la modification de date complète (heure, enregistrement, impression). | G12: Comportement identique à l'existant, hormis le blocage des dates futures.
A13: R3-01 | B13: 3 | C13: Titre écran | D13: Nominal | E13: - | F13: Ouvrir la gestion des utilisateurs. | G13: Le titre affiché est « Gestion des Utilisateurs ».
... A57: R12-10 | B57: 12 | C57: Aucun produit UG | D57: Limite | E57: Aucun produit avec stock UG | F57: Cliquer « Creer inventaire ». | G57: Message « Aucun produit à UG à inventorier » ; aucun inventaire créé.
